Workbook

Sheet DEPARTMENTS
A1: ID | B1: NAME | C1: B/F | D1: COLLECTIONS | E1: EXP | F1: BAL | H1: JAN | I1: FEB | J1: MAR | K1: APR | L1: MAY | M1: JUN | N1: JUL | O1: AUG | P1: SEP | Q1: OCT | R1: NOV | S1: DEC | T1: TOTAL
B2: SABBATH SCHOOL | C2: 0 | D2: =SUMIF(COLLECTION!D:D,DEPARTMENTS!B:B,COLLECTION!E:E)+SUMIF(BANK!D:D,DEPARTMENTS!B:B,BANK!E:E)+SUMIF(TRUST!D:D,DEPARTMENTS!B:B,TRUST!E:E) -> 49940 | H2: =SUMIFS(COLLECTION!$E:$E, COLLECTION!$D:$D,DEPARTMENTS!$B:$B, COLLECTION!$B:$B, H$13, COLLECTION!$B:$B, H$13) + SUMIFS(BANK!$E:$E, BANK!$D:$D,DEPARTMENTS!$B:$B, BANK!$B:$B, H$13, BANK!$B:$B, H$13) + SUMIFS(TRUST!$E:$E, TRUST!$D:$D,DEPARTMENTS!$B:$B, TRUST!$B:$B, H$13, TRUST!$B:$B, H$13) -> 12095 | I2: =SUMIFS(COLLECTION!$E:$E, COLLECTION!$D:$D,DEPARTMENTS!$B:$B, COLLECTION!$B:$B, I$13, COLLECTION!$B:$B, I$13) + SUMIFS(BANK!$E:$E, BANK!$D:$D,DEPARTMENTS!$B:$B, BANK!$B:$B, I$13, BANK!$B:$B, I$13) + SUMIFS(TRUST!$E:$E, TRUST!$D:$D,DEPARTMENTS!$B:$B, TRUST!$B:$B, I$13, TRUST!$B:$B, I$13) -> 8435 | J2: =SUMIFS(COLLECTION!$E:$E, COLLECTION!$D:$D,DEPARTMENTS!$B:$B, COLLECTION!$B:$B, J$13, COLLECTION!$B:$B, J$13) + SUMIFS(BANK!$E:$E, BANK!$D:$D,DEPARTMENTS!$B:$B, BANK!$B:$B, J$13, BANK!$B:$B, J$13) + SUMIFS(TRUST!$E:$E, TRUST!$D:$D,DEPARTMENTS!$B:$B, TRUST!$B:$B, J$13, TRUST!$B:$B, J$13) -> 7665 | K2: =SUMIFS(COLLECTION!$E:$E, COLLECTION!$D:$D,DEPARTMENTS!$B:$B, COLLECTION!$B:$B, K$13, COLLECTION!$B:$B, K$13) + SUMIFS(BANK!$E:$E, BANK!$D:$D,DEPARTMENTS!$B:$B, BANK!$B:$B, K$13, BANK!$B:$B, K$13) + SUMIFS(TRUST!$E:$E, TRUST!$D:$D,DEPARTMENTS!$B:$B, TRUST!$B:$B, K$13, TRUST!$B:$B, K$13) -> 10700 | L2: =SUMIFS(COLLECTION!$E:$E, COLLECTION!$D:$D,DEPARTMENTS!$B:$B, COLLECTION!$B:$B, L$13, COLLECTION!$B:$B, L$13) + SUMIFS(BANK!$E:$E, BANK!$D:$D,DEPARTMENTS!$B:$B, BANK!$B:$B, L$13, BANK!$B:$B, L$13) + SUMIFS(TRUST!$E:$E, TRUST!$D:$D,DEPARTMENTS!$B:$B, TRUST!$B:$B, L$13, TRUST!$B:$B, L$13) -> 9160 | M2: =SUMIFS(COLLECTION!$E:$E, COLLECTION!$D:$D,DEPARTMENTS!$B:$B, COLLECTION!$B:$B, M$13, COLLECTION!$B:$B, M$13) + SUMIFS(BANK!$E:$E, BANK!$D:$D,DEPARTMENTS!$B:$B, BANK!$B:$B, M$13, BANK!$B:$B, M$13) + SUMIFS(TRUST!$E:$E, TRUST!$D:$D,DEPARTMENTS!$B:$B, TRUST!$B:$B, M$13, TRUST!$B:$B, M$13) -> 1885 | N2: =SUMIFS(COLLECTION!$E:$E, COLLECTION!$D:$D,DEPARTMENTS!$B:$B, COLLECTION!$B:$B, N$13, COLLECTION!$B:$B, N$13) + SUMIFS(BANK!$E:$E, BANK!$D:$D,DEPARTMENTS!$B:$B, BANK!$B:$B, N$13, BANK!$B:$B, N$13) + SUMIFS(TRUST!$E:$E, TRUST!$D:$D,DEPARTMENTS!$B:$B, TRUST!$B:$B, N$13, TRUST!$B:$B, N$13) -> 0 | O2: =SUMIFS(COLLECTION!$E:$E, COLLECTION!$D:$D,DEPARTMENTS!$B:$B, COLLECTION!$B:$B, O$13, COLLECTION!$B:$B, O$13) + SUMIFS(BANK!$E:$E, BANK!$D:$D,DEPARTMENTS!$B:$B, BANK!$B:$B, O$13, BANK!$B:$B, O$13) + SUMIFS(TRUST!$E:$E, TRUST!$D:$D,DEPARTMENTS!$B:$B, TRUST!$B:$B, O$13, TRUST!$B:$B, O$13) -> 0 | ... S2: =SUMIFS(COLLECTION!$E:$E, COLLECTION!$D:$D,DEPARTMENTS!$B:$B, COLLECTION!$B:$B, S$13, COLLECTION!$B:$B, S$13) + SUMIFS(BANK!$E:$E, BANK!$D:$D,DEPARTMENTS!$B:$B, BANK!$B:$B, S$13, BANK!$B:$B, S$13) + SUMIFS(TRUST!$E:$E, TRUST!$D:$D,DEPARTMENTS!$B:$B, TRUST!$B:$B, S$13, TRUST!$B:$B, S$13) -> 0 | T2: =SUM(H2:S2) -> 49940 | AK2: =SUMIFS(COLLECTION!$E:$E, COLLECTION!$D:$D,DEPARTMENTS!$B:$B, COLLECTION!$B:$B, AK$12, COLLECTION!$C:$C, AK$13) + SUMIFS(BANK!$E:$E, BANK!$D:$D,DEPARTMENTS!$B:$B, BANK!$B:$B, AK$12, BANK!$C:$C, AK$13) + SUMIFS(TRUST!$E:$E, TRUST!$D:$D,DEPARTMENTS!$B:$B, TRUST!$B:$B, AK$12, TRUST!$C:$C, AK$13) -> 4685 | AL2: =SUMIFS(COLLECTION!$E:$E, COLLECTION!$D:$D,DEPARTMENTS!$B:$B, COLLECTION!$B:$B, AL$12, COLLECTION!$C:$C, AL$13) + SUMIFS(BANK!$E:$E, BANK!$D:$D,DEPARTMENTS!$B:$B, BANK!$B:$B, AL$12, BANK!$C:$C, AL$13) + SUMIFS(TRUST!$E:$E, TRUST!$D:$D,DEPARTMENTS!$B:$B, TRUST!$B:$B, AL$12, TRUST!$C:$C, AL$13) -> 2565 | AM2: =SUMIFS(COLLECTION!$E:$E, COLLECTION!$D:$D,DEPARTMENTS!$B:$B, COLLECTION!$B:$B, AM$12, COLLECTION!$C:$C, AM$13) + SUMIFS(BANK!$E:$E, BANK!$D:$D,DEPARTMENTS!$B:$B, BANK!$B:$B, AM$12, BANK!$C:$C, AM$13) + SUMIFS(TRUST!$E:$E, TRUST!$D:$D,DEPARTMENTS!$B:$B, TRUST!$B:$B, AM$12, TRUST!$C:$C, AM$13) -> 2765 | AN2: =SUMIFS(COLLECTION!$E:$E, COLLECTION!$D:$D,DEPARTMENTS!$B:$B, COLLECTION!$B:$B, AN$12, COLLECTION!$C:$C, AN$13) + SUMIFS(BANK!$E:$E, BANK!$D:$D,DEPARTMENTS!$B:$B, BANK!$B:$B, AN$12, BANK!$C:$C, AN$13) + SUMIFS(TRUST!$E:$E, TRUST!$D:$D,DEPARTMENTS!$B:$B, TRUST!$B:$B, AN$12, TRUST!$C:$C, AN$13) -> 2080 | AO2: =SUMIFS(COLLECTION!$E:$E, COLLECTION!$D:$D,DEPARTMENTS!$B:$B, COLLECTION!$B:$B, AO$12, COLLECTION!$C:$C, AO$13) + SUMIFS(BANK!$E:$E, BANK!$D:$D,DEPARTMENTS!$B:$B, BANK!$B:$B, AO$12, BANK!$C:$C, AO$13) + SUMIFS(TRUST!$E:$E, TRUST!$D:$D,DEPARTMENTS!$B:$B, TRUST!$B:$B, AO$12, TRUST!$C:$C, AO$13) -> 0 | AP2: =SUMIFS(COLLECTION!$E:$E, COLLECTION!$D:$D,DEPARTMENTS!$B:$B, COLLECTION!$B:$B, AP$12, COLLECTION!$C:$C, AP$13) + SUMIFS(BANK!$E:$E, BANK!$D:$D,DEPARTMENTS!$B:$B, BANK!$B:$B, AP$12, BANK!$C:$C, AP$13) + SUMIFS(TRUST!$E:$E, TRUST!$D:$D,DEPARTMENTS!$B:$B, TRUST!$B:$B, AP$12, TRUST!$C:$C, AP$13) -> 2015 | AQ2: =SUMIFS(COLLECTION!$E:$E, COLLECTION!$D:$D,DEPARTMENTS!$B:$B, COLLECTION!$B:$B, AQ$12, COLLECTION!$C:$C, AQ$13) + SUMIFS(BANK!$E:$E, BANK!$D:$D,DEPARTMENTS!$B:$B, BANK!$B:$B, AQ$12, BANK!$C:$C, AQ$13) + SUMIFS(TRUST!$E:$E, TRUST!$D:$D,DEPARTMENTS!$B:$B, TRUST!$B:$B, AQ$12, TRUST!$C:$C, AQ$13) -> 2370 | AR2: =SUMIFS(COLLECTION!$E:$E, COLLECTION!$D:$D,DEPARTMENTS!$B:$B, COLLECTION!$B:$B, AR$12, COLLECTION!$C:$C, AR$13) + SUMIFS(BANK!$E:$E, BANK!$D:$D,DEPARTMENTS!$B:$B, BANK!$B:$B, AR$12, BANK!$C:$C, AR$13) + SUMIFS(TRUST!$E:$E, TRUST!$D:$D,DEPARTMENTS!$B:$B, TRUST!$B:$B, AR$12, TRUST!$C:$C, AR$13) -> 2215 | ... BC2: =SUMIFS(COLLECTION!$E:$E, COLLECTION!$D:$D,DEPARTMENTS!$B:$B, COLLECTION!$B:$B, BC$12, COLLECTION!$C:$C, BC$13) + SUMIFS(BANK!$E:$E, BANK!$D:$D,DEPARTMENTS!$B:$B, BANK!$B:$B, BC$12, BANK!$C:$C, BC$13) + SUMIFS(TRUST!$E:$E, TRUST!$D:$D,DEPARTMENTS!$B:$B, TRUST!$B:$B, BC$12, TRUST!$C:$C, BC$13) -> 2130 | BE2: =SUMIFS(COLLECTION!$E:$E, COLLECTION!$D:$D,DEPARTMENTS!$B:$B, COLLECTION!$B:$B, BE$12, COLLECTION!$C:$C, BE$13) + SUMIFS(BANK!$E:$E, BANK!$D:$D,DEPARTMENTS!$B:$B, BANK!$B:$B, BE$12, BANK!$C:$C, BE$13) + SUMIFS(TRUST!$E:$E, TRUST!$D:$D,DEPARTMENTS!$B:$B, TRUST!$B:$B, BE$12, TRUST!$C:$C, BE$13) -> 2130 | BF2: =SUMIFS(COLLECTION!$E:$E, COLLECTION!$D:$D,DEPARTMENTS!$B:$B, COLLECTION!$B:$B, BF$12, COLLECTION!$C:$C, BF$13) + SUMIFS(BANK!$E:$E, BANK!$D:$D,DEPARTMENTS!$B:$B, BANK!$B:$B, BF$12, BANK!$C:$C, BF$13) + SUMIFS(TRUST!$E:$E, TRUST!$D:$D,DEPARTMENTS!$B:$B, TRUST!$B:$B, BF$12, TRUST!$C:$C, BF$13) -> 2490 | BG2: =SUMIFS(COLLECTION!$E:$E, COLLECTION!$D:$D,DEPARTMENTS!$B:$B, COLLECTION!$B:$B, BG$12, COLLECTION!$C:$C, BG$13) + SUMIFS(BANK!$E:$E, BANK!$D:$D,DEPARTMENTS!$B:$B, BANK!$B:$B, BG$12, BANK!$C:$C, BG$13) + SUMIFS(TRUST!$E:$E, TRUST!$D:$D,DEPARTMENTS!$B:$B, TRUST!$B:$B, BG$12, TRUST!$C:$C, BG$13) -> 1900 | BH2: =SUMIFS(COLLECTION!$E:$E, COLLECTION!$D:$D,DEPARTMENTS!$B:$B, COLLECTION!$B:$B, BH$12, COLLECTION!$C:$C, BH$13) + SUMIFS(BANK!$E:$E, BANK!$D:$D,DEPARTMENTS!$B:$B, BANK!$B:$B, BH$12, BANK!$C:$C, BH$13) + SUMIFS(TRUST!$E:$E, TRUST!$D:$D,DEPARTMENTS!$B:$B, TRUST!$B:$B, BH$12, TRUST!$C:$C, BH$13) -> 1195 | BI2: =SUMIFS(COLLECTION!$E:$E, COLLECTION!$D:$D,DEPARTMENTS!$B:$B, COLLECTION!$B:$B, BI$12, COLLECTION!$C:$C, BI$13) + SUMIFS(BANK!$E:$E, BANK!$D:$D,DEPARTMENTS!$B:$B, BANK!$B:$B, BI$12, BANK!$C:$C, BI$13) + SUMIFS(TRUST!$E:$E, TRUST!$D:$D,DEPARTMENTS!$B:$B, TRUST!$B:$B, BI$12, TRUST!$C:$C, BI$13) -> 1445 | BJ2: =SUMIFS(COLLECTION!$E:$E, COLLECTION!$D:$D,DEPARTMENTS!$B:$B, COLLECTION!$B:$B, BJ$12, COLLECTION!$C:$C, BJ$13) + SUMIFS(BANK!$E:$E, BANK!$D:$D,DEPARTMENTS!$B:$B, BANK!$B:$B, BJ$12, BANK!$C:$C, BJ$13) + SUMIFS(TRUST!$E:$E, TRUST!$D:$D,DEPARTMENTS!$B:$B, TRUST!$B:$B, BJ$12, TRUST!$C:$C, BJ$13) -> 100 | BK2: =SUMIFS(COLLECTION!$E:$E, COLLECTION!$D:$D,DEPARTMENTS!$B:$B, COLLECTION!$B:$B, BK$12, COLLECTION!$C:$C, BK$13) + SUMIFS(BANK!$E:$E, BANK!$D:$D,DEPARTMENTS!$B:$B, BANK!$B:$B, BK$12, BANK!$C:$C, BK$13) + SUMIFS(TRUST!$E:$E, TRUST!$D:$D,DEPARTMENTS!$B:$B, TRUST!$B:$B, BK$12, TRUST!$C:$C, BK$13) -> 0 | BL2: =SUMIFS(COLLECTION!$E:$E, COLLECTION!$D:$D,DEPARTMENTS!$B:$B, COLLECTION!$B:$B, BL$12, COLLECTION!$C:$C, BL$13) + SUMIFS(BANK!$E:$E, BANK!$D:$D,DEPARTMENTS!$B:$B, BANK!$B:$B, BL$12, BANK!$C:$C, BL$13) + SUMIFS(TRUST!$E:$E, TRUST!$D:$D,DEPARTMENTS!$B:$B, TRUST!$B:$B, BL$12, TRUST!$C:$C, BL$13) -> 0 | ... CQ2: =SUMIFS(COLLECTION!$E:$E, COLLECTION!$D:$D,DEPARTMENTS!$B:$B, COLLECTION!$B:$B, CQ$12, COLLECTION!$C:$C, CQ$13) + SUMIFS(BANK!$E:$E, BANK!$D:$D,DEPARTMENTS!$B:$B, BANK!$B:$B, CQ$12, BANK!$C:$C, CQ$13) + SUMIFS(TRUST!$E:$E, TRUST!$D:$D,DEPARTMENTS!$B:$B, TRUST!$B:$B, CQ$12, TRUST!$C:$C, CQ$13) -> 0 | CR2: =SUM(AK2:CQ2) -> 48155
B3: LOOSE OFFERING | C3: 0 | D3: =SUMIF(COLLECTION!D:D,DEPARTMENTS!B:B,COLLECTION!E:E)+SUMIF(BANK!D:D,DEPARTMENTS!B:B,BANK!E:E)+SUMIF(TRUST!D:D,DEPARTMENTS!B:B,TRUST!E:E) -> 130359 | H3: =SUMIFS(COLLECTION!$E:$E, COLLECTION!$D:$D,DEPARTMENTS!$B:$B, COLLECTION!$B:$B, H$13, COLLECTION!$B:$B, H$13) + SUMIFS(BANK!$E:$E, BANK!$D:$D,DEPARTMENTS!$B:$B, BANK!$B:$B, H$13, BANK!$B:$B, H$13) + SUMIFS(TRUST!$E:$E, TRUST!$D:$D,DEPARTMENTS!$B:$B, TRUST!$B:$B, H$13, TRUST!$B:$B, H$13) -> 33134 | I3: =SUMIFS(COLLECTION!$E:$E, COLLECTION!$D:$D,DEPARTMENTS!$B:$B, COLLECTION!$B:$B, I$13, COLLECTION!$B:$B, I$13) + SUMIFS(BANK!$E:$E, BANK!$D:$D,DEPARTMENTS!$B:$B, BANK!$B:$B, I$13, BANK!$B:$B, I$13) + SUMIFS(TRUST!$E:$E, TRUST!$D:$D,DEPARTMENTS!$B:$B, TRUST!$B:$B, I$13, TRUST!$B:$B, I$13) -> 20463 | J3: =SUMIFS(COLLECTION!$E:$E, COLLECTION!$D:$D,DEPARTMENTS!$B:$B, COLLECTION!$B:$B, J$13, COLLECTION!$B:$B, J$13) + SUMIFS(BANK!$E:$E, BANK!$D:$D,DEPARTMENTS!$B:$B, BANK!$B:$B, J$13, BANK!$B:$B, J$13) + SUMIFS(TRUST!$E:$E, TRUST!$D:$D,DEPARTMENTS!$B:$B, TRUST!$B:$B, J$13, TRUST!$B:$B, J$13) -> 15935 | K3: =SUMIFS(COLLECTION!$E:$E, COLLECTION!$D:$D,DEPARTMENTS!$B:$B, COLLECTION!$B:$B, K$13, COLLECTION!$B:$B, K$13) + SUMIFS(BANK!$E:$E, BANK!$D:$D,DEPARTMENTS!$B:$B, BANK!$B:$B, K$13, BANK!$B:$B, K$13) + SUMIFS(TRUST!$E:$E, TRUST!$D:$D,DEPARTMENTS!$B:$B, TRUST!$B:$B, K$13, TRUST!$B:$B, K$13) -> 25786 | L3: =SUMIFS(COLLECTION!$E:$E, COLLECTION!$D:$D,DEPARTMENTS!$B:$B, COLLECTION!$B:$B, L$13, COLLECTION!$B:$B, L$13) + SUMIFS(BANK!$E:$E, BANK!$D:$D,DEPARTMENTS!$B:$B, BANK!$B:$B, L$13, BANK!$B:$B, L$13) + SUMIFS(TRUST!$E:$E, TRUST!$D:$D,DEPARTMENTS!$B:$B, TRUST!$B:$B, L$13, TRUST!$B:$B, L$13) -> 28805 | M3: =SUMIFS(COLLECTION!$E:$E, COLLECTION!$D:$D,DEPARTMENTS!$B:$B, COLLECTION!$B:$B, M$13, COLLECTION!$B:$B, M$13) + SUMIFS(BANK!$E:$E, BANK!$D:$D,DEPARTMENTS!$B:$B, BANK!$B:$B, M$13, BANK!$B:$B, M$13) + SUMIFS(TRUST!$E:$E, TRUST!$D:$D,DEPARTMENTS!$B:$B, TRUST!$B:$B, M$13, TRUST!$B:$B, M$13) -> 6236 | N3: =SUMIFS(COLLECTION!$E:$E, COLLECTION!$D:$D,DEPARTMENTS!$B:$B, COLLECTION!$B:$B, N$13, COLLECTION!$B:$B, N$13) + SUMIFS(BANK!$E:$E, BANK!$D:$D,DEPARTMENTS!$B:$B, BANK!$B:$B, N$13, BANK!$B:$B, N$13) + SUMIFS(TRUST!$E:$E, TRUST!$D:$D,DEPARTMENTS!$B:$B, TRUST!$B:$B, N$13, TRUST!$B:$B, N$13) -> 0 | O3: =SUMIFS(COLLECTION!$E:$E, COLLECTION!$D:$D,DEPARTMENTS!$B:$B, COLLECTION!$B:$B, O$13, COLLECTION!$B:$B, O$13) + SUMIFS(BANK!$E:$E, BANK!$D:$D,DEPARTMENTS!$B:$B, BANK!$B:$B, O$13, BANK!$B:$B, O$13) + SUMIFS(TRUST!$E:$E, TRUST!$D:$D,DEPARTMENTS!$B:$B, TRUST!$B:$B, O$13, TRUST!$B:$B, O$13) -> 0 | ... S3: =SUMIFS(COLLECTION!$E:$E, COLLECTION!$D:$D,DEPARTMENTS!$B:$B, COLLECTION!$B:$B, S$13, COLLECTION!$B:$B, S$13) + SUMIFS(BANK!$E:$E, BANK!$D:$D,DEPARTMENTS!$B:$B, BANK!$B:$B, S$13, BANK!$B:$B, S$13) + SUMIFS(TRUST!$E:$E, TRUST!$D:$D,DEPARTMENTS!$B:$B, TRUST!$B:$B, S$13, TRUST!$B:$B, S$13) -> 0 | T3: =SUM(H3:S3) -> 130359 | AK3: =SUMIFS(COLLECTION!$E:$E, COLLECTION!$D:$D,DEPARTMENTS!$B:$B, COLLECTION!$B:$B, AK$12, COLLECTION!$C:$C, AK$13) + SUMIFS(BANK!$E:$E, BANK!$D:$D,DEPARTMENTS!$B:$B, BANK!$B:$B, AK$12, BANK!$C:$C, AK$13) + SUMIFS(TRUST!$E:$E, TRUST!$D:$D,DEPARTMENTS!$B:$B, TRUST!$B:$B, AK$12, TRUST!$C:$C, AK$13) -> 15662 | AL3: =SUMIFS(COLLECTION!$E:$E, COLLECTION!$D:$D,DEPARTMENTS!$B:$B, COLLECTION!$B:$B, AL$12, COLLECTION!$C:$C, AL$13) + SUMIFS(BANK!$E:$E, BANK!$D:$D,DEPARTMENTS!$B:$B, BANK!$B:$B, AL$12, BANK!$C:$C, AL$13) + SUMIFS(TRUST!$E:$E, TRUST!$D:$D,DEPARTMENTS!$B:$B, TRUST!$B:$B, AL$12, TRUST!$C:$C, AL$13) -> 7012 | AM3: =SUMIFS(COLLECTION!$E:$E, COLLECTION!$D:$D,DEPARTMENTS!$B:$B, COLLECTION!$B:$B, AM$12, COLLECTION!$C:$C, AM$13) + SUMIFS(BANK!$E:$E, BANK!$D:$D,DEPARTMENTS!$B:$B, BANK!$B:$B, AM$12, BANK!$C:$C, AM$13) + SUMIFS(TRUST!$E:$E, TRUST!$D:$D,DEPARTMENTS!$B:$B, TRUST!$B:$B, AM$12, TRUST!$C:$C, AM$13) -> 5775 | AN3: =SUMIFS(COLLECTION!$E:$E, COLLECTION!$D:$D,DEPARTMENTS!$B:$B, COLLECTION!$B:$B, AN$12, COLLECTION!$C:$C, AN$13) + SUMIFS(BANK!$E:$E, BANK!$D:$D,DEPARTMENTS!$B:$B, BANK!$B:$B, AN$12, BANK!$C:$C, AN$13) + SUMIFS(TRUST!$E:$E, TRUST!$D:$D,DEPARTMENTS!$B:$B, TRUST!$B:$B, AN$12, TRUST!$C:$C, AN$13) -> 4685 | AO3: =SUMIFS(COLLECTION!$E:$E, COLLECTION!$D:$D,DEPARTMENTS!$B:$B, COLLECTION!$B:$B, AO$12, COLLECTION!$C:$C, AO$13) + SUMIFS(BANK!$E:$E, BANK!$D:$D,DEPARTMENTS!$B:$B, BANK!$B:$B, AO$12, BANK!$C:$C, AO$13) + SUMIFS(TRUST!$E:$E, TRUST!$D:$D,DEPARTMENTS!$B:$B, TRUST!$B:$B, AO$12, TRUST!$C:$C, AO$13) -> 0 | AP3: =SUMIFS(COLLECTION!$E:$E, COLLECTION!$D:$D,DEPARTMENTS!$B:$B, COLLECTION!$B:$B, AP$12, COLLECTION!$C:$C, AP$13) + SUMIFS(BANK!$E:$E, BANK!$D:$D,DEPARTMENTS!$B:$B, BANK!$B:$B, AP$12, BANK!$C:$C, AP$13) + SUMIFS(TRUST!$E:$E, TRUST!$D:$D,DEPARTMENTS!$B:$B, TRUST!$B:$B, AP$12, TRUST!$C:$C, AP$13) -> 5230 | AQ3: =SUMIFS(COLLECTION!$E:$E, COLLECTION!$D:$D,DEPARTMENTS!$B:$B, COLLECTION!$B:$B, AQ$12, COLLECTION!$C:$C, AQ$13) + SUMIFS(BANK!$E:$E, BANK!$D:$D,DEPARTMENTS!$B:$B, BANK!$B:$B, AQ$12, BANK!$C:$C, AQ$13) + SUMIFS(TRUST!$E:$E, TRUST!$D:$D,DEPARTMENTS!$B:$B, TRUST!$B:$B, AQ$12, TRUST!$C:$C, AQ$13) -> 4723 | AR3: =SUMIFS(COLLECTION!$E:$E, COLLECTION!$D:$D,DEPARTMENTS!$B:$B, COLLECTION!$B:$B, AR$12, COLLECTION!$C:$C, AR$13) + SUMIFS(BANK!$E:$E, BANK!$D:$D,DEPARTMENTS!$B:$B, BANK!$B:$B, AR$12, BANK!$C:$C, AR$13) + SUMIFS(TRUST!$E:$E, TRUST!$D:$D,DEPARTMENTS!$B:$B, TRUST!$B:$B, AR$12, TRUST!$C:$C, AR$13) -> 4590 | ... BC3: =SUMIFS(COLLECTION!$E:$E, COLLECTION!$D:$D,DEPARTMENTS!$B:$B, COLLECTION!$B:$B, BC$12, COLLECTION!$C:$C, BC$13) + SUMIFS(BANK!$E:$E, BANK!$D:$D,DEPARTMENTS!$B:$B, BANK!$B:$B, BC$12, BANK!$C:$C, BC$13) + SUMIFS(TRUST!$E:$E, TRUST!$D:$D,DEPARTMENTS!$B:$B, TRUST!$B:$B, BC$12, TRUST!$C:$C, BC$13) -> 7355 | BE3: =SUMIFS(COLLECTION!$E:$E, COLLECTION!$D:$D,DEPARTMENTS!$B:$B, COLLECTION!$B:$B, BE$12, COLLECTION!$C:$C, BE$13) + SUMIFS(BANK!$E:$E, BANK!$D:$D,DEPARTMENTS!$B:$B, BANK!$B:$B, BE$12, BANK!$C:$C, BE$13) + SUMIFS(TRUST!$E:$E, TRUST!$D:$D,DEPARTMENTS!$B:$B, TRUST!$B:$B, BE$12, TRUST!$C:$C, BE$13) -> 7175 | BF3: =SUMIFS(COLLECTION!$E:$E, COLLECTION!$D:$D,DEPARTMENTS!$B:$B, COLLECTION!$B:$B, BF$12, COLLECTION!$C:$C, BF$13) + SUMIFS(BANK!$E:$E, BANK!$D:$D,DEPARTMENTS!$B:$B, BANK!$B:$B, BF$12, BANK!$C:$C, BF$13) + SUMIFS(TRUST!$E:$E, TRUST!$D:$D,DEPARTMENTS!$B:$B, TRUST!$B:$B, BF$12, TRUST!$C:$C, BF$13) -> 6285 | BG3: =SUMIFS(COLLECTION!$E:$E, COLLECTION!$D:$D,DEPARTMENTS!$B:$B, COLLECTION!$B:$B, BG$12, COLLECTION!$C:$C, BG$13) + SUMIFS(BANK!$E:$E, BANK!$D:$D,DEPARTMENTS!$B:$B, BANK!$B:$B, BG$12, BANK!$C:$C, BG$13) + SUMIFS(TRUST!$E:$E, TRUST!$D:$D,DEPARTMENTS!$B:$B, TRUST!$B:$B, BG$12, TRUST!$C:$C, BG$13) -> 3925 | BH3: =SUMIFS(COLLECTION!$E:$E, COLLECTION!$D:$D,DEPARTMENTS!$B:$B, COLLECTION!$B:$B, BH$12, COLLECTION!$C:$C, BH$13) + SUMIFS(BANK!$E:$E, BANK!$D:$D,DEPARTMENTS!$B:$B, BANK!$B:$B, BH$12, BANK!$C:$C, BH$13) + SUMIFS(TRUST!$E:$E, TRUST!$D:$D,DEPARTMENTS!$B:$B, TRUST!$B:$B, BH$12, TRUST!$C:$C, BH$13) -> 6550 | BI3: =SUMIFS(COLLECTION!$E:$E, COLLECTION!$D:$D,DEPARTMENTS!$B:$B, COLLECTION!$B:$B, BI$12, COLLECTION!$C:$C, BI$13) + SUMIFS(BANK!$E:$E, BANK!$D:$D,DEPARTMENTS!$B:$B, BANK!$B:$B, BI$12, BANK!$C:$C, BI$13) + SUMIFS(TRUST!$E:$E, TRUST!$D:$D,DEPARTMENTS!$B:$B, TRUST!$B:$B, BI$12, TRUST!$C:$C, BI$13) -> 4870 | BJ3: =SUMIFS(COLLECTION!$E:$E, COLLECTION!$D:$D,DEPARTMENTS!$B:$B, COLLECTION!$B:$B, BJ$12, COLLECTION!$C:$C, BJ$13) + SUMIFS(BANK!$E:$E, BANK!$D:$D,DEPARTMENTS!$B:$B, BANK!$B:$B, BJ$12, BANK!$C:$C, BJ$13) + SUMIFS(TRUST!$E:$E, TRUST!$D:$D,DEPARTMENTS!$B:$B, TRUST!$B:$B, BJ$12, TRUST!$C:$C, BJ$13) -> 0 | BK3: =SUMIFS(COLLECTION!$E:$E, COLLECTION!$D:$D,DEPARTMENTS!$B:$B, COLLECTION!$B:$B, BK$12, COLLECTION!$C:$C, BK$13) + SUMIFS(BANK!$E:$E, BANK!$D:$D,DEPARTMENTS!$B:$B, BANK!$B:$B, BK$12, BANK!$C:$C, BK$13) + SUMIFS(TRUST!$E:$E, TRUST!$D:$D,DEPARTMENTS!$B:$B, TRUST!$B:$B, BK$12, TRUST!$C:$C, BK$13) -> 0 | BL3: =SUMIFS(COLLECTION!$E:$E, COLLECTION!$D:$D,DEPARTMENTS!$B:$B, COLLECTION!$B:$B, BL$12, COLLECTION!$C:$C, BL$13) + SUMIFS(BANK!$E:$E, BANK!$D:$D,DEPARTMENTS!$B:$B, BANK!$B:$B, BL$12, BANK!$C:$C, BL$13) + SUMIFS(TRUST!$E:$E, TRUST!$D:$D,DEPARTMENTS!$B:$B, TRUST!$B:$B, BL$12, TRUST!$C:$C, BL$13) -> 0 | ... CQ3: =SUMIFS(COLLECTION!$E:$E, COLLECTION!$D:$D,DEPARTMENTS!$B:$B, COLLECTION!$B:$B, CQ$12, COLLECTION!$C:$C, CQ$13) + SUMIFS(BANK!$E:$E, BANK!$D:$D,DEPARTMENTS!$B:$B, BANK!$B:$B, CQ$12, BANK!$C:$C, CQ$13) + SUMIFS(TRUST!$E:$E, TRUST!$D:$D,DEPARTMENTS!$B:$B, TRUST!$B:$B, CQ$12, TRUST!$C:$C, CQ$13) -> 0 | CR3: =SUM(AK3:CQ3) -> 124123
B4: COMBINED - LCB | C4: 0 | D4: =SUMIF(COLLECTION!D:D,DEPARTMENTS!B:B,COLLECTION!E:E)+SUMIF(BANK!D:D,DEPARTMENTS!B:B,BANK!E:E)+SUMIF(TRUST!D:D,DEPARTMENTS!B:B,TRUST!E:E) -> 107931.5 | H4: =SUMIFS(COLLECTION!$E:$E, COLLECTION!$D:$D,DEPARTMENTS!$B:$B, COLLECTION!$B:$B, H$13, COLLECTION!$B:$B, H$13) + SUMIFS(BANK!$E:$E, BANK!$D:$D,DEPARTMENTS!$B:$B, BANK!$B:$B, H$13, BANK!$B:$B, H$13) + SUMIFS(TRUST!$E:$E, TRUST!$D:$D,DEPARTMENTS!$B:$B, TRUST!$B:$B, H$13, TRUST!$B:$B, H$13) -> 27573 | I4: =SUMIFS(COLLECTION!$E:$E, COLLECTION!$D:$D,DEPARTMENTS!$B:$B, COLLECTION!$B:$B, I$13, COLLECTION!$B:$B, I$13) + SUMIFS(BANK!$E:$E, BANK!$D:$D,DEPARTMENTS!$B:$B, BANK!$B:$B, I$13, BANK!$B:$B, I$13) + SUMIFS(TRUST!$E:$E, TRUST!$D:$D,DEPARTMENTS!$B:$B, TRUST!$B:$B, I$13, TRUST!$B:$B, I$13) -> 18746.5 | J4: =SUMIFS(COLLECTION!$E:$E, COLLECTION!$D:$D,DEPARTMENTS!$B:$B, COLLECTION!$B:$B, J$13, COLLECTION!$B:$B, J$13) + SUMIFS(BANK!$E:$E, BANK!$D:$D,DEPARTMENTS!$B:$B, BANK!$B:$B, J$13, BANK!$B:$B, J$13) + SUMIFS(TRUST!$E:$E, TRUST!$D:$D,DEPARTMENTS!$B:$B, TRUST!$B:$B, J$13, TRUST!$B:$B, J$13) -> 15955.5 | K4: =SUMIFS(COLLECTION!$E:$E, COLLECTION!$D:$D,DEPARTMENTS!$B:$B, COLLECTION!$B:$B, K$13, COLLECTION!$B:$B, K$13) + SUMIFS(BANK!$E:$E, BANK!$D:$D,DEPARTMENTS!$B:$B, BANK!$B:$B, K$13, BANK!$B:$B, K$13) + SUMIFS(TRUST!$E:$E, TRUST!$D:$D,DEPARTMENTS!$B:$B, TRUST!$B:$B, K$13, TRUST!$B:$B, K$13) -> 19379.5 | L4: =SUMIFS(COLLECTION!$E:$E, COLLECTION!$D:$D,DEPARTMENTS!$B:$B, COLLECTION!$B:$B, L$13, COLLECTION!$B:$B, L$13) + SUMIFS(BANK!$E:$E, BANK!$D:$D,DEPARTMENTS!$B:$B, BANK!$B:$B, L$13, BANK!$B:$B, L$13) + SUMIFS(TRUST!$E:$E, TRUST!$D:$D,DEPARTMENTS!$B:$B, TRUST!$B:$B, L$13, TRUST!$B:$B, L$13) -> 23284.5 | M4: =SUMIFS(COLLECTION!$E:$E, COLLECTION!$D:$D,DEPARTMENTS!$B:$B, COLLECTION!$B:$B, M$13, COLLECTION!$B:$B, M$13) + SUMIFS(BANK!$E:$E, BANK!$D:$D,DEPARTMENTS!$B:$B, BANK!$B:$B, M$13, BANK!$B:$B, M$13) + SUMIFS(TRUST!$E:$E, TRUST!$D:$D,DEPARTMENTS!$B:$B, TRUST!$B:$B, M$13, TRUST!$B:$B, M$13) -> 2992.5 | N4: =SUMIFS(COLLECTION!$E:$E, COLLECTION!$D:$D,DEPARTMENTS!$B:$B, COLLECTION!$B:$B, N$13, COLLECTION!$B:$B, N$13) + SUMIFS(BANK!$E:$E, BANK!$D:$D,DEPARTMENTS!$B:$B, BANK!$B:$B, N$13, BANK!$B:$B, N$13) + SUMIFS(TRUST!$E:$E, TRUST!$D:$D,DEPARTMENTS!$B:$B, TRUST!$B:$B, N$13, TRUST!$B:$B, N$13) -> 0 | O4: =SUMIFS(COLLECTION!$E:$E, COLLECTION!$D:$D,DEPARTMENTS!$B:$B, COLLECTION!$B:$B, O$13, COLLECTION!$B:$B, O$13) + SUMIFS(BANK!$E:$E, BANK!$D:$D,DEPARTMENTS!$B:$B, BANK!$B:$B, O$13, BANK!$B:$B, O$13) + SUMIFS(TRUST!$E:$E, TRUST!$D:$D,DEPARTMENTS!$B:$B, TRUST!$B:$B, O$13, TRUST!$B:$B, O$13) -> 0 | ... S4: =SUMIFS(COLLECTION!$E:$E, COLLECTION!$D:$D,DEPARTMENTS!$B:$B, COLLECTION!$B:$B, S$13, COLLECTION!$B:$B, S$13) + SUMIFS(BANK!$E:$E, BANK!$D:$D,DEPARTMENTS!$B:$B, BANK!$B:$B, S$13, BANK!$B:$B, S$13) + SUMIFS(TRUST!$E:$E, TRUST!$D:$D,DEPARTMENTS!$B:$B, TRUST!$B:$B, S$13, TRUST!$B:$B, S$13) -> 0 | T4: =SUM(H4:S4) -> 107931.5 | AK4: =SUMIFS(COLLECTION!$E:$E, COLLECTION!$D:$D,DEPARTMENTS!$B:$B, COLLECTION!$B:$B, AK$12, COLLECTION!$C:$C, AK$13) + SUMIFS(BANK!$E:$E, BANK!$D:$D,DEPARTMENTS!$B:$B, BANK!$B:$B, AK$12, BANK!$C:$C, AK$13) + SUMIFS(TRUST!$E:$E, TRUST!$D:$D,DEPARTMENTS!$B:$B, TRUST!$B:$B, AK$12, TRUST!$C:$C, AK$13) -> 5200 | AL4: =SUMIFS(COLLECTION!$E:$E, COLLECTION!$D:$D,DEPARTMENTS!$B:$B, COLLECTION!$B:$B, AL$12, COLLECTION!$C:$C, AL$13) + SUMIFS(BANK!$E:$E, BANK!$D:$D,DEPARTMENTS!$B:$B, BANK!$B:$B, AL$12, BANK!$C:$C, AL$13) + SUMIFS(TRUST!$E:$E, TRUST!$D:$D,DEPARTMENTS!$B:$B, TRUST!$B:$B, AL$12, TRUST!$C:$C, AL$13) -> 4330 | AM4: =SUMIFS(COLLECTION!$E:$E, COLLECTION!$D:$D,DEPARTMENTS!$B:$B, COLLECTION!$B:$B, AM$12, COLLECTION!$C:$C, AM$13) + SUMIFS(BANK!$E:$E, BANK!$D:$D,DEPARTMENTS!$B:$B, BANK!$B:$B, AM$12, BANK!$C:$C, AM$13) + SUMIFS(TRUST!$E:$E, TRUST!$D:$D,DEPARTMENTS!$B:$B, TRUST!$B:$B, AM$12, TRUST!$C:$C, AM$13) -> 6376.5 | AN4: =SUMIFS(COLLECTION!$E:$E, COLLECTION!$D:$D,DEPARTMENTS!$B:$B, COLLECTION!$B:$B, AN$12, COLLECTION!$C:$C, AN$13) + SUMIFS(BANK!$E:$E, BANK!$D:$D,DEPARTMENTS!$B:$B, BANK!$B:$B, AN$12, BANK!$C:$C, AN$13) + SUMIFS(TRUST!$E:$E, TRUST!$D:$D,DEPARTMENTS!$B:$B, TRUST!$B:$B, AN$12, TRUST!$C:$C, AN$13) -> 5617.5 | AO4: =SUMIFS(COLLECTION!$E:$E, COLLECTION!$D:$D,DEPARTMENTS!$B:$B, COLLECTION!$B:$B, AO$12, COLLECTION!$C:$C, AO$13) + SUMIFS(BANK!$E:$E, BANK!$D:$D,DEPARTMENTS!$B:$B, BANK!$B:$B, AO$12, BANK!$C:$C, AO$13) + SUMIFS(TRUST!$E:$E, TRUST!$D:$D,DEPARTMENTS!$B:$B, TRUST!$B:$B, AO$12, TRUST!$C:$C, AO$13) -> 6049 | AP4: =SUMIFS(COLLECTION!$E:$E, COLLECTION!$D:$D,DEPARTMENTS!$B:$B, COLLECTION!$B:$B, AP$12, COLLECTION!$C:$C, AP$13) + SUMIFS(BANK!$E:$E, BANK!$D:$D,DEPARTMENTS!$B:$B, BANK!$B:$B, AP$12, BANK!$C:$C, AP$13) + SUMIFS(TRUST!$E:$E, TRUST!$D:$D,DEPARTMENTS!$B:$B, TRUST!$B:$B, AP$12, TRUST!$C:$C, AP$13) -> 2834.5 | AQ4: =SUMIFS(COLLECTION!$E:$E, COLLECTION!$D:$D,DEPARTMENTS!$B:$B, COLLECTION!$B:$B, AQ$12, COLLECTION!$C:$C, AQ$13) + SUMIFS(BANK!$E:$E, BANK!$D:$D,DEPARTMENTS!$B:$B, BANK!$B:$B, AQ$12, BANK!$C:$C, AQ$13) + SUMIFS(TRUST!$E:$E, TRUST!$D:$D,DEPARTMENTS!$B:$B, TRUST!$B:$B, AQ$12, TRUST!$C:$C, AQ$13) -> 8829.5 | AR4: =SUMIFS(COLLECTION!$E:$E, COLLECTION!$D:$D,DEPARTMENTS!$B:$B, COLLECTION!$B:$B, AR$12, COLLECTION!$C:$C, AR$13) + SUMIFS(BANK!$E:$E, BANK!$D:$D,DEPARTMENTS!$B:$B, BANK!$B:$B, AR$12, BANK!$C:$C, AR$13) + SUMIFS(TRUST!$E:$E, TRUST!$D:$D,DEPARTMENTS!$B:$B, TRUST!$B:$B, AR$12, TRUST!$C:$C, AR$13) -> 3627.5 | ... BC4: =SUMIFS(COLLECTION!$E:$E, COLLECTION!$D:$D,DEPARTMENTS!$B:$B, COLLECTION!$B:$B, BC$12, COLLECTION!$C:$C, BC$13) + SUMIFS(BANK!$E:$E, BANK!$D:$D,DEPARTMENTS!$B:$B, BANK!$B:$B, BC$12, BANK!$C:$C, BC$13) + SUMIFS(TRUST!$E:$E, TRUST!$D:$D,DEPARTMENTS!$B:$B, TRUST!$B:$B, BC$12, TRUST!$C:$C, BC$13) -> 4310 | BE4: =SUMIFS(COLLECTION!$E:$E, COLLECTION!$D:$D,DEPARTMENTS!$B:$B, COLLECTION!$B:$B, BE$12, COLLECTION!$C:$C, BE$13) + SUMIFS(BANK!$E:$E, BANK!$D:$D,DEPARTMENTS!$B:$B, BANK!$B:$B, BE$12, BANK!$C:$C, BE$13) + SUMIFS(TRUST!$E:$E, TRUST!$D:$D,DEPARTMENTS!$B:$B, TRUST!$B:$B, BE$12, TRUST!$C:$C, BE$13) -> 5185 | BF4: =SUMIFS(COLLECTION!$E:$E, COLLECTION!$D:$D,DEPARTMENTS!$B:$B, COLLECTION!$B:$B, BF$12, COLLECTION!$C:$C, BF$13) + SUMIFS(BANK!$E:$E, BANK!$D:$D,DEPARTMENTS!$B:$B, BANK!$B:$B, BF$12, BANK!$C:$C, BF$13) + SUMIFS(TRUST!$E:$E, TRUST!$D:$D,DEPARTMENTS!$B:$B, TRUST!$B:$B, BF$12, TRUST!$C:$C, BF$13) -> 5347 | BG4: =SUMIFS(COLLECTION!$E:$E, COLLECTION!$D:$D,DEPARTMENTS!$B:$B, COLLECTION!$B:$B, BG$12, COLLECTION!$C:$C, BG$13) + SUMIFS(BANK!$E:$E, BANK!$D:$D,DEPARTMENTS!$B:$B, BANK!$B:$B, BG$12, BANK!$C:$C, BG$13) + SUMIFS(TRUST!$E:$E, TRUST!$D:$D,DEPARTMENTS!$B:$B, TRUST!$B:$B, BG$12, TRUST!$C:$C, BG$13) -> 7582.5 | BH4: =SUMIFS(COLLECTION!$E:$E, COLLECTION!$D:$D,DEPARTMENTS!$B:$B, COLLECTION!$B:$B, BH$12, COLLECTION!$C:$C, BH$13) + SUMIFS(BANK!$E:$E, BANK!$D:$D,DEPARTMENTS!$B:$B, BANK!$B:$B, BH$12, BANK!$C:$C, BH$13) + SUMIFS(TRUST!$E:$E, TRUST!$D:$D,DEPARTMENTS!$B:$B, TRUST!$B:$B, BH$12, TRUST!$C:$C, BH$13) -> 2525 | BI4: =SUMIFS(COLLECTION!$E:$E, COLLECTION!$D:$D,DEPARTMENTS!$B:$B, COLLECTION!$B:$B, BI$12, COLLECTION!$C:$C, BI$13) + SUMIFS(BANK!$E:$E, BANK!$D:$D,DEPARTMENTS!$B:$B, BANK!$B:$B, BI$12, BANK!$C:$C, BI$13) + SUMIFS(TRUST!$E:$E, TRUST!$D:$D,DEPARTMENTS!$B:$B, TRUST!$B:$B, BI$12, TRUST!$C:$C, BI$13) -> 2645 | BJ4: =SUMIFS(COLLECTION!$E:$E, COLLECTION!$D:$D,DEPARTMENTS!$B:$B, COLLECTION!$B:$B, BJ$12, COLLECTION!$C:$C, BJ$13) + SUMIFS(BANK!$E:$E, BANK!$D:$D,DEPARTMENTS!$B:$B, BANK!$B:$B, BJ$12, BANK!$C:$C, BJ$13) + SUMIFS(TRUST!$E:$E, TRUST!$D:$D,DEPARTMENTS!$B:$B, TRUST!$B:$B, BJ$12, TRUST!$C:$C, BJ$13) -> 2992.5 | BK4: =SUMIFS(COLLECTION!$E:$E, COLLECTION!$D:$D,DEPARTMENTS!$B:$B, COLLECTION!$B:$B, BK$12, COLLECTION!$C:$C, BK$13) + SUMIFS(BANK!$E:$E, BANK!$D:$D,DEPARTMENTS!$B:$B, BANK!$B:$B, BK$12, BANK!$C:$C, BK$13) + SUMIFS(TRUST!$E:$E, TRUST!$D:$D,DEPARTMENTS!$B:$B, TRUST!$B:$B, BK$12, TRUST!$C:$C, BK$13) -> 0 | BL4: =SUMIFS(COLLECTION!$E:$E, COLLECTION!$D:$D,DEPARTMENTS!$B:$B, COLLECTION!$B:$B, BL$12, COLLECTION!$C:$C, BL$13) + SUMIFS(BANK!$E:$E, BANK!$D:$D,DEPARTMENTS!$B:$B, BANK!$B:$B, BL$12, BANK!$C:$C, BL$13) + SUMIFS(TRUST!$E:$E, TRUST!$D:$D,DEPARTMENTS!$B:$B, TRUST!$B:$B, BL$12, TRUST!$C:$C, BL$13) -> 0 | ... CQ4: =SUMIFS(COLLECTION!$E:$E, COLLECTION!$D:$D,DEPARTMENTS!$B:$B, COLLECTION!$B:$B, CQ$12, COLLECTION!$C:$C, CQ$13) + SUMIFS(BANK!$E:$E, BANK!$D:$D,DEPARTMENTS!$B:$B, BANK!$B:$B, CQ$12, BANK!$C:$C, CQ$13) + SUMIFS(TRUST!$E:$E, TRUST!$D:$D,DEPARTMENTS!$B:$B, TRUST!$B:$B, CQ$12, TRUST!$C:$C, CQ$13) -> 0 | CR4: =SUM(AK4:CQ4) -> 107931.5
B5: THANKGIVING - LCB | C5: 0 | D5: =SUMIF(COLLECTION!D:D,DEPARTMENTS!B:B,COLLECTION!E:E)+SUMIF(BANK!D:D,DEPARTMENTS!B:B,BANK!E:E)+SUMIF(TRUST!D:D,DEPARTMENTS!B:B,TRUST!E:E) -> 39831 | H5: =SUMIFS(COLLECTION!$E:$E, COLLECTION!$D:$D,DEPARTMENTS!$B:$B, COLLECTION!$B:$B, H$13, COLLECTION!$B:$B, H$13) + SUMIFS(BANK!$E:$E, BANK!$D:$D,DEPARTMENTS!$B:$B, BANK!$B:$B, H$13, BANK!$B:$B, H$13) + SUMIFS(TRUST!$E:$E, TRUST!$D:$D,DEPARTMENTS!$B:$B, TRUST!$B:$B, H$13, TRUST!$B:$B, H$13) -> 19141 | I5: =SUMIFS(COLLECTION!$E:$E, COLLECTION!$D:$D,DEPARTMENTS!$B:$B, COLLECTION!$B:$B, I$13, COLLECTION!$B:$B, I$13) + SUMIFS(BANK!$E:$E, BANK!$D:$D,DEPARTMENTS!$B:$B, BANK!$B:$B, I$13, BANK!$B:$B, I$13) + SUMIFS(TRUST!$E:$E, TRUST!$D:$D,DEPARTMENTS!$B:$B, TRUST!$B:$B, I$13, TRUST!$B:$B, I$13) -> 6625 | J5: =SUMIFS(COLLECTION!$E:$E, COLLECTION!$D:$D,DEPARTMENTS!$B:$B, COLLECTION!$B:$B, J$13, COLLECTION!$B:$B, J$13) + SUMIFS(BANK!$E:$E, BANK!$D:$D,DEPARTMENTS!$B:$B, BANK!$B:$B, J$13, BANK!$B:$B, J$13) + SUMIFS(TRUST!$E:$E, TRUST!$D:$D,DEPARTMENTS!$B:$B, TRUST!$B:$B, J$13, TRUST!$B:$B, J$13) -> 3850 | K5: =SUMIFS(COLLECTION!$E:$E, COLLECTION!$D:$D,DEPARTMENTS!$B:$B, COLLECTION!$B:$B, K$13, COLLECTION!$B:$B, K$13) + SUMIFS(BANK!$E:$E, BANK!$D:$D,DEPARTMENTS!$B:$B, BANK!$B:$B, K$13, BANK!$B:$B, K$13) + SUMIFS(TRUST!$E:$E, TRUST!$D:$D,DEPARTMENTS!$B:$B, TRUST!$B:$B, K$13, TRUST!$B:$B, K$13) -> 3815 | L5: =SUMIFS(COLLECTION!$E:$E, COLLECTION!$D:$D,DEPARTMENTS!$B:$B, COLLECTION!$B:$B, L$13, COLLECTION!$B:$B, L$13) + SUMIFS(BANK!$E:$E, BANK!$D:$D,DEPARTMENTS!$B:$B, BANK!$B:$B, L$13, BANK!$B:$B, L$13) + SUMIFS(TRUST!$E:$E, TRUST!$D:$D,DEPARTMENTS!$B:$B, TRUST!$B:$B, L$13, TRUST!$B:$B, L$13) -> 5075 | M5: =SUMIFS(COLLECTION!$E:$E, COLLECTION!$D:$D,DEPARTMENTS!$B:$B, COLLECTION!$B:$B, M$13, COLLECTION!$B:$B, M$13) + SUMIFS(BANK!$E:$E, BANK!$D:$D,DEPARTMENTS!$B:$B, BANK!$B:$B, M$13, BANK!$B:$B, M$13) + SUMIFS(TRUST!$E:$E, TRUST!$D:$D,DEPARTMENTS!$B:$B, TRUST!$B:$B, M$13, TRUST!$B:$B, M$13) -> 1325 | N5: =SUMIFS(COLLECTION!$E:$E, COLLECTION!$D:$D,DEPARTMENTS!$B:$B, COLLECTION!$B:$B, N$13, COLLECTION!$B:$B, N$13) + SUMIFS(BANK!$E:$E, BANK!$D:$D,DEPARTMENTS!$B:$B, BANK!$B:$B, N$13, BANK!$B:$B, N$13) + SUMIFS(TRUST!$E:$E, TRUST!$D:$D,DEPARTMENTS!$B:$B, TRUST!$B:$B, N$13, TRUST!$B:$B, N$13) -> 0 | O5: =SUMIFS(COLLECTION!$E:$E, COLLECTION!$D:$D,DEPARTMENTS!$B:$B, COLLECTION!$B:$B, O$13, COLLECTION!$B:$B, O$13) + SUMIFS(BANK!$E:$E, BANK!$D:$D,DEPARTMENTS!$B:$B, BANK!$B:$B, O$13, BANK!$B:$B, O$13) + SUMIFS(TRUST!$E:$E, TRUST!$D:$D,DEPARTMENTS!$B:$B, TRUST!$B:$B, O$13, TRUST!$B:$B, O$13) -> 0 | ... S5: =SUMIFS(COLLECTION!$E:$E, COLLECTION!$D:$D,DEPARTMENTS!$B:$B, COLLECTION!$B:$B, S$13, COLLECTION!$B:$B, S$13) + SUMIFS(BANK!$E:$E, BANK!$D:$D,DEPARTMENTS!$B:$B, BANK!$B:$B, S$13, BANK!$B:$B, S$13) + SUMIFS(TRUST!$E:$E, TRUST!$D:$D,DEPARTMENTS!$B:$B, TRUST!$B:$B, S$13, TRUST!$B:$B, S$13) -> 0 | T5: =SUM(H5:S5) -> 39831 | AK5: =SUMIFS(COLLECTION!$E:$E, COLLECTION!$D:$D,DEPARTMENTS!$B:$B, COLLECTION!$B:$B, AK$12, COLLECTION!$C:$C, AK$13) + SUMIFS(BANK!$E:$E, BANK!$D:$D,DEPARTMENTS!$B:$B, BANK!$B:$B, AK$12, BANK!$C:$C, AK$13) + SUMIFS(TRUST!$E:$E, TRUST!$D:$D,DEPARTMENTS!$B:$B, TRUST!$B:$B, AK$12, TRUST!$C:$C, AK$13) -> 9591 | AL5: =SUMIFS(COLLECTION!$E:$E, COLLECTION!$D:$D,DEPARTMENTS!$B:$B, COLLECTION!$B:$B, AL$12, COLLECTION!$C:$C, AL$13) + SUMIFS(BANK!$E:$E, BANK!$D:$D,DEPARTMENTS!$B:$B, BANK!$B:$B, AL$12, BANK!$C:$C, AL$13) + SUMIFS(TRUST!$E:$E, TRUST!$D:$D,DEPARTMENTS!$B:$B, TRUST!$B:$B, AL$12, TRUST!$C:$C, AL$13) -> 4650 | AM5: =SUMIFS(COLLECTION!$E:$E, COLLECTION!$D:$D,DEPARTMENTS!$B:$B, COLLECTION!$B:$B, AM$12, COLLECTION!$C:$C, AM$13) + SUMIFS(BANK!$E:$E, BANK!$D:$D,DEPARTMENTS!$B:$B, BANK!$B:$B, AM$12, BANK!$C:$C, AM$13) + SUMIFS(TRUST!$E:$E, TRUST!$D:$D,DEPARTMENTS!$B:$B, TRUST!$B:$B, AM$12, TRUST!$C:$C, AM$13) -> 950 | AN5: =SUMIFS(COLLECTION!$E:$E, COLLECTION!$D:$D,DEPARTMENTS!$B:$B, COLLECTION!$B:$B, AN$12, COLLECTION!$C:$C, AN$13) + SUMIFS(BANK!$E:$E, BANK!$D:$D,DEPARTMENTS!$B:$B, BANK!$B:$B, AN$12, BANK!$C:$C, AN$13) + SUMIFS(TRUST!$E:$E, TRUST!$D:$D,DEPARTMENTS!$B:$B, TRUST!$B:$B, AN$12, TRUST!$C:$C, AN$13) -> 300 | AO5: =SUMIFS(COLLECTION!$E:$E, COLLECTION!$D:$D,DEPARTMENTS!$B:$B, COLLECTION!$B:$B, AO$12, COLLECTION!$C:$C, AO$13) + SUMIFS(BANK!$E:$E, BANK!$D:$D,DEPARTMENTS!$B:$B, BANK!$B:$B, AO$12, BANK!$C:$C, AO$13) + SUMIFS(TRUST!$E:$E, TRUST!$D:$D,DEPARTMENTS!$B:$B, TRUST!$B:$B, AO$12, TRUST!$C:$C, AO$13) -> 3650 | AP5: =SUMIFS(COLLECTION!$E:$E, COLLECTION!$D:$D,DEPARTMENTS!$B:$B, COLLECTION!$B:$B, AP$12, COLLECTION!$C:$C, AP$13) + SUMIFS(BANK!$E:$E, BANK!$D:$D,DEPARTMENTS!$B:$B, BANK!$B:$B, AP$12, BANK!$C:$C, AP$13) + SUMIFS(TRUST!$E:$E, TRUST!$D:$D,DEPARTMENTS!$B:$B, TRUST!$B:$B, AP$12, TRUST!$C:$C, AP$13) -> 2925 | AQ5: =SUMIFS(COLLECTION!$E:$E, COLLECTION!$D:$D,DEPARTMENTS!$B:$B, COLLECTION!$B:$B, AQ$12, COLLECTION!$C:$C, AQ$13) + SUMIFS(BANK!$E:$E, BANK!$D:$D,DEPARTMENTS!$B:$B, BANK!$B:$B, AQ$12, BANK!$C:$C, AQ$13) + SUMIFS(TRUST!$E:$E, TRUST!$D:$D,DEPARTMENTS!$B:$B, TRUST!$B:$B, AQ$12, TRUST!$C:$C, AQ$13) -> 350 | AR5: =SUMIFS(COLLECTION!$E:$E, COLLECTION!$D:$D,DEPARTMENTS!$B:$B, COLLECTION!$B:$B, AR$12, COLLECTION!$C:$C, AR$13) + SUMIFS(BANK!$E:$E, BANK!$D:$D,DEPARTMENTS!$B:$B, BANK!$B:$B, AR$12, BANK!$C:$C, AR$13) + SUMIFS(TRUST!$E:$E, TRUST!$D:$D,DEPARTMENTS!$B:$B, TRUST!$B:$B, AR$12, TRUST!$C:$C, AR$13) -> 2700 | ... BC5: =SUMIFS(COLLECTION!$E:$E, COLLECTION!$D:$D,DEPARTMENTS!$B:$B, COLLECTION!$B:$B, BC$12, COLLECTION!$C:$C, BC$13) + SUMIFS(BANK!$E:$E, BANK!$D:$D,DEPARTMENTS!$B:$B, BANK!$B:$B, BC$12, BANK!$C:$C, BC$13) + SUMIFS(TRUST!$E:$E, TRUST!$D:$D,DEPARTMENTS!$B:$B, TRUST!$B:$B, BC$12, TRUST!$C:$C, BC$13) -> 500 | BE5: =SUMIFS(COLLECTION!$E:$E, COLLECTION!$D:$D,DEPARTMENTS!$B:$B, COLLECTION!$B:$B, BE$12, COLLECTION!$C:$C, BE$13) + SUMIFS(BANK!$E:$E, BANK!$D:$D,DEPARTMENTS!$B:$B, BANK!$B:$B, BE$12, BANK!$C:$C, BE$13) + SUMIFS(TRUST!$E:$E, TRUST!$D:$D,DEPARTMENTS!$B:$B, TRUST!$B:$B, BE$12, TRUST!$C:$C, BE$13) -> 3275 | BF5: =SUMIFS(COLLECTION!$E:$E, COLLECTION!$D:$D,DEPARTMENTS!$B:$B, COLLECTION!$B:$B, BF$12, COLLECTION!$C:$C, BF$13) + SUMIFS(BANK!$E:$E, BANK!$D:$D,DEPARTMENTS!$B:$B, BANK!$B:$B, BF$12, BANK!$C:$C, BF$13) + SUMIFS(TRUST!$E:$E, TRUST!$D:$D,DEPARTMENTS!$B:$B, TRUST!$B:$B, BF$12, TRUST!$C:$C, BF$13) -> 1550 | BG5: =SUMIFS(COLLECTION!$E:$E, COLLECTION!$D:$D,DEPARTMENTS!$B:$B, COLLECTION!$B:$B, BG$12, COLLECTION!$C:$C, BG$13) + SUMIFS(BANK!$E:$E, BANK!$D:$D,DEPARTMENTS!$B:$B, BANK!$B:$B, BG$12, BANK!$C:$C, BG$13) + SUMIFS(TRUST!$E:$E, TRUST!$D:$D,DEPARTMENTS!$B:$B, TRUST!$B:$B, BG$12, TRUST!$C:$C, BG$13) -> 50 | BH5: =SUMIFS(COLLECTION!$E:$E, COLLECTION!$D:$D,DEPARTMENTS!$B:$B, COLLECTION!$B:$B, BH$12, COLLECTION!$C:$C, BH$13) + SUMIFS(BANK!$E:$E, BANK!$D:$D,DEPARTMENTS!$B:$B, BANK!$B:$B, BH$12, BANK!$C:$C, BH$13) + SUMIFS(TRUST!$E:$E, TRUST!$D:$D,DEPARTMENTS!$B:$B, TRUST!$B:$B, BH$12, TRUST!$C:$C, BH$13) -> 50 | BI5: =SUMIFS(COLLECTION!$E:$E, COLLECTION!$D:$D,DEPARTMENTS!$B:$B, COLLECTION!$B:$B, BI$12, COLLECTION!$C:$C, BI$13) + SUMIFS(BANK!$E:$E, BANK!$D:$D,DEPARTMENTS!$B:$B, BANK!$B:$B, BI$12, BANK!$C:$C, BI$13) + SUMIFS(TRUST!$E:$E, TRUST!$D:$D,DEPARTMENTS!$B:$B, TRUST!$B:$B, BI$12, TRUST!$C:$C, BI$13) -> 150 | BJ5: =SUMIFS(COLLECTION!$E:$E, COLLECTION!$D:$D,DEPARTMENTS!$B:$B, COLLECTION!$B:$B, BJ$12, COLLECTION!$C:$C, BJ$13) + SUMIFS(BANK!$E:$E, BANK!$D:$D,DEPARTMENTS!$B:$B, BANK!$B:$B, BJ$12, BANK!$C:$C, BJ$13) + SUMIFS(TRUST!$E:$E, TRUST!$D:$D,DEPARTMENTS!$B:$B, TRUST!$B:$B, BJ$12, TRUST!$C:$C, BJ$13) -> 1325 | BK5: =SUMIFS(COLLECTION!$E:$E, COLLECTION!$D:$D,DEPARTMENTS!$B:$B, COLLECTION!$B:$B, BK$12, COLLECTION!$C:$C, BK$13) + SUMIFS(BANK!$E:$E, BANK!$D:$D,DEPARTMENTS!$B:$B, BANK!$B:$B, BK$12, BANK!$C:$C, BK$13) + SUMIFS(TRUST!$E:$E, TRUST!$D:$D,DEPARTMENTS!$B:$B, TRUST!$B:$B, BK$12, TRUST!$C:$C, BK$13) -> 0 | BL5: =SUMIFS(COLLECTION!$E:$E, COLLECTION!$D:$D,DEPARTMENTS!$B:$B, COLLECTION!$B:$B, BL$12, COLLECTION!$C:$C, BL$13) + SUMIFS(BANK!$E:$E, BANK!$D:$D,DEPARTMENTS!$B:$B, BANK!$B:$B, BL$12, BANK!$C:$C, BL$13) + SUMIFS(TRUST!$E:$E, TRUST!$D:$D,DEPARTMENTS!$B:$B, TRUST!$B:$B, BL$12, TRUST!$C:$C, BL$13) -> 0 | ... CQ5: =SUMIFS(COLLECTION!$E:$E, COLLECTION!$D:$D,DEPARTMENTS!$B:$B, COLLECTION!$B:$B, CQ$12, COLLECTION!$C:$C, CQ$13) + SUMIFS(BANK!$E:$E, BANK!$D:$D,DEPARTMENTS!$B:$B, BANK!$B:$B, CQ$12, BANK!$C:$C, CQ$13) + SUMIFS(TRUST!$E:$E, TRUST!$D:$D,DEPARTMENTS!$B:$B, TRUST!$B:$B, CQ$12, TRUST!$C:$C, CQ$13) -> 0 | CR5: =SUM(AK5:CQ5) -> 39831
B6: LOCAL CHURCH BUDGET | C6: 0 | D6: =SUMIF(COLLECTION!D:D,DEPARTMENTS!B:B,COLLECTION!E:E)+SUMIF(BANK!D:D,DEPARTMENTS!B:B,BANK!E:E)+SUMIF(TRUST!D:D,DEPARTMENTS!B:B,TRUST!E:E) -> 201802 | H6: =SUMIFS(COLLECTION!$E:$E, COLLECTION!$D:$D,DEPARTMENTS!$B:$B, COLLECTION!$B:$B, H$13, COLLECTION!$B:$B, H$13) + SUMIFS(BANK!$E:$E, BANK!$D:$D,DEPARTMENTS!$B:$B, BANK!$B:$B, H$13, BANK!$B:$B, H$13) + SUMIFS(TRUST!$E:$E, TRUST!$D:$D,DEPARTMENTS!$B:$B, TRUST!$B:$B, H$13, TRUST!$B:$B, H$13) -> 54062 | I6: =SUMIFS(COLLECTION!$E:$E, COLLECTION!$D:$D,DEPARTMENTS!$B:$B, COLLECTION!$B:$B, I$13, COLLECTION!$B:$B, I$13) + SUMIFS(BANK!$E:$E, BANK!$D:$D,DEPARTMENTS!$B:$B, BANK!$B:$B, I$13, BANK!$B:$B, I$13) + SUMIFS(TRUST!$E:$E, TRUST!$D:$D,DEPARTMENTS!$B:$B, TRUST!$B:$B, I$13, TRUST!$B:$B, I$13) -> 30890 | J6: =SUMIFS(COLLECTION!$E:$E, COLLECTION!$D:$D,DEPARTMENTS!$B:$B, COLLECTION!$B:$B, J$13, COLLECTION!$B:$B, J$13) + SUMIFS(BANK!$E:$E, BANK!$D:$D,DEPARTMENTS!$B:$B, BANK!$B:$B, J$13, BANK!$B:$B, J$13) + SUMIFS(TRUST!$E:$E, TRUST!$D:$D,DEPARTMENTS!$B:$B, TRUST!$B:$B, J$13, TRUST!$B:$B, J$13) -> 37945 | K6: =SUMIFS(COLLECTION!$E:$E, COLLECTION!$D:$D,DEPARTMENTS!$B:$B, COLLECTION!$B:$B, K$13, COLLECTION!$B:$B, K$13) + SUMIFS(BANK!$E:$E, BANK!$D:$D,DEPARTMENTS!$B:$B, BANK!$B:$B, K$13, BANK!$B:$B, K$13) + SUMIFS(TRUST!$E:$E, TRUST!$D:$D,DEPARTMENTS!$B:$B, TRUST!$B:$B, K$13, TRUST!$B:$B, K$13) -> 23560 | L6: =SUMIFS(COLLECTION!$E:$E, COLLECTION!$D:$D,DEPARTMENTS!$B:$B, COLLECTION!$B:$B, L$13, COLLECTION!$B:$B, L$13) + SUMIFS(BANK!$E:$E, BANK!$D:$D,DEPARTMENTS!$B:$B, BANK!$B:$B, L$13, BANK!$B:$B, L$13) + SUMIFS(TRUST!$E:$E, TRUST!$D:$D,DEPARTMENTS!$B:$B, TRUST!$B:$B, L$13, TRUST!$B:$B, L$13) -> 45495 | M6: =SUMIFS(COLLECTION!$E:$E, COLLECTION!$D:$D,DEPARTMENTS!$B:$B, COLLECTION!$B:$B, M$13, COLLECTION!$B:$B, M$13) + SUMIFS(BANK!$E:$E, BANK!$D:$D,DEPARTMENTS!$B:$B, BANK!$B:$B, M$13, BANK!$B:$B, M$13) + SUMIFS(TRUST!$E:$E, TRUST!$D:$D,DEPARTMENTS!$B:$B, TRUST!$B:$B, M$13, TRUST!$B:$B, M$13) -> 9850 | N6: =SUMIFS(COLLECTION!$E:$E, COLLECTION!$D:$D,DEPARTMENTS!$B:$B, COLLECTION!$B:$B, N$13, COLLECTION!$B:$B, N$13) + SUMIFS(BANK!$E:$E, BANK!$D:$D,DEPARTMENTS!$B:$B, BANK!$B:$B, N$13, BANK!$B:$B, N$13) + SUMIFS(TRUST!$E:$E, TRUST!$D:$D,DEPARTMENTS!$B:$B, TRUST!$B:$B, N$13, TRUST!$B:$B, N$13) -> 0 | O6: =SUMIFS(COLLECTION!$E:$E, COLLECTION!$D:$D,DEPARTMENTS!$B:$B, COLLECTION!$B:$B, O$13, COLLECTION!$B:$B, O$13) + SUMIFS(BANK!$E:$E, BANK!$D:$D,DEPARTMENTS!$B:$B, BANK!$B:$B, O$13, BANK!$B:$B, O$13) + SUMIFS(TRUST!$E:$E, TRUST!$D:$D,DEPARTMENTS!$B:$B, TRUST!$B:$B, O$13, TRUST!$B:$B, O$13) -> 0 | ... S6: =SUMIFS(COLLECTION!$E:$E, COLLECTION!$D:$D,DEPARTMENTS!$B:$B, COLLECTION!$B:$B, S$13, COLLECTION!$B:$B, S$13) + SUMIFS(BANK!$E:$E, BANK!$D:$D,DEPARTMENTS!$B:$B, BANK!$B:$B, S$13, BANK!$B:$B, S$13) + SUMIFS(TRUST!$E:$E, TRUST!$D:$D,DEPARTMENTS!$B:$B, TRUST!$B:$B, S$13, TRUST!$B:$B, S$13) -> 0 | T6: =SUM(H6:S6) -> 201802 | AK6: =SUMIFS(COLLECTION!$E:$E, COLLECTION!$D:$D,DEPARTMENTS!$B:$B, COLLECTION!$B:$B, AK$12, COLLECTION!$C:$C, AK$13) + SUMIFS(BANK!$E:$E, BANK!$D:$D,DEPARTMENTS!$B:$B, BANK!$B:$B, AK$12, BANK!$C:$C, AK$13) + SUMIFS(TRUST!$E:$E, TRUST!$D:$D,DEPARTMENTS!$B:$B, TRUST!$B:$B, AK$12, TRUST!$C:$C, AK$13) -> 8655 | AL6: =SUMIFS(COLLECTION!$E:$E, COLLECTION!$D:$D,DEPARTMENTS!$B:$B, COLLECTION!$B:$B, AL$12, COLLECTION!$C:$C, AL$13) + SUMIFS(BANK!$E:$E, BANK!$D:$D,DEPARTMENTS!$B:$B, BANK!$B:$B, AL$12, BANK!$C:$C, AL$13) + SUMIFS(TRUST!$E:$E, TRUST!$D:$D,DEPARTMENTS!$B:$B, TRUST!$B:$B, AL$12, TRUST!$C:$C, AL$13) -> 12750 | AM6: =SUMIFS(COLLECTION!$E:$E, COLLECTION!$D:$D,DEPARTMENTS!$B:$B, COLLECTION!$B:$B, AM$12, COLLECTION!$C:$C, AM$13) + SUMIFS(BANK!$E:$E, BANK!$D:$D,DEPARTMENTS!$B:$B, BANK!$B:$B, AM$12, BANK!$C:$C, AM$13) + SUMIFS(TRUST!$E:$E, TRUST!$D:$D,DEPARTMENTS!$B:$B, TRUST!$B:$B, AM$12, TRUST!$C:$C, AM$13) -> 5175 | AN6: =SUMIFS(COLLECTION!$E:$E, COLLECTION!$D:$D,DEPARTMENTS!$B:$B, COLLECTION!$B:$B, AN$12, COLLECTION!$C:$C, AN$13) + SUMIFS(BANK!$E:$E, BANK!$D:$D,DEPARTMENTS!$B:$B, BANK!$B:$B, AN$12, BANK!$C:$C, AN$13) + SUMIFS(TRUST!$E:$E, TRUST!$D:$D,DEPARTMENTS!$B:$B, TRUST!$B:$B, AN$12, TRUST!$C:$C, AN$13) -> 7735 | AO6: =SUMIFS(COLLECTION!$E:$E, COLLECTION!$D:$D,DEPARTMENTS!$B:$B, COLLECTION!$B:$B, AO$12, COLLECTION!$C:$C, AO$13) + SUMIFS(BANK!$E:$E, BANK!$D:$D,DEPARTMENTS!$B:$B, BANK!$B:$B, AO$12, BANK!$C:$C, AO$13) + SUMIFS(TRUST!$E:$E, TRUST!$D:$D,DEPARTMENTS!$B:$B, TRUST!$B:$B, AO$12, TRUST!$C:$C, AO$13) -> 19747 | AP6: =SUMIFS(COLLECTION!$E:$E, COLLECTION!$D:$D,DEPARTMENTS!$B:$B, COLLECTION!$B:$B, AP$12, COLLECTION!$C:$C, AP$13) + SUMIFS(BANK!$E:$E, BANK!$D:$D,DEPARTMENTS!$B:$B, BANK!$B:$B, AP$12, BANK!$C:$C, AP$13) + SUMIFS(TRUST!$E:$E, TRUST!$D:$D,DEPARTMENTS!$B:$B, TRUST!$B:$B, AP$12, TRUST!$C:$C, AP$13) -> 4570 | AQ6: =SUMIFS(COLLECTION!$E:$E, COLLECTION!$D:$D,DEPARTMENTS!$B:$B, COLLECTION!$B:$B, AQ$12, COLLECTION!$C:$C, AQ$13) + SUMIFS(BANK!$E:$E, BANK!$D:$D,DEPARTMENTS!$B:$B, BANK!$B:$B, AQ$12, BANK!$C:$C, AQ$13) + SUMIFS(TRUST!$E:$E, TRUST!$D:$D,DEPARTMENTS!$B:$B, TRUST!$B:$B, AQ$12, TRUST!$C:$C, AQ$13) -> 6650 | AR6: =SUMIFS(COLLECTION!$E:$E, COLLECTION!$D:$D,DEPARTMENTS!$B:$B, COLLECTION!$B:$B, AR$12, COLLECTION!$C:$C, AR$13) + SUMIFS(BANK!$E:$E, BANK!$D:$D,DEPARTMENTS!$B:$B, BANK!$B:$B, AR$12, BANK!$C:$C, AR$13) + SUMIFS(TRUST!$E:$E, TRUST!$D:$D,DEPARTMENTS!$B:$B, TRUST!$B:$B, AR$12, TRUST!$C:$C, AR$13) -> 13870 | ... BC6: =SUMIFS(COLLECTION!$E:$E, COLLECTION!$D:$D,DEPARTMENTS!$B:$B, COLLECTION!$B:$B, BC$12, COLLECTION!$C:$C, BC$13) + SUMIFS(BANK!$E:$E, BANK!$D:$D,DEPARTMENTS!$B:$B, BANK!$B:$B, BC$12, BANK!$C:$C, BC$13) + SUMIFS(TRUST!$E:$E, TRUST!$D:$D,DEPARTMENTS!$B:$B, TRUST!$B:$B, BC$12, TRUST!$C:$C, BC$13) -> 7350 | BE6: =SUMIFS(COLLECTION!$E:$E, COLLECTION!$D:$D,DEPARTMENTS!$B:$B, COLLECTION!$B:$B, BE$12, COLLECTION!$C:$C, BE$13) + SUMIFS(BANK!$E:$E, BANK!$D:$D,DEPARTMENTS!$B:$B, BANK!$B:$B, BE$12, BANK!$C:$C, BE$13) + SUMIFS(TRUST!$E:$E, TRUST!$D:$D,DEPARTMENTS!$B:$B, TRUST!$B:$B, BE$12, TRUST!$C:$C, BE$13) -> 6930 | BF6: =SUMIFS(COLLECTION!$E:$E, COLLECTION!$D:$D,DEPARTMENTS!$B:$B, COLLECTION!$B:$B, BF$12, COLLECTION!$C:$C, BF$13) + SUMIFS(BANK!$E:$E, BANK!$D:$D,DEPARTMENTS!$B:$B, BANK!$B:$B, BF$12, BANK!$C:$C, BF$13) + SUMIFS(TRUST!$E:$E, TRUST!$D:$D,DEPARTMENTS!$B:$B, TRUST!$B:$B, BF$12, TRUST!$C:$C, BF$13) -> 28770 | BG6: =SUMIFS(COLLECTION!$E:$E, COLLECTION!$D:$D,DEPARTMENTS!$B:$B, COLLECTION!$B:$B, BG$12, COLLECTION!$C:$C, BG$13) + SUMIFS(BANK!$E:$E, BANK!$D:$D,DEPARTMENTS!$B:$B, BANK!$B:$B, BG$12, BANK!$C:$C, BG$13) + SUMIFS(TRUST!$E:$E, TRUST!$D:$D,DEPARTMENTS!$B:$B, TRUST!$B:$B, BG$12, TRUST!$C:$C, BG$13) -> 4320 | BH6: =SUMIFS(COLLECTION!$E:$E, COLLECTION!$D:$D,DEPARTMENTS!$B:$B, COLLECTION!$B:$B, BH$12, COLLECTION!$C:$C, BH$13) + SUMIFS(BANK!$E:$E, BANK!$D:$D,DEPARTMENTS!$B:$B, BANK!$B:$B, BH$12, BANK!$C:$C, BH$13) + SUMIFS(TRUST!$E:$E, TRUST!$D:$D,DEPARTMENTS!$B:$B, TRUST!$B:$B, BH$12, TRUST!$C:$C, BH$13) -> 3030 | BI6: =SUMIFS(COLLECTION!$E:$E, COLLECTION!$D:$D,DEPARTMENTS!$B:$B, COLLECTION!$B:$B, BI$12, COLLECTION!$C:$C, BI$13) + SUMIFS(BANK!$E:$E, BANK!$D:$D,DEPARTMENTS!$B:$B, BANK!$B:$B, BI$12, BANK!$C:$C, BI$13) + SUMIFS(TRUST!$E:$E, TRUST!$D:$D,DEPARTMENTS!$B:$B, TRUST!$B:$B, BI$12, TRUST!$C:$C, BI$13) -> 2445 | BJ6: =SUMIFS(COLLECTION!$E:$E, COLLECTION!$D:$D,DEPARTMENTS!$B:$B, COLLECTION!$B:$B, BJ$12, COLLECTION!$C:$C, BJ$13) + SUMIFS(BANK!$E:$E, BANK!$D:$D,DEPARTMENTS!$B:$B, BANK!$B:$B, BJ$12, BANK!$C:$C, BJ$13) + SUMIFS(TRUST!$E:$E, TRUST!$D:$D,DEPARTMENTS!$B:$B, TRUST!$B:$B, BJ$12, TRUST!$C:$C, BJ$13) -> 9850 | BK6: =SUMIFS(COLLECTION!$E:$E, COLLECTION!$D:$D,DEPARTMENTS!$B:$B, COLLECTION!$B:$B, BK$12, COLLECTION!$C:$C, BK$13) + SUMIFS(BANK!$E:$E, BANK!$D:$D,DEPARTMENTS!$B:$B, BANK!$B:$B, BK$12, BANK!$C:$C, BK$13) + SUMIFS(TRUST!$E:$E, TRUST!$D:$D,DEPARTMENTS!$B:$B, TRUST!$B:$B, BK$12, TRUST!$C:$C, BK$13) -> 0 | BL6: =SUMIFS(COLLECTION!$E:$E, COLLECTION!$D:$D,DEPARTMENTS!$B:$B, COLLECTION!$B:$B, BL$12, COLLECTION!$C:$C, BL$13) + SUMIFS(BANK!$E:$E, BANK!$D:$D,DEPARTMENTS!$B:$B, BANK!$B:$B, BL$12, BANK!$C:$C, BL$13) + SUMIFS(TRUST!$E:$E, TRUST!$D:$D,DEPARTMENTS!$B:$B, TRUST!$B:$B, BL$12, TRUST!$C:$C, BL$13) -> 0 | ... CQ6: =SUMIFS(COLLECTION!$E:$E, COLLECTION!$D:$D,DEPARTMENTS!$B:$B, COLLECTION!$B:$B, CQ$12, COLLECTION!$C:$C, CQ$13) + SUMIFS(BANK!$E:$E, BANK!$D:$D,DEPARTMENTS!$B:$B, BANK!$B:$B, CQ$12, BANK!$C:$C, CQ$13) + SUMIFS(TRUST!$E:$E, TRUST!$D:$D,DEPARTMENTS!$B:$B, TRUST!$B:$B, CQ$12, TRUST!$C:$C, CQ$13) -> 0 | CR6: =SUM(AK6:CQ6) -> 201802
B7: ENVELOPES | C7: 0 | D7: =SUMIF(COLLECTION!D:D,DEPARTMENTS!B:B,COLLECTION!E:E)+SUMIF(BANK!D:D,DEPARTMENTS!B:B,BANK!E:E)+SUMIF(TRUST!D:D,DEPARTMENTS!B:B,TRUST!E:E)-D69 -> 2190 | E7: =(ABS(D7))/DASHBOARD!B7 -> 0.00023235845 | H7: =SUMIFS(COLLECTION!$E:$E, COLLECTION!$D:$D,DEPARTMENTS!$B:$B, COLLECTION!$B:$B, H$13, COLLECTION!$B:$B, H$13) + SUMIFS(BANK!$E:$E, BANK!$D:$D,DEPARTMENTS!$B:$B, BANK!$B:$B, H$13, BANK!$B:$B, H$13) + SUMIFS(TRUST!$E:$E, TRUST!$D:$D,DEPARTMENTS!$B:$B, TRUST!$B:$B, H$13, TRUST!$B:$B, H$13)-H69 -> 3947 | I7: =SUMIFS(COLLECTION!$E:$E, COLLECTION!$D:$D,DEPARTMENTS!$B:$B, COLLECTION!$B:$B, I$13, COLLECTION!$B:$B, I$13) + SUMIFS(BANK!$E:$E, BANK!$D:$D,DEPARTMENTS!$B:$B, BANK!$B:$B, I$13, BANK!$B:$B, I$13) + SUMIFS(TRUST!$E:$E, TRUST!$D:$D,DEPARTMENTS!$B:$B, TRUST!$B:$B, I$13, TRUST!$B:$B, I$13)-I69 -> 21 | J7: =SUMIFS(COLLECTION!$E:$E, COLLECTION!$D:$D,DEPARTMENTS!$B:$B, COLLECTION!$B:$B, J$13, COLLECTION!$B:$B, J$13) + SUMIFS(BANK!$E:$E, BANK!$D:$D,DEPARTMENTS!$B:$B, BANK!$B:$B, J$13, BANK!$B:$B, J$13) + SUMIFS(TRUST!$E:$E, TRUST!$D:$D,DEPARTMENTS!$B:$B, TRUST!$B:$B, J$13, TRUST!$B:$B, J$13)-J69 -> 14538 | K7: =SUMIFS(COLLECTION!$E:$E, COLLECTION!$D:$D,DEPARTMENTS!$B:$B, COLLECTION!$B:$B, K$13, COLLECTION!$B:$B, K$13) + SUMIFS(BANK!$E:$E, BANK!$D:$D,DEPARTMENTS!$B:$B, BANK!$B:$B, K$13, BANK!$B:$B, K$13) + SUMIFS(TRUST!$E:$E, TRUST!$D:$D,DEPARTMENTS!$B:$B, TRUST!$B:$B, K$13, TRUST!$B:$B, K$13)-K69 -> 19401 | L7: =SUMIFS(COLLECTION!$E:$E, COLLECTION!$D:$D,DEPARTMENTS!$B:$B, COLLECTION!$B:$B, L$13, COLLECTION!$B:$B, L$13) + SUMIFS(BANK!$E:$E, BANK!$D:$D,DEPARTMENTS!$B:$B, BANK!$B:$B, L$13, BANK!$B:$B, L$13) + SUMIFS(TRUST!$E:$E, TRUST!$D:$D,DEPARTMENTS!$B:$B, TRUST!$B:$B, L$13, TRUST!$B:$B, L$13)-L69 -> -4467 | M7: =SUMIFS(COLLECTION!$E:$E, COLLECTION!$D:$D,DEPARTMENTS!$B:$B, COLLECTION!$B:$B, M$13, COLLECTION!$B:$B, M$13) + SUMIFS(BANK!$E:$E, BANK!$D:$D,DEPARTMENTS!$B:$B, BANK!$B:$B, M$13, BANK!$B:$B, M$13) + SUMIFS(TRUST!$E:$E, TRUST!$D:$D,DEPARTMENTS!$B:$B, TRUST!$B:$B, M$13, TRUST!$B:$B, M$13)-M69 -> -31250 | N7: =SUMIFS(COLLECTION!$E:$E, COLLECTION!$D:$D,DEPARTMENTS!$B:$B, COLLECTION!$B:$B, N$13, COLLECTION!$B:$B, N$13) + SUMIFS(BANK!$E:$E, BANK!$D:$D,DEPARTMENTS!$B:$B, BANK!$B:$B, N$13, BANK!$B:$B, N$13) + SUMIFS(TRUST!$E:$E, TRUST!$D:$D,DEPARTMENTS!$B:$B, TRUST!$B:$B, N$13, TRUST!$B:$B, N$13)-N69 -> 0 | O7: =SUMIFS(COLLECTION!$E:$E, COLLECTION!$D:$D,DEPARTMENTS!$B:$B, COLLECTION!$B:$B, O$13, COLLECTION!$B:$B, O$13) + SUMIFS(BANK!$E:$E, BANK!$D:$D,DEPARTMENTS!$B:$B, BANK!$B:$B, O$13, BANK!$B:$B, O$13) + SUMIFS(TRUST!$E:$E, TRUST!$D:$D,DEPARTMENTS!$B:$B, TRUST!$B:$B, O$13, TRUST!$B:$B, O$13)-O69 -> 0 | ... S7: =SUMIFS(COLLECTION!$E:$E, COLLECTION!$D:$D,DEPARTMENTS!$B:$B, COLLECTION!$B:$B, S$13, COLLECTION!$B:$B, S$13) + SUMIFS(BANK!$E:$E, BANK!$D:$D,DEPARTMENTS!$B:$B, BANK!$B:$B, S$13, BANK!$B:$B, S$13) + SUMIFS(TRUST!$E:$E, TRUST!$D:$D,DEPARTMENTS!$B:$B, TRUST!$B:$B, S$13, TRUST!$B:$B, S$13)-S69 -> 0 | T7: =SUM(H7:S7) -> 2190 | AK7: =SUMIFS(COLLECTION!$E:$E, COLLECTION!$D:$D,DEPARTMENTS!$B:$B, COLLECTION!$B:$B, AK$12, COLLECTION!$C:$C, AK$13) + SUMIFS(BANK!$E:$E, BANK!$D:$D,DEPARTMENTS!$B:$B, BANK!$B:$B, AK$12, BANK!$C:$C, AK$13) + SUMIFS(TRUST!$E:$E, TRUST!$D:$D,DEPARTMENTS!$B:$B, TRUST!$B:$B, AK$12, TRUST!$C:$C, AK$13)-AK69 -> 11558 | AL7: =SUMIFS(COLLECTION!$E:$E, COLLECTION!$D:$D,DEPARTMENTS!$B:$B, COLLECTION!$B:$B, AL$12, COLLECTION!$C:$C, AL$13) + SUMIFS(BANK!$E:$E, BANK!$D:$D,DEPARTMENTS!$B:$B, BANK!$B:$B, AL$12, BANK!$C:$C, AL$13) + SUMIFS(TRUST!$E:$E, TRUST!$D:$D,DEPARTMENTS!$B:$B, TRUST!$B:$B, AL$12, TRUST!$C:$C, AL$13)-AL69 -> -11501.5 | AM7: =SUMIFS(COLLECTION!$E:$E, COLLECTION!$D:$D,DEPARTMENTS!$B:$B, COLLECTION!$B:$B, AM$12, COLLECTION!$C:$C, AM$13) + SUMIFS(BANK!$E:$E, BANK!$D:$D,DEPARTMENTS!$B:$B, BANK!$B:$B, AM$12, BANK!$C:$C, AM$13) + SUMIFS(TRUST!$E:$E, TRUST!$D:$D,DEPARTMENTS!$B:$B, TRUST!$B:$B, AM$12, TRUST!$C:$C, AM$13)-AM69 -> 15739 | AN7: =SUMIFS(COLLECTION!$E:$E, COLLECTION!$D:$D,DEPARTMENTS!$B:$B, COLLECTION!$B:$B, AN$12, COLLECTION!$C:$C, AN$13) + SUMIFS(BANK!$E:$E, BANK!$D:$D,DEPARTMENTS!$B:$B, BANK!$B:$B, AN$12, BANK!$C:$C, AN$13) + SUMIFS(TRUST!$E:$E, TRUST!$D:$D,DEPARTMENTS!$B:$B, TRUST!$B:$B, AN$12, TRUST!$C:$C, AN$13)-AN69 -> -19577.5 | AO7: =SUMIFS(COLLECTION!$E:$E, COLLECTION!$D:$D,DEPARTMENTS!$B:$B, COLLECTION!$B:$B, AO$12, COLLECTION!$C:$C, AO$13) + SUMIFS(BANK!$E:$E, BANK!$D:$D,DEPARTMENTS!$B:$B, BANK!$B:$B, AO$12, BANK!$C:$C, AO$13) + SUMIFS(TRUST!$E:$E, TRUST!$D:$D,DEPARTMENTS!$B:$B, TRUST!$B:$B, AO$12, TRUST!$C:$C, AO$13)-AO69 -> 7729 | AP7: =SUMIFS(COLLECTION!$E:$E, COLLECTION!$D:$D,DEPARTMENTS!$B:$B, COLLECTION!$B:$B, AP$12, COLLECTION!$C:$C, AP$13) + SUMIFS(BANK!$E:$E, BANK!$D:$D,DEPARTMENTS!$B:$B, BANK!$B:$B, AP$12, BANK!$C:$C, AP$13) + SUMIFS(TRUST!$E:$E, TRUST!$D:$D,DEPARTMENTS!$B:$B, TRUST!$B:$B, AP$12, TRUST!$C:$C, AP$13)-AP69 -> 145 | AQ7: =SUMIFS(COLLECTION!$E:$E, COLLECTION!$D:$D,DEPARTMENTS!$B:$B, COLLECTION!$B:$B, AQ$12, COLLECTION!$C:$C, AQ$13) + SUMIFS(BANK!$E:$E, BANK!$D:$D,DEPARTMENTS!$B:$B, BANK!$B:$B, AQ$12, BANK!$C:$C, AQ$13) + SUMIFS(TRUST!$E:$E, TRUST!$D:$D,DEPARTMENTS!$B:$B, TRUST!$B:$B, AQ$12, TRUST!$C:$C, AQ$13)-AQ69 -> -580 | AR7: =SUMIFS(COLLECTION!$E:$E, COLLECTION!$D:$D,DEPARTMENTS!$B:$B, COLLECTION!$B:$B, AR$12, COLLECTION!$C:$C, AR$13) + SUMIFS(BANK!$E:$E, BANK!$D:$D,DEPARTMENTS!$B:$B, BANK!$B:$B, AR$12, BANK!$C:$C, AR$13) + SUMIFS(TRUST!$E:$E, TRUST!$D:$D,DEPARTMENTS!$B:$B, TRUST!$B:$B, AR$12, TRUST!$C:$C, AR$13)-AR69 -> 3700 | ... BC7: =SUMIFS(COLLECTION!$E:$E, COLLECTION!$D:$D,DEPARTMENTS!$B:$B, COLLECTION!$B:$B, BC$12, COLLECTION!$C:$C, BC$13) + SUMIFS(BANK!$E:$E, BANK!$D:$D,DEPARTMENTS!$B:$B, BANK!$B:$B, BC$12, BANK!$C:$C, BC$13) + SUMIFS(TRUST!$E:$E, TRUST!$D:$D,DEPARTMENTS!$B:$B, TRUST!$B:$B, BC$12, TRUST!$C:$C, BC$13)-BC69 -> 501 | BE7: =SUMIFS(COLLECTION!$E:$E, COLLECTION!$D:$D,DEPARTMENTS!$B:$B, COLLECTION!$B:$B, BE$12, COLLECTION!$C:$C, BE$13) + SUMIFS(BANK!$E:$E, BANK!$D:$D,DEPARTMENTS!$B:$B, BANK!$B:$B, BE$12, BANK!$C:$C, BE$13) + SUMIFS(TRUST!$E:$E, TRUST!$D:$D,DEPARTMENTS!$B:$B, TRUST!$B:$B, BE$12, TRUST!$C:$C, BE$13)-BE69 -> -29475 | BF7: =SUMIFS(COLLECTION!$E:$E, COLLECTION!$D:$D,DEPARTMENTS!$B:$B, COLLECTION!$B:$B, BF$12, COLLECTION!$C:$C, BF$13) + SUMIFS(BANK!$E:$E, BANK!$D:$D,DEPARTMENTS!$B:$B, BANK!$B:$B, BF$12, BANK!$C:$C, BF$13) + SUMIFS(TRUST!$E:$E, TRUST!$D:$D,DEPARTMENTS!$B:$B, TRUST!$B:$B, BF$12, TRUST!$C:$C, BF$13)-BF69 -> -7235 | BG7: =SUMIFS(COLLECTION!$E:$E, COLLECTION!$D:$D,DEPARTMENTS!$B:$B, COLLECTION!$B:$B, BG$12, COLLECTION!$C:$C, BG$13) + SUMIFS(BANK!$E:$E, BANK!$D:$D,DEPARTMENTS!$B:$B, BANK!$B:$B, BG$12, BANK!$C:$C, BG$13) + SUMIFS(TRUST!$E:$E, TRUST!$D:$D,DEPARTMENTS!$B:$B, TRUST!$B:$B, BG$12, TRUST!$C:$C, BG$13)-BG69 -> -10780 | BH7: =SUMIFS(COLLECTION!$E:$E, COLLECTION!$D:$D,DEPARTMENTS!$B:$B, COLLECTION!$B:$B, BH$12, COLLECTION!$C:$C, BH$13) + SUMIFS(BANK!$E:$E, BANK!$D:$D,DEPARTMENTS!$B:$B, BANK!$B:$B, BH$12, BANK!$C:$C, BH$13) + SUMIFS(TRUST!$E:$E, TRUST!$D:$D,DEPARTMENTS!$B:$B, TRUST!$B:$B, BH$12, TRUST!$C:$C, BH$13)-BH69 -> 10005 | BI7: =SUMIFS(COLLECTION!$E:$E, COLLECTION!$D:$D,DEPARTMENTS!$B:$B, COLLECTION!$B:$B, BI$12, COLLECTION!$C:$C, BI$13) + SUMIFS(BANK!$E:$E, BANK!$D:$D,DEPARTMENTS!$B:$B, BANK!$B:$B, BI$12, BANK!$C:$C, BI$13) + SUMIFS(TRUST!$E:$E, TRUST!$D:$D,DEPARTMENTS!$B:$B, TRUST!$B:$B, BI$12, TRUST!$C:$C, BI$13)-BI69 -> 33018 | BJ7: =SUMIFS(COLLECTION!$E:$E, COLLECTION!$D:$D,DEPARTMENTS!$B:$B, COLLECTION!$B:$B, BJ$12, COLLECTION!$C:$C, BJ$13) + SUMIFS(BANK!$E:$E, BANK!$D:$D,DEPARTMENTS!$B:$B, BANK!$B:$B, BJ$12, BANK!$C:$C, BJ$13) + SUMIFS(TRUST!$E:$E, TRUST!$D:$D,DEPARTMENTS!$B:$B, TRUST!$B:$B, BJ$12, TRUST!$C:$C, BJ$13)-BJ69 -> -19442.5 | BK7: =SUMIFS(COLLECTION!$E:$E, COLLECTION!$D:$D,DEPARTMENTS!$B:$B, COLLECTION!$B:$B, BK$12, COLLECTION!$C:$C, BK$13) + SUMIFS(BANK!$E:$E, BANK!$D:$D,DEPARTMENTS!$B:$B, BANK!$B:$B, BK$12, BANK!$C:$C, BK$13) + SUMIFS(TRUST!$E:$E, TRUST!$D:$D,DEPARTMENTS!$B:$B, TRUST!$B:$B, BK$12, TRUST!$C:$C, BK$13)-BK69 -> 0 | BL7: =SUMIFS(COLLECTION!$E:$E, COLLECTION!$D:$D,DEPARTMENTS!$B:$B, COLLECTION!$B:$B, BL$12, COLLECTION!$C:$C, BL$13) + SUMIFS(BANK!$E:$E, BANK!$D:$D,DEPARTMENTS!$B:$B, BANK!$B:$B, BL$12, BANK!$C:$C, BL$13) + SUMIFS(TRUST!$E:$E, TRUST!$D:$D,DEPARTMENTS!$B:$B, TRUST!$B:$B, BL$12, TRUST!$C:$C, BL$13)-BL69 -> 0 | ... CQ7: =SUMIFS(COLLECTION!$E:$E, COLLECTION!$D:$D,DEPARTMENTS!$B:$B, COLLECTION!$B:$B, CQ$12, COLLECTION!$C:$C, CQ$13) + SUMIFS(BANK!$E:$E, BANK!$D:$D,DEPARTMENTS!$B:$B, BANK!$B:$B, CQ$12, BANK!$C:$C, CQ$13) + SUMIFS(TRUST!$E:$E, TRUST!$D:$D,DEPARTMENTS!$B:$B, TRUST!$B:$B, CQ$12, TRUST!$C:$C, CQ$13)-CQ69 -> 0 | CR7: =SUM(AK7:CQ7) -> -15322.5
B8: LCB_DEPARTMENTS | C8: 0 | D8: =SUMIF(COLLECTION!D:D,DEPARTMENTS!B:B,COLLECTION!E:E)+SUMIF(BANK!D:D,DEPARTMENTS!B:B,BANK!E:E)+SUMIF(TRUST!D:D,DEPARTMENTS!B:B,TRUST!E:E)-D70 -> 41783 | H8: =SUMIFS(COLLECTION!$E:$E, COLLECTION!$D:$D,DEPARTMENTS!$B:$B, COLLECTION!$B:$B, H$13, COLLECTION!$B:$B, H$13) + SUMIFS(BANK!$E:$E, BANK!$D:$D,DEPARTMENTS!$B:$B, BANK!$B:$B, H$13, BANK!$B:$B, H$13) + SUMIFS(TRUST!$E:$E, TRUST!$D:$D,DEPARTMENTS!$B:$B, TRUST!$B:$B, H$13, TRUST!$B:$B, H$13)-H70 -> 0 | I8: =SUMIFS(COLLECTION!$E:$E, COLLECTION!$D:$D,DEPARTMENTS!$B:$B, COLLECTION!$B:$B, I$13, COLLECTION!$B:$B, I$13) + SUMIFS(BANK!$E:$E, BANK!$D:$D,DEPARTMENTS!$B:$B, BANK!$B:$B, I$13, BANK!$B:$B, I$13) + SUMIFS(TRUST!$E:$E, TRUST!$D:$D,DEPARTMENTS!$B:$B, TRUST!$B:$B, I$13, TRUST!$B:$B, I$13)-I70 -> 0 | J8: =SUMIFS(COLLECTION!$E:$E, COLLECTION!$D:$D,DEPARTMENTS!$B:$B, COLLECTION!$B:$B, J$13, COLLECTION!$B:$B, J$13) + SUMIFS(BANK!$E:$E, BANK!$D:$D,DEPARTMENTS!$B:$B, BANK!$B:$B, J$13, BANK!$B:$B, J$13) + SUMIFS(TRUST!$E:$E, TRUST!$D:$D,DEPARTMENTS!$B:$B, TRUST!$B:$B, J$13, TRUST!$B:$B, J$13)-J70 -> 7139 | K8: =SUMIFS(COLLECTION!$E:$E, COLLECTION!$D:$D,DEPARTMENTS!$B:$B, COLLECTION!$B:$B, K$13, COLLECTION!$B:$B, K$13) + SUMIFS(BANK!$E:$E, BANK!$D:$D,DEPARTMENTS!$B:$B, BANK!$B:$B, K$13, BANK!$B:$B, K$13) + SUMIFS(TRUST!$E:$E, TRUST!$D:$D,DEPARTMENTS!$B:$B, TRUST!$B:$B, K$13, TRUST!$B:$B, K$13)-K70 -> 34644 | L8: =SUMIFS(COLLECTION!$E:$E, COLLECTION!$D:$D,DEPARTMENTS!$B:$B, COLLECTION!$B:$B, L$13, COLLECTION!$B:$B, L$13) + SUMIFS(BANK!$E:$E, BANK!$D:$D,DEPARTMENTS!$B:$B, BANK!$B:$B, L$13, BANK!$B:$B, L$13) + SUMIFS(TRUST!$E:$E, TRUST!$D:$D,DEPARTMENTS!$B:$B, TRUST!$B:$B, L$13, TRUST!$B:$B, L$13)-L70 -> 0 | M8: =SUMIFS(COLLECTION!$E:$E, COLLECTION!$D:$D,DEPARTMENTS!$B:$B, COLLECTION!$B:$B, M$13, COLLECTION!$B:$B, M$13) + SUMIFS(BANK!$E:$E, BANK!$D:$D,DEPARTMENTS!$B:$B, BANK!$B:$B, M$13, BANK!$B:$B, M$13) + SUMIFS(TRUST!$E:$E, TRUST!$D:$D,DEPARTMENTS!$B:$B, TRUST!$B:$B, M$13, TRUST!$B:$B, M$13)-M70 -> 0 | N8: =SUMIFS(COLLECTION!$E:$E, COLLECTION!$D:$D,DEPARTMENTS!$B:$B, COLLECTION!$B:$B, N$13, COLLECTION!$B:$B, N$13) + SUMIFS(BANK!$E:$E, BANK!$D:$D,DEPARTMENTS!$B:$B, BANK!$B:$B, N$13, BANK!$B:$B, N$13) + SUMIFS(TRUST!$E:$E, TRUST!$D:$D,DEPARTMENTS!$B:$B, TRUST!$B:$B, N$13, TRUST!$B:$B, N$13)-N70 -> 0 | O8: =SUMIFS(COLLECTION!$E:$E, COLLECTION!$D:$D,DEPARTMENTS!$B:$B, COLLECTION!$B:$B, O$13, COLLECTION!$B:$B, O$13) + SUMIFS(BANK!$E:$E, BANK!$D:$D,DEPARTMENTS!$B:$B, BANK!$B:$B, O$13, BANK!$B:$B, O$13) + SUMIFS(TRUST!$E:$E, TRUST!$D:$D,DEPARTMENTS!$B:$B, TRUST!$B:$B, O$13, TRUST!$B:$B, O$13)-O70 -> 0 | ... S8: =SUMIFS(COLLECTION!$E:$E, COLLECTION!$D:$D,DEPARTMENTS!$B:$B, COLLECTION!$B:$B, S$13, COLLECTION!$B:$B, S$13) + SUMIFS(BANK!$E:$E, BANK!$D:$D,DEPARTMENTS!$B:$B, BANK!$B:$B, S$13, BANK!$B:$B, S$13) + SUMIFS(TRUST!$E:$E, TRUST!$D:$D,DEPARTMENTS!$B:$B, TRUST!$B:$B, S$13, TRUST!$B:$B, S$13)-S70 -> 0 | T8: =SUM(H8:S8) -> 41783 | AK8: =SUMIFS(COLLECTION!$E:$E, COLLECTION!$D:$D,DEPARTMENTS!$B:$B, COLLECTION!$B:$B, AK$12, COLLECTION!$C:$C, AK$13) + SUMIFS(BANK!$E:$E, BANK!$D:$D,DEPARTMENTS!$B:$B, BANK!$B:$B, AK$12, BANK!$C:$C, AK$13) + SUMIFS(TRUST!$E:$E, TRUST!$D:$D,DEPARTMENTS!$B:$B, TRUST!$B:$B, AK$12, TRUST!$C:$C, AK$13) -> 0 | AL8: =SUMIFS(COLLECTION!$E:$E, COLLECTION!$D:$D,DEPARTMENTS!$B:$B, COLLECTION!$B:$B, AL$12, COLLECTION!$C:$C, AL$13) + SUMIFS(BANK!$E:$E, BANK!$D:$D,DEPARTMENTS!$B:$B, BANK!$B:$B, AL$12, BANK!$C:$C, AL$13) + SUMIFS(TRUST!$E:$E, TRUST!$D:$D,DEPARTMENTS!$B:$B, TRUST!$B:$B, AL$12, TRUST!$C:$C, AL$13) -> 0 | AM8: =SUMIFS(COLLECTION!$E:$E, COLLECTION!$D:$D,DEPARTMENTS!$B:$B, COLLECTION!$B:$B, AM$12, COLLECTION!$C:$C, AM$13) + SUMIFS(BANK!$E:$E, BANK!$D:$D,DEPARTMENTS!$B:$B, BANK!$B:$B, AM$12, BANK!$C:$C, AM$13) + SUMIFS(TRUST!$E:$E, TRUST!$D:$D,DEPARTMENTS!$B:$B, TRUST!$B:$B, AM$12, TRUST!$C:$C, AM$13) -> 0 | AN8: =SUMIFS(COLLECTION!$E:$E, COLLECTION!$D:$D,DEPARTMENTS!$B:$B, COLLECTION!$B:$B, AN$12, COLLECTION!$C:$C, AN$13) + SUMIFS(BANK!$E:$E, BANK!$D:$D,DEPARTMENTS!$B:$B, BANK!$B:$B, AN$12, BANK!$C:$C, AN$13) + SUMIFS(TRUST!$E:$E, TRUST!$D:$D,DEPARTMENTS!$B:$B, TRUST!$B:$B, AN$12, TRUST!$C:$C, AN$13) -> 0 | AO8: =SUMIFS(COLLECTION!$E:$E, COLLECTION!$D:$D,DEPARTMENTS!$B:$B, COLLECTION!$B:$B, AO$12, COLLECTION!$C:$C, AO$13) + SUMIFS(BANK!$E:$E, BANK!$D:$D,DEPARTMENTS!$B:$B, BANK!$B:$B, AO$12, BANK!$C:$C, AO$13) + SUMIFS(TRUST!$E:$E, TRUST!$D:$D,DEPARTMENTS!$B:$B, TRUST!$B:$B, AO$12, TRUST!$C:$C, AO$13) -> 0 | AP8: =SUMIFS(COLLECTION!$E:$E, COLLECTION!$D:$D,DEPARTMENTS!$B:$B, COLLECTION!$B:$B, AP$12, COLLECTION!$C:$C, AP$13) + SUMIFS(BANK!$E:$E, BANK!$D:$D,DEPARTMENTS!$B:$B, BANK!$B:$B, AP$12, BANK!$C:$C, AP$13) + SUMIFS(TRUST!$E:$E, TRUST!$D:$D,DEPARTMENTS!$B:$B, TRUST!$B:$B, AP$12, TRUST!$C:$C, AP$13) -> 0 | AQ8: =SUMIFS(COLLECTION!$E:$E, COLLECTION!$D:$D,DEPARTMENTS!$B:$B, COLLECTION!$B:$B, AQ$12, COLLECTION!$C:$C, AQ$13) + SUMIFS(BANK!$E:$E, BANK!$D:$D,DEPARTMENTS!$B:$B, BANK!$B:$B, AQ$12, BANK!$C:$C, AQ$13) + SUMIFS(TRUST!$E:$E, TRUST!$D:$D,DEPARTMENTS!$B:$B, TRUST!$B:$B, AQ$12, TRUST!$C:$C, AQ$13) -> 0 | AR8: =SUMIFS(COLLECTION!$E:$E, COLLECTION!$D:$D,DEPARTMENTS!$B:$B, COLLECTION!$B:$B, AR$12, COLLECTION!$C:$C, AR$13) + SUMIFS(BANK!$E:$E, BANK!$D:$D,DEPARTMENTS!$B:$B, BANK!$B:$B, AR$12, BANK!$C:$C, AR$13) + SUMIFS(TRUST!$E:$E, TRUST!$D:$D,DEPARTMENTS!$B:$B, TRUST!$B:$B, AR$12, TRUST!$C:$C, AR$13) -> 0 | ... BC8: =SUMIFS(COLLECTION!$E:$E, COLLECTION!$D:$D,DEPARTMENTS!$B:$B, COLLECTION!$B:$B, BC$12, COLLECTION!$C:$C, BC$13) + SUMIFS(BANK!$E:$E, BANK!$D:$D,DEPARTMENTS!$B:$B, BANK!$B:$B, BC$12, BANK!$C:$C, BC$13) + SUMIFS(TRUST!$E:$E, TRUST!$D:$D,DEPARTMENTS!$B:$B, TRUST!$B:$B, BC$12, TRUST!$C:$C, BC$13) -> 34644 | BE8: =SUMIFS(COLLECTION!$E:$E, COLLECTION!$D:$D,DEPARTMENTS!$B:$B, COLLECTION!$B:$B, BE$12, COLLECTION!$C:$C, BE$13) + SUMIFS(BANK!$E:$E, BANK!$D:$D,DEPARTMENTS!$B:$B, BANK!$B:$B, BE$12, BANK!$C:$C, BE$13) + SUMIFS(TRUST!$E:$E, TRUST!$D:$D,DEPARTMENTS!$B:$B, TRUST!$B:$B, BE$12, TRUST!$C:$C, BE$13) -> 0 | BF8: =SUMIFS(COLLECTION!$E:$E, COLLECTION!$D:$D,DEPARTMENTS!$B:$B, COLLECTION!$B:$B, BF$12, COLLECTION!$C:$C, BF$13) + SUMIFS(BANK!$E:$E, BANK!$D:$D,DEPARTMENTS!$B:$B, BANK!$B:$B, BF$12, BANK!$C:$C, BF$13) + SUMIFS(TRUST!$E:$E, TRUST!$D:$D,DEPARTMENTS!$B:$B, TRUST!$B:$B, BF$12, TRUST!$C:$C, BF$13) -> 0 | BG8: =SUMIFS(COLLECTION!$E:$E, COLLECTION!$D:$D,DEPARTMENTS!$B:$B, COLLECTION!$B:$B, BG$12, COLLECTION!$C:$C, BG$13) + SUMIFS(BANK!$E:$E, BANK!$D:$D,DEPARTMENTS!$B:$B, BANK!$B:$B, BG$12, BANK!$C:$C, BG$13) + SUMIFS(TRUST!$E:$E, TRUST!$D:$D,DEPARTMENTS!$B:$B, TRUST!$B:$B, BG$12, TRUST!$C:$C, BG$13) -> 0 | BH8: =SUMIFS(COLLECTION!$E:$E, COLLECTION!$D:$D,DEPARTMENTS!$B:$B, COLLECTION!$B:$B, BH$12, COLLECTION!$C:$C, BH$13) + SUMIFS(BANK!$E:$E, BANK!$D:$D,DEPARTMENTS!$B:$B, BANK!$B:$B, BH$12, BANK!$C:$C, BH$13) + SUMIFS(TRUST!$E:$E, TRUST!$D:$D,DEPARTMENTS!$B:$B, TRUST!$B:$B, BH$12, TRUST!$C:$C, BH$13) -> 0 | BI8: =SUMIFS(COLLECTION!$E:$E, COLLECTION!$D:$D,DEPARTMENTS!$B:$B, COLLECTION!$B:$B, BI$12, COLLECTION!$C:$C, BI$13) + SUMIFS(BANK!$E:$E, BANK!$D:$D,DEPARTMENTS!$B:$B, BANK!$B:$B, BI$12, BANK!$C:$C, BI$13) + SUMIFS(TRUST!$E:$E, TRUST!$D:$D,DEPARTMENTS!$B:$B, TRUST!$B:$B, BI$12, TRUST!$C:$C, BI$13) -> 0 | BJ8: =SUMIFS(COLLECTION!$E:$E, COLLECTION!$D:$D,DEPARTMENTS!$B:$B, COLLECTION!$B:$B, BJ$12, COLLECTION!$C:$C, BJ$13) + SUMIFS(BANK!$E:$E, BANK!$D:$D,DEPARTMENTS!$B:$B, BANK!$B:$B, BJ$12, BANK!$C:$C, BJ$13) + SUMIFS(TRUST!$E:$E, TRUST!$D:$D,DEPARTMENTS!$B:$B, TRUST!$B:$B, BJ$12, TRUST!$C:$C, BJ$13) -> 0 | BK8: =SUMIFS(COLLECTION!$E:$E, COLLECTION!$D:$D,DEPARTMENTS!$B:$B, COLLECTION!$B:$B, BK$12, COLLECTION!$C:$C, BK$13) + SUMIFS(BANK!$E:$E, BANK!$D:$D,DEPARTMENTS!$B:$B, BANK!$B:$B, BK$12, BANK!$C:$C, BK$13) + SUMIFS(TRUST!$E:$E, TRUST!$D:$D,DEPARTMENTS!$B:$B, TRUST!$B:$B, BK$12, TRUST!$C:$C, BK$13) -> 0 | BL8: =SUMIFS(COLLECTION!$E:$E, COLLECTION!$D:$D,DEPARTMENTS!$B:$B, COLLECTION!$B:$B, BL$12, COLLECTION!$C:$C, BL$13) + SUMIFS(BANK!$E:$E, BANK!$D:$D,DEPARTMENTS!$B:$B, BANK!$B:$B, BL$12, BANK!$C:$C, BL$13) + SUMIFS(TRUST!$E:$E, TRUST!$D:$D,DEPARTMENTS!$B:$B, TRUST!$B:$B, BL$12, TRUST!$C:$C, BL$13) -> 0 | ... CQ8: =SUMIFS(COLLECTION!$E:$E, COLLECTION!$D:$D,DEPARTMENTS!$B:$B, COLLECTION!$B:$B, CQ$12, COLLECTION!$C:$C, CQ$13) + SUMIFS(BANK!$E:$E, BANK!$D:$D,DEPARTMENTS!$B:$B, BANK!$B:$B, CQ$12, BANK!$C:$C, CQ$13) + SUMIFS(TRUST!$E:$E, TRUST!$D:$D,DEPARTMENTS!$B:$B, TRUST!$B:$B, CQ$12, TRUST!$C:$C, CQ$13) -> 0 | CR8: =SUM(AK8:CQ8) -> 41783
B9: LCB | D9: =SUM(D2:D8) -> 573836.5 | H9: =SUM(H2:H8) -> 149952 | I9: =SUM(I2:I8) -> 85180.5 | J9: =SUM(J2:J8) -> 103027.5 | K9: =SUM(K2:K8) -> 137285.5 | L9: =SUM(L2:L8) -> 107352.5 | M9: =SUM(M2:M8) -> -8961.5 | N9: =SUM(N2:N8) -> 0 | O9: =SUM(O2:O8) -> 0 | ... T9: =SUM(T2:T8) -> 573836.5 | AK9: =SUM(AK2:AK8) -> 55351 | AL9: =SUM(AL2:AL8) -> 19805.5 | AM9: =SUM(AM2:AM8) -> 36780.5 | AN9: =SUM(AN2:AN8) -> 840 | AO9: =SUM(AO2:AO8) -> 37175 | AP9: =SUM(AP2:AP8) -> 17719.5 | AQ9: =SUM(AQ2:AQ8) -> 22342.5 | AR9: =SUM(AR2:AR8) -> 30702.5 | ... BC9: =SUM(BC2:BC8) -> 56790 | BE9: =SUM(BE2:BE8) -> -4780 | BF9: =SUM(BF2:BF8) -> 37207 | BG9: =SUM(BG2:BG8) -> 6997.5 | BH9: =SUM(BH2:BH8) -> 23355 | BI9: =SUM(BI2:BI8) -> 44573 | BJ9: =SUM(BJ2:BJ8) -> -5175 | BK9: =SUM(BK2:BK8) -> 0 | BL9: =SUM(BL2:BL8) -> 0 | ... CR9: =SUM(CR2:CR8) -> 548303
AI11: COLLECTIONS | AJ11: PER | AK11: PERIOD
G12: COLLECTIONS | U12: EXPENSES | AK12: JAN | AL12: JAN | AM12: JAN | AN12: JAN | AO12: JAN | AP12: FEB | AQ12: FEB | AR12: FEB | AS12: FEB | AT12: FEB | AU12: MAR | AV12: MAR | AW12: MAR | AX12: MAR | AY12: MAR | AZ12: APR | BA12: APR | BB12: APR | BC12: APR | BD12: APR | BE12: MAY | BF12: MAY | BG12: MAY | BH12: MAY | BI12: MAY | BJ12: JUN | BK12: JUN | BL12: JUN | BM12: JUN | BN12: JUN | BO12: JUL | BP12: JUL | BQ12: JUL | BR12: JUL | BS12: JUL | BT12: AUG | BU12: AUG | BV12: AUG | BW12: AUG | BX12: AUG | BY12: SEP | BZ12: SEP | CA12: SEP | CB12: SEP | CC12: SEP | CD12: OCT | CE12: OCT | CF12: OCT | CG12: OCT | CH12: OCT | CI12: NOV | CJ12: NOV | CK12: NOV | CL12: NOV | CM12: NOV | CN12: DEC | CO12: DEC | CP12: DEC | CQ12: DEC | CR12: TOTAL
A13: ID | B13: NAME | C13: B/F | D13: COLLECTIONS | E13: EXPENSES | F13: BALANCE | H13: JAN | I13: FEB | J13: MAR | K13: APR | L13: MAY | M13: JUN | N13: JUL | O13: AUG | P13: SEP | Q13: OCT | R13: NOV | S13: DEC | T13: TOTAL | V13: JAN | W13: FEB | X13: MAR | Y13: APR | Z13: MAY | AA13: JUN | AB13: JUL | AC13: AUG | AD13: SEP | AE13: OCT | AF13: NOV | AG13: DEC | AH13: TOTAL | AK13: 1 | AL13: 2 | AM13: 3 | AN13: 4 | AO13: 5 | AP13: 1 | AQ13: 2 | AR13: 3 | AS13: 4 | AT13: 5 | AU13: 1 | AV13: 2 | AW13: 3 | AX13: 4 | AY13: 5 | AZ13: 1 | BA13: 2 | BB13: 3 | BC13: 4 | BD13: 5 | BE13: 1 | BF13: 2 | BG13: 3 | BH13: 4 | BI13: 5 | BJ13: 1 | BK13: 2 | BL13: 3 | BM13: 4 | BN13: 5 | BO13: 1 | BP13: 2 | BQ13: 3 | BR13: 4 | BS13: 5 | BT13: 1 | BU13: 2 | BV13: 3 | BW13: 4 | BX13: 5 | BY13: 1 | BZ13: 2 | CA13: 3 | CB13: 4 | CC13: 5 | CD13: 1 | CE13: 2 | CF13: 3 | CG13: 4 | CH13: 5 | CI13: 1 | CJ13: 2 | CK13: 3 | CL13: 4 | CM13: 5 | CN13: 1 | CO13: 2 | CP13: 3 | CQ13: 4
B14: LCB | C14: =-116800.030000001-2604-33+797+53462.72+66984.1+8443+3000+3068+26073 -> 42390.79 | D14: =D9 -> 573836.5 | E14: =SUMIF(EXPENSES!D:D,DEPARTMENTS!B:B,EXPENSES!F:F) -> 731331.8 | F14: =D14-E14+C14 -> -115104.51 | H14: =H9 -> 149952 | I14: =I9 -> 85180.5 | J14: =J9 -> 103027.5 | K14: =K9 -> 137285.5 | L14: =L9 -> 107352.5 | M14: =M9 -> -8961.5 | N14: =N9 -> 0 | O14: =O9 -> 0 | ... S14: =S9 -> 0 | T14: =SUM(H14:S14) -> 573836.5 | V14: =SUMIFS(EXPENSES!$F:$F, EXPENSES!$D:$D,DEPARTMENTS!$B:$B, EXPENSES!$B:$B, V$13) -> 173774.8 | W14: =SUMIFS(EXPENSES!$F:$F, EXPENSES!$D:$D,DEPARTMENTS!$B:$B, EXPENSES!$B:$B, W$13) -> 177920 | X14: =SUMIFS(EXPENSES!$F:$F, EXPENSES!$D:$D,DEPARTMENTS!$B:$B, EXPENSES!$B:$B, X$13) -> 92822 | Y14: =SUMIFS(EXPENSES!$F:$F, EXPENSES!$D:$D,DEPARTMENTS!$B:$B, EXPENSES!$B:$B, Y$13) -> 110481 | Z14: =SUMIFS(EXPENSES!$F:$F, EXPENSES!$D:$D,DEPARTMENTS!$B:$B, EXPENSES!$B:$B, Z$13) -> 80166 | AA14: =SUMIFS(EXPENSES!$F:$F, EXPENSES!$D:$D,DEPARTMENTS!$B:$B, EXPENSES!$B:$B, AA$13) -> 96168 | AB14: =SUMIFS(EXPENSES!$F:$F, EXPENSES!$D:$D,DEPARTMENTS!$B:$B, EXPENSES!$B:$B, AB$13) -> 0 | AC14: =SUMIFS(EXPENSES!$F:$F, EXPENSES!$D:$D,DEPARTMENTS!$B:$B, EXPENSES!$B:$B, AC$13) -> 0 | ... AG14: =SUMIFS(EXPENSES!$F:$F, EXPENSES!$D:$D,DEPARTMENTS!$B:$B, EXPENSES!$B:$B, AG$13) -> 0 | AH14: =SUM(V14:AG14) -> 731331.8 | AK14: =AK9 -> 55351 | AL14: =AL9 -> 19805.5 | AM14: =AM9 -> 36780.5 | AN14: =AN9 -> 840 | AO14: =AO9 -> 37175 | AP14: =AP9 -> 17719.5 | AQ14: =AQ9 -> 22342.5 | AR14: =AR9 -> 30702.5 | ... CQ14: =CQ9 -> 0 | CR14: =SUM(AK14:CQ14) -> 548303
B15: SOCIAL_SUNDAY | C15: 0 | D15: =SUMIF(COLLECTION!D:D,DEPARTMENTS!B:B,COLLECTION!E:E)+SUMIF(BANK!D:D,DEPARTMENTS!B:B,BANK!E:E)+SUMIF(TRUST!D:D,DEPARTMENTS!B:B,TRUST!E:E) -> 13950 | E15: =SUMIF(EXPENSES!D:D,DEPARTMENTS!B:B,EXPENSES!F:F) -> 13950 | F15: =D15-E15+C15 -> 0 | H15: =SUMIFS(COLLECTION!$E:$E, COLLECTION!$D:$D,DEPARTMENTS!$B:$B, COLLECTION!$B:$B, H$13, COLLECTION!$B:$B, H$13) + SUMIFS(BANK!$E:$E, BANK!$D:$D,DEPARTMENTS!$B:$B, BANK!$B:$B, H$13, BANK!$B:$B, H$13) + SUMIFS(TRUST!$E:$E, TRUST!$D:$D,DEPARTMENTS!$B:$B, TRUST!$B:$B, H$13, TRUST!$B:$B, H$13) -> 0 | I15: =SUMIFS(COLLECTION!$E:$E, COLLECTION!$D:$D,DEPARTMENTS!$B:$B, COLLECTION!$B:$B, I$13, COLLECTION!$B:$B, I$13) + SUMIFS(BANK!$E:$E, BANK!$D:$D,DEPARTMENTS!$B:$B, BANK!$B:$B, I$13, BANK!$B:$B, I$13) + SUMIFS(TRUST!$E:$E, TRUST!$D:$D,DEPARTMENTS!$B:$B, TRUST!$B:$B, I$13, TRUST!$B:$B, I$13) -> 13950 | J15: =SUMIFS(COLLECTION!$E:$E, COLLECTION!$D:$D,DEPARTMENTS!$B:$B, COLLECTION!$B:$B, J$13, COLLECTION!$B:$B, J$13) + SUMIFS(BANK!$E:$E, BANK!$D:$D,DEPARTMENTS!$B:$B, BANK!$B:$B, J$13, BANK!$B:$B, J$13) + SUMIFS(TRUST!$E:$E, TRUST!$D:$D,DEPARTMENTS!$B:$B, TRUST!$B:$B, J$13, TRUST!$B:$B, J$13) -> 0 | K15: =SUMIFS(COLLECTION!$E:$E, COLLECTION!$D:$D,DEPARTMENTS!$B:$B, COLLECTION!$B:$B, K$13, COLLECTION!$B:$B, K$13) + SUMIFS(BANK!$E:$E, BANK!$D:$D,DEPARTMENTS!$B:$B, BANK!$B:$B, K$13, BANK!$B:$B, K$13) + SUMIFS(TRUST!$E:$E, TRUST!$D:$D,DEPARTMENTS!$B:$B, TRUST!$B:$B, K$13, TRUST!$B:$B, K$13) -> 0 | L15: =SUMIFS(COLLECTION!$E:$E, COLLECTION!$D:$D,DEPARTMENTS!$B:$B, COLLECTION!$B:$B, L$13, COLLECTION!$B:$B, L$13) + SUMIFS(BANK!$E:$E, BANK!$D:$D,DEPARTMENTS!$B:$B, BANK!$B:$B, L$13, BANK!$B:$B, L$13) + SUMIFS(TRUST!$E:$E, TRUST!$D:$D,DEPARTMENTS!$B:$B, TRUST!$B:$B, L$13, TRUST!$B:$B, L$13) -> 0 | M15: =SUMIFS(COLLECTION!$E:$E, COLLECTION!$D:$D,DEPARTMENTS!$B:$B, COLLECTION!$B:$B, M$13, COLLECTION!$B:$B, M$13) + SUMIFS(BANK!$E:$E, BANK!$D:$D,DEPARTMENTS!$B:$B, BANK!$B:$B, M$13, BANK!$B:$B, M$13) + SUMIFS(TRUST!$E:$E, TRUST!$D:$D,DEPARTMENTS!$B:$B, TRUST!$B:$B, M$13, TRUST!$B:$B, M$13) -> 0 | N15: =SUMIFS(COLLECTION!$E:$E, COLLECTION!$D:$D,DEPARTMENTS!$B:$B, COLLECTION!$B:$B, N$13, COLLECTION!$B:$B, N$13) + SUMIFS(BANK!$E:$E, BANK!$D:$D,DEPARTMENTS!$B:$B, BANK!$B:$B, N$13, BANK!$B:$B, N$13) + SUMIFS(TRUST!$E:$E, TRUST!$D:$D,DEPARTMENTS!$B:$B, TRUST!$B:$B, N$13, TRUST!$B:$B, N$13) -> 0 | O15: =SUMIFS(COLLECTION!$E:$E, COLLECTION!$D:$D,DEPARTMENTS!$B:$B, COLLECTION!$B:$B, O$13, COLLECTION!$B:$B, O$13) + SUMIFS(BANK!$E:$E, BANK!$D:$D,DEPARTMENTS!$B:$B, BANK!$B:$B, O$13, BANK!$B:$B, O$13) + SUMIFS(TRUST!$E:$E, TRUST!$D:$D,DEPARTMENTS!$B:$B, TRUST!$B:$B, O$13, TRUST!$B:$B, O$13) -> 0 | ... S15: =SUMIFS(COLLECTION!$E:$E, COLLECTION!$D:$D,DEPARTMENTS!$B:$B, COLLECTION!$B:$B, S$13, COLLECTION!$B:$B, S$13) + SUMIFS(BANK!$E:$E, BANK!$D:$D,DEPARTMENTS!$B:$B, BANK!$B:$B, S$13, BANK!$B:$B, S$13) + SUMIFS(TRUST!$E:$E, TRUST!$D:$D,DEPARTMENTS!$B:$B, TRUST!$B:$B, S$13, TRUST!$B:$B, S$13) -> 0 | T15: =SUM(H15:S15) -> 13950 | V15: =SUMIFS(EXPENSES!$F:$F, EXPENSES!$D:$D,DEPARTMENTS!$B:$B, EXPENSES!$B:$B, V$13) -> 0 | W15: =SUMIFS(EXPENSES!$F:$F, EXPENSES!$D:$D,DEPARTMENTS!$B:$B, EXPENSES!$B:$B, W$13) -> 13950 | X15: =SUMIFS(EXPENSES!$F:$F, EXPENSES!$D:$D,DEPARTMENTS!$B:$B, EXPENSES!$B:$B, X$13) -> 0 | Y15: =SUMIFS(EXPENSES!$F:$F, EXPENSES!$D:$D,DEPARTMENTS!$B:$B, EXPENSES!$B:$B, Y$13) -> 0 | Z15: =SUMIFS(EXPENSES!$F:$F, EXPENSES!$D:$D,DEPARTMENTS!$B:$B, EXPENSES!$B:$B, Z$13) -> 0 | AA15: =SUMIFS(EXPENSES!$F:$F, EXPENSES!$D:$D,DEPARTMENTS!$B:$B, EXPENSES!$B:$B, AA$13) -> 0 | AB15: =SUMIFS(EXPENSES!$F:$F, EXPENSES!$D:$D,DEPARTMENTS!$B:$B, EXPENSES!$B:$B, AB$13) -> 0 | AC15: =SUMIFS(EXPENSES!$F:$F, EXPENSES!$D:$D,DEPARTMENTS!$B:$B, EXPENSES!$B:$B, AC$13) -> 0 | ... AG15: =SUMIFS(EXPENSES!$F:$F, EXPENSES!$D:$D,DEPARTMENTS!$B:$B, EXPENSES!$B:$B, AG$13) -> 0 | AH15: =SUM(V15:AG15) -> 13950 | AK15: =SUMIFS(COLLECTION!$E:$E, COLLECTION!$D:$D,DEPARTMENTS!$B:$B, COLLECTION!$B:$B, AK$12, COLLECTION!$C:$C, AK$13) + SUMIFS(BANK!$E:$E, BANK!$D:$D,DEPARTMENTS!$B:$B, BANK!$B:$B, AK$12, BANK!$C:$C, AK$13) + SUMIFS(TRUST!$E:$E, TRUST!$D:$D,DEPARTMENTS!$B:$B, TRUST!$B:$B, AK$12, TRUST!$C:$C, AK$13) -> 0 | AL15: =SUMIFS(COLLECTION!$E:$E, COLLECTION!$D:$D,DEPARTMENTS!$B:$B, COLLECTION!$B:$B, AL$12, COLLECTION!$C:$C, AL$13) + SUMIFS(BANK!$E:$E, BANK!$D:$D,DEPARTMENTS!$B:$B, BANK!$B:$B, AL$12, BANK!$C:$C, AL$13) + SUMIFS(TRUST!$E:$E, TRUST!$D:$D,DEPARTMENTS!$B:$B, TRUST!$B:$B, AL$12, TRUST!$C:$C, AL$13) -> 0 | AM15: =SUMIFS(COLLECTION!$E:$E, COLLECTION!$D:$D,DEPARTMENTS!$B:$B, COLLECTION!$B:$B, AM$12, COLLECTION!$C:$C, AM$13) + SUMIFS(BANK!$E:$E, BANK!$D:$D,DEPARTMENTS!$B:$B, BANK!$B:$B, AM$12, BANK!$C:$C, AM$13) + SUMIFS(TRUST!$E:$E, TRUST!$D:$D,DEPARTMENTS!$B:$B, TRUST!$B:$B, AM$12, TRUST!$C:$C, AM$13) -> 0 | AN15: =SUMIFS(COLLECTION!$E:$E, COLLECTION!$D:$D,DEPARTMENTS!$B:$B, COLLECTION!$B:$B, AN$12, COLLECTION!$C:$C, AN$13) + SUMIFS(BANK!$E:$E, BANK!$D:$D,DEPARTMENTS!$B:$B, BANK!$B:$B, AN$12, BANK!$C:$C, AN$13) + SUMIFS(TRUST!$E:$E, TRUST!$D:$D,DEPARTMENTS!$B:$B, TRUST!$B:$B, AN$12, TRUST!$C:$C, AN$13) -> 0 | AO15: =SUMIFS(COLLECTION!$E:$E, COLLECTION!$D:$D,DEPARTMENTS!$B:$B, COLLECTION!$B:$B, AO$12, COLLECTION!$C:$C, AO$13) + SUMIFS(BANK!$E:$E, BANK!$D:$D,DEPARTMENTS!$B:$B, BANK!$B:$B, AO$12, BANK!$C:$C, AO$13) + SUMIFS(TRUST!$E:$E, TRUST!$D:$D,DEPARTMENTS!$B:$B, TRUST!$B:$B, AO$12, TRUST!$C:$C, AO$13) -> 0 | AP15: =SUMIFS(COLLECTION!$E:$E, COLLECTION!$D:$D,DEPARTMENTS!$B:$B, COLLECTION!$B:$B, AP$12, COLLECTION!$C:$C, AP$13) + SUMIFS(BANK!$E:$E, BANK!$D:$D,DEPARTMENTS!$B:$B, BANK!$B:$B, AP$12, BANK!$C:$C, AP$13) + SUMIFS(TRUST!$E:$E, TRUST!$D:$D,DEPARTMENTS!$B:$B, TRUST!$B:$B, AP$12, TRUST!$C:$C, AP$13) -> 0 | AQ15: =SUMIFS(COLLECTION!$E:$E, COLLECTION!$D:$D,DEPARTMENTS!$B:$B, COLLECTION!$B:$B, AQ$12, COLLECTION!$C:$C, AQ$13) + SUMIFS(BANK!$E:$E, BANK!$D:$D,DEPARTMENTS!$B:$B, BANK!$B:$B, AQ$12, BANK!$C:$C, AQ$13) + SUMIFS(TRUST!$E:$E, TRUST!$D:$D,DEPARTMENTS!$B:$B, TRUST!$B:$B, AQ$12, TRUST!$C:$C, AQ$13) -> 0 | AR15: =SUMIFS(COLLECTION!$E:$E, COLLECTION!$D:$D,DEPARTMENTS!$B:$B, COLLECTION!$B:$B, AR$12, COLLECTION!$C:$C, AR$13) + SUMIFS(BANK!$E:$E, BANK!$D:$D,DEPARTMENTS!$B:$B, BANK!$B:$B, AR$12, BANK!$C:$C, AR$13) + SUMIFS(TRUST!$E:$E, TRUST!$D:$D,DEPARTMENTS!$B:$B, TRUST!$B:$B, AR$12, TRUST!$C:$C, AR$13) -> 13950 | ... CQ15: =SUMIFS(COLLECTION!$E:$E, COLLECTION!$D:$D,DEPARTMENTS!$B:$B, COLLECTION!$B:$B, CQ$12, COLLECTION!$C:$C, CQ$13) + SUMIFS(BANK!$E:$E, BANK!$D:$D,DEPARTMENTS!$B:$B, BANK!$B:$B, CQ$12, BANK!$C:$C, CQ$13) + SUMIFS(TRUST!$E:$E, TRUST!$D:$D,DEPARTMENTS!$B:$B, TRUST!$B:$B, CQ$12, TRUST!$C:$C, CQ$13) -> 0 | CR15: =SUM(AK15:CQ15) -> 13950
B16: CHURCH CHOIR | C16: =77921 -> 77921 | D16: =SUMIF(COLLECTION!D:D,DEPARTMENTS!B:B,COLLECTION!E:E)+SUMIF(BANK!D:D,DEPARTMENTS!B:B,BANK!E:E)+SUMIF(TRUST!D:D,DEPARTMENTS!B:B,TRUST!E:E) -> 11550 | E16: =SUMIF(EXPENSES!D:D,DEPARTMENTS!B:B,EXPENSES!F:F) -> 16053 | F16: =D16-E16+C16 -> 73418 | H16: =SUMIFS(COLLECTION!$E:$E, COLLECTION!$D:$D,DEPARTMENTS!$B:$B, COLLECTION!$B:$B, H$13, COLLECTION!$B:$B, H$13) + SUMIFS(BANK!$E:$E, BANK!$D:$D,DEPARTMENTS!$B:$B, BANK!$B:$B, H$13, BANK!$B:$B, H$13) + SUMIFS(TRUST!$E:$E, TRUST!$D:$D,DEPARTMENTS!$B:$B, TRUST!$B:$B, H$13, TRUST!$B:$B, H$13) -> 11550 | I16: =SUMIFS(COLLECTION!$E:$E, COLLECTION!$D:$D,DEPARTMENTS!$B:$B, COLLECTION!$B:$B, I$13, COLLECTION!$B:$B, I$13) + SUMIFS(BANK!$E:$E, BANK!$D:$D,DEPARTMENTS!$B:$B, BANK!$B:$B, I$13, BANK!$B:$B, I$13) + SUMIFS(TRUST!$E:$E, TRUST!$D:$D,DEPARTMENTS!$B:$B, TRUST!$B:$B, I$13, TRUST!$B:$B, I$13) -> 0 | J16: =SUMIFS(COLLECTION!$E:$E, COLLECTION!$D:$D,DEPARTMENTS!$B:$B, COLLECTION!$B:$B, J$13, COLLECTION!$B:$B, J$13) + SUMIFS(BANK!$E:$E, BANK!$D:$D,DEPARTMENTS!$B:$B, BANK!$B:$B, J$13, BANK!$B:$B, J$13) + SUMIFS(TRUST!$E:$E, TRUST!$D:$D,DEPARTMENTS!$B:$B, TRUST!$B:$B, J$13, TRUST!$B:$B, J$13) -> 0 | K16: =SUMIFS(COLLECTION!$E:$E, COLLECTION!$D:$D,DEPARTMENTS!$B:$B, COLLECTION!$B:$B, K$13, COLLECTION!$B:$B, K$13) + SUMIFS(BANK!$E:$E, BANK!$D:$D,DEPARTMENTS!$B:$B, BANK!$B:$B, K$13, BANK!$B:$B, K$13) + SUMIFS(TRUST!$E:$E, TRUST!$D:$D,DEPARTMENTS!$B:$B, TRUST!$B:$B, K$13, TRUST!$B:$B, K$13) -> 0 | L16: =SUMIFS(COLLECTION!$E:$E, COLLECTION!$D:$D,DEPARTMENTS!$B:$B, COLLECTION!$B:$B, L$13, COLLECTION!$B:$B, L$13) + SUMIFS(BANK!$E:$E, BANK!$D:$D,DEPARTMENTS!$B:$B, BANK!$B:$B, L$13, BANK!$B:$B, L$13) + SUMIFS(TRUST!$E:$E, TRUST!$D:$D,DEPARTMENTS!$B:$B, TRUST!$B:$B, L$13, TRUST!$B:$B, L$13) -> 0 | M16: =SUMIFS(COLLECTION!$E:$E, COLLECTION!$D:$D,DEPARTMENTS!$B:$B, COLLECTION!$B:$B, M$13, COLLECTION!$B:$B, M$13) + SUMIFS(BANK!$E:$E, BANK!$D:$D,DEPARTMENTS!$B:$B, BANK!$B:$B, M$13, BANK!$B:$B, M$13) + SUMIFS(TRUST!$E:$E, TRUST!$D:$D,DEPARTMENTS!$B:$B, TRUST!$B:$B, M$13, TRUST!$B:$B, M$13) -> 0 | N16: =SUMIFS(COLLECTION!$E:$E, COLLECTION!$D:$D,DEPARTMENTS!$B:$B, COLLECTION!$B:$B, N$13, COLLECTION!$B:$B, N$13) + SUMIFS(BANK!$E:$E, BANK!$D:$D,DEPARTMENTS!$B:$B, BANK!$B:$B, N$13, BANK!$B:$B, N$13) + SUMIFS(TRUST!$E:$E, TRUST!$D:$D,DEPARTMENTS!$B:$B, TRUST!$B:$B, N$13, TRUST!$B:$B, N$13) -> 0 | O16: =SUMIFS(COLLECTION!$E:$E, COLLECTION!$D:$D,DEPARTMENTS!$B:$B, COLLECTION!$B:$B, O$13, COLLECTION!$B:$B, O$13) + SUMIFS(BANK!$E:$E, BANK!$D:$D,DEPARTMENTS!$B:$B, BANK!$B:$B, O$13, BANK!$B:$B, O$13) + SUMIFS(TRUST!$E:$E, TRUST!$D:$D,DEPARTMENTS!$B:$B, TRUST!$B:$B, O$13, TRUST!$B:$B, O$13) -> 0 | ... S16: =SUMIFS(COLLECTION!$E:$E, COLLECTION!$D:$D,DEPARTMENTS!$B:$B, COLLECTION!$B:$B, S$13, COLLECTION!$B:$B, S$13) + SUMIFS(BANK!$E:$E, BANK!$D:$D,DEPARTMENTS!$B:$B, BANK!$B:$B, S$13, BANK!$B:$B, S$13) + SUMIFS(TRUST!$E:$E, TRUST!$D:$D,DEPARTMENTS!$B:$B, TRUST!$B:$B, S$13, TRUST!$B:$B, S$13) -> 0 | T16: =SUM(H16:S16) -> 11550 | V16: =SUMIFS(EXPENSES!$F:$F, EXPENSES!$D:$D,DEPARTMENTS!$B:$B, EXPENSES!$B:$B, V$13) -> 0 | W16: =SUMIFS(EXPENSES!$F:$F, EXPENSES!$D:$D,DEPARTMENTS!$B:$B, EXPENSES!$B:$B, W$13) -> 0 | X16: =SUMIFS(EXPENSES!$F:$F, EXPENSES!$D:$D,DEPARTMENTS!$B:$B, EXPENSES!$B:$B, X$13) -> 0 | Y16: =SUMIFS(EXPENSES!$F:$F, EXPENSES!$D:$D,DEPARTMENTS!$B:$B, EXPENSES!$B:$B, Y$13) -> 0 | Z16: =SUMIFS(EXPENSES!$F:$F, EXPENSES!$D:$D,DEPARTMENTS!$B:$B, EXPENSES!$B:$B, Z$13) -> 16053 | AA16: =SUMIFS(EXPENSES!$F:$F, EXPENSES!$D:$D,DEPARTMENTS!$B:$B, EXPENSES!$B:$B, AA$13) -> 0 | AB16: =SUMIFS(EXPENSES!$F:$F, EXPENSES!$D:$D,DEPARTMENTS!$B:$B, EXPENSES!$B:$B, AB$13) -> 0 | AC16: =SUMIFS(EXPENSES!$F:$F, EXPENSES!$D:$D,DEPARTMENTS!$B:$B, EXPENSES!$B:$B, AC$13) -> 0 | ... AG16: =SUMIFS(EXPENSES!$F:$F, EXPENSES!$D:$D,DEPARTMENTS!$B:$B, EXPENSES!$B:$B, AG$13) -> 0 | AH16: =SUM(V16:AG16) -> 16053 | AK16: =SUMIFS(COLLECTION!$E:$E, COLLECTION!$D:$D,DEPARTMENTS!$B:$B, COLLECTION!$B:$B, AK$12, COLLECTION!$C:$C, AK$13) + SUMIFS(BANK!$E:$E, BANK!$D:$D,DEPARTMENTS!$B:$B, BANK!$B:$B, AK$12, BANK!$C:$C, AK$13) + SUMIFS(TRUST!$E:$E, TRUST!$D:$D,DEPARTMENTS!$B:$B, TRUST!$B:$B, AK$12, TRUST!$C:$C, AK$13) -> 0 | AL16: =SUMIFS(COLLECTION!$E:$E, COLLECTION!$D:$D,DEPARTMENTS!$B:$B, COLLECTION!$B:$B, AL$12, COLLECTION!$C:$C, AL$13) + SUMIFS(BANK!$E:$E, BANK!$D:$D,DEPARTMENTS!$B:$B, BANK!$B:$B, AL$12, BANK!$C:$C, AL$13) + SUMIFS(TRUST!$E:$E, TRUST!$D:$D,DEPARTMENTS!$B:$B, TRUST!$B:$B, AL$12, TRUST!$C:$C, AL$13) -> 0 | AM16: =SUMIFS(COLLECTION!$E:$E, COLLECTION!$D:$D,DEPARTMENTS!$B:$B, COLLECTION!$B:$B, AM$12, COLLECTION!$C:$C, AM$13) + SUMIFS(BANK!$E:$E, BANK!$D:$D,DEPARTMENTS!$B:$B, BANK!$B:$B, AM$12, BANK!$C:$C, AM$13) + SUMIFS(TRUST!$E:$E, TRUST!$D:$D,DEPARTMENTS!$B:$B, TRUST!$B:$B, AM$12, TRUST!$C:$C, AM$13) -> 0 | AN16: =SUMIFS(COLLECTION!$E:$E, COLLECTION!$D:$D,DEPARTMENTS!$B:$B, COLLECTION!$B:$B, AN$12, COLLECTION!$C:$C, AN$13) + SUMIFS(BANK!$E:$E, BANK!$D:$D,DEPARTMENTS!$B:$B, BANK!$B:$B, AN$12, BANK!$C:$C, AN$13) + SUMIFS(TRUST!$E:$E, TRUST!$D:$D,DEPARTMENTS!$B:$B, TRUST!$B:$B, AN$12, TRUST!$C:$C, AN$13) -> 0 | AO16: =SUMIFS(COLLECTION!$E:$E, COLLECTION!$D:$D,DEPARTMENTS!$B:$B, COLLECTION!$B:$B, AO$12, COLLECTION!$C:$C, AO$13) + SUMIFS(BANK!$E:$E, BANK!$D:$D,DEPARTMENTS!$B:$B, BANK!$B:$B, AO$12, BANK!$C:$C, AO$13) + SUMIFS(TRUST!$E:$E, TRUST!$D:$D,DEPARTMENTS!$B:$B, TRUST!$B:$B, AO$12, TRUST!$C:$C, AO$13) -> 11550 | AP16: =SUMIFS(COLLECTION!$E:$E, COLLECTION!$D:$D,DEPARTMENTS!$B:$B, COLLECTION!$B:$B, AP$12, COLLECTION!$C:$C, AP$13) + SUMIFS(BANK!$E:$E, BANK!$D:$D,DEPARTMENTS!$B:$B, BANK!$B:$B, AP$12, BANK!$C:$C, AP$13) + SUMIFS(TRUST!$E:$E, TRUST!$D:$D,DEPARTMENTS!$B:$B, TRUST!$B:$B, AP$12, TRUST!$C:$C, AP$13) -> 0 | AQ16: =SUMIFS(COLLECTION!$E:$E, COLLECTION!$D:$D,DEPARTMENTS!$B:$B, COLLECTION!$B:$B, AQ$12, COLLECTION!$C:$C, AQ$13) + SUMIFS(BANK!$E:$E, BANK!$D:$D,DEPARTMENTS!$B:$B, BANK!$B:$B, AQ$12, BANK!$C:$C, AQ$13) + SUMIFS(TRUST!$E:$E, TRUST!$D:$D,DEPARTMENTS!$B:$B, TRUST!$B:$B, AQ$12, TRUST!$C:$C, AQ$13) -> 0 | AR16: =SUMIFS(COLLECTION!$E:$E, COLLECTION!$D:$D,DEPARTMENTS!$B:$B, COLLECTION!$B:$B, AR$12, COLLECTION!$C:$C, AR$13) + SUMIFS(BANK!$E:$E, BANK!$D:$D,DEPARTMENTS!$B:$B, BANK!$B:$B, AR$12, BANK!$C:$C, AR$13) + SUMIFS(TRUST!$E:$E, TRUST!$D:$D,DEPARTMENTS!$B:$B, TRUST!$B:$B, AR$12, TRUST!$C:$C, AR$13) -> 0 | ... CQ16: =SUMIFS(COLLECTION!$E:$E, COLLECTION!$D:$D,DEPARTMENTS!$B:$B, COLLECTION!$B:$B, CQ$12, COLLECTION!$C:$C, CQ$13) + SUMIFS(BANK!$E:$E, BANK!$D:$D,DEPARTMENTS!$B:$B, BANK!$B:$B, CQ$12, BANK!$C:$C, CQ$13) + SUMIFS(TRUST!$E:$E, TRUST!$D:$D,DEPARTMENTS!$B:$B, TRUST!$B:$B, CQ$12, TRUST!$C:$C, CQ$13) -> 0 | CR16: =SUM(AK16:CQ16) -> 11550
B17: KYETHANI | C17: 0 | D17: =SUMIF(COLLECTION!D:D,DEPARTMENTS!B:B,COLLECTION!E:E)+SUMIF(BANK!D:D,DEPARTMENTS!B:B,BANK!E:E)+SUMIF(TRUST!D:D,DEPARTMENTS!B:B,TRUST!E:E) -> 25660 | E17: =SUMIF(EXPENSES!D:D,DEPARTMENTS!B:B,EXPENSES!F:F) -> 13101 | F17: =D17-E17+C17 -> 12559 | H17: =SUMIFS(COLLECTION!$E:$E, COLLECTION!$D:$D,DEPARTMENTS!$B:$B, COLLECTION!$B:$B, H$13, COLLECTION!$B:$B, H$13) + SUMIFS(BANK!$E:$E, BANK!$D:$D,DEPARTMENTS!$B:$B, BANK!$B:$B, H$13, BANK!$B:$B, H$13) + SUMIFS(TRUST!$E:$E, TRUST!$D:$D,DEPARTMENTS!$B:$B, TRUST!$B:$B, H$13, TRUST!$B:$B, H$13) -> 25660 | I17: =SUMIFS(COLLECTION!$E:$E, COLLECTION!$D:$D,DEPARTMENTS!$B:$B, COLLECTION!$B:$B, I$13, COLLECTION!$B:$B, I$13) + SUMIFS(BANK!$E:$E, BANK!$D:$D,DEPARTMENTS!$B:$B, BANK!$B:$B, I$13, BANK!$B:$B, I$13) + SUMIFS(TRUST!$E:$E, TRUST!$D:$D,DEPARTMENTS!$B:$B, TRUST!$B:$B, I$13, TRUST!$B:$B, I$13) -> 0 | J17: =SUMIFS(COLLECTION!$E:$E, COLLECTION!$D:$D,DEPARTMENTS!$B:$B, COLLECTION!$B:$B, J$13, COLLECTION!$B:$B, J$13) + SUMIFS(BANK!$E:$E, BANK!$D:$D,DEPARTMENTS!$B:$B, BANK!$B:$B, J$13, BANK!$B:$B, J$13) + SUMIFS(TRUST!$E:$E, TRUST!$D:$D,DEPARTMENTS!$B:$B, TRUST!$B:$B, J$13, TRUST!$B:$B, J$13) -> 0 | K17: =SUMIFS(COLLECTION!$E:$E, COLLECTION!$D:$D,DEPARTMENTS!$B:$B, COLLECTION!$B:$B, K$13, COLLECTION!$B:$B, K$13) + SUMIFS(BANK!$E:$E, BANK!$D:$D,DEPARTMENTS!$B:$B, BANK!$B:$B, K$13, BANK!$B:$B, K$13) + SUMIFS(TRUST!$E:$E, TRUST!$D:$D,DEPARTMENTS!$B:$B, TRUST!$B:$B, K$13, TRUST!$B:$B, K$13) -> 0 | L17: =SUMIFS(COLLECTION!$E:$E, COLLECTION!$D:$D,DEPARTMENTS!$B:$B, COLLECTION!$B:$B, L$13, COLLECTION!$B:$B, L$13) + SUMIFS(BANK!$E:$E, BANK!$D:$D,DEPARTMENTS!$B:$B, BANK!$B:$B, L$13, BANK!$B:$B, L$13) + SUMIFS(TRUST!$E:$E, TRUST!$D:$D,DEPARTMENTS!$B:$B, TRUST!$B:$B, L$13, TRUST!$B:$B, L$13) -> 0 | M17: =SUMIFS(COLLECTION!$E:$E, COLLECTION!$D:$D,DEPARTMENTS!$B:$B, COLLECTION!$B:$B, M$13, COLLECTION!$B:$B, M$13) + SUMIFS(BANK!$E:$E, BANK!$D:$D,DEPARTMENTS!$B:$B, BANK!$B:$B, M$13, BANK!$B:$B, M$13) + SUMIFS(TRUST!$E:$E, TRUST!$D:$D,DEPARTMENTS!$B:$B, TRUST!$B:$B, M$13, TRUST!$B:$B, M$13) -> 0 | N17: =SUMIFS(COLLECTION!$E:$E, COLLECTION!$D:$D,DEPARTMENTS!$B:$B, COLLECTION!$B:$B, N$13, COLLECTION!$B:$B, N$13) + SUMIFS(BANK!$E:$E, BANK!$D:$D,DEPARTMENTS!$B:$B, BANK!$B:$B, N$13, BANK!$B:$B, N$13) + SUMIFS(TRUST!$E:$E, TRUST!$D:$D,DEPARTMENTS!$B:$B, TRUST!$B:$B, N$13, TRUST!$B:$B, N$13) -> 0 | O17: =SUMIFS(COLLECTION!$E:$E, COLLECTION!$D:$D,DEPARTMENTS!$B:$B, COLLECTION!$B:$B, O$13, COLLECTION!$B:$B, O$13) + SUMIFS(BANK!$E:$E, BANK!$D:$D,DEPARTMENTS!$B:$B, BANK!$B:$B, O$13, BANK!$B:$B, O$13) + SUMIFS(TRUST!$E:$E, TRUST!$D:$D,DEPARTMENTS!$B:$B, TRUST!$B:$B, O$13, TRUST!$B:$B, O$13) -> 0 | ... S17: =SUMIFS(COLLECTION!$E:$E, COLLECTION!$D:$D,DEPARTMENTS!$B:$B, COLLECTION!$B:$B, S$13, COLLECTION!$B:$B, S$13) + SUMIFS(BANK!$E:$E, BANK!$D:$D,DEPARTMENTS!$B:$B, BANK!$B:$B, S$13, BANK!$B:$B, S$13) + SUMIFS(TRUST!$E:$E, TRUST!$D:$D,DEPARTMENTS!$B:$B, TRUST!$B:$B, S$13, TRUST!$B:$B, S$13) -> 0 | T17: =SUM(H17:S17) -> 25660 | V17: =SUMIFS(EXPENSES!$F:$F, EXPENSES!$D:$D,DEPARTMENTS!$B:$B, EXPENSES!$B:$B, V$13) -> 8057 | W17: =SUMIFS(EXPENSES!$F:$F, EXPENSES!$D:$D,DEPARTMENTS!$B:$B, EXPENSES!$B:$B, W$13) -> 0 | X17: =SUMIFS(EXPENSES!$F:$F, EXPENSES!$D:$D,DEPARTMENTS!$B:$B, EXPENSES!$B:$B, X$13) -> 5044 | Y17: =SUMIFS(EXPENSES!$F:$F, EXPENSES!$D:$D,DEPARTMENTS!$B:$B, EXPENSES!$B:$B, Y$13) -> 0 | Z17: =SUMIFS(EXPENSES!$F:$F, EXPENSES!$D:$D,DEPARTMENTS!$B:$B, EXPENSES!$B:$B, Z$13) -> 0 | AA17: =SUMIFS(EXPENSES!$F:$F, EXPENSES!$D:$D,DEPARTMENTS!$B:$B, EXPENSES!$B:$B, AA$13) -> 0 | AB17: =SUMIFS(EXPENSES!$F:$F, EXPENSES!$D:$D,DEPARTMENTS!$B:$B, EXPENSES!$B:$B, AB$13) -> 0 | AC17: =SUMIFS(EXPENSES!$F:$F, EXPENSES!$D:$D,DEPARTMENTS!$B:$B, EXPENSES!$B:$B, AC$13) -> 0 | ... AG17: =SUMIFS(EXPENSES!$F:$F, EXPENSES!$D:$D,DEPARTMENTS!$B:$B, EXPENSES!$B:$B, AG$13) -> 0 | AH17: =SUM(V17:AG17) -> 13101 | AK17: =SUMIFS(COLLECTION!$E:$E, COLLECTION!$D:$D,DEPARTMENTS!$B:$B, COLLECTION!$B:$B, AK$12, COLLECTION!$C:$C, AK$13) + SUMIFS(BANK!$E:$E, BANK!$D:$D,DEPARTMENTS!$B:$B, BANK!$B:$B, AK$12, BANK!$C:$C, AK$13) + SUMIFS(TRUST!$E:$E, TRUST!$D:$D,DEPARTMENTS!$B:$B, TRUST!$B:$B, AK$12, TRUST!$C:$C, AK$13) -> 0 | AL17: =SUMIFS(COLLECTION!$E:$E, COLLECTION!$D:$D,DEPARTMENTS!$B:$B, COLLECTION!$B:$B, AL$12, COLLECTION!$C:$C, AL$13) + SUMIFS(BANK!$E:$E, BANK!$D:$D,DEPARTMENTS!$B:$B, BANK!$B:$B, AL$12, BANK!$C:$C, AL$13) + SUMIFS(TRUST!$E:$E, TRUST!$D:$D,DEPARTMENTS!$B:$B, TRUST!$B:$B, AL$12, TRUST!$C:$C, AL$13) -> 0 | AM17: =SUMIFS(COLLECTION!$E:$E, COLLECTION!$D:$D,DEPARTMENTS!$B:$B, COLLECTION!$B:$B, AM$12, COLLECTION!$C:$C, AM$13) + SUMIFS(BANK!$E:$E, BANK!$D:$D,DEPARTMENTS!$B:$B, BANK!$B:$B, AM$12, BANK!$C:$C, AM$13) + SUMIFS(TRUST!$E:$E, TRUST!$D:$D,DEPARTMENTS!$B:$B, TRUST!$B:$B, AM$12, TRUST!$C:$C, AM$13) -> 2155 | AN17: =SUMIFS(COLLECTION!$E:$E, COLLECTION!$D:$D,DEPARTMENTS!$B:$B, COLLECTION!$B:$B, AN$12, COLLECTION!$C:$C, AN$13) + SUMIFS(BANK!$E:$E, BANK!$D:$D,DEPARTMENTS!$B:$B, BANK!$B:$B, AN$12, BANK!$C:$C, AN$13) + SUMIFS(TRUST!$E:$E, TRUST!$D:$D,DEPARTMENTS!$B:$B, TRUST!$B:$B, AN$12, TRUST!$C:$C, AN$13) -> 22655 | AO17: =SUMIFS(COLLECTION!$E:$E, COLLECTION!$D:$D,DEPARTMENTS!$B:$B, COLLECTION!$B:$B, AO$12, COLLECTION!$C:$C, AO$13) + SUMIFS(BANK!$E:$E, BANK!$D:$D,DEPARTMENTS!$B:$B, BANK!$B:$B, AO$12, BANK!$C:$C, AO$13) + SUMIFS(TRUST!$E:$E, TRUST!$D:$D,DEPARTMENTS!$B:$B, TRUST!$B:$B, AO$12, TRUST!$C:$C, AO$13) -> 850 | AP17: =SUMIFS(COLLECTION!$E:$E, COLLECTION!$D:$D,DEPARTMENTS!$B:$B, COLLECTION!$B:$B, AP$12, COLLECTION!$C:$C, AP$13) + SUMIFS(BANK!$E:$E, BANK!$D:$D,DEPARTMENTS!$B:$B, BANK!$B:$B, AP$12, BANK!$C:$C, AP$13) + SUMIFS(TRUST!$E:$E, TRUST!$D:$D,DEPARTMENTS!$B:$B, TRUST!$B:$B, AP$12, TRUST!$C:$C, AP$13) -> 0 | AQ17: =SUMIFS(COLLECTION!$E:$E, COLLECTION!$D:$D,DEPARTMENTS!$B:$B, COLLECTION!$B:$B, AQ$12, COLLECTION!$C:$C, AQ$13) + SUMIFS(BANK!$E:$E, BANK!$D:$D,DEPARTMENTS!$B:$B, BANK!$B:$B, AQ$12, BANK!$C:$C, AQ$13) + SUMIFS(TRUST!$E:$E, TRUST!$D:$D,DEPARTMENTS!$B:$B, TRUST!$B:$B, AQ$12, TRUST!$C:$C, AQ$13) -> 0 | AR17: =SUMIFS(COLLECTION!$E:$E, COLLECTION!$D:$D,DEPARTMENTS!$B:$B, COLLECTION!$B:$B, AR$12, COLLECTION!$C:$C, AR$13) + SUMIFS(BANK!$E:$E, BANK!$D:$D,DEPARTMENTS!$B:$B, BANK!$B:$B, AR$12, BANK!$C:$C, AR$13) + SUMIFS(TRUST!$E:$E, TRUST!$D:$D,DEPARTMENTS!$B:$B, TRUST!$B:$B, AR$12, TRUST!$C:$C, AR$13) -> 0 | ... CQ17: =SUMIFS(COLLECTION!$E:$E, COLLECTION!$D:$D,DEPARTMENTS!$B:$B, COLLECTION!$B:$B, CQ$12, COLLECTION!$C:$C, CQ$13) + SUMIFS(BANK!$E:$E, BANK!$D:$D,DEPARTMENTS!$B:$B, BANK!$B:$B, CQ$12, BANK!$C:$C, CQ$13) + SUMIFS(TRUST!$E:$E, TRUST!$D:$D,DEPARTMENTS!$B:$B, TRUST!$B:$B, CQ$12, TRUST!$C:$C, CQ$13) -> 0 | CR17: =SUM(AK17:CQ17) -> 25660
B18: YOUTH | C18: 33316 | D18: =SUMIF(COLLECTION!D:D,DEPARTMENTS!B:B,COLLECTION!E:E)+SUMIF(BANK!D:D,DEPARTMENTS!B:B,BANK!E:E)+SUMIF(TRUST!D:D,DEPARTMENTS!B:B,TRUST!E:E) -> 113254 | E18: =SUMIF(EXPENSES!D:D,DEPARTMENTS!B:B,EXPENSES!F:F) -> 107441 | F18: =D18-E18+C18 -> 39129 | H18: =SUMIFS(COLLECTION!$E:$E, COLLECTION!$D:$D,DEPARTMENTS!$B:$B, COLLECTION!$B:$B, H$13, COLLECTION!$B:$B, H$13) + SUMIFS(BANK!$E:$E, BANK!$D:$D,DEPARTMENTS!$B:$B, BANK!$B:$B, H$13, BANK!$B:$B, H$13) + SUMIFS(TRUST!$E:$E, TRUST!$D:$D,DEPARTMENTS!$B:$B, TRUST!$B:$B, H$13, TRUST!$B:$B, H$13) -> 0 | I18: =SUMIFS(COLLECTION!$E:$E, COLLECTION!$D:$D,DEPARTMENTS!$B:$B, COLLECTION!$B:$B, I$13, COLLECTION!$B:$B, I$13) + SUMIFS(BANK!$E:$E, BANK!$D:$D,DEPARTMENTS!$B:$B, BANK!$B:$B, I$13, BANK!$B:$B, I$13) + SUMIFS(TRUST!$E:$E, TRUST!$D:$D,DEPARTMENTS!$B:$B, TRUST!$B:$B, I$13, TRUST!$B:$B, I$13) -> 34143 | J18: =SUMIFS(COLLECTION!$E:$E, COLLECTION!$D:$D,DEPARTMENTS!$B:$B, COLLECTION!$B:$B, J$13, COLLECTION!$B:$B, J$13) + SUMIFS(BANK!$E:$E, BANK!$D:$D,DEPARTMENTS!$B:$B, BANK!$B:$B, J$13, BANK!$B:$B, J$13) + SUMIFS(TRUST!$E:$E, TRUST!$D:$D,DEPARTMENTS!$B:$B, TRUST!$B:$B, J$13, TRUST!$B:$B, J$13) -> 74230 | K18: =SUMIFS(COLLECTION!$E:$E, COLLECTION!$D:$D,DEPARTMENTS!$B:$B, COLLECTION!$B:$B, K$13, COLLECTION!$B:$B, K$13) + SUMIFS(BANK!$E:$E, BANK!$D:$D,DEPARTMENTS!$B:$B, BANK!$B:$B, K$13, BANK!$B:$B, K$13) + SUMIFS(TRUST!$E:$E, TRUST!$D:$D,DEPARTMENTS!$B:$B, TRUST!$B:$B, K$13, TRUST!$B:$B, K$13) -> 3031 | L18: =SUMIFS(COLLECTION!$E:$E, COLLECTION!$D:$D,DEPARTMENTS!$B:$B, COLLECTION!$B:$B, L$13, COLLECTION!$B:$B, L$13) + SUMIFS(BANK!$E:$E, BANK!$D:$D,DEPARTMENTS!$B:$B, BANK!$B:$B, L$13, BANK!$B:$B, L$13) + SUMIFS(TRUST!$E:$E, TRUST!$D:$D,DEPARTMENTS!$B:$B, TRUST!$B:$B, L$13, TRUST!$B:$B, L$13) -> 1850 | M18: =SUMIFS(COLLECTION!$E:$E, COLLECTION!$D:$D,DEPARTMENTS!$B:$B, COLLECTION!$B:$B, M$13, COLLECTION!$B:$B, M$13) + SUMIFS(BANK!$E:$E, BANK!$D:$D,DEPARTMENTS!$B:$B, BANK!$B:$B, M$13, BANK!$B:$B, M$13) + SUMIFS(TRUST!$E:$E, TRUST!$D:$D,DEPARTMENTS!$B:$B, TRUST!$B:$B, M$13, TRUST!$B:$B, M$13) -> 0 | N18: =SUMIFS(COLLECTION!$E:$E, COLLECTION!$D:$D,DEPARTMENTS!$B:$B, COLLECTION!$B:$B, N$13, COLLECTION!$B:$B, N$13) + SUMIFS(BANK!$E:$E, BANK!$D:$D,DEPARTMENTS!$B:$B, BANK!$B:$B, N$13, BANK!$B:$B, N$13) + SUMIFS(TRUST!$E:$E, TRUST!$D:$D,DEPARTMENTS!$B:$B, TRUST!$B:$B, N$13, TRUST!$B:$B, N$13) -> 0 | O18: =SUMIFS(COLLECTION!$E:$E, COLLECTION!$D:$D,DEPARTMENTS!$B:$B, COLLECTION!$B:$B, O$13, COLLECTION!$B:$B, O$13) + SUMIFS(BANK!$E:$E, BANK!$D:$D,DEPARTMENTS!$B:$B, BANK!$B:$B, O$13, BANK!$B:$B, O$13) + SUMIFS(TRUST!$E:$E, TRUST!$D:$D,DEPARTMENTS!$B:$B, TRUST!$B:$B, O$13, TRUST!$B:$B, O$13) -> 0 | ... S18: =SUMIFS(COLLECTION!$E:$E, COLLECTION!$D:$D,DEPARTMENTS!$B:$B, COLLECTION!$B:$B, S$13, COLLECTION!$B:$B, S$13) + SUMIFS(BANK!$E:$E, BANK!$D:$D,DEPARTMENTS!$B:$B, BANK!$B:$B, S$13, BANK!$B:$B, S$13) + SUMIFS(TRUST!$E:$E, TRUST!$D:$D,DEPARTMENTS!$B:$B, TRUST!$B:$B, S$13, TRUST!$B:$B, S$13) -> 0 | T18: =SUM(H18:S18) -> 113254 | V18: =SUMIFS(EXPENSES!$F:$F, EXPENSES!$D:$D,DEPARTMENTS!$B:$B, EXPENSES!$B:$B, V$13) -> 0 | W18: =SUMIFS(EXPENSES!$F:$F, EXPENSES!$D:$D,DEPARTMENTS!$B:$B, EXPENSES!$B:$B, W$13) -> 33553 | X18: =SUMIFS(EXPENSES!$F:$F, EXPENSES!$D:$D,DEPARTMENTS!$B:$B, EXPENSES!$B:$B, X$13) -> 46388 | Y18: =SUMIFS(EXPENSES!$F:$F, EXPENSES!$D:$D,DEPARTMENTS!$B:$B, EXPENSES!$B:$B, Y$13) -> 7800 | Z18: =SUMIFS(EXPENSES!$F:$F, EXPENSES!$D:$D,DEPARTMENTS!$B:$B, EXPENSES!$B:$B, Z$13) -> 19700 | AA18: =SUMIFS(EXPENSES!$F:$F, EXPENSES!$D:$D,DEPARTMENTS!$B:$B, EXPENSES!$B:$B, AA$13) -> 0 | AB18: =SUMIFS(EXPENSES!$F:$F, EXPENSES!$D:$D,DEPARTMENTS!$B:$B, EXPENSES!$B:$B, AB$13) -> 0 | AC18: =SUMIFS(EXPENSES!$F:$F, EXPENSES!$D:$D,DEPARTMENTS!$B:$B, EXPENSES!$B:$B, AC$13) -> 0 | ... AG18: =SUMIFS(EXPENSES!$F:$F, EXPENSES!$D:$D,DEPARTMENTS!$B:$B, EXPENSES!$B:$B, AG$13) -> 0 | AH18: =SUM(V18:AG18) -> 107441 | AK18: =SUMIFS(COLLECTION!$E:$E, COLLECTION!$D:$D,DEPARTMENTS!$B:$B, COLLECTION!$B:$B, AK$12, COLLECTION!$C:$C, AK$13) + SUMIFS(BANK!$E:$E, BANK!$D:$D,DEPARTMENTS!$B:$B, BANK!$B:$B, AK$12, BANK!$C:$C, AK$13) + SUMIFS(TRUST!$E:$E, TRUST!$D:$D,DEPARTMENTS!$B:$B, TRUST!$B:$B, AK$12, TRUST!$C:$C, AK$13) -> 0 | AL18: =SUMIFS(COLLECTION!$E:$E, COLLECTION!$D:$D,DEPARTMENTS!$B:$B, COLLECTION!$B:$B, AL$12, COLLECTION!$C:$C, AL$13) + SUMIFS(BANK!$E:$E, BANK!$D:$D,DEPARTMENTS!$B:$B, BANK!$B:$B, AL$12, BANK!$C:$C, AL$13) + SUMIFS(TRUST!$E:$E, TRUST!$D:$D,DEPARTMENTS!$B:$B, TRUST!$B:$B, AL$12, TRUST!$C:$C, AL$13) -> 0 | AM18: =SUMIFS(COLLECTION!$E:$E, COLLECTION!$D:$D,DEPARTMENTS!$B:$B, COLLECTION!$B:$B, AM$12, COLLECTION!$C:$C, AM$13) + SUMIFS(BANK!$E:$E, BANK!$D:$D,DEPARTMENTS!$B:$B, BANK!$B:$B, AM$12, BANK!$C:$C, AM$13) + SUMIFS(TRUST!$E:$E, TRUST!$D:$D,DEPARTMENTS!$B:$B, TRUST!$B:$B, AM$12, TRUST!$C:$C, AM$13) -> 0 | AN18: =SUMIFS(COLLECTION!$E:$E, COLLECTION!$D:$D,DEPARTMENTS!$B:$B, COLLECTION!$B:$B, AN$12, COLLECTION!$C:$C, AN$13) + SUMIFS(BANK!$E:$E, BANK!$D:$D,DEPARTMENTS!$B:$B, BANK!$B:$B, AN$12, BANK!$C:$C, AN$13) + SUMIFS(TRUST!$E:$E, TRUST!$D:$D,DEPARTMENTS!$B:$B, TRUST!$B:$B, AN$12, TRUST!$C:$C, AN$13) -> 0 | AO18: =SUMIFS(COLLECTION!$E:$E, COLLECTION!$D:$D,DEPARTMENTS!$B:$B, COLLECTION!$B:$B, AO$12, COLLECTION!$C:$C, AO$13) + SUMIFS(BANK!$E:$E, BANK!$D:$D,DEPARTMENTS!$B:$B, BANK!$B:$B, AO$12, BANK!$C:$C, AO$13) + SUMIFS(TRUST!$E:$E, TRUST!$D:$D,DEPARTMENTS!$B:$B, TRUST!$B:$B, AO$12, TRUST!$C:$C, AO$13) -> 0 | AP18: =SUMIFS(COLLECTION!$E:$E, COLLECTION!$D:$D,DEPARTMENTS!$B:$B, COLLECTION!$B:$B, AP$12, COLLECTION!$C:$C, AP$13) + SUMIFS(BANK!$E:$E, BANK!$D:$D,DEPARTMENTS!$B:$B, BANK!$B:$B, AP$12, BANK!$C:$C, AP$13) + SUMIFS(TRUST!$E:$E, TRUST!$D:$D,DEPARTMENTS!$B:$B, TRUST!$B:$B, AP$12, TRUST!$C:$C, AP$13) -> 2100 | AQ18: =SUMIFS(COLLECTION!$E:$E, COLLECTION!$D:$D,DEPARTMENTS!$B:$B, COLLECTION!$B:$B, AQ$12, COLLECTION!$C:$C, AQ$13) + SUMIFS(BANK!$E:$E, BANK!$D:$D,DEPARTMENTS!$B:$B, BANK!$B:$B, AQ$12, BANK!$C:$C, AQ$13) + SUMIFS(TRUST!$E:$E, TRUST!$D:$D,DEPARTMENTS!$B:$B, TRUST!$B:$B, AQ$12, TRUST!$C:$C, AQ$13) -> 26600 | AR18: =SUMIFS(COLLECTION!$E:$E, COLLECTION!$D:$D,DEPARTMENTS!$B:$B, COLLECTION!$B:$B, AR$12, COLLECTION!$C:$C, AR$13) + SUMIFS(BANK!$E:$E, BANK!$D:$D,DEPARTMENTS!$B:$B, BANK!$B:$B, AR$12, BANK!$C:$C, AR$13) + SUMIFS(TRUST!$E:$E, TRUST!$D:$D,DEPARTMENTS!$B:$B, TRUST!$B:$B, AR$12, TRUST!$C:$C, AR$13) -> 4208 | ... CQ18: =SUMIFS(COLLECTION!$E:$E, COLLECTION!$D:$D,DEPARTMENTS!$B:$B, COLLECTION!$B:$B, CQ$12, COLLECTION!$C:$C, CQ$13) + SUMIFS(BANK!$E:$E, BANK!$D:$D,DEPARTMENTS!$B:$B, BANK!$B:$B, CQ$12, BANK!$C:$C, CQ$13) + SUMIFS(TRUST!$E:$E, TRUST!$D:$D,DEPARTMENTS!$B:$B, TRUST!$B:$B, CQ$12, TRUST!$C:$C, CQ$13) -> 0 | CR18: =SUM(AK18:CQ18) -> 113254
B19: DEACONRY | C19: 2280 | D19: =SUMIF(COLLECTION!D:D,DEPARTMENTS!B:B,COLLECTION!E:E)+SUMIF(BANK!D:D,DEPARTMENTS!B:B,BANK!E:E)+SUMIF(TRUST!D:D,DEPARTMENTS!B:B,TRUST!E:E) -> 0 | E19: =SUMIF(EXPENSES!D:D,DEPARTMENTS!B:B,EXPENSES!F:F) -> 0 | F19: =D19-E19+C19 -> 2280 | H19: =SUMIFS(COLLECTION!$E:$E, COLLECTION!$D:$D,DEPARTMENTS!$B:$B, COLLECTION!$B:$B, H$13, COLLECTION!$B:$B, H$13) + SUMIFS(BANK!$E:$E, BANK!$D:$D,DEPARTMENTS!$B:$B, BANK!$B:$B, H$13, BANK!$B:$B, H$13) + SUMIFS(TRUST!$E:$E, TRUST!$D:$D,DEPARTMENTS!$B:$B, TRUST!$B:$B, H$13, TRUST!$B:$B, H$13) -> 0 | I19: =SUMIFS(COLLECTION!$E:$E, COLLECTION!$D:$D,DEPARTMENTS!$B:$B, COLLECTION!$B:$B, I$13, COLLECTION!$B:$B, I$13) + SUMIFS(BANK!$E:$E, BANK!$D:$D,DEPARTMENTS!$B:$B, BANK!$B:$B, I$13, BANK!$B:$B, I$13) + SUMIFS(TRUST!$E:$E, TRUST!$D:$D,DEPARTMENTS!$B:$B, TRUST!$B:$B, I$13, TRUST!$B:$B, I$13) -> 0 | J19: =SUMIFS(COLLECTION!$E:$E, COLLECTION!$D:$D,DEPARTMENTS!$B:$B, COLLECTION!$B:$B, J$13, COLLECTION!$B:$B, J$13) + SUMIFS(BANK!$E:$E, BANK!$D:$D,DEPARTMENTS!$B:$B, BANK!$B:$B, J$13, BANK!$B:$B, J$13) + SUMIFS(TRUST!$E:$E, TRUST!$D:$D,DEPARTMENTS!$B:$B, TRUST!$B:$B, J$13, TRUST!$B:$B, J$13) -> 0 | K19: =SUMIFS(COLLECTION!$E:$E, COLLECTION!$D:$D,DEPARTMENTS!$B:$B, COLLECTION!$B:$B, K$13, COLLECTION!$B:$B, K$13) + SUMIFS(BANK!$E:$E, BANK!$D:$D,DEPARTMENTS!$B:$B, BANK!$B:$B, K$13, BANK!$B:$B, K$13) + SUMIFS(TRUST!$E:$E, TRUST!$D:$D,DEPARTMENTS!$B:$B, TRUST!$B:$B, K$13, TRUST!$B:$B, K$13) -> 0 | L19: =SUMIFS(COLLECTION!$E:$E, COLLECTION!$D:$D,DEPARTMENTS!$B:$B, COLLECTION!$B:$B, L$13, COLLECTION!$B:$B, L$13) + SUMIFS(BANK!$E:$E, BANK!$D:$D,DEPARTMENTS!$B:$B, BANK!$B:$B, L$13, BANK!$B:$B, L$13) + SUMIFS(TRUST!$E:$E, TRUST!$D:$D,DEPARTMENTS!$B:$B, TRUST!$B:$B, L$13, TRUST!$B:$B, L$13) -> 0 | M19: =SUMIFS(COLLECTION!$E:$E, COLLECTION!$D:$D,DEPARTMENTS!$B:$B, COLLECTION!$B:$B, M$13, COLLECTION!$B:$B, M$13) + SUMIFS(BANK!$E:$E, BANK!$D:$D,DEPARTMENTS!$B:$B, BANK!$B:$B, M$13, BANK!$B:$B, M$13) + SUMIFS(TRUST!$E:$E, TRUST!$D:$D,DEPARTMENTS!$B:$B, TRUST!$B:$B, M$13, TRUST!$B:$B, M$13) -> 0 | N19: =SUMIFS(COLLECTION!$E:$E, COLLECTION!$D:$D,DEPARTMENTS!$B:$B, COLLECTION!$B:$B, N$13, COLLECTION!$B:$B, N$13) + SUMIFS(BANK!$E:$E, BANK!$D:$D,DEPARTMENTS!$B:$B, BANK!$B:$B, N$13, BANK!$B:$B, N$13) + SUMIFS(TRUST!$E:$E, TRUST!$D:$D,DEPARTMENTS!$B:$B, TRUST!$B:$B, N$13, TRUST!$B:$B, N$13) -> 0 | O19: =SUMIFS(COLLECTION!$E:$E, COLLECTION!$D:$D,DEPARTMENTS!$B:$B, COLLECTION!$B:$B, O$13, COLLECTION!$B:$B, O$13) + SUMIFS(BANK!$E:$E, BANK!$D:$D,DEPARTMENTS!$B:$B, BANK!$B:$B, O$13, BANK!$B:$B, O$13) + SUMIFS(TRUST!$E:$E, TRUST!$D:$D,DEPARTMENTS!$B:$B, TRUST!$B:$B, O$13, TRUST!$B:$B, O$13) -> 0 | ... S19: =SUMIFS(COLLECTION!$E:$E, COLLECTION!$D:$D,DEPARTMENTS!$B:$B, COLLECTION!$B:$B, S$13, COLLECTION!$B:$B, S$13) + SUMIFS(BANK!$E:$E, BANK!$D:$D,DEPARTMENTS!$B:$B, BANK!$B:$B, S$13, BANK!$B:$B, S$13) + SUMIFS(TRUST!$E:$E, TRUST!$D:$D,DEPARTMENTS!$B:$B, TRUST!$B:$B, S$13, TRUST!$B:$B, S$13) -> 0 | T19: =SUM(H19:S19) -> 0 | V19: =SUMIFS(EXPENSES!$F:$F, EXPENSES!$D:$D,DEPARTMENTS!$B:$B, EXPENSES!$B:$B, V$13) -> 0 | W19: =SUMIFS(EXPENSES!$F:$F, EXPENSES!$D:$D,DEPARTMENTS!$B:$B, EXPENSES!$B:$B, W$13) -> 0 | X19: =SUMIFS(EXPENSES!$F:$F, EXPENSES!$D:$D,DEPARTMENTS!$B:$B, EXPENSES!$B:$B, X$13) -> 0 | Y19: =SUMIFS(EXPENSES!$F:$F, EXPENSES!$D:$D,DEPARTMENTS!$B:$B, EXPENSES!$B:$B, Y$13) -> 0 | Z19: =SUMIFS(EXPENSES!$F:$F, EXPENSES!$D:$D,DEPARTMENTS!$B:$B, EXPENSES!$B:$B, Z$13) -> 0 | AA19: =SUMIFS(EXPENSES!$F:$F, EXPENSES!$D:$D,DEPARTMENTS!$B:$B, EXPENSES!$B:$B, AA$13) -> 0 | AB19: =SUMIFS(EXPENSES!$F:$F, EXPENSES!$D:$D,DEPARTMENTS!$B:$B, EXPENSES!$B:$B, AB$13) -> 0 | AC19: =SUMIFS(EXPENSES!$F:$F, EXPENSES!$D:$D,DEPARTMENTS!$B:$B, EXPENSES!$B:$B, AC$13) -> 0 | ... AG19: =SUMIFS(EXPENSES!$F:$F, EXPENSES!$D:$D,DEPARTMENTS!$B:$B, EXPENSES!$B:$B, AG$13) -> 0 | AH19: =SUM(V19:AG19) -> 0 | AK19: =SUMIFS(COLLECTION!$E:$E, COLLECTION!$D:$D,DEPARTMENTS!$B:$B, COLLECTION!$B:$B, AK$12, COLLECTION!$C:$C, AK$13) + SUMIFS(BANK!$E:$E, BANK!$D:$D,DEPARTMENTS!$B:$B, BANK!$B:$B, AK$12, BANK!$C:$C, AK$13) + SUMIFS(TRUST!$E:$E, TRUST!$D:$D,DEPARTMENTS!$B:$B, TRUST!$B:$B, AK$12, TRUST!$C:$C, AK$13) -> 0 | AL19: =SUMIFS(COLLECTION!$E:$E, COLLECTION!$D:$D,DEPARTMENTS!$B:$B, COLLECTION!$B:$B, AL$12, COLLECTION!$C:$C, AL$13) + SUMIFS(BANK!$E:$E, BANK!$D:$D,DEPARTMENTS!$B:$B, BANK!$B:$B, AL$12, BANK!$C:$C, AL$13) + SUMIFS(TRUST!$E:$E, TRUST!$D:$D,DEPARTMENTS!$B:$B, TRUST!$B:$B, AL$12, TRUST!$C:$C, AL$13) -> 0 | AM19: =SUMIFS(COLLECTION!$E:$E, COLLECTION!$D:$D,DEPARTMENTS!$B:$B, COLLECTION!$B:$B, AM$12, COLLECTION!$C:$C, AM$13) + SUMIFS(BANK!$E:$E, BANK!$D:$D,DEPARTMENTS!$B:$B, BANK!$B:$B, AM$12, BANK!$C:$C, AM$13) + SUMIFS(TRUST!$E:$E, TRUST!$D:$D,DEPARTMENTS!$B:$B, TRUST!$B:$B, AM$12, TRUST!$C:$C, AM$13) -> 0 | AN19: =SUMIFS(COLLECTION!$E:$E, COLLECTION!$D:$D,DEPARTMENTS!$B:$B, COLLECTION!$B:$B, AN$12, COLLECTION!$C:$C, AN$13) + SUMIFS(BANK!$E:$E, BANK!$D:$D,DEPARTMENTS!$B:$B, BANK!$B:$B, AN$12, BANK!$C:$C, AN$13) + SUMIFS(TRUST!$E:$E, TRUST!$D:$D,DEPARTMENTS!$B:$B, TRUST!$B:$B, AN$12, TRUST!$C:$C, AN$13) -> 0 | AO19: =SUMIFS(COLLECTION!$E:$E, COLLECTION!$D:$D,DEPARTMENTS!$B:$B, COLLECTION!$B:$B, AO$12, COLLECTION!$C:$C, AO$13) + SUMIFS(BANK!$E:$E, BANK!$D:$D,DEPARTMENTS!$B:$B, BANK!$B:$B, AO$12, BANK!$C:$C, AO$13) + SUMIFS(TRUST!$E:$E, TRUST!$D:$D,DEPARTMENTS!$B:$B, TRUST!$B:$B, AO$12, TRUST!$C:$C, AO$13) -> 0 | AP19: =SUMIFS(COLLECTION!$E:$E, COLLECTION!$D:$D,DEPARTMENTS!$B:$B, COLLECTION!$B:$B, AP$12, COLLECTION!$C:$C, AP$13) + SUMIFS(BANK!$E:$E, BANK!$D:$D,DEPARTMENTS!$B:$B, BANK!$B:$B, AP$12, BANK!$C:$C, AP$13) + SUMIFS(TRUST!$E:$E, TRUST!$D:$D,DEPARTMENTS!$B:$B, TRUST!$B:$B, AP$12, TRUST!$C:$C, AP$13) -> 0 | AQ19: =SUMIFS(COLLECTION!$E:$E, COLLECTION!$D:$D,DEPARTMENTS!$B:$B, COLLECTION!$B:$B, AQ$12, COLLECTION!$C:$C, AQ$13) + SUMIFS(BANK!$E:$E, BANK!$D:$D,DEPARTMENTS!$B:$B, BANK!$B:$B, AQ$12, BANK!$C:$C, AQ$13) + SUMIFS(TRUST!$E:$E, TRUST!$D:$D,DEPARTMENTS!$B:$B, TRUST!$B:$B, AQ$12, TRUST!$C:$C, AQ$13) -> 0 | AR19: =SUMIFS(COLLECTION!$E:$E, COLLECTION!$D:$D,DEPARTMENTS!$B:$B, COLLECTION!$B:$B, AR$12, COLLECTION!$C:$C, AR$13) + SUMIFS(BANK!$E:$E, BANK!$D:$D,DEPARTMENTS!$B:$B, BANK!$B:$B, AR$12, BANK!$C:$C, AR$13) + SUMIFS(TRUST!$E:$E, TRUST!$D:$D,DEPARTMENTS!$B:$B, TRUST!$B:$B, AR$12, TRUST!$C:$C, AR$13) -> 0 | ... CQ19: =SUMIFS(COLLECTION!$E:$E, COLLECTION!$D:$D,DEPARTMENTS!$B:$B, COLLECTION!$B:$B, CQ$12, COLLECTION!$C:$C, CQ$13) + SUMIFS(BANK!$E:$E, BANK!$D:$D,DEPARTMENTS!$B:$B, BANK!$B:$B, CQ$12, BANK!$C:$C, CQ$13) + SUMIFS(TRUST!$E:$E, TRUST!$D:$D,DEPARTMENTS!$B:$B, TRUST!$B:$B, CQ$12, TRUST!$C:$C, CQ$13) -> 0 | CR19: =SUM(AK19:CQ19) -> 0
B20: CHAPLAINCY | C20: 9444 | D20: =SUMIF(COLLECTION!D:D,DEPARTMENTS!B:B,COLLECTION!E:E)+SUMIF(BANK!D:D,DEPARTMENTS!B:B,BANK!E:E)+SUMIF(TRUST!D:D,DEPARTMENTS!B:B,TRUST!E:E) -> 14600 | E20: =SUMIF(EXPENSES!D:D,DEPARTMENTS!B:B,EXPENSES!F:F) -> 14394 | F20: =D20-E20+C20 -> 9650 | H20: =SUMIFS(COLLECTION!$E:$E, COLLECTION!$D:$D,DEPARTMENTS!$B:$B, COLLECTION!$B:$B, H$13, COLLECTION!$B:$B, H$13) + SUMIFS(BANK!$E:$E, BANK!$D:$D,DEPARTMENTS!$B:$B, BANK!$B:$B, H$13, BANK!$B:$B, H$13) + SUMIFS(TRUST!$E:$E, TRUST!$D:$D,DEPARTMENTS!$B:$B, TRUST!$B:$B, H$13, TRUST!$B:$B, H$13) -> 2600 | I20: =SUMIFS(COLLECTION!$E:$E, COLLECTION!$D:$D,DEPARTMENTS!$B:$B, COLLECTION!$B:$B, I$13, COLLECTION!$B:$B, I$13) + SUMIFS(BANK!$E:$E, BANK!$D:$D,DEPARTMENTS!$B:$B, BANK!$B:$B, I$13, BANK!$B:$B, I$13) + SUMIFS(TRUST!$E:$E, TRUST!$D:$D,DEPARTMENTS!$B:$B, TRUST!$B:$B, I$13, TRUST!$B:$B, I$13) -> 1000 | J20: =SUMIFS(COLLECTION!$E:$E, COLLECTION!$D:$D,DEPARTMENTS!$B:$B, COLLECTION!$B:$B, J$13, COLLECTION!$B:$B, J$13) + SUMIFS(BANK!$E:$E, BANK!$D:$D,DEPARTMENTS!$B:$B, BANK!$B:$B, J$13, BANK!$B:$B, J$13) + SUMIFS(TRUST!$E:$E, TRUST!$D:$D,DEPARTMENTS!$B:$B, TRUST!$B:$B, J$13, TRUST!$B:$B, J$13) -> 400 | K20: =SUMIFS(COLLECTION!$E:$E, COLLECTION!$D:$D,DEPARTMENTS!$B:$B, COLLECTION!$B:$B, K$13, COLLECTION!$B:$B, K$13) + SUMIFS(BANK!$E:$E, BANK!$D:$D,DEPARTMENTS!$B:$B, BANK!$B:$B, K$13, BANK!$B:$B, K$13) + SUMIFS(TRUST!$E:$E, TRUST!$D:$D,DEPARTMENTS!$B:$B, TRUST!$B:$B, K$13, TRUST!$B:$B, K$13) -> 700 | L20: =SUMIFS(COLLECTION!$E:$E, COLLECTION!$D:$D,DEPARTMENTS!$B:$B, COLLECTION!$B:$B, L$13, COLLECTION!$B:$B, L$13) + SUMIFS(BANK!$E:$E, BANK!$D:$D,DEPARTMENTS!$B:$B, BANK!$B:$B, L$13, BANK!$B:$B, L$13) + SUMIFS(TRUST!$E:$E, TRUST!$D:$D,DEPARTMENTS!$B:$B, TRUST!$B:$B, L$13, TRUST!$B:$B, L$13) -> 9900 | M20: =SUMIFS(COLLECTION!$E:$E, COLLECTION!$D:$D,DEPARTMENTS!$B:$B, COLLECTION!$B:$B, M$13, COLLECTION!$B:$B, M$13) + SUMIFS(BANK!$E:$E, BANK!$D:$D,DEPARTMENTS!$B:$B, BANK!$B:$B, M$13, BANK!$B:$B, M$13) + SUMIFS(TRUST!$E:$E, TRUST!$D:$D,DEPARTMENTS!$B:$B, TRUST!$B:$B, M$13, TRUST!$B:$B, M$13) -> 0 | N20: =SUMIFS(COLLECTION!$E:$E, COLLECTION!$D:$D,DEPARTMENTS!$B:$B, COLLECTION!$B:$B, N$13, COLLECTION!$B:$B, N$13) + SUMIFS(BANK!$E:$E, BANK!$D:$D,DEPARTMENTS!$B:$B, BANK!$B:$B, N$13, BANK!$B:$B, N$13) + SUMIFS(TRUST!$E:$E, TRUST!$D:$D,DEPARTMENTS!$B:$B, TRUST!$B:$B, N$13, TRUST!$B:$B, N$13) -> 0 | O20: =SUMIFS(COLLECTION!$E:$E, COLLECTION!$D:$D,DEPARTMENTS!$B:$B, COLLECTION!$B:$B, O$13, COLLECTION!$B:$B, O$13) + SUMIFS(BANK!$E:$E, BANK!$D:$D,DEPARTMENTS!$B:$B, BANK!$B:$B, O$13, BANK!$B:$B, O$13) + SUMIFS(TRUST!$E:$E, TRUST!$D:$D,DEPARTMENTS!$B:$B, TRUST!$B:$B, O$13, TRUST!$B:$B, O$13) -> 0 | ... S20: =SUMIFS(COLLECTION!$E:$E, COLLECTION!$D:$D,DEPARTMENTS!$B:$B, COLLECTION!$B:$B, S$13, COLLECTION!$B:$B, S$13) + SUMIFS(BANK!$E:$E, BANK!$D:$D,DEPARTMENTS!$B:$B, BANK!$B:$B, S$13, BANK!$B:$B, S$13) + SUMIFS(TRUST!$E:$E, TRUST!$D:$D,DEPARTMENTS!$B:$B, TRUST!$B:$B, S$13, TRUST!$B:$B, S$13) -> 0 | T20: =SUM(H20:S20) -> 14600 | V20: =SUMIFS(EXPENSES!$F:$F, EXPENSES!$D:$D,DEPARTMENTS!$B:$B, EXPENSES!$B:$B, V$13) -> 0 | W20: =SUMIFS(EXPENSES!$F:$F, EXPENSES!$D:$D,DEPARTMENTS!$B:$B, EXPENSES!$B:$B, W$13) -> 0 | X20: =SUMIFS(EXPENSES!$F:$F, EXPENSES!$D:$D,DEPARTMENTS!$B:$B, EXPENSES!$B:$B, X$13) -> 0 | Y20: =SUMIFS(EXPENSES!$F:$F, EXPENSES!$D:$D,DEPARTMENTS!$B:$B, EXPENSES!$B:$B, Y$13) -> 0 | Z20: =SUMIFS(EXPENSES!$F:$F, EXPENSES!$D:$D,DEPARTMENTS!$B:$B, EXPENSES!$B:$B, Z$13) -> 14394 | AA20: =SUMIFS(EXPENSES!$F:$F, EXPENSES!$D:$D,DEPARTMENTS!$B:$B, EXPENSES!$B:$B, AA$13) -> 0 | AB20: =SUMIFS(EXPENSES!$F:$F, EXPENSES!$D:$D,DEPARTMENTS!$B:$B, EXPENSES!$B:$B, AB$13) -> 0 | AC20: =SUMIFS(EXPENSES!$F:$F, EXPENSES!$D:$D,DEPARTMENTS!$B:$B, EXPENSES!$B:$B, AC$13) -> 0 | ... AG20: =SUMIFS(EXPENSES!$F:$F, EXPENSES!$D:$D,DEPARTMENTS!$B:$B, EXPENSES!$B:$B, AG$13) -> 0 | AH20: =SUM(V20:AG20) -> 14394 | AK20: =SUMIFS(COLLECTION!$E:$E, COLLECTION!$D:$D,DEPARTMENTS!$B:$B, COLLECTION!$B:$B, AK$12, COLLECTION!$C:$C, AK$13) + SUMIFS(BANK!$E:$E, BANK!$D:$D,DEPARTMENTS!$B:$B, BANK!$B:$B, AK$12, BANK!$C:$C, AK$13) + SUMIFS(TRUST!$E:$E, TRUST!$D:$D,DEPARTMENTS!$B:$B, TRUST!$B:$B, AK$12, TRUST!$C:$C, AK$13) -> 0 | AL20: =SUMIFS(COLLECTION!$E:$E, COLLECTION!$D:$D,DEPARTMENTS!$B:$B, COLLECTION!$B:$B, AL$12, COLLECTION!$C:$C, AL$13) + SUMIFS(BANK!$E:$E, BANK!$D:$D,DEPARTMENTS!$B:$B, BANK!$B:$B, AL$12, BANK!$C:$C, AL$13) + SUMIFS(TRUST!$E:$E, TRUST!$D:$D,DEPARTMENTS!$B:$B, TRUST!$B:$B, AL$12, TRUST!$C:$C, AL$13) -> 0 | AM20: =SUMIFS(COLLECTION!$E:$E, COLLECTION!$D:$D,DEPARTMENTS!$B:$B, COLLECTION!$B:$B, AM$12, COLLECTION!$C:$C, AM$13) + SUMIFS(BANK!$E:$E, BANK!$D:$D,DEPARTMENTS!$B:$B, BANK!$B:$B, AM$12, BANK!$C:$C, AM$13) + SUMIFS(TRUST!$E:$E, TRUST!$D:$D,DEPARTMENTS!$B:$B, TRUST!$B:$B, AM$12, TRUST!$C:$C, AM$13) -> 0 | AN20: =SUMIFS(COLLECTION!$E:$E, COLLECTION!$D:$D,DEPARTMENTS!$B:$B, COLLECTION!$B:$B, AN$12, COLLECTION!$C:$C, AN$13) + SUMIFS(BANK!$E:$E, BANK!$D:$D,DEPARTMENTS!$B:$B, BANK!$B:$B, AN$12, BANK!$C:$C, AN$13) + SUMIFS(TRUST!$E:$E, TRUST!$D:$D,DEPARTMENTS!$B:$B, TRUST!$B:$B, AN$12, TRUST!$C:$C, AN$13) -> 800 | AO20: =SUMIFS(COLLECTION!$E:$E, COLLECTION!$D:$D,DEPARTMENTS!$B:$B, COLLECTION!$B:$B, AO$12, COLLECTION!$C:$C, AO$13) + SUMIFS(BANK!$E:$E, BANK!$D:$D,DEPARTMENTS!$B:$B, BANK!$B:$B, AO$12, BANK!$C:$C, AO$13) + SUMIFS(TRUST!$E:$E, TRUST!$D:$D,DEPARTMENTS!$B:$B, TRUST!$B:$B, AO$12, TRUST!$C:$C, AO$13) -> 1800 | AP20: =SUMIFS(COLLECTION!$E:$E, COLLECTION!$D:$D,DEPARTMENTS!$B:$B, COLLECTION!$B:$B, AP$12, COLLECTION!$C:$C, AP$13) + SUMIFS(BANK!$E:$E, BANK!$D:$D,DEPARTMENTS!$B:$B, BANK!$B:$B, AP$12, BANK!$C:$C, AP$13) + SUMIFS(TRUST!$E:$E, TRUST!$D:$D,DEPARTMENTS!$B:$B, TRUST!$B:$B, AP$12, TRUST!$C:$C, AP$13) -> 200 | AQ20: =SUMIFS(COLLECTION!$E:$E, COLLECTION!$D:$D,DEPARTMENTS!$B:$B, COLLECTION!$B:$B, AQ$12, COLLECTION!$C:$C, AQ$13) + SUMIFS(BANK!$E:$E, BANK!$D:$D,DEPARTMENTS!$B:$B, BANK!$B:$B, AQ$12, BANK!$C:$C, AQ$13) + SUMIFS(TRUST!$E:$E, TRUST!$D:$D,DEPARTMENTS!$B:$B, TRUST!$B:$B, AQ$12, TRUST!$C:$C, AQ$13) -> 800 | AR20: =SUMIFS(COLLECTION!$E:$E, COLLECTION!$D:$D,DEPARTMENTS!$B:$B, COLLECTION!$B:$B, AR$12, COLLECTION!$C:$C, AR$13) + SUMIFS(BANK!$E:$E, BANK!$D:$D,DEPARTMENTS!$B:$B, BANK!$B:$B, AR$12, BANK!$C:$C, AR$13) + SUMIFS(TRUST!$E:$E, TRUST!$D:$D,DEPARTMENTS!$B:$B, TRUST!$B:$B, AR$12, TRUST!$C:$C, AR$13) -> 0 | ... CQ20: =SUMIFS(COLLECTION!$E:$E, COLLECTION!$D:$D,DEPARTMENTS!$B:$B, COLLECTION!$B:$B, CQ$12, COLLECTION!$C:$C, CQ$13) + SUMIFS(BANK!$E:$E, BANK!$D:$D,DEPARTMENTS!$B:$B, BANK!$B:$B, CQ$12, BANK!$C:$C, CQ$13) + SUMIFS(TRUST!$E:$E, TRUST!$D:$D,DEPARTMENTS!$B:$B, TRUST!$B:$B, CQ$12, TRUST!$C:$C, CQ$13) -> 0 | CR20: =SUM(AK20:CQ20) -> 14600
B21: BENEVOLENT FUND | C21: 207951 | D21: =SUMIF(COLLECTION!D:D,DEPARTMENTS!B:B,COLLECTION!E:E)+SUMIF(BANK!D:D,DEPARTMENTS!B:B,BANK!E:E)+SUMIF(TRUST!D:D,DEPARTMENTS!B:B,TRUST!E:E) -> 157000 | E21: =SUMIF(EXPENSES!D:D,DEPARTMENTS!B:B,EXPENSES!F:F) -> 0 | F21: =D21-E21+C21 -> 364951 | H21: =SUMIFS(COLLECTION!$E:$E, COLLECTION!$D:$D,DEPARTMENTS!$B:$B, COLLECTION!$B:$B, H$13, COLLECTION!$B:$B, H$13) + SUMIFS(BANK!$E:$E, BANK!$D:$D,DEPARTMENTS!$B:$B, BANK!$B:$B, H$13, BANK!$B:$B, H$13) + SUMIFS(TRUST!$E:$E, TRUST!$D:$D,DEPARTMENTS!$B:$B, TRUST!$B:$B, H$13, TRUST!$B:$B, H$13) -> 500 | I21: =SUMIFS(COLLECTION!$E:$E, COLLECTION!$D:$D,DEPARTMENTS!$B:$B, COLLECTION!$B:$B, I$13, COLLECTION!$B:$B, I$13) + SUMIFS(BANK!$E:$E, BANK!$D:$D,DEPARTMENTS!$B:$B, BANK!$B:$B, I$13, BANK!$B:$B, I$13) + SUMIFS(TRUST!$E:$E, TRUST!$D:$D,DEPARTMENTS!$B:$B, TRUST!$B:$B, I$13, TRUST!$B:$B, I$13) -> 500 | J21: =SUMIFS(COLLECTION!$E:$E, COLLECTION!$D:$D,DEPARTMENTS!$B:$B, COLLECTION!$B:$B, J$13, COLLECTION!$B:$B, J$13) + SUMIFS(BANK!$E:$E, BANK!$D:$D,DEPARTMENTS!$B:$B, BANK!$B:$B, J$13, BANK!$B:$B, J$13) + SUMIFS(TRUST!$E:$E, TRUST!$D:$D,DEPARTMENTS!$B:$B, TRUST!$B:$B, J$13, TRUST!$B:$B, J$13) -> 500 | K21: =SUMIFS(COLLECTION!$E:$E, COLLECTION!$D:$D,DEPARTMENTS!$B:$B, COLLECTION!$B:$B, K$13, COLLECTION!$B:$B, K$13) + SUMIFS(BANK!$E:$E, BANK!$D:$D,DEPARTMENTS!$B:$B, BANK!$B:$B, K$13, BANK!$B:$B, K$13) + SUMIFS(TRUST!$E:$E, TRUST!$D:$D,DEPARTMENTS!$B:$B, TRUST!$B:$B, K$13, TRUST!$B:$B, K$13) -> 500 | L21: =SUMIFS(COLLECTION!$E:$E, COLLECTION!$D:$D,DEPARTMENTS!$B:$B, COLLECTION!$B:$B, L$13, COLLECTION!$B:$B, L$13) + SUMIFS(BANK!$E:$E, BANK!$D:$D,DEPARTMENTS!$B:$B, BANK!$B:$B, L$13, BANK!$B:$B, L$13) + SUMIFS(TRUST!$E:$E, TRUST!$D:$D,DEPARTMENTS!$B:$B, TRUST!$B:$B, L$13, TRUST!$B:$B, L$13) -> 155000 | M21: =SUMIFS(COLLECTION!$E:$E, COLLECTION!$D:$D,DEPARTMENTS!$B:$B, COLLECTION!$B:$B, M$13, COLLECTION!$B:$B, M$13) + SUMIFS(BANK!$E:$E, BANK!$D:$D,DEPARTMENTS!$B:$B, BANK!$B:$B, M$13, BANK!$B:$B, M$13) + SUMIFS(TRUST!$E:$E, TRUST!$D:$D,DEPARTMENTS!$B:$B, TRUST!$B:$B, M$13, TRUST!$B:$B, M$13) -> 0 | N21: =SUMIFS(COLLECTION!$E:$E, COLLECTION!$D:$D,DEPARTMENTS!$B:$B, COLLECTION!$B:$B, N$13, COLLECTION!$B:$B, N$13) + SUMIFS(BANK!$E:$E, BANK!$D:$D,DEPARTMENTS!$B:$B, BANK!$B:$B, N$13, BANK!$B:$B, N$13) + SUMIFS(TRUST!$E:$E, TRUST!$D:$D,DEPARTMENTS!$B:$B, TRUST!$B:$B, N$13, TRUST!$B:$B, N$13) -> 0 | O21: =SUMIFS(COLLECTION!$E:$E, COLLECTION!$D:$D,DEPARTMENTS!$B:$B, COLLECTION!$B:$B, O$13, COLLECTION!$B:$B, O$13) + SUMIFS(BANK!$E:$E, BANK!$D:$D,DEPARTMENTS!$B:$B, BANK!$B:$B, O$13, BANK!$B:$B, O$13) + SUMIFS(TRUST!$E:$E, TRUST!$D:$D,DEPARTMENTS!$B:$B, TRUST!$B:$B, O$13, TRUST!$B:$B, O$13) -> 0 | ... S21: =SUMIFS(COLLECTION!$E:$E, COLLECTION!$D:$D,DEPARTMENTS!$B:$B, COLLECTION!$B:$B, S$13, COLLECTION!$B:$B, S$13) + SUMIFS(BANK!$E:$E, BANK!$D:$D,DEPARTMENTS!$B:$B, BANK!$B:$B, S$13, BANK!$B:$B, S$13) + SUMIFS(TRUST!$E:$E, TRUST!$D:$D,DEPARTMENTS!$B:$B, TRUST!$B:$B, S$13, TRUST!$B:$B, S$13) -> 0 | T21: =SUM(H21:S21) -> 157000 | V21: =SUMIFS(EXPENSES!$F:$F, EXPENSES!$D:$D,DEPARTMENTS!$B:$B, EXPENSES!$B:$B, V$13) -> 0 | W21: =SUMIFS(EXPENSES!$F:$F, EXPENSES!$D:$D,DEPARTMENTS!$B:$B, EXPENSES!$B:$B, W$13) -> 0 | X21: =SUMIFS(EXPENSES!$F:$F, EXPENSES!$D:$D,DEPARTMENTS!$B:$B, EXPENSES!$B:$B, X$13) -> 0 | Y21: =SUMIFS(EXPENSES!$F:$F, EXPENSES!$D:$D,DEPARTMENTS!$B:$B, EXPENSES!$B:$B, Y$13) -> 0 | Z21: =SUMIFS(EXPENSES!$F:$F, EXPENSES!$D:$D,DEPARTMENTS!$B:$B, EXPENSES!$B:$B, Z$13) -> 0 | AA21: =SUMIFS(EXPENSES!$F:$F, EXPENSES!$D:$D,DEPARTMENTS!$B:$B, EXPENSES!$B:$B, AA$13) -> 0 | AB21: =SUMIFS(EXPENSES!$F:$F, EXPENSES!$D:$D,DEPARTMENTS!$B:$B, EXPENSES!$B:$B, AB$13) -> 0 | AC21: =SUMIFS(EXPENSES!$F:$F, EXPENSES!$D:$D,DEPARTMENTS!$B:$B, EXPENSES!$B:$B, AC$13) -> 0 | ... AG21: =SUMIFS(EXPENSES!$F:$F, EXPENSES!$D:$D,DEPARTMENTS!$B:$B, EXPENSES!$B:$B, AG$13) -> 0 | AH21: =SUM(V21:AG21) -> 0 | AK21: =SUMIFS(COLLECTION!$E:$E, COLLECTION!$D:$D,DEPARTMENTS!$B:$B, COLLECTION!$B:$B, AK$12, COLLECTION!$C:$C, AK$13) + SUMIFS(BANK!$E:$E, BANK!$D:$D,DEPARTMENTS!$B:$B, BANK!$B:$B, AK$12, BANK!$C:$C, AK$13) + SUMIFS(TRUST!$E:$E, TRUST!$D:$D,DEPARTMENTS!$B:$B, TRUST!$B:$B, AK$12, TRUST!$C:$C, AK$13) -> 0 | AL21: =SUMIFS(COLLECTION!$E:$E, COLLECTION!$D:$D,DEPARTMENTS!$B:$B, COLLECTION!$B:$B, AL$12, COLLECTION!$C:$C, AL$13) + SUMIFS(BANK!$E:$E, BANK!$D:$D,DEPARTMENTS!$B:$B, BANK!$B:$B, AL$12, BANK!$C:$C, AL$13) + SUMIFS(TRUST!$E:$E, TRUST!$D:$D,DEPARTMENTS!$B:$B, TRUST!$B:$B, AL$12, TRUST!$C:$C, AL$13) -> 0 | AM21: =SUMIFS(COLLECTION!$E:$E, COLLECTION!$D:$D,DEPARTMENTS!$B:$B, COLLECTION!$B:$B, AM$12, COLLECTION!$C:$C, AM$13) + SUMIFS(BANK!$E:$E, BANK!$D:$D,DEPARTMENTS!$B:$B, BANK!$B:$B, AM$12, BANK!$C:$C, AM$13) + SUMIFS(TRUST!$E:$E, TRUST!$D:$D,DEPARTMENTS!$B:$B, TRUST!$B:$B, AM$12, TRUST!$C:$C, AM$13) -> 500 | AN21: =SUMIFS(COLLECTION!$E:$E, COLLECTION!$D:$D,DEPARTMENTS!$B:$B, COLLECTION!$B:$B, AN$12, COLLECTION!$C:$C, AN$13) + SUMIFS(BANK!$E:$E, BANK!$D:$D,DEPARTMENTS!$B:$B, BANK!$B:$B, AN$12, BANK!$C:$C, AN$13) + SUMIFS(TRUST!$E:$E, TRUST!$D:$D,DEPARTMENTS!$B:$B, TRUST!$B:$B, AN$12, TRUST!$C:$C, AN$13) -> 0 | AO21: =SUMIFS(COLLECTION!$E:$E, COLLECTION!$D:$D,DEPARTMENTS!$B:$B, COLLECTION!$B:$B, AO$12, COLLECTION!$C:$C, AO$13) + SUMIFS(BANK!$E:$E, BANK!$D:$D,DEPARTMENTS!$B:$B, BANK!$B:$B, AO$12, BANK!$C:$C, AO$13) + SUMIFS(TRUST!$E:$E, TRUST!$D:$D,DEPARTMENTS!$B:$B, TRUST!$B:$B, AO$12, TRUST!$C:$C, AO$13) -> 0 | AP21: =SUMIFS(COLLECTION!$E:$E, COLLECTION!$D:$D,DEPARTMENTS!$B:$B, COLLECTION!$B:$B, AP$12, COLLECTION!$C:$C, AP$13) + SUMIFS(BANK!$E:$E, BANK!$D:$D,DEPARTMENTS!$B:$B, BANK!$B:$B, AP$12, BANK!$C:$C, AP$13) + SUMIFS(TRUST!$E:$E, TRUST!$D:$D,DEPARTMENTS!$B:$B, TRUST!$B:$B, AP$12, TRUST!$C:$C, AP$13) -> 0 | AQ21: =SUMIFS(COLLECTION!$E:$E, COLLECTION!$D:$D,DEPARTMENTS!$B:$B, COLLECTION!$B:$B, AQ$12, COLLECTION!$C:$C, AQ$13) + SUMIFS(BANK!$E:$E, BANK!$D:$D,DEPARTMENTS!$B:$B, BANK!$B:$B, AQ$12, BANK!$C:$C, AQ$13) + SUMIFS(TRUST!$E:$E, TRUST!$D:$D,DEPARTMENTS!$B:$B, TRUST!$B:$B, AQ$12, TRUST!$C:$C, AQ$13) -> 500 | AR21: =SUMIFS(COLLECTION!$E:$E, COLLECTION!$D:$D,DEPARTMENTS!$B:$B, COLLECTION!$B:$B, AR$12, COLLECTION!$C:$C, AR$13) + SUMIFS(BANK!$E:$E, BANK!$D:$D,DEPARTMENTS!$B:$B, BANK!$B:$B, AR$12, BANK!$C:$C, AR$13) + SUMIFS(TRUST!$E:$E, TRUST!$D:$D,DEPARTMENTS!$B:$B, TRUST!$B:$B, AR$12, TRUST!$C:$C, AR$13) -> 0 | ... CQ21: =SUMIFS(COLLECTION!$E:$E, COLLECTION!$D:$D,DEPARTMENTS!$B:$B, COLLECTION!$B:$B, CQ$12, COLLECTION!$C:$C, CQ$13) + SUMIFS(BANK!$E:$E, BANK!$D:$D,DEPARTMENTS!$B:$B, BANK!$B:$B, CQ$12, BANK!$C:$C, CQ$13) + SUMIFS(TRUST!$E:$E, TRUST!$D:$D,DEPARTMENTS!$B:$B, TRUST!$B:$B, CQ$12, TRUST!$C:$C, CQ$13) -> 0 | CR21: =SUM(AK21:CQ21) -> 157000
B22: AWM | C22: 9155 | D22: =SUMIF(COLLECTION!D:D,DEPARTMENTS!B:B,COLLECTION!E:E)+SUMIF(BANK!D:D,DEPARTMENTS!B:B,BANK!E:E)+SUMIF(TRUST!D:D,DEPARTMENTS!B:B,TRUST!E:E) -> 14300 | E22: =SUMIF(EXPENSES!D:D,DEPARTMENTS!B:B,EXPENSES!F:F) -> 7000 | F22: =D22-E22+C22 -> 16455 | H22: =SUMIFS(COLLECTION!$E:$E, COLLECTION!$D:$D,DEPARTMENTS!$B:$B, COLLECTION!$B:$B, H$13, COLLECTION!$B:$B, H$13) + SUMIFS(BANK!$E:$E, BANK!$D:$D,DEPARTMENTS!$B:$B, BANK!$B:$B, H$13, BANK!$B:$B, H$13) + SUMIFS(TRUST!$E:$E, TRUST!$D:$D,DEPARTMENTS!$B:$B, TRUST!$B:$B, H$13, TRUST!$B:$B, H$13) -> 11400 | I22: =SUMIFS(COLLECTION!$E:$E, COLLECTION!$D:$D,DEPARTMENTS!$B:$B, COLLECTION!$B:$B, I$13, COLLECTION!$B:$B, I$13) + SUMIFS(BANK!$E:$E, BANK!$D:$D,DEPARTMENTS!$B:$B, BANK!$B:$B, I$13, BANK!$B:$B, I$13) + SUMIFS(TRUST!$E:$E, TRUST!$D:$D,DEPARTMENTS!$B:$B, TRUST!$B:$B, I$13, TRUST!$B:$B, I$13) -> 2900 | J22: =SUMIFS(COLLECTION!$E:$E, COLLECTION!$D:$D,DEPARTMENTS!$B:$B, COLLECTION!$B:$B, J$13, COLLECTION!$B:$B, J$13) + SUMIFS(BANK!$E:$E, BANK!$D:$D,DEPARTMENTS!$B:$B, BANK!$B:$B, J$13, BANK!$B:$B, J$13) + SUMIFS(TRUST!$E:$E, TRUST!$D:$D,DEPARTMENTS!$B:$B, TRUST!$B:$B, J$13, TRUST!$B:$B, J$13) -> 0 | K22: =SUMIFS(COLLECTION!$E:$E, COLLECTION!$D:$D,DEPARTMENTS!$B:$B, COLLECTION!$B:$B, K$13, COLLECTION!$B:$B, K$13) + SUMIFS(BANK!$E:$E, BANK!$D:$D,DEPARTMENTS!$B:$B, BANK!$B:$B, K$13, BANK!$B:$B, K$13) + SUMIFS(TRUST!$E:$E, TRUST!$D:$D,DEPARTMENTS!$B:$B, TRUST!$B:$B, K$13, TRUST!$B:$B, K$13) -> 0 | L22: =SUMIFS(COLLECTION!$E:$E, COLLECTION!$D:$D,DEPARTMENTS!$B:$B, COLLECTION!$B:$B, L$13, COLLECTION!$B:$B, L$13) + SUMIFS(BANK!$E:$E, BANK!$D:$D,DEPARTMENTS!$B:$B, BANK!$B:$B, L$13, BANK!$B:$B, L$13) + SUMIFS(TRUST!$E:$E, TRUST!$D:$D,DEPARTMENTS!$B:$B, TRUST!$B:$B, L$13, TRUST!$B:$B, L$13) -> 0 | M22: =SUMIFS(COLLECTION!$E:$E, COLLECTION!$D:$D,DEPARTMENTS!$B:$B, COLLECTION!$B:$B, M$13, COLLECTION!$B:$B, M$13) + SUMIFS(BANK!$E:$E, BANK!$D:$D,DEPARTMENTS!$B:$B, BANK!$B:$B, M$13, BANK!$B:$B, M$13) + SUMIFS(TRUST!$E:$E, TRUST!$D:$D,DEPARTMENTS!$B:$B, TRUST!$B:$B, M$13, TRUST!$B:$B, M$13) -> 0 | N22: =SUMIFS(COLLECTION!$E:$E, COLLECTION!$D:$D,DEPARTMENTS!$B:$B, COLLECTION!$B:$B, N$13, COLLECTION!$B:$B, N$13) + SUMIFS(BANK!$E:$E, BANK!$D:$D,DEPARTMENTS!$B:$B, BANK!$B:$B, N$13, BANK!$B:$B, N$13) + SUMIFS(TRUST!$E:$E, TRUST!$D:$D,DEPARTMENTS!$B:$B, TRUST!$B:$B, N$13, TRUST!$B:$B, N$13) -> 0 | O22: =SUMIFS(COLLECTION!$E:$E, COLLECTION!$D:$D,DEPARTMENTS!$B:$B, COLLECTION!$B:$B, O$13, COLLECTION!$B:$B, O$13) + SUMIFS(BANK!$E:$E, BANK!$D:$D,DEPARTMENTS!$B:$B, BANK!$B:$B, O$13, BANK!$B:$B, O$13) + SUMIFS(TRUST!$E:$E, TRUST!$D:$D,DEPARTMENTS!$B:$B, TRUST!$B:$B, O$13, TRUST!$B:$B, O$13) -> 0 | ... S22: =SUMIFS(COLLECTION!$E:$E, COLLECTION!$D:$D,DEPARTMENTS!$B:$B, COLLECTION!$B:$B, S$13, COLLECTION!$B:$B, S$13) + SUMIFS(BANK!$E:$E, BANK!$D:$D,DEPARTMENTS!$B:$B, BANK!$B:$B, S$13, BANK!$B:$B, S$13) + SUMIFS(TRUST!$E:$E, TRUST!$D:$D,DEPARTMENTS!$B:$B, TRUST!$B:$B, S$13, TRUST!$B:$B, S$13) -> 0 | T22: =SUM(H22:S22) -> 14300 | V22: =SUMIFS(EXPENSES!$F:$F, EXPENSES!$D:$D,DEPARTMENTS!$B:$B, EXPENSES!$B:$B, V$13) -> 0 | W22: =SUMIFS(EXPENSES!$F:$F, EXPENSES!$D:$D,DEPARTMENTS!$B:$B, EXPENSES!$B:$B, W$13) -> 0 | X22: =SUMIFS(EXPENSES!$F:$F, EXPENSES!$D:$D,DEPARTMENTS!$B:$B, EXPENSES!$B:$B, X$13) -> 2000 | Y22: =SUMIFS(EXPENSES!$F:$F, EXPENSES!$D:$D,DEPARTMENTS!$B:$B, EXPENSES!$B:$B, Y$13) -> 5000 | Z22: =SUMIFS(EXPENSES!$F:$F, EXPENSES!$D:$D,DEPARTMENTS!$B:$B, EXPENSES!$B:$B, Z$13) -> 0 | AA22: =SUMIFS(EXPENSES!$F:$F, EXPENSES!$D:$D,DEPARTMENTS!$B:$B, EXPENSES!$B:$B, AA$13) -> 0 | AB22: =SUMIFS(EXPENSES!$F:$F, EXPENSES!$D:$D,DEPARTMENTS!$B:$B, EXPENSES!$B:$B, AB$13) -> 0 | AC22: =SUMIFS(EXPENSES!$F:$F, EXPENSES!$D:$D,DEPARTMENTS!$B:$B, EXPENSES!$B:$B, AC$13) -> 0 | ... AG22: =SUMIFS(EXPENSES!$F:$F, EXPENSES!$D:$D,DEPARTMENTS!$B:$B, EXPENSES!$B:$B, AG$13) -> 0 | AH22: =SUM(V22:AG22) -> 7000 | AK22: =SUMIFS(COLLECTION!$E:$E, COLLECTION!$D:$D,DEPARTMENTS!$B:$B, COLLECTION!$B:$B, AK$12, COLLECTION!$C:$C, AK$13) + SUMIFS(BANK!$E:$E, BANK!$D:$D,DEPARTMENTS!$B:$B, BANK!$B:$B, AK$12, BANK!$C:$C, AK$13) + SUMIFS(TRUST!$E:$E, TRUST!$D:$D,DEPARTMENTS!$B:$B, TRUST!$B:$B, AK$12, TRUST!$C:$C, AK$13) -> 0 | AL22: =SUMIFS(COLLECTION!$E:$E, COLLECTION!$D:$D,DEPARTMENTS!$B:$B, COLLECTION!$B:$B, AL$12, COLLECTION!$C:$C, AL$13) + SUMIFS(BANK!$E:$E, BANK!$D:$D,DEPARTMENTS!$B:$B, BANK!$B:$B, AL$12, BANK!$C:$C, AL$13) + SUMIFS(TRUST!$E:$E, TRUST!$D:$D,DEPARTMENTS!$B:$B, TRUST!$B:$B, AL$12, TRUST!$C:$C, AL$13) -> 3800 | AM22: =SUMIFS(COLLECTION!$E:$E, COLLECTION!$D:$D,DEPARTMENTS!$B:$B, COLLECTION!$B:$B, AM$12, COLLECTION!$C:$C, AM$13) + SUMIFS(BANK!$E:$E, BANK!$D:$D,DEPARTMENTS!$B:$B, BANK!$B:$B, AM$12, BANK!$C:$C, AM$13) + SUMIFS(TRUST!$E:$E, TRUST!$D:$D,DEPARTMENTS!$B:$B, TRUST!$B:$B, AM$12, TRUST!$C:$C, AM$13) -> 3200 | AN22: =SUMIFS(COLLECTION!$E:$E, COLLECTION!$D:$D,DEPARTMENTS!$B:$B, COLLECTION!$B:$B, AN$12, COLLECTION!$C:$C, AN$13) + SUMIFS(BANK!$E:$E, BANK!$D:$D,DEPARTMENTS!$B:$B, BANK!$B:$B, AN$12, BANK!$C:$C, AN$13) + SUMIFS(TRUST!$E:$E, TRUST!$D:$D,DEPARTMENTS!$B:$B, TRUST!$B:$B, AN$12, TRUST!$C:$C, AN$13) -> 1800 | AO22: =SUMIFS(COLLECTION!$E:$E, COLLECTION!$D:$D,DEPARTMENTS!$B:$B, COLLECTION!$B:$B, AO$12, COLLECTION!$C:$C, AO$13) + SUMIFS(BANK!$E:$E, BANK!$D:$D,DEPARTMENTS!$B:$B, BANK!$B:$B, AO$12, BANK!$C:$C, AO$13) + SUMIFS(TRUST!$E:$E, TRUST!$D:$D,DEPARTMENTS!$B:$B, TRUST!$B:$B, AO$12, TRUST!$C:$C, AO$13) -> 2600 | AP22: =SUMIFS(COLLECTION!$E:$E, COLLECTION!$D:$D,DEPARTMENTS!$B:$B, COLLECTION!$B:$B, AP$12, COLLECTION!$C:$C, AP$13) + SUMIFS(BANK!$E:$E, BANK!$D:$D,DEPARTMENTS!$B:$B, BANK!$B:$B, AP$12, BANK!$C:$C, AP$13) + SUMIFS(TRUST!$E:$E, TRUST!$D:$D,DEPARTMENTS!$B:$B, TRUST!$B:$B, AP$12, TRUST!$C:$C, AP$13) -> 1600 | AQ22: =SUMIFS(COLLECTION!$E:$E, COLLECTION!$D:$D,DEPARTMENTS!$B:$B, COLLECTION!$B:$B, AQ$12, COLLECTION!$C:$C, AQ$13) + SUMIFS(BANK!$E:$E, BANK!$D:$D,DEPARTMENTS!$B:$B, BANK!$B:$B, AQ$12, BANK!$C:$C, AQ$13) + SUMIFS(TRUST!$E:$E, TRUST!$D:$D,DEPARTMENTS!$B:$B, TRUST!$B:$B, AQ$12, TRUST!$C:$C, AQ$13) -> 1100 | AR22: =SUMIFS(COLLECTION!$E:$E, COLLECTION!$D:$D,DEPARTMENTS!$B:$B, COLLECTION!$B:$B, AR$12, COLLECTION!$C:$C, AR$13) + SUMIFS(BANK!$E:$E, BANK!$D:$D,DEPARTMENTS!$B:$B, BANK!$B:$B, AR$12, BANK!$C:$C, AR$13) + SUMIFS(TRUST!$E:$E, TRUST!$D:$D,DEPARTMENTS!$B:$B, TRUST!$B:$B, AR$12, TRUST!$C:$C, AR$13) -> 200 | ... CQ22: =SUMIFS(COLLECTION!$E:$E, COLLECTION!$D:$D,DEPARTMENTS!$B:$B, COLLECTION!$B:$B, CQ$12, COLLECTION!$C:$C, CQ$13) + SUMIFS(BANK!$E:$E, BANK!$D:$D,DEPARTMENTS!$B:$B, BANK!$B:$B, CQ$12, BANK!$C:$C, CQ$13) + SUMIFS(TRUST!$E:$E, TRUST!$D:$D,DEPARTMENTS!$B:$B, TRUST!$B:$B, CQ$12, TRUST!$C:$C, CQ$13) -> 0 | CR22: =SUM(AK22:CQ22) -> 14300
B23: ADVENTURERS | C23: 0 | D23: =SUMIF(COLLECTION!D:D,DEPARTMENTS!B:B,COLLECTION!E:E)+SUMIF(BANK!D:D,DEPARTMENTS!B:B,BANK!E:E)+SUMIF(TRUST!D:D,DEPARTMENTS!B:B,TRUST!E:E) -> 33810 | E23: =SUMIF(EXPENSES!D:D,DEPARTMENTS!B:B,EXPENSES!F:F) -> 31249 | F23: =D23-E23+C23 -> 2561 | H23: =SUMIFS(COLLECTION!$E:$E, COLLECTION!$D:$D,DEPARTMENTS!$B:$B, COLLECTION!$B:$B, H$13, COLLECTION!$B:$B, H$13) + SUMIFS(BANK!$E:$E, BANK!$D:$D,DEPARTMENTS!$B:$B, BANK!$B:$B, H$13, BANK!$B:$B, H$13) + SUMIFS(TRUST!$E:$E, TRUST!$D:$D,DEPARTMENTS!$B:$B, TRUST!$B:$B, H$13, TRUST!$B:$B, H$13) -> 3000 | I23: =SUMIFS(COLLECTION!$E:$E, COLLECTION!$D:$D,DEPARTMENTS!$B:$B, COLLECTION!$B:$B, I$13, COLLECTION!$B:$B, I$13) + SUMIFS(BANK!$E:$E, BANK!$D:$D,DEPARTMENTS!$B:$B, BANK!$B:$B, I$13, BANK!$B:$B, I$13) + SUMIFS(TRUST!$E:$E, TRUST!$D:$D,DEPARTMENTS!$B:$B, TRUST!$B:$B, I$13, TRUST!$B:$B, I$13) -> 3000 | J23: =SUMIFS(COLLECTION!$E:$E, COLLECTION!$D:$D,DEPARTMENTS!$B:$B, COLLECTION!$B:$B, J$13, COLLECTION!$B:$B, J$13) + SUMIFS(BANK!$E:$E, BANK!$D:$D,DEPARTMENTS!$B:$B, BANK!$B:$B, J$13, BANK!$B:$B, J$13) + SUMIFS(TRUST!$E:$E, TRUST!$D:$D,DEPARTMENTS!$B:$B, TRUST!$B:$B, J$13, TRUST!$B:$B, J$13) -> 16400 | K23: =SUMIFS(COLLECTION!$E:$E, COLLECTION!$D:$D,DEPARTMENTS!$B:$B, COLLECTION!$B:$B, K$13, COLLECTION!$B:$B, K$13) + SUMIFS(BANK!$E:$E, BANK!$D:$D,DEPARTMENTS!$B:$B, BANK!$B:$B, K$13, BANK!$B:$B, K$13) + SUMIFS(TRUST!$E:$E, TRUST!$D:$D,DEPARTMENTS!$B:$B, TRUST!$B:$B, K$13, TRUST!$B:$B, K$13) -> 0 | L23: =SUMIFS(COLLECTION!$E:$E, COLLECTION!$D:$D,DEPARTMENTS!$B:$B, COLLECTION!$B:$B, L$13, COLLECTION!$B:$B, L$13) + SUMIFS(BANK!$E:$E, BANK!$D:$D,DEPARTMENTS!$B:$B, BANK!$B:$B, L$13, BANK!$B:$B, L$13) + SUMIFS(TRUST!$E:$E, TRUST!$D:$D,DEPARTMENTS!$B:$B, TRUST!$B:$B, L$13, TRUST!$B:$B, L$13) -> 11410 | M23: =SUMIFS(COLLECTION!$E:$E, COLLECTION!$D:$D,DEPARTMENTS!$B:$B, COLLECTION!$B:$B, M$13, COLLECTION!$B:$B, M$13) + SUMIFS(BANK!$E:$E, BANK!$D:$D,DEPARTMENTS!$B:$B, BANK!$B:$B, M$13, BANK!$B:$B, M$13) + SUMIFS(TRUST!$E:$E, TRUST!$D:$D,DEPARTMENTS!$B:$B, TRUST!$B:$B, M$13, TRUST!$B:$B, M$13) -> 0 | N23: =SUMIFS(COLLECTION!$E:$E, COLLECTION!$D:$D,DEPARTMENTS!$B:$B, COLLECTION!$B:$B, N$13, COLLECTION!$B:$B, N$13) + SUMIFS(BANK!$E:$E, BANK!$D:$D,DEPARTMENTS!$B:$B, BANK!$B:$B, N$13, BANK!$B:$B, N$13) + SUMIFS(TRUST!$E:$E, TRUST!$D:$D,DEPARTMENTS!$B:$B, TRUST!$B:$B, N$13, TRUST!$B:$B, N$13) -> 0 | O23: =SUMIFS(COLLECTION!$E:$E, COLLECTION!$D:$D,DEPARTMENTS!$B:$B, COLLECTION!$B:$B, O$13, COLLECTION!$B:$B, O$13) + SUMIFS(BANK!$E:$E, BANK!$D:$D,DEPARTMENTS!$B:$B, BANK!$B:$B, O$13, BANK!$B:$B, O$13) + SUMIFS(TRUST!$E:$E, TRUST!$D:$D,DEPARTMENTS!$B:$B, TRUST!$B:$B, O$13, TRUST!$B:$B, O$13) -> 0 | ... S23: =SUMIFS(COLLECTION!$E:$E, COLLECTION!$D:$D,DEPARTMENTS!$B:$B, COLLECTION!$B:$B, S$13, COLLECTION!$B:$B, S$13) + SUMIFS(BANK!$E:$E, BANK!$D:$D,DEPARTMENTS!$B:$B, BANK!$B:$B, S$13, BANK!$B:$B, S$13) + SUMIFS(TRUST!$E:$E, TRUST!$D:$D,DEPARTMENTS!$B:$B, TRUST!$B:$B, S$13, TRUST!$B:$B, S$13) -> 0 | T23: =SUM(H23:S23) -> 33810 | V23: =SUMIFS(EXPENSES!$F:$F, EXPENSES!$D:$D,DEPARTMENTS!$B:$B, EXPENSES!$B:$B, V$13) -> 0 | W23: =SUMIFS(EXPENSES!$F:$F, EXPENSES!$D:$D,DEPARTMENTS!$B:$B, EXPENSES!$B:$B, W$13) -> 4000 | X23: =SUMIFS(EXPENSES!$F:$F, EXPENSES!$D:$D,DEPARTMENTS!$B:$B, EXPENSES!$B:$B, X$13) -> 17105 | Y23: =SUMIFS(EXPENSES!$F:$F, EXPENSES!$D:$D,DEPARTMENTS!$B:$B, EXPENSES!$B:$B, Y$13) -> 0 | Z23: =SUMIFS(EXPENSES!$F:$F, EXPENSES!$D:$D,DEPARTMENTS!$B:$B, EXPENSES!$B:$B, Z$13) -> 10144 | AA23: =SUMIFS(EXPENSES!$F:$F, EXPENSES!$D:$D,DEPARTMENTS!$B:$B, EXPENSES!$B:$B, AA$13) -> 0 | AB23: =SUMIFS(EXPENSES!$F:$F, EXPENSES!$D:$D,DEPARTMENTS!$B:$B, EXPENSES!$B:$B, AB$13) -> 0 | AC23: =SUMIFS(EXPENSES!$F:$F, EXPENSES!$D:$D,DEPARTMENTS!$B:$B, EXPENSES!$B:$B, AC$13) -> 0 | ... AG23: =SUMIFS(EXPENSES!$F:$F, EXPENSES!$D:$D,DEPARTMENTS!$B:$B, EXPENSES!$B:$B, AG$13) -> 0 | AH23: =SUM(V23:AG23) -> 31249 | AK23: =SUMIFS(COLLECTION!$E:$E, COLLECTION!$D:$D,DEPARTMENTS!$B:$B, COLLECTION!$B:$B, AK$12, COLLECTION!$C:$C, AK$13) + SUMIFS(BANK!$E:$E, BANK!$D:$D,DEPARTMENTS!$B:$B, BANK!$B:$B, AK$12, BANK!$C:$C, AK$13) + SUMIFS(TRUST!$E:$E, TRUST!$D:$D,DEPARTMENTS!$B:$B, TRUST!$B:$B, AK$12, TRUST!$C:$C, AK$13) -> 2800 | AL23: =SUMIFS(COLLECTION!$E:$E, COLLECTION!$D:$D,DEPARTMENTS!$B:$B, COLLECTION!$B:$B, AL$12, COLLECTION!$C:$C, AL$13) + SUMIFS(BANK!$E:$E, BANK!$D:$D,DEPARTMENTS!$B:$B, BANK!$B:$B, AL$12, BANK!$C:$C, AL$13) + SUMIFS(TRUST!$E:$E, TRUST!$D:$D,DEPARTMENTS!$B:$B, TRUST!$B:$B, AL$12, TRUST!$C:$C, AL$13) -> 0 | AM23: =SUMIFS(COLLECTION!$E:$E, COLLECTION!$D:$D,DEPARTMENTS!$B:$B, COLLECTION!$B:$B, AM$12, COLLECTION!$C:$C, AM$13) + SUMIFS(BANK!$E:$E, BANK!$D:$D,DEPARTMENTS!$B:$B, BANK!$B:$B, AM$12, BANK!$C:$C, AM$13) + SUMIFS(TRUST!$E:$E, TRUST!$D:$D,DEPARTMENTS!$B:$B, TRUST!$B:$B, AM$12, TRUST!$C:$C, AM$13) -> 200 | AN23: =SUMIFS(COLLECTION!$E:$E, COLLECTION!$D:$D,DEPARTMENTS!$B:$B, COLLECTION!$B:$B, AN$12, COLLECTION!$C:$C, AN$13) + SUMIFS(BANK!$E:$E, BANK!$D:$D,DEPARTMENTS!$B:$B, BANK!$B:$B, AN$12, BANK!$C:$C, AN$13) + SUMIFS(TRUST!$E:$E, TRUST!$D:$D,DEPARTMENTS!$B:$B, TRUST!$B:$B, AN$12, TRUST!$C:$C, AN$13) -> 0 | AO23: =SUMIFS(COLLECTION!$E:$E, COLLECTION!$D:$D,DEPARTMENTS!$B:$B, COLLECTION!$B:$B, AO$12, COLLECTION!$C:$C, AO$13) + SUMIFS(BANK!$E:$E, BANK!$D:$D,DEPARTMENTS!$B:$B, BANK!$B:$B, AO$12, BANK!$C:$C, AO$13) + SUMIFS(TRUST!$E:$E, TRUST!$D:$D,DEPARTMENTS!$B:$B, TRUST!$B:$B, AO$12, TRUST!$C:$C, AO$13) -> 0 | AP23: =SUMIFS(COLLECTION!$E:$E, COLLECTION!$D:$D,DEPARTMENTS!$B:$B, COLLECTION!$B:$B, AP$12, COLLECTION!$C:$C, AP$13) + SUMIFS(BANK!$E:$E, BANK!$D:$D,DEPARTMENTS!$B:$B, BANK!$B:$B, AP$12, BANK!$C:$C, AP$13) + SUMIFS(TRUST!$E:$E, TRUST!$D:$D,DEPARTMENTS!$B:$B, TRUST!$B:$B, AP$12, TRUST!$C:$C, AP$13) -> 0 | AQ23: =SUMIFS(COLLECTION!$E:$E, COLLECTION!$D:$D,DEPARTMENTS!$B:$B, COLLECTION!$B:$B, AQ$12, COLLECTION!$C:$C, AQ$13) + SUMIFS(BANK!$E:$E, BANK!$D:$D,DEPARTMENTS!$B:$B, BANK!$B:$B, AQ$12, BANK!$C:$C, AQ$13) + SUMIFS(TRUST!$E:$E, TRUST!$D:$D,DEPARTMENTS!$B:$B, TRUST!$B:$B, AQ$12, TRUST!$C:$C, AQ$13) -> 300 | AR23: =SUMIFS(COLLECTION!$E:$E, COLLECTION!$D:$D,DEPARTMENTS!$B:$B, COLLECTION!$B:$B, AR$12, COLLECTION!$C:$C, AR$13) + SUMIFS(BANK!$E:$E, BANK!$D:$D,DEPARTMENTS!$B:$B, BANK!$B:$B, AR$12, BANK!$C:$C, AR$13) + SUMIFS(TRUST!$E:$E, TRUST!$D:$D,DEPARTMENTS!$B:$B, TRUST!$B:$B, AR$12, TRUST!$C:$C, AR$13) -> 0 | ... CQ23: =SUMIFS(COLLECTION!$E:$E, COLLECTION!$D:$D,DEPARTMENTS!$B:$B, COLLECTION!$B:$B, CQ$12, COLLECTION!$C:$C, CQ$13) + SUMIFS(BANK!$E:$E, BANK!$D:$D,DEPARTMENTS!$B:$B, BANK!$B:$B, CQ$12, BANK!$C:$C, CQ$13) + SUMIFS(TRUST!$E:$E, TRUST!$D:$D,DEPARTMENTS!$B:$B, TRUST!$B:$B, CQ$12, TRUST!$C:$C, CQ$13) -> 0 | CR23: =SUM(AK23:CQ23) -> 33810
B24: CHILDREN MINISTRY | C24: 28078 | D24: =SUMIF(COLLECTION!D:D,DEPARTMENTS!B:B,COLLECTION!E:E)+SUMIF(BANK!D:D,DEPARTMENTS!B:B,BANK!E:E)+SUMIF(TRUST!D:D,DEPARTMENTS!B:B,TRUST!E:E) -> 12898 | E24: =SUMIF(EXPENSES!D:D,DEPARTMENTS!B:B,EXPENSES!F:F) -> 21421 | F24: =D24-E24+C24 -> 19555 | H24: =SUMIFS(COLLECTION!$E:$E, COLLECTION!$D:$D,DEPARTMENTS!$B:$B, COLLECTION!$B:$B, H$13, COLLECTION!$B:$B, H$13) + SUMIFS(BANK!$E:$E, BANK!$D:$D,DEPARTMENTS!$B:$B, BANK!$B:$B, H$13, BANK!$B:$B, H$13) + SUMIFS(TRUST!$E:$E, TRUST!$D:$D,DEPARTMENTS!$B:$B, TRUST!$B:$B, H$13, TRUST!$B:$B, H$13) -> 35 | I24: =SUMIFS(COLLECTION!$E:$E, COLLECTION!$D:$D,DEPARTMENTS!$B:$B, COLLECTION!$B:$B, I$13, COLLECTION!$B:$B, I$13) + SUMIFS(BANK!$E:$E, BANK!$D:$D,DEPARTMENTS!$B:$B, BANK!$B:$B, I$13, BANK!$B:$B, I$13) + SUMIFS(TRUST!$E:$E, TRUST!$D:$D,DEPARTMENTS!$B:$B, TRUST!$B:$B, I$13, TRUST!$B:$B, I$13) -> 0 | J24: =SUMIFS(COLLECTION!$E:$E, COLLECTION!$D:$D,DEPARTMENTS!$B:$B, COLLECTION!$B:$B, J$13, COLLECTION!$B:$B, J$13) + SUMIFS(BANK!$E:$E, BANK!$D:$D,DEPARTMENTS!$B:$B, BANK!$B:$B, J$13, BANK!$B:$B, J$13) + SUMIFS(TRUST!$E:$E, TRUST!$D:$D,DEPARTMENTS!$B:$B, TRUST!$B:$B, J$13, TRUST!$B:$B, J$13) -> 0 | K24: =SUMIFS(COLLECTION!$E:$E, COLLECTION!$D:$D,DEPARTMENTS!$B:$B, COLLECTION!$B:$B, K$13, COLLECTION!$B:$B, K$13) + SUMIFS(BANK!$E:$E, BANK!$D:$D,DEPARTMENTS!$B:$B, BANK!$B:$B, K$13, BANK!$B:$B, K$13) + SUMIFS(TRUST!$E:$E, TRUST!$D:$D,DEPARTMENTS!$B:$B, TRUST!$B:$B, K$13, TRUST!$B:$B, K$13) -> 0 | L24: =SUMIFS(COLLECTION!$E:$E, COLLECTION!$D:$D,DEPARTMENTS!$B:$B, COLLECTION!$B:$B, L$13, COLLECTION!$B:$B, L$13) + SUMIFS(BANK!$E:$E, BANK!$D:$D,DEPARTMENTS!$B:$B, BANK!$B:$B, L$13, BANK!$B:$B, L$13) + SUMIFS(TRUST!$E:$E, TRUST!$D:$D,DEPARTMENTS!$B:$B, TRUST!$B:$B, L$13, TRUST!$B:$B, L$13) -> 12863 | M24: =SUMIFS(COLLECTION!$E:$E, COLLECTION!$D:$D,DEPARTMENTS!$B:$B, COLLECTION!$B:$B, M$13, COLLECTION!$B:$B, M$13) + SUMIFS(BANK!$E:$E, BANK!$D:$D,DEPARTMENTS!$B:$B, BANK!$B:$B, M$13, BANK!$B:$B, M$13) + SUMIFS(TRUST!$E:$E, TRUST!$D:$D,DEPARTMENTS!$B:$B, TRUST!$B:$B, M$13, TRUST!$B:$B, M$13) -> 0 | N24: =SUMIFS(COLLECTION!$E:$E, COLLECTION!$D:$D,DEPARTMENTS!$B:$B, COLLECTION!$B:$B, N$13, COLLECTION!$B:$B, N$13) + SUMIFS(BANK!$E:$E, BANK!$D:$D,DEPARTMENTS!$B:$B, BANK!$B:$B, N$13, BANK!$B:$B, N$13) + SUMIFS(TRUST!$E:$E, TRUST!$D:$D,DEPARTMENTS!$B:$B, TRUST!$B:$B, N$13, TRUST!$B:$B, N$13) -> 0 | O24: =SUMIFS(COLLECTION!$E:$E, COLLECTION!$D:$D,DEPARTMENTS!$B:$B, COLLECTION!$B:$B, O$13, COLLECTION!$B:$B, O$13) + SUMIFS(BANK!$E:$E, BANK!$D:$D,DEPARTMENTS!$B:$B, BANK!$B:$B, O$13, BANK!$B:$B, O$13) + SUMIFS(TRUST!$E:$E, TRUST!$D:$D,DEPARTMENTS!$B:$B, TRUST!$B:$B, O$13, TRUST!$B:$B, O$13) -> 0 | ... S24: =SUMIFS(COLLECTION!$E:$E, COLLECTION!$D:$D,DEPARTMENTS!$B:$B, COLLECTION!$B:$B, S$13, COLLECTION!$B:$B, S$13) + SUMIFS(BANK!$E:$E, BANK!$D:$D,DEPARTMENTS!$B:$B, BANK!$B:$B, S$13, BANK!$B:$B, S$13) + SUMIFS(TRUST!$E:$E, TRUST!$D:$D,DEPARTMENTS!$B:$B, TRUST!$B:$B, S$13, TRUST!$B:$B, S$13) -> 0 | T24: =SUM(H24:S24) -> 12898 | V24: =SUMIFS(EXPENSES!$F:$F, EXPENSES!$D:$D,DEPARTMENTS!$B:$B, EXPENSES!$B:$B, V$13) -> 0 | W24: =SUMIFS(EXPENSES!$F:$F, EXPENSES!$D:$D,DEPARTMENTS!$B:$B, EXPENSES!$B:$B, W$13) -> 3203 | X24: =SUMIFS(EXPENSES!$F:$F, EXPENSES!$D:$D,DEPARTMENTS!$B:$B, EXPENSES!$B:$B, X$13) -> 2537 | Y24: =SUMIFS(EXPENSES!$F:$F, EXPENSES!$D:$D,DEPARTMENTS!$B:$B, EXPENSES!$B:$B, Y$13) -> 0 | Z24: =SUMIFS(EXPENSES!$F:$F, EXPENSES!$D:$D,DEPARTMENTS!$B:$B, EXPENSES!$B:$B, Z$13) -> 15681 | AA24: =SUMIFS(EXPENSES!$F:$F, EXPENSES!$D:$D,DEPARTMENTS!$B:$B, EXPENSES!$B:$B, AA$13) -> 0 | AB24: =SUMIFS(EXPENSES!$F:$F, EXPENSES!$D:$D,DEPARTMENTS!$B:$B, EXPENSES!$B:$B, AB$13) -> 0 | AC24: =SUMIFS(EXPENSES!$F:$F, EXPENSES!$D:$D,DEPARTMENTS!$B:$B, EXPENSES!$B:$B, AC$13) -> 0 | ... AG24: =SUMIFS(EXPENSES!$F:$F, EXPENSES!$D:$D,DEPARTMENTS!$B:$B, EXPENSES!$B:$B, AG$13) -> 0 | AH24: =SUM(V24:AG24) -> 21421 | AK24: =SUMIFS(COLLECTION!$E:$E, COLLECTION!$D:$D,DEPARTMENTS!$B:$B, COLLECTION!$B:$B, AK$12, COLLECTION!$C:$C, AK$13) + SUMIFS(BANK!$E:$E, BANK!$D:$D,DEPARTMENTS!$B:$B, BANK!$B:$B, AK$12, BANK!$C:$C, AK$13) + SUMIFS(TRUST!$E:$E, TRUST!$D:$D,DEPARTMENTS!$B:$B, TRUST!$B:$B, AK$12, TRUST!$C:$C, AK$13) -> 0 | AL24: =SUMIFS(COLLECTION!$E:$E, COLLECTION!$D:$D,DEPARTMENTS!$B:$B, COLLECTION!$B:$B, AL$12, COLLECTION!$C:$C, AL$13) + SUMIFS(BANK!$E:$E, BANK!$D:$D,DEPARTMENTS!$B:$B, BANK!$B:$B, AL$12, BANK!$C:$C, AL$13) + SUMIFS(TRUST!$E:$E, TRUST!$D:$D,DEPARTMENTS!$B:$B, TRUST!$B:$B, AL$12, TRUST!$C:$C, AL$13) -> 0 | AM24: =SUMIFS(COLLECTION!$E:$E, COLLECTION!$D:$D,DEPARTMENTS!$B:$B, COLLECTION!$B:$B, AM$12, COLLECTION!$C:$C, AM$13) + SUMIFS(BANK!$E:$E, BANK!$D:$D,DEPARTMENTS!$B:$B, BANK!$B:$B, AM$12, BANK!$C:$C, AM$13) + SUMIFS(TRUST!$E:$E, TRUST!$D:$D,DEPARTMENTS!$B:$B, TRUST!$B:$B, AM$12, TRUST!$C:$C, AM$13) -> 0 | AN24: =SUMIFS(COLLECTION!$E:$E, COLLECTION!$D:$D,DEPARTMENTS!$B:$B, COLLECTION!$B:$B, AN$12, COLLECTION!$C:$C, AN$13) + SUMIFS(BANK!$E:$E, BANK!$D:$D,DEPARTMENTS!$B:$B, BANK!$B:$B, AN$12, BANK!$C:$C, AN$13) + SUMIFS(TRUST!$E:$E, TRUST!$D:$D,DEPARTMENTS!$B:$B, TRUST!$B:$B, AN$12, TRUST!$C:$C, AN$13) -> 35 | AO24: =SUMIFS(COLLECTION!$E:$E, COLLECTION!$D:$D,DEPARTMENTS!$B:$B, COLLECTION!$B:$B, AO$12, COLLECTION!$C:$C, AO$13) + SUMIFS(BANK!$E:$E, BANK!$D:$D,DEPARTMENTS!$B:$B, BANK!$B:$B, AO$12, BANK!$C:$C, AO$13) + SUMIFS(TRUST!$E:$E, TRUST!$D:$D,DEPARTMENTS!$B:$B, TRUST!$B:$B, AO$12, TRUST!$C:$C, AO$13) -> 0 | AP24: =SUMIFS(COLLECTION!$E:$E, COLLECTION!$D:$D,DEPARTMENTS!$B:$B, COLLECTION!$B:$B, AP$12, COLLECTION!$C:$C, AP$13) + SUMIFS(BANK!$E:$E, BANK!$D:$D,DEPARTMENTS!$B:$B, BANK!$B:$B, AP$12, BANK!$C:$C, AP$13) + SUMIFS(TRUST!$E:$E, TRUST!$D:$D,DEPARTMENTS!$B:$B, TRUST!$B:$B, AP$12, TRUST!$C:$C, AP$13) -> 0 | AQ24: =SUMIFS(COLLECTION!$E:$E, COLLECTION!$D:$D,DEPARTMENTS!$B:$B, COLLECTION!$B:$B, AQ$12, COLLECTION!$C:$C, AQ$13) + SUMIFS(BANK!$E:$E, BANK!$D:$D,DEPARTMENTS!$B:$B, BANK!$B:$B, AQ$12, BANK!$C:$C, AQ$13) + SUMIFS(TRUST!$E:$E, TRUST!$D:$D,DEPARTMENTS!$B:$B, TRUST!$B:$B, AQ$12, TRUST!$C:$C, AQ$13) -> 0 | AR24: =SUMIFS(COLLECTION!$E:$E, COLLECTION!$D:$D,DEPARTMENTS!$B:$B, COLLECTION!$B:$B, AR$12, COLLECTION!$C:$C, AR$13) + SUMIFS(BANK!$E:$E, BANK!$D:$D,DEPARTMENTS!$B:$B, BANK!$B:$B, AR$12, BANK!$C:$C, AR$13) + SUMIFS(TRUST!$E:$E, TRUST!$D:$D,DEPARTMENTS!$B:$B, TRUST!$B:$B, AR$12, TRUST!$C:$C, AR$13) -> 0 | ... CQ24: =SUMIFS(COLLECTION!$E:$E, COLLECTION!$D:$D,DEPARTMENTS!$B:$B, COLLECTION!$B:$B, CQ$12, COLLECTION!$C:$C, CQ$13) + SUMIFS(BANK!$E:$E, BANK!$D:$D,DEPARTMENTS!$B:$B, BANK!$B:$B, CQ$12, BANK!$C:$C, CQ$13) + SUMIFS(TRUST!$E:$E, TRUST!$D:$D,DEPARTMENTS!$B:$B, TRUST!$B:$B, CQ$12, TRUST!$C:$C, CQ$13) -> 0 | CR24: =SUM(AK24:CQ24) -> 12898
B25: PATHFINDERS | C25: 13207 | D25: =SUMIF(COLLECTION!D:D,DEPARTMENTS!B:B,COLLECTION!E:E)+SUMIF(BANK!D:D,DEPARTMENTS!B:B,BANK!E:E)+SUMIF(TRUST!D:D,DEPARTMENTS!B:B,TRUST!E:E) -> 6200 | E25: =SUMIF(EXPENSES!D:D,DEPARTMENTS!B:B,EXPENSES!F:F) -> 2287 | F25: =D25-E25+C25 -> 17120 | H25: =SUMIFS(COLLECTION!$E:$E, COLLECTION!$D:$D,DEPARTMENTS!$B:$B, COLLECTION!$B:$B, H$13, COLLECTION!$B:$B, H$13) + SUMIFS(BANK!$E:$E, BANK!$D:$D,DEPARTMENTS!$B:$B, BANK!$B:$B, H$13, BANK!$B:$B, H$13) + SUMIFS(TRUST!$E:$E, TRUST!$D:$D,DEPARTMENTS!$B:$B, TRUST!$B:$B, H$13, TRUST!$B:$B, H$13) -> 5600 | I25: =SUMIFS(COLLECTION!$E:$E, COLLECTION!$D:$D,DEPARTMENTS!$B:$B, COLLECTION!$B:$B, I$13, COLLECTION!$B:$B, I$13) + SUMIFS(BANK!$E:$E, BANK!$D:$D,DEPARTMENTS!$B:$B, BANK!$B:$B, I$13, BANK!$B:$B, I$13) + SUMIFS(TRUST!$E:$E, TRUST!$D:$D,DEPARTMENTS!$B:$B, TRUST!$B:$B, I$13, TRUST!$B:$B, I$13) -> 600 | J25: =SUMIFS(COLLECTION!$E:$E, COLLECTION!$D:$D,DEPARTMENTS!$B:$B, COLLECTION!$B:$B, J$13, COLLECTION!$B:$B, J$13) + SUMIFS(BANK!$E:$E, BANK!$D:$D,DEPARTMENTS!$B:$B, BANK!$B:$B, J$13, BANK!$B:$B, J$13) + SUMIFS(TRUST!$E:$E, TRUST!$D:$D,DEPARTMENTS!$B:$B, TRUST!$B:$B, J$13, TRUST!$B:$B, J$13) -> 0 | K25: =SUMIFS(COLLECTION!$E:$E, COLLECTION!$D:$D,DEPARTMENTS!$B:$B, COLLECTION!$B:$B, K$13, COLLECTION!$B:$B, K$13) + SUMIFS(BANK!$E:$E, BANK!$D:$D,DEPARTMENTS!$B:$B, BANK!$B:$B, K$13, BANK!$B:$B, K$13) + SUMIFS(TRUST!$E:$E, TRUST!$D:$D,DEPARTMENTS!$B:$B, TRUST!$B:$B, K$13, TRUST!$B:$B, K$13) -> 0 | L25: =SUMIFS(COLLECTION!$E:$E, COLLECTION!$D:$D,DEPARTMENTS!$B:$B, COLLECTION!$B:$B, L$13, COLLECTION!$B:$B, L$13) + SUMIFS(BANK!$E:$E, BANK!$D:$D,DEPARTMENTS!$B:$B, BANK!$B:$B, L$13, BANK!$B:$B, L$13) + SUMIFS(TRUST!$E:$E, TRUST!$D:$D,DEPARTMENTS!$B:$B, TRUST!$B:$B, L$13, TRUST!$B:$B, L$13) -> 0 | M25: =SUMIFS(COLLECTION!$E:$E, COLLECTION!$D:$D,DEPARTMENTS!$B:$B, COLLECTION!$B:$B, M$13, COLLECTION!$B:$B, M$13) + SUMIFS(BANK!$E:$E, BANK!$D:$D,DEPARTMENTS!$B:$B, BANK!$B:$B, M$13, BANK!$B:$B, M$13) + SUMIFS(TRUST!$E:$E, TRUST!$D:$D,DEPARTMENTS!$B:$B, TRUST!$B:$B, M$13, TRUST!$B:$B, M$13) -> 0 | N25: =SUMIFS(COLLECTION!$E:$E, COLLECTION!$D:$D,DEPARTMENTS!$B:$B, COLLECTION!$B:$B, N$13, COLLECTION!$B:$B, N$13) + SUMIFS(BANK!$E:$E, BANK!$D:$D,DEPARTMENTS!$B:$B, BANK!$B:$B, N$13, BANK!$B:$B, N$13) + SUMIFS(TRUST!$E:$E, TRUST!$D:$D,DEPARTMENTS!$B:$B, TRUST!$B:$B, N$13, TRUST!$B:$B, N$13) -> 0 | O25: =SUMIFS(COLLECTION!$E:$E, COLLECTION!$D:$D,DEPARTMENTS!$B:$B, COLLECTION!$B:$B, O$13, COLLECTION!$B:$B, O$13) + SUMIFS(BANK!$E:$E, BANK!$D:$D,DEPARTMENTS!$B:$B, BANK!$B:$B, O$13, BANK!$B:$B, O$13) + SUMIFS(TRUST!$E:$E, TRUST!$D:$D,DEPARTMENTS!$B:$B, TRUST!$B:$B, O$13, TRUST!$B:$B, O$13) -> 0 | ... S25: =SUMIFS(COLLECTION!$E:$E, COLLECTION!$D:$D,DEPARTMENTS!$B:$B, COLLECTION!$B:$B, S$13, COLLECTION!$B:$B, S$13) + SUMIFS(BANK!$E:$E, BANK!$D:$D,DEPARTMENTS!$B:$B, BANK!$B:$B, S$13, BANK!$B:$B, S$13) + SUMIFS(TRUST!$E:$E, TRUST!$D:$D,DEPARTMENTS!$B:$B, TRUST!$B:$B, S$13, TRUST!$B:$B, S$13) -> 0 | T25: =SUM(H25:S25) -> 6200 | V25: =SUMIFS(EXPENSES!$F:$F, EXPENSES!$D:$D,DEPARTMENTS!$B:$B, EXPENSES!$B:$B, V$13) -> 0 | W25: =SUMIFS(EXPENSES!$F:$F, EXPENSES!$D:$D,DEPARTMENTS!$B:$B, EXPENSES!$B:$B, W$13) -> 0 | X25: =SUMIFS(EXPENSES!$F:$F, EXPENSES!$D:$D,DEPARTMENTS!$B:$B, EXPENSES!$B:$B, X$13) -> 0 | Y25: =SUMIFS(EXPENSES!$F:$F, EXPENSES!$D:$D,DEPARTMENTS!$B:$B, EXPENSES!$B:$B, Y$13) -> 0 | Z25: =SUMIFS(EXPENSES!$F:$F, EXPENSES!$D:$D,DEPARTMENTS!$B:$B, EXPENSES!$B:$B, Z$13) -> 2287 | AA25: =SUMIFS(EXPENSES!$F:$F, EXPENSES!$D:$D,DEPARTMENTS!$B:$B, EXPENSES!$B:$B, AA$13) -> 0 | AB25: =SUMIFS(EXPENSES!$F:$F, EXPENSES!$D:$D,DEPARTMENTS!$B:$B, EXPENSES!$B:$B, AB$13) -> 0 | AC25: =SUMIFS(EXPENSES!$F:$F, EXPENSES!$D:$D,DEPARTMENTS!$B:$B, EXPENSES!$B:$B, AC$13) -> 0 | ... AG25: =SUMIFS(EXPENSES!$F:$F, EXPENSES!$D:$D,DEPARTMENTS!$B:$B, EXPENSES!$B:$B, AG$13) -> 0 | AH25: =SUM(V25:AG25) -> 2287 | AK25: =SUMIFS(COLLECTION!$E:$E, COLLECTION!$D:$D,DEPARTMENTS!$B:$B, COLLECTION!$B:$B, AK$12, COLLECTION!$C:$C, AK$13) + SUMIFS(BANK!$E:$E, BANK!$D:$D,DEPARTMENTS!$B:$B, BANK!$B:$B, AK$12, BANK!$C:$C, AK$13) + SUMIFS(TRUST!$E:$E, TRUST!$D:$D,DEPARTMENTS!$B:$B, TRUST!$B:$B, AK$12, TRUST!$C:$C, AK$13) -> 4800 | AL25: =SUMIFS(COLLECTION!$E:$E, COLLECTION!$D:$D,DEPARTMENTS!$B:$B, COLLECTION!$B:$B, AL$12, COLLECTION!$C:$C, AL$13) + SUMIFS(BANK!$E:$E, BANK!$D:$D,DEPARTMENTS!$B:$B, BANK!$B:$B, AL$12, BANK!$C:$C, AL$13) + SUMIFS(TRUST!$E:$E, TRUST!$D:$D,DEPARTMENTS!$B:$B, TRUST!$B:$B, AL$12, TRUST!$C:$C, AL$13) -> 200 | AM25: =SUMIFS(COLLECTION!$E:$E, COLLECTION!$D:$D,DEPARTMENTS!$B:$B, COLLECTION!$B:$B, AM$12, COLLECTION!$C:$C, AM$13) + SUMIFS(BANK!$E:$E, BANK!$D:$D,DEPARTMENTS!$B:$B, BANK!$B:$B, AM$12, BANK!$C:$C, AM$13) + SUMIFS(TRUST!$E:$E, TRUST!$D:$D,DEPARTMENTS!$B:$B, TRUST!$B:$B, AM$12, TRUST!$C:$C, AM$13) -> 600 | AN25: =SUMIFS(COLLECTION!$E:$E, COLLECTION!$D:$D,DEPARTMENTS!$B:$B, COLLECTION!$B:$B, AN$12, COLLECTION!$C:$C, AN$13) + SUMIFS(BANK!$E:$E, BANK!$D:$D,DEPARTMENTS!$B:$B, BANK!$B:$B, AN$12, BANK!$C:$C, AN$13) + SUMIFS(TRUST!$E:$E, TRUST!$D:$D,DEPARTMENTS!$B:$B, TRUST!$B:$B, AN$12, TRUST!$C:$C, AN$13) -> 0 | AO25: =SUMIFS(COLLECTION!$E:$E, COLLECTION!$D:$D,DEPARTMENTS!$B:$B, COLLECTION!$B:$B, AO$12, COLLECTION!$C:$C, AO$13) + SUMIFS(BANK!$E:$E, BANK!$D:$D,DEPARTMENTS!$B:$B, BANK!$B:$B, AO$12, BANK!$C:$C, AO$13) + SUMIFS(TRUST!$E:$E, TRUST!$D:$D,DEPARTMENTS!$B:$B, TRUST!$B:$B, AO$12, TRUST!$C:$C, AO$13) -> 0 | AP25: =SUMIFS(COLLECTION!$E:$E, COLLECTION!$D:$D,DEPARTMENTS!$B:$B, COLLECTION!$B:$B, AP$12, COLLECTION!$C:$C, AP$13) + SUMIFS(BANK!$E:$E, BANK!$D:$D,DEPARTMENTS!$B:$B, BANK!$B:$B, AP$12, BANK!$C:$C, AP$13) + SUMIFS(TRUST!$E:$E, TRUST!$D:$D,DEPARTMENTS!$B:$B, TRUST!$B:$B, AP$12, TRUST!$C:$C, AP$13) -> 600 | AQ25: =SUMIFS(COLLECTION!$E:$E, COLLECTION!$D:$D,DEPARTMENTS!$B:$B, COLLECTION!$B:$B, AQ$12, COLLECTION!$C:$C, AQ$13) + SUMIFS(BANK!$E:$E, BANK!$D:$D,DEPARTMENTS!$B:$B, BANK!$B:$B, AQ$12, BANK!$C:$C, AQ$13) + SUMIFS(TRUST!$E:$E, TRUST!$D:$D,DEPARTMENTS!$B:$B, TRUST!$B:$B, AQ$12, TRUST!$C:$C, AQ$13) -> 0 | AR25: =SUMIFS(COLLECTION!$E:$E, COLLECTION!$D:$D,DEPARTMENTS!$B:$B, COLLECTION!$B:$B, AR$12, COLLECTION!$C:$C, AR$13) + SUMIFS(BANK!$E:$E, BANK!$D:$D,DEPARTMENTS!$B:$B, BANK!$B:$B, AR$12, BANK!$C:$C, AR$13) + SUMIFS(TRUST!$E:$E, TRUST!$D:$D,DEPARTMENTS!$B:$B, TRUST!$B:$B, AR$12, TRUST!$C:$C, AR$13) -> 0 | ... CQ25: =SUMIFS(COLLECTION!$E:$E, COLLECTION!$D:$D,DEPARTMENTS!$B:$B, COLLECTION!$B:$B, CQ$12, COLLECTION!$C:$C, CQ$13) + SUMIFS(BANK!$E:$E, BANK!$D:$D,DEPARTMENTS!$B:$B, BANK!$B:$B, CQ$12, BANK!$C:$C, CQ$13) + SUMIFS(TRUST!$E:$E, TRUST!$D:$D,DEPARTMENTS!$B:$B, TRUST!$B:$B, CQ$12, TRUST!$C:$C, CQ$13) -> 0 | CR25: =SUM(AK25:CQ25) -> 6200
B26: ADVENTIST SINGLE ADULT MINISTRIES | C26: 0 | D26: =SUMIF(COLLECTION!D:D,DEPARTMENTS!B:B,COLLECTION!E:E)+SUMIF(BANK!D:D,DEPARTMENTS!B:B,BANK!E:E)+SUMIF(TRUST!D:D,DEPARTMENTS!B:B,TRUST!E:E) -> 400 | E26: =SUMIF(EXPENSES!D:D,DEPARTMENTS!B:B,EXPENSES!F:F) -> 0 | F26: =D26-E26+C26 -> 400 | H26: =SUMIFS(COLLECTION!$E:$E, COLLECTION!$D:$D,DEPARTMENTS!$B:$B, COLLECTION!$B:$B, H$13, COLLECTION!$B:$B, H$13) + SUMIFS(BANK!$E:$E, BANK!$D:$D,DEPARTMENTS!$B:$B, BANK!$B:$B, H$13, BANK!$B:$B, H$13) + SUMIFS(TRUST!$E:$E, TRUST!$D:$D,DEPARTMENTS!$B:$B, TRUST!$B:$B, H$13, TRUST!$B:$B, H$13) -> 0 | I26: =SUMIFS(COLLECTION!$E:$E, COLLECTION!$D:$D,DEPARTMENTS!$B:$B, COLLECTION!$B:$B, I$13, COLLECTION!$B:$B, I$13) + SUMIFS(BANK!$E:$E, BANK!$D:$D,DEPARTMENTS!$B:$B, BANK!$B:$B, I$13, BANK!$B:$B, I$13) + SUMIFS(TRUST!$E:$E, TRUST!$D:$D,DEPARTMENTS!$B:$B, TRUST!$B:$B, I$13, TRUST!$B:$B, I$13) -> 200 | J26: =SUMIFS(COLLECTION!$E:$E, COLLECTION!$D:$D,DEPARTMENTS!$B:$B, COLLECTION!$B:$B, J$13, COLLECTION!$B:$B, J$13) + SUMIFS(BANK!$E:$E, BANK!$D:$D,DEPARTMENTS!$B:$B, BANK!$B:$B, J$13, BANK!$B:$B, J$13) + SUMIFS(TRUST!$E:$E, TRUST!$D:$D,DEPARTMENTS!$B:$B, TRUST!$B:$B, J$13, TRUST!$B:$B, J$13) -> 0 | K26: =SUMIFS(COLLECTION!$E:$E, COLLECTION!$D:$D,DEPARTMENTS!$B:$B, COLLECTION!$B:$B, K$13, COLLECTION!$B:$B, K$13) + SUMIFS(BANK!$E:$E, BANK!$D:$D,DEPARTMENTS!$B:$B, BANK!$B:$B, K$13, BANK!$B:$B, K$13) + SUMIFS(TRUST!$E:$E, TRUST!$D:$D,DEPARTMENTS!$B:$B, TRUST!$B:$B, K$13, TRUST!$B:$B, K$13) -> 200 | L26: =SUMIFS(COLLECTION!$E:$E, COLLECTION!$D:$D,DEPARTMENTS!$B:$B, COLLECTION!$B:$B, L$13, COLLECTION!$B:$B, L$13) + SUMIFS(BANK!$E:$E, BANK!$D:$D,DEPARTMENTS!$B:$B, BANK!$B:$B, L$13, BANK!$B:$B, L$13) + SUMIFS(TRUST!$E:$E, TRUST!$D:$D,DEPARTMENTS!$B:$B, TRUST!$B:$B, L$13, TRUST!$B:$B, L$13) -> 0 | M26: =SUMIFS(COLLECTION!$E:$E, COLLECTION!$D:$D,DEPARTMENTS!$B:$B, COLLECTION!$B:$B, M$13, COLLECTION!$B:$B, M$13) + SUMIFS(BANK!$E:$E, BANK!$D:$D,DEPARTMENTS!$B:$B, BANK!$B:$B, M$13, BANK!$B:$B, M$13) + SUMIFS(TRUST!$E:$E, TRUST!$D:$D,DEPARTMENTS!$B:$B, TRUST!$B:$B, M$13, TRUST!$B:$B, M$13) -> 0 | N26: =SUMIFS(COLLECTION!$E:$E, COLLECTION!$D:$D,DEPARTMENTS!$B:$B, COLLECTION!$B:$B, N$13, COLLECTION!$B:$B, N$13) + SUMIFS(BANK!$E:$E, BANK!$D:$D,DEPARTMENTS!$B:$B, BANK!$B:$B, N$13, BANK!$B:$B, N$13) + SUMIFS(TRUST!$E:$E, TRUST!$D:$D,DEPARTMENTS!$B:$B, TRUST!$B:$B, N$13, TRUST!$B:$B, N$13) -> 0 | O26: =SUMIFS(COLLECTION!$E:$E, COLLECTION!$D:$D,DEPARTMENTS!$B:$B, COLLECTION!$B:$B, O$13, COLLECTION!$B:$B, O$13) + SUMIFS(BANK!$E:$E, BANK!$D:$D,DEPARTMENTS!$B:$B, BANK!$B:$B, O$13, BANK!$B:$B, O$13) + SUMIFS(TRUST!$E:$E, TRUST!$D:$D,DEPARTMENTS!$B:$B, TRUST!$B:$B, O$13, TRUST!$B:$B, O$13) -> 0 | ... S26: =SUMIFS(COLLECTION!$E:$E, COLLECTION!$D:$D,DEPARTMENTS!$B:$B, COLLECTION!$B:$B, S$13, COLLECTION!$B:$B, S$13) + SUMIFS(BANK!$E:$E, BANK!$D:$D,DEPARTMENTS!$B:$B, BANK!$B:$B, S$13, BANK!$B:$B, S$13) + SUMIFS(TRUST!$E:$E, TRUST!$D:$D,DEPARTMENTS!$B:$B, TRUST!$B:$B, S$13, TRUST!$B:$B, S$13) -> 0 | T26: =SUM(H26:S26) -> 400 | V26: =SUMIFS(EXPENSES!$F:$F, EXPENSES!$D:$D,DEPARTMENTS!$B:$B, EXPENSES!$B:$B, V$13) -> 0 | W26: =SUMIFS(EXPENSES!$F:$F, EXPENSES!$D:$D,DEPARTMENTS!$B:$B, EXPENSES!$B:$B, W$13) -> 0 | X26: =SUMIFS(EXPENSES!$F:$F, EXPENSES!$D:$D,DEPARTMENTS!$B:$B, EXPENSES!$B:$B, X$13) -> 0 | Y26: =SUMIFS(EXPENSES!$F:$F, EXPENSES!$D:$D,DEPARTMENTS!$B:$B, EXPENSES!$B:$B, Y$13) -> 0 | Z26: =SUMIFS(EXPENSES!$F:$F, EXPENSES!$D:$D,DEPARTMENTS!$B:$B, EXPENSES!$B:$B, Z$13) -> 0 | AA26: =SUMIFS(EXPENSES!$F:$F, EXPENSES!$D:$D,DEPARTMENTS!$B:$B, EXPENSES!$B:$B, AA$13) -> 0 | AB26: =SUMIFS(EXPENSES!$F:$F, EXPENSES!$D:$D,DEPARTMENTS!$B:$B, EXPENSES!$B:$B, AB$13) -> 0 | AC26: =SUMIFS(EXPENSES!$F:$F, EXPENSES!$D:$D,DEPARTMENTS!$B:$B, EXPENSES!$B:$B, AC$13) -> 0 | ... AG26: =SUMIFS(EXPENSES!$F:$F, EXPENSES!$D:$D,DEPARTMENTS!$B:$B, EXPENSES!$B:$B, AG$13) -> 0 | AH26: =SUM(V26:AG26) -> 0 | AK26: =SUMIFS(COLLECTION!$E:$E, COLLECTION!$D:$D,DEPARTMENTS!$B:$B, COLLECTION!$B:$B, AK$12, COLLECTION!$C:$C, AK$13) + SUMIFS(BANK!$E:$E, BANK!$D:$D,DEPARTMENTS!$B:$B, BANK!$B:$B, AK$12, BANK!$C:$C, AK$13) + SUMIFS(TRUST!$E:$E, TRUST!$D:$D,DEPARTMENTS!$B:$B, TRUST!$B:$B, AK$12, TRUST!$C:$C, AK$13) -> 0 | AL26: =SUMIFS(COLLECTION!$E:$E, COLLECTION!$D:$D,DEPARTMENTS!$B:$B, COLLECTION!$B:$B, AL$12, COLLECTION!$C:$C, AL$13) + SUMIFS(BANK!$E:$E, BANK!$D:$D,DEPARTMENTS!$B:$B, BANK!$B:$B, AL$12, BANK!$C:$C, AL$13) + SUMIFS(TRUST!$E:$E, TRUST!$D:$D,DEPARTMENTS!$B:$B, TRUST!$B:$B, AL$12, TRUST!$C:$C, AL$13) -> 0 | AM26: =SUMIFS(COLLECTION!$E:$E, COLLECTION!$D:$D,DEPARTMENTS!$B:$B, COLLECTION!$B:$B, AM$12, COLLECTION!$C:$C, AM$13) + SUMIFS(BANK!$E:$E, BANK!$D:$D,DEPARTMENTS!$B:$B, BANK!$B:$B, AM$12, BANK!$C:$C, AM$13) + SUMIFS(TRUST!$E:$E, TRUST!$D:$D,DEPARTMENTS!$B:$B, TRUST!$B:$B, AM$12, TRUST!$C:$C, AM$13) -> 0 | AN26: =SUMIFS(COLLECTION!$E:$E, COLLECTION!$D:$D,DEPARTMENTS!$B:$B, COLLECTION!$B:$B, AN$12, COLLECTION!$C:$C, AN$13) + SUMIFS(BANK!$E:$E, BANK!$D:$D,DEPARTMENTS!$B:$B, BANK!$B:$B, AN$12, BANK!$C:$C, AN$13) + SUMIFS(TRUST!$E:$E, TRUST!$D:$D,DEPARTMENTS!$B:$B, TRUST!$B:$B, AN$12, TRUST!$C:$C, AN$13) -> 0 | AO26: =SUMIFS(COLLECTION!$E:$E, COLLECTION!$D:$D,DEPARTMENTS!$B:$B, COLLECTION!$B:$B, AO$12, COLLECTION!$C:$C, AO$13) + SUMIFS(BANK!$E:$E, BANK!$D:$D,DEPARTMENTS!$B:$B, BANK!$B:$B, AO$12, BANK!$C:$C, AO$13) + SUMIFS(TRUST!$E:$E, TRUST!$D:$D,DEPARTMENTS!$B:$B, TRUST!$B:$B, AO$12, TRUST!$C:$C, AO$13) -> 0 | AP26: =SUMIFS(COLLECTION!$E:$E, COLLECTION!$D:$D,DEPARTMENTS!$B:$B, COLLECTION!$B:$B, AP$12, COLLECTION!$C:$C, AP$13) + SUMIFS(BANK!$E:$E, BANK!$D:$D,DEPARTMENTS!$B:$B, BANK!$B:$B, AP$12, BANK!$C:$C, AP$13) + SUMIFS(TRUST!$E:$E, TRUST!$D:$D,DEPARTMENTS!$B:$B, TRUST!$B:$B, AP$12, TRUST!$C:$C, AP$13) -> 200 | AQ26: =SUMIFS(COLLECTION!$E:$E, COLLECTION!$D:$D,DEPARTMENTS!$B:$B, COLLECTION!$B:$B, AQ$12, COLLECTION!$C:$C, AQ$13) + SUMIFS(BANK!$E:$E, BANK!$D:$D,DEPARTMENTS!$B:$B, BANK!$B:$B, AQ$12, BANK!$C:$C, AQ$13) + SUMIFS(TRUST!$E:$E, TRUST!$D:$D,DEPARTMENTS!$B:$B, TRUST!$B:$B, AQ$12, TRUST!$C:$C, AQ$13) -> 0 | AR26: =SUMIFS(COLLECTION!$E:$E, COLLECTION!$D:$D,DEPARTMENTS!$B:$B, COLLECTION!$B:$B, AR$12, COLLECTION!$C:$C, AR$13) + SUMIFS(BANK!$E:$E, BANK!$D:$D,DEPARTMENTS!$B:$B, BANK!$B:$B, AR$12, BANK!$C:$C, AR$13) + SUMIFS(TRUST!$E:$E, TRUST!$D:$D,DEPARTMENTS!$B:$B, TRUST!$B:$B, AR$12, TRUST!$C:$C, AR$13) -> 0 | ... CQ26: =SUMIFS(COLLECTION!$E:$E, COLLECTION!$D:$D,DEPARTMENTS!$B:$B, COLLECTION!$B:$B, CQ$12, COLLECTION!$C:$C, CQ$13) + SUMIFS(BANK!$E:$E, BANK!$D:$D,DEPARTMENTS!$B:$B, BANK!$B:$B, CQ$12, BANK!$C:$C, CQ$13) + SUMIFS(TRUST!$E:$E, TRUST!$D:$D,DEPARTMENTS!$B:$B, TRUST!$B:$B, CQ$12, TRUST!$C:$C, CQ$13) -> 0 | CR26: =SUM(AK26:CQ26) -> 400
B27: ADVENTIST POSSIBILITY MINISTRY | C27: 297 | D27: =SUMIF(COLLECTION!D:D,DEPARTMENTS!B:B,COLLECTION!E:E)+SUMIF(BANK!D:D,DEPARTMENTS!B:B,BANK!E:E)+SUMIF(TRUST!D:D,DEPARTMENTS!B:B,TRUST!E:E) -> 3500 | E27: =SUMIF(EXPENSES!D:D,DEPARTMENTS!B:B,EXPENSES!F:F) -> 0 | F27: =D27-E27+C27 -> 3797 | H27: =SUMIFS(COLLECTION!$E:$E, COLLECTION!$D:$D,DEPARTMENTS!$B:$B, COLLECTION!$B:$B, H$13, COLLECTION!$B:$B, H$13) + SUMIFS(BANK!$E:$E, BANK!$D:$D,DEPARTMENTS!$B:$B, BANK!$B:$B, H$13, BANK!$B:$B, H$13) + SUMIFS(TRUST!$E:$E, TRUST!$D:$D,DEPARTMENTS!$B:$B, TRUST!$B:$B, H$13, TRUST!$B:$B, H$13) -> 0 | I27: =SUMIFS(COLLECTION!$E:$E, COLLECTION!$D:$D,DEPARTMENTS!$B:$B, COLLECTION!$B:$B, I$13, COLLECTION!$B:$B, I$13) + SUMIFS(BANK!$E:$E, BANK!$D:$D,DEPARTMENTS!$B:$B, BANK!$B:$B, I$13, BANK!$B:$B, I$13) + SUMIFS(TRUST!$E:$E, TRUST!$D:$D,DEPARTMENTS!$B:$B, TRUST!$B:$B, I$13, TRUST!$B:$B, I$13) -> 0 | J27: =SUMIFS(COLLECTION!$E:$E, COLLECTION!$D:$D,DEPARTMENTS!$B:$B, COLLECTION!$B:$B, J$13, COLLECTION!$B:$B, J$13) + SUMIFS(BANK!$E:$E, BANK!$D:$D,DEPARTMENTS!$B:$B, BANK!$B:$B, J$13, BANK!$B:$B, J$13) + SUMIFS(TRUST!$E:$E, TRUST!$D:$D,DEPARTMENTS!$B:$B, TRUST!$B:$B, J$13, TRUST!$B:$B, J$13) -> 0 | K27: =SUMIFS(COLLECTION!$E:$E, COLLECTION!$D:$D,DEPARTMENTS!$B:$B, COLLECTION!$B:$B, K$13, COLLECTION!$B:$B, K$13) + SUMIFS(BANK!$E:$E, BANK!$D:$D,DEPARTMENTS!$B:$B, BANK!$B:$B, K$13, BANK!$B:$B, K$13) + SUMIFS(TRUST!$E:$E, TRUST!$D:$D,DEPARTMENTS!$B:$B, TRUST!$B:$B, K$13, TRUST!$B:$B, K$13) -> 3500 | L27: =SUMIFS(COLLECTION!$E:$E, COLLECTION!$D:$D,DEPARTMENTS!$B:$B, COLLECTION!$B:$B, L$13, COLLECTION!$B:$B, L$13) + SUMIFS(BANK!$E:$E, BANK!$D:$D,DEPARTMENTS!$B:$B, BANK!$B:$B, L$13, BANK!$B:$B, L$13) + SUMIFS(TRUST!$E:$E, TRUST!$D:$D,DEPARTMENTS!$B:$B, TRUST!$B:$B, L$13, TRUST!$B:$B, L$13) -> 0 | M27: =SUMIFS(COLLECTION!$E:$E, COLLECTION!$D:$D,DEPARTMENTS!$B:$B, COLLECTION!$B:$B, M$13, COLLECTION!$B:$B, M$13) + SUMIFS(BANK!$E:$E, BANK!$D:$D,DEPARTMENTS!$B:$B, BANK!$B:$B, M$13, BANK!$B:$B, M$13) + SUMIFS(TRUST!$E:$E, TRUST!$D:$D,DEPARTMENTS!$B:$B, TRUST!$B:$B, M$13, TRUST!$B:$B, M$13) -> 0 | N27: =SUMIFS(COLLECTION!$E:$E, COLLECTION!$D:$D,DEPARTMENTS!$B:$B, COLLECTION!$B:$B, N$13, COLLECTION!$B:$B, N$13) + SUMIFS(BANK!$E:$E, BANK!$D:$D,DEPARTMENTS!$B:$B, BANK!$B:$B, N$13, BANK!$B:$B, N$13) + SUMIFS(TRUST!$E:$E, TRUST!$D:$D,DEPARTMENTS!$B:$B, TRUST!$B:$B, N$13, TRUST!$B:$B, N$13) -> 0 | O27: =SUMIFS(COLLECTION!$E:$E, COLLECTION!$D:$D,DEPARTMENTS!$B:$B, COLLECTION!$B:$B, O$13, COLLECTION!$B:$B, O$13) + SUMIFS(BANK!$E:$E, BANK!$D:$D,DEPARTMENTS!$B:$B, BANK!$B:$B, O$13, BANK!$B:$B, O$13) + SUMIFS(TRUST!$E:$E, TRUST!$D:$D,DEPARTMENTS!$B:$B, TRUST!$B:$B, O$13, TRUST!$B:$B, O$13) -> 0 | ... S27: =SUMIFS(COLLECTION!$E:$E, COLLECTION!$D:$D,DEPARTMENTS!$B:$B, COLLECTION!$B:$B, S$13, COLLECTION!$B:$B, S$13) + SUMIFS(BANK!$E:$E, BANK!$D:$D,DEPARTMENTS!$B:$B, BANK!$B:$B, S$13, BANK!$B:$B, S$13) + SUMIFS(TRUST!$E:$E, TRUST!$D:$D,DEPARTMENTS!$B:$B, TRUST!$B:$B, S$13, TRUST!$B:$B, S$13) -> 0 | T27: =SUM(H27:S27) -> 3500 | V27: =SUMIFS(EXPENSES!$F:$F, EXPENSES!$D:$D,DEPARTMENTS!$B:$B, EXPENSES!$B:$B, V$13) -> 0 | W27: =SUMIFS(EXPENSES!$F:$F, EXPENSES!$D:$D,DEPARTMENTS!$B:$B, EXPENSES!$B:$B, W$13) -> 0 | X27: =SUMIFS(EXPENSES!$F:$F, EXPENSES!$D:$D,DEPARTMENTS!$B:$B, EXPENSES!$B:$B, X$13) -> 0 | Y27: =SUMIFS(EXPENSES!$F:$F, EXPENSES!$D:$D,DEPARTMENTS!$B:$B, EXPENSES!$B:$B, Y$13) -> 0 | Z27: =SUMIFS(EXPENSES!$F:$F, EXPENSES!$D:$D,DEPARTMENTS!$B:$B, EXPENSES!$B:$B, Z$13) -> 0 | AA27: =SUMIFS(EXPENSES!$F:$F, EXPENSES!$D:$D,DEPARTMENTS!$B:$B, EXPENSES!$B:$B, AA$13) -> 0 | AB27: =SUMIFS(EXPENSES!$F:$F, EXPENSES!$D:$D,DEPARTMENTS!$B:$B, EXPENSES!$B:$B, AB$13) -> 0 | AC27: =SUMIFS(EXPENSES!$F:$F, EXPENSES!$D:$D,DEPARTMENTS!$B:$B, EXPENSES!$B:$B, AC$13) -> 0 | ... AG27: =SUMIFS(EXPENSES!$F:$F, EXPENSES!$D:$D,DEPARTMENTS!$B:$B, EXPENSES!$B:$B, AG$13) -> 0 | AH27: =SUM(V27:AG27) -> 0 | AK27: =SUMIFS(COLLECTION!$E:$E, COLLECTION!$D:$D,DEPARTMENTS!$B:$B, COLLECTION!$B:$B, AK$12, COLLECTION!$C:$C, AK$13) + SUMIFS(BANK!$E:$E, BANK!$D:$D,DEPARTMENTS!$B:$B, BANK!$B:$B, AK$12, BANK!$C:$C, AK$13) + SUMIFS(TRUST!$E:$E, TRUST!$D:$D,DEPARTMENTS!$B:$B, TRUST!$B:$B, AK$12, TRUST!$C:$C, AK$13) -> 0 | AL27: =SUMIFS(COLLECTION!$E:$E, COLLECTION!$D:$D,DEPARTMENTS!$B:$B, COLLECTION!$B:$B, AL$12, COLLECTION!$C:$C, AL$13) + SUMIFS(BANK!$E:$E, BANK!$D:$D,DEPARTMENTS!$B:$B, BANK!$B:$B, AL$12, BANK!$C:$C, AL$13) + SUMIFS(TRUST!$E:$E, TRUST!$D:$D,DEPARTMENTS!$B:$B, TRUST!$B:$B, AL$12, TRUST!$C:$C, AL$13) -> 0 | AM27: =SUMIFS(COLLECTION!$E:$E, COLLECTION!$D:$D,DEPARTMENTS!$B:$B, COLLECTION!$B:$B, AM$12, COLLECTION!$C:$C, AM$13) + SUMIFS(BANK!$E:$E, BANK!$D:$D,DEPARTMENTS!$B:$B, BANK!$B:$B, AM$12, BANK!$C:$C, AM$13) + SUMIFS(TRUST!$E:$E, TRUST!$D:$D,DEPARTMENTS!$B:$B, TRUST!$B:$B, AM$12, TRUST!$C:$C, AM$13) -> 0 | AN27: =SUMIFS(COLLECTION!$E:$E, COLLECTION!$D:$D,DEPARTMENTS!$B:$B, COLLECTION!$B:$B, AN$12, COLLECTION!$C:$C, AN$13) + SUMIFS(BANK!$E:$E, BANK!$D:$D,DEPARTMENTS!$B:$B, BANK!$B:$B, AN$12, BANK!$C:$C, AN$13) + SUMIFS(TRUST!$E:$E, TRUST!$D:$D,DEPARTMENTS!$B:$B, TRUST!$B:$B, AN$12, TRUST!$C:$C, AN$13) -> 0 | AO27: =SUMIFS(COLLECTION!$E:$E, COLLECTION!$D:$D,DEPARTMENTS!$B:$B, COLLECTION!$B:$B, AO$12, COLLECTION!$C:$C, AO$13) + SUMIFS(BANK!$E:$E, BANK!$D:$D,DEPARTMENTS!$B:$B, BANK!$B:$B, AO$12, BANK!$C:$C, AO$13) + SUMIFS(TRUST!$E:$E, TRUST!$D:$D,DEPARTMENTS!$B:$B, TRUST!$B:$B, AO$12, TRUST!$C:$C, AO$13) -> 0 | AP27: =SUMIFS(COLLECTION!$E:$E, COLLECTION!$D:$D,DEPARTMENTS!$B:$B, COLLECTION!$B:$B, AP$12, COLLECTION!$C:$C, AP$13) + SUMIFS(BANK!$E:$E, BANK!$D:$D,DEPARTMENTS!$B:$B, BANK!$B:$B, AP$12, BANK!$C:$C, AP$13) + SUMIFS(TRUST!$E:$E, TRUST!$D:$D,DEPARTMENTS!$B:$B, TRUST!$B:$B, AP$12, TRUST!$C:$C, AP$13) -> 0 | AQ27: =SUMIFS(COLLECTION!$E:$E, COLLECTION!$D:$D,DEPARTMENTS!$B:$B, COLLECTION!$B:$B, AQ$12, COLLECTION!$C:$C, AQ$13) + SUMIFS(BANK!$E:$E, BANK!$D:$D,DEPARTMENTS!$B:$B, BANK!$B:$B, AQ$12, BANK!$C:$C, AQ$13) + SUMIFS(TRUST!$E:$E, TRUST!$D:$D,DEPARTMENTS!$B:$B, TRUST!$B:$B, AQ$12, TRUST!$C:$C, AQ$13) -> 0 | AR27: =SUMIFS(COLLECTION!$E:$E, COLLECTION!$D:$D,DEPARTMENTS!$B:$B, COLLECTION!$B:$B, AR$12, COLLECTION!$C:$C, AR$13) + SUMIFS(BANK!$E:$E, BANK!$D:$D,DEPARTMENTS!$B:$B, BANK!$B:$B, AR$12, BANK!$C:$C, AR$13) + SUMIFS(TRUST!$E:$E, TRUST!$D:$D,DEPARTMENTS!$B:$B, TRUST!$B:$B, AR$12, TRUST!$C:$C, AR$13) -> 0 | ... CQ27: =SUMIFS(COLLECTION!$E:$E, COLLECTION!$D:$D,DEPARTMENTS!$B:$B, COLLECTION!$B:$B, CQ$12, COLLECTION!$C:$C, CQ$13) + SUMIFS(BANK!$E:$E, BANK!$D:$D,DEPARTMENTS!$B:$B, BANK!$B:$B, CQ$12, BANK!$C:$C, CQ$13) + SUMIFS(TRUST!$E:$E, TRUST!$D:$D,DEPARTMENTS!$B:$B, TRUST!$B:$B, CQ$12, TRUST!$C:$C, CQ$13) -> 0 | CR27: =SUM(AK27:CQ27) -> 3500
B28: MSAMARIA | C28: 575 | D28: =SUMIF(COLLECTION!D:D,DEPARTMENTS!B:B,COLLECTION!E:E)+SUMIF(BANK!D:D,DEPARTMENTS!B:B,BANK!E:E)+SUMIF(TRUST!D:D,DEPARTMENTS!B:B,TRUST!E:E) -> 5805 | E28: =SUMIF(EXPENSES!D:D,DEPARTMENTS!B:B,EXPENSES!F:F) -> 4000 | F28: =D28-E28+C28 -> 2380 | H28: =SUMIFS(COLLECTION!$E:$E, COLLECTION!$D:$D,DEPARTMENTS!$B:$B, COLLECTION!$B:$B, H$13, COLLECTION!$B:$B, H$13) + SUMIFS(BANK!$E:$E, BANK!$D:$D,DEPARTMENTS!$B:$B, BANK!$B:$B, H$13, BANK!$B:$B, H$13) + SUMIFS(TRUST!$E:$E, TRUST!$D:$D,DEPARTMENTS!$B:$B, TRUST!$B:$B, H$13, TRUST!$B:$B, H$13) -> 400 | I28: =SUMIFS(COLLECTION!$E:$E, COLLECTION!$D:$D,DEPARTMENTS!$B:$B, COLLECTION!$B:$B, I$13, COLLECTION!$B:$B, I$13) + SUMIFS(BANK!$E:$E, BANK!$D:$D,DEPARTMENTS!$B:$B, BANK!$B:$B, I$13, BANK!$B:$B, I$13) + SUMIFS(TRUST!$E:$E, TRUST!$D:$D,DEPARTMENTS!$B:$B, TRUST!$B:$B, I$13, TRUST!$B:$B, I$13) -> 1550 | J28: =SUMIFS(COLLECTION!$E:$E, COLLECTION!$D:$D,DEPARTMENTS!$B:$B, COLLECTION!$B:$B, J$13, COLLECTION!$B:$B, J$13) + SUMIFS(BANK!$E:$E, BANK!$D:$D,DEPARTMENTS!$B:$B, BANK!$B:$B, J$13, BANK!$B:$B, J$13) + SUMIFS(TRUST!$E:$E, TRUST!$D:$D,DEPARTMENTS!$B:$B, TRUST!$B:$B, J$13, TRUST!$B:$B, J$13) -> 3855 | K28: =SUMIFS(COLLECTION!$E:$E, COLLECTION!$D:$D,DEPARTMENTS!$B:$B, COLLECTION!$B:$B, K$13, COLLECTION!$B:$B, K$13) + SUMIFS(BANK!$E:$E, BANK!$D:$D,DEPARTMENTS!$B:$B, BANK!$B:$B, K$13, BANK!$B:$B, K$13) + SUMIFS(TRUST!$E:$E, TRUST!$D:$D,DEPARTMENTS!$B:$B, TRUST!$B:$B, K$13, TRUST!$B:$B, K$13) -> 0 | L28: =SUMIFS(COLLECTION!$E:$E, COLLECTION!$D:$D,DEPARTMENTS!$B:$B, COLLECTION!$B:$B, L$13, COLLECTION!$B:$B, L$13) + SUMIFS(BANK!$E:$E, BANK!$D:$D,DEPARTMENTS!$B:$B, BANK!$B:$B, L$13, BANK!$B:$B, L$13) + SUMIFS(TRUST!$E:$E, TRUST!$D:$D,DEPARTMENTS!$B:$B, TRUST!$B:$B, L$13, TRUST!$B:$B, L$13) -> 0 | M28: =SUMIFS(COLLECTION!$E:$E, COLLECTION!$D:$D,DEPARTMENTS!$B:$B, COLLECTION!$B:$B, M$13, COLLECTION!$B:$B, M$13) + SUMIFS(BANK!$E:$E, BANK!$D:$D,DEPARTMENTS!$B:$B, BANK!$B:$B, M$13, BANK!$B:$B, M$13) + SUMIFS(TRUST!$E:$E, TRUST!$D:$D,DEPARTMENTS!$B:$B, TRUST!$B:$B, M$13, TRUST!$B:$B, M$13) -> 0 | N28: =SUMIFS(COLLECTION!$E:$E, COLLECTION!$D:$D,DEPARTMENTS!$B:$B, COLLECTION!$B:$B, N$13, COLLECTION!$B:$B, N$13) + SUMIFS(BANK!$E:$E, BANK!$D:$D,DEPARTMENTS!$B:$B, BANK!$B:$B, N$13, BANK!$B:$B, N$13) + SUMIFS(TRUST!$E:$E, TRUST!$D:$D,DEPARTMENTS!$B:$B, TRUST!$B:$B, N$13, TRUST!$B:$B, N$13) -> 0 | O28: =SUMIFS(COLLECTION!$E:$E, COLLECTION!$D:$D,DEPARTMENTS!$B:$B, COLLECTION!$B:$B, O$13, COLLECTION!$B:$B, O$13) + SUMIFS(BANK!$E:$E, BANK!$D:$D,DEPARTMENTS!$B:$B, BANK!$B:$B, O$13, BANK!$B:$B, O$13) + SUMIFS(TRUST!$E:$E, TRUST!$D:$D,DEPARTMENTS!$B:$B, TRUST!$B:$B, O$13, TRUST!$B:$B, O$13) -> 0 | ... S28: =SUMIFS(COLLECTION!$E:$E, COLLECTION!$D:$D,DEPARTMENTS!$B:$B, COLLECTION!$B:$B, S$13, COLLECTION!$B:$B, S$13) + SUMIFS(BANK!$E:$E, BANK!$D:$D,DEPARTMENTS!$B:$B, BANK!$B:$B, S$13, BANK!$B:$B, S$13) + SUMIFS(TRUST!$E:$E, TRUST!$D:$D,DEPARTMENTS!$B:$B, TRUST!$B:$B, S$13, TRUST!$B:$B, S$13) -> 0 | T28: =SUM(H28:S28) -> 5805 | V28: =SUMIFS(EXPENSES!$F:$F, EXPENSES!$D:$D,DEPARTMENTS!$B:$B, EXPENSES!$B:$B, V$13) -> 0 | W28: =SUMIFS(EXPENSES!$F:$F, EXPENSES!$D:$D,DEPARTMENTS!$B:$B, EXPENSES!$B:$B, W$13) -> 0 | X28: =SUMIFS(EXPENSES!$F:$F, EXPENSES!$D:$D,DEPARTMENTS!$B:$B, EXPENSES!$B:$B, X$13) -> 0 | Y28: =SUMIFS(EXPENSES!$F:$F, EXPENSES!$D:$D,DEPARTMENTS!$B:$B, EXPENSES!$B:$B, Y$13) -> 4000 | Z28: =SUMIFS(EXPENSES!$F:$F, EXPENSES!$D:$D,DEPARTMENTS!$B:$B, EXPENSES!$B:$B, Z$13) -> 0 | AA28: =SUMIFS(EXPENSES!$F:$F, EXPENSES!$D:$D,DEPARTMENTS!$B:$B, EXPENSES!$B:$B, AA$13) -> 0 | AB28: =SUMIFS(EXPENSES!$F:$F, EXPENSES!$D:$D,DEPARTMENTS!$B:$B, EXPENSES!$B:$B, AB$13) -> 0 | AC28: =SUMIFS(EXPENSES!$F:$F, EXPENSES!$D:$D,DEPARTMENTS!$B:$B, EXPENSES!$B:$B, AC$13) -> 0 | ... AG28: =SUMIFS(EXPENSES!$F:$F, EXPENSES!$D:$D,DEPARTMENTS!$B:$B, EXPENSES!$B:$B, AG$13) -> 0 | AH28: =SUM(V28:AG28) -> 4000 | AK28: =SUMIFS(COLLECTION!$E:$E, COLLECTION!$D:$D,DEPARTMENTS!$B:$B, COLLECTION!$B:$B, AK$12, COLLECTION!$C:$C, AK$13) + SUMIFS(BANK!$E:$E, BANK!$D:$D,DEPARTMENTS!$B:$B, BANK!$B:$B, AK$12, BANK!$C:$C, AK$13) + SUMIFS(TRUST!$E:$E, TRUST!$D:$D,DEPARTMENTS!$B:$B, TRUST!$B:$B, AK$12, TRUST!$C:$C, AK$13) -> 200 | AL28: =SUMIFS(COLLECTION!$E:$E, COLLECTION!$D:$D,DEPARTMENTS!$B:$B, COLLECTION!$B:$B, AL$12, COLLECTION!$C:$C, AL$13) + SUMIFS(BANK!$E:$E, BANK!$D:$D,DEPARTMENTS!$B:$B, BANK!$B:$B, AL$12, BANK!$C:$C, AL$13) + SUMIFS(TRUST!$E:$E, TRUST!$D:$D,DEPARTMENTS!$B:$B, TRUST!$B:$B, AL$12, TRUST!$C:$C, AL$13) -> 200 | AM28: =SUMIFS(COLLECTION!$E:$E, COLLECTION!$D:$D,DEPARTMENTS!$B:$B, COLLECTION!$B:$B, AM$12, COLLECTION!$C:$C, AM$13) + SUMIFS(BANK!$E:$E, BANK!$D:$D,DEPARTMENTS!$B:$B, BANK!$B:$B, AM$12, BANK!$C:$C, AM$13) + SUMIFS(TRUST!$E:$E, TRUST!$D:$D,DEPARTMENTS!$B:$B, TRUST!$B:$B, AM$12, TRUST!$C:$C, AM$13) -> 0 | AN28: =SUMIFS(COLLECTION!$E:$E, COLLECTION!$D:$D,DEPARTMENTS!$B:$B, COLLECTION!$B:$B, AN$12, COLLECTION!$C:$C, AN$13) + SUMIFS(BANK!$E:$E, BANK!$D:$D,DEPARTMENTS!$B:$B, BANK!$B:$B, AN$12, BANK!$C:$C, AN$13) + SUMIFS(TRUST!$E:$E, TRUST!$D:$D,DEPARTMENTS!$B:$B, TRUST!$B:$B, AN$12, TRUST!$C:$C, AN$13) -> 0 | AO28: =SUMIFS(COLLECTION!$E:$E, COLLECTION!$D:$D,DEPARTMENTS!$B:$B, COLLECTION!$B:$B, AO$12, COLLECTION!$C:$C, AO$13) + SUMIFS(BANK!$E:$E, BANK!$D:$D,DEPARTMENTS!$B:$B, BANK!$B:$B, AO$12, BANK!$C:$C, AO$13) + SUMIFS(TRUST!$E:$E, TRUST!$D:$D,DEPARTMENTS!$B:$B, TRUST!$B:$B, AO$12, TRUST!$C:$C, AO$13) -> 0 | AP28: =SUMIFS(COLLECTION!$E:$E, COLLECTION!$D:$D,DEPARTMENTS!$B:$B, COLLECTION!$B:$B, AP$12, COLLECTION!$C:$C, AP$13) + SUMIFS(BANK!$E:$E, BANK!$D:$D,DEPARTMENTS!$B:$B, BANK!$B:$B, AP$12, BANK!$C:$C, AP$13) + SUMIFS(TRUST!$E:$E, TRUST!$D:$D,DEPARTMENTS!$B:$B, TRUST!$B:$B, AP$12, TRUST!$C:$C, AP$13) -> 0 | AQ28: =SUMIFS(COLLECTION!$E:$E, COLLECTION!$D:$D,DEPARTMENTS!$B:$B, COLLECTION!$B:$B, AQ$12, COLLECTION!$C:$C, AQ$13) + SUMIFS(BANK!$E:$E, BANK!$D:$D,DEPARTMENTS!$B:$B, BANK!$B:$B, AQ$12, BANK!$C:$C, AQ$13) + SUMIFS(TRUST!$E:$E, TRUST!$D:$D,DEPARTMENTS!$B:$B, TRUST!$B:$B, AQ$12, TRUST!$C:$C, AQ$13) -> 1550 | AR28: =SUMIFS(COLLECTION!$E:$E, COLLECTION!$D:$D,DEPARTMENTS!$B:$B, COLLECTION!$B:$B, AR$12, COLLECTION!$C:$C, AR$13) + SUMIFS(BANK!$E:$E, BANK!$D:$D,DEPARTMENTS!$B:$B, BANK!$B:$B, AR$12, BANK!$C:$C, AR$13) + SUMIFS(TRUST!$E:$E, TRUST!$D:$D,DEPARTMENTS!$B:$B, TRUST!$B:$B, AR$12, TRUST!$C:$C, AR$13) -> 0 | ... CQ28: =SUMIFS(COLLECTION!$E:$E, COLLECTION!$D:$D,DEPARTMENTS!$B:$B, COLLECTION!$B:$B, CQ$12, COLLECTION!$C:$C, CQ$13) + SUMIFS(BANK!$E:$E, BANK!$D:$D,DEPARTMENTS!$B:$B, BANK!$B:$B, CQ$12, BANK!$C:$C, CQ$13) + SUMIFS(TRUST!$E:$E, TRUST!$D:$D,DEPARTMENTS!$B:$B, TRUST!$B:$B, CQ$12, TRUST!$C:$C, CQ$13) -> 0 | CR28: =SUM(AK28:CQ28) -> 5805
... B32: COMMUNICATION | C32: 25867 | D32: =SUMIF(COLLECTION!D:D,DEPARTMENTS!B:B,COLLECTION!E:E)+SUMIF(BANK!D:D,DEPARTMENTS!B:B,BANK!E:E)+SUMIF(TRUST!D:D,DEPARTMENTS!B:B,TRUST!E:E) -> 300 | E32: =SUMIF(EXPENSES!D:D,DEPARTMENTS!B:B,EXPENSES!F:F) -> 15175 | F32: =D32-E32+C32 -> 10992 | H32: =SUMIFS(COLLECTION!$E:$E, COLLECTION!$D:$D,DEPARTMENTS!$B:$B, COLLECTION!$B:$B, H$13, COLLECTION!$B:$B, H$13) + SUMIFS(BANK!$E:$E, BANK!$D:$D,DEPARTMENTS!$B:$B, BANK!$B:$B, H$13, BANK!$B:$B, H$13) + SUMIFS(TRUST!$E:$E, TRUST!$D:$D,DEPARTMENTS!$B:$B, TRUST!$B:$B, H$13, TRUST!$B:$B, H$13) -> 0 | I32: =SUMIFS(COLLECTION!$E:$E, COLLECTION!$D:$D,DEPARTMENTS!$B:$B, COLLECTION!$B:$B, I$13, COLLECTION!$B:$B, I$13) + SUMIFS(BANK!$E:$E, BANK!$D:$D,DEPARTMENTS!$B:$B, BANK!$B:$B, I$13, BANK!$B:$B, I$13) + SUMIFS(TRUST!$E:$E, TRUST!$D:$D,DEPARTMENTS!$B:$B, TRUST!$B:$B, I$13, TRUST!$B:$B, I$13) -> 0 | J32: =SUMIFS(COLLECTION!$E:$E, COLLECTION!$D:$D,DEPARTMENTS!$B:$B, COLLECTION!$B:$B, J$13, COLLECTION!$B:$B, J$13) + SUMIFS(BANK!$E:$E, BANK!$D:$D,DEPARTMENTS!$B:$B, BANK!$B:$B, J$13, BANK!$B:$B, J$13) + SUMIFS(TRUST!$E:$E, TRUST!$D:$D,DEPARTMENTS!$B:$B, TRUST!$B:$B, J$13, TRUST!$B:$B, J$13) -> 0 | K32: =SUMIFS(COLLECTION!$E:$E, COLLECTION!$D:$D,DEPARTMENTS!$B:$B, COLLECTION!$B:$B, K$13, COLLECTION!$B:$B, K$13) + SUMIFS(BANK!$E:$E, BANK!$D:$D,DEPARTMENTS!$B:$B, BANK!$B:$B, K$13, BANK!$B:$B, K$13) + SUMIFS(TRUST!$E:$E, TRUST!$D:$D,DEPARTMENTS!$B:$B, TRUST!$B:$B, K$13, TRUST!$B:$B, K$13) -> 300 | L32: =SUMIFS(COLLECTION!$E:$E, COLLECTION!$D:$D,DEPARTMENTS!$B:$B, COLLECTION!$B:$B, L$13, COLLECTION!$B:$B, L$13) + SUMIFS(BANK!$E:$E, BANK!$D:$D,DEPARTMENTS!$B:$B, BANK!$B:$B, L$13, BANK!$B:$B, L$13) + SUMIFS(TRUST!$E:$E, TRUST!$D:$D,DEPARTMENTS!$B:$B, TRUST!$B:$B, L$13, TRUST!$B:$B, L$13) -> 0 | M32: =SUMIFS(COLLECTION!$E:$E, COLLECTION!$D:$D,DEPARTMENTS!$B:$B, COLLECTION!$B:$B, M$13, COLLECTION!$B:$B, M$13) + SUMIFS(BANK!$E:$E, BANK!$D:$D,DEPARTMENTS!$B:$B, BANK!$B:$B, M$13, BANK!$B:$B, M$13) + SUMIFS(TRUST!$E:$E, TRUST!$D:$D,DEPARTMENTS!$B:$B, TRUST!$B:$B, M$13, TRUST!$B:$B, M$13) -> 0 | N32: =SUMIFS(COLLECTION!$E:$E, COLLECTION!$D:$D,DEPARTMENTS!$B:$B, COLLECTION!$B:$B, N$13, COLLECTION!$B:$B, N$13) + SUMIFS(BANK!$E:$E, BANK!$D:$D,DEPARTMENTS!$B:$B, BANK!$B:$B, N$13, BANK!$B:$B, N$13) + SUMIFS(TRUST!$E:$E, TRUST!$D:$D,DEPARTMENTS!$B:$B, TRUST!$B:$B, N$13, TRUST!$B:$B, N$13) -> 0 | O32: =SUMIFS(COLLECTION!$E:$E, COLLECTION!$D:$D,DEPARTMENTS!$B:$B, COLLECTION!$B:$B, O$13, COLLECTION!$B:$B, O$13) + SUMIFS(BANK!$E:$E, BANK!$D:$D,DEPARTMENTS!$B:$B, BANK!$B:$B, O$13, BANK!$B:$B, O$13) + SUMIFS(TRUST!$E:$E, TRUST!$D:$D,DEPARTMENTS!$B:$B, TRUST!$B:$B, O$13, TRUST!$B:$B, O$13) -> 0 | ... S32: =SUMIFS(COLLECTION!$E:$E, COLLECTION!$D:$D,DEPARTMENTS!$B:$B, COLLECTION!$B:$B, S$13, COLLECTION!$B:$B, S$13) + SUMIFS(BANK!$E:$E, BANK!$D:$D,DEPARTMENTS!$B:$B, BANK!$B:$B, S$13, BANK!$B:$B, S$13) + SUMIFS(TRUST!$E:$E, TRUST!$D:$D,DEPARTMENTS!$B:$B, TRUST!$B:$B, S$13, TRUST!$B:$B, S$13) -> 0 | T32: =SUM(H32:S32) -> 300 | V32: =SUMIFS(EXPENSES!$F:$F, EXPENSES!$D:$D,DEPARTMENTS!$B:$B, EXPENSES!$B:$B, V$13) -> 1033 | W32: =SUMIFS(EXPENSES!$F:$F, EXPENSES!$D:$D,DEPARTMENTS!$B:$B, EXPENSES!$B:$B, W$13) -> 4142 | X32: =SUMIFS(EXPENSES!$F:$F, EXPENSES!$D:$D,DEPARTMENTS!$B:$B, EXPENSES!$B:$B, X$13) -> 10000 | Y32: =SUMIFS(EXPENSES!$F:$F, EXPENSES!$D:$D,DEPARTMENTS!$B:$B, EXPENSES!$B:$B, Y$13) -> 0 | Z32: =SUMIFS(EXPENSES!$F:$F, EXPENSES!$D:$D,DEPARTMENTS!$B:$B, EXPENSES!$B:$B, Z$13) -> 0 | AA32: =SUMIFS(EXPENSES!$F:$F, EXPENSES!$D:$D,DEPARTMENTS!$B:$B, EXPENSES!$B:$B, AA$13) -> 0 | AB32: =SUMIFS(EXPENSES!$F:$F, EXPENSES!$D:$D,DEPARTMENTS!$B:$B, EXPENSES!$B:$B, AB$13) -> 0 | AC32: =SUMIFS(EXPENSES!$F:$F, EXPENSES!$D:$D,DEPARTMENTS!$B:$B, EXPENSES!$B:$B, AC$13) -> 0 | ... AG32: =SUMIFS(EXPENSES!$F:$F, EXPENSES!$D:$D,DEPARTMENTS!$B:$B, EXPENSES!$B:$B, AG$13) -> 0 | AH32: =SUM(V32:AG32) -> 15175 | AK32: =SUMIFS(COLLECTION!$E:$E, COLLECTION!$D:$D,DEPARTMENTS!$B:$B, COLLECTION!$B:$B, AK$12, COLLECTION!$C:$C, AK$13) + SUMIFS(BANK!$E:$E, BANK!$D:$D,DEPARTMENTS!$B:$B, BANK!$B:$B, AK$12, BANK!$C:$C, AK$13) + SUMIFS(TRUST!$E:$E, TRUST!$D:$D,DEPARTMENTS!$B:$B, TRUST!$B:$B, AK$12, TRUST!$C:$C, AK$13) -> 0 | AL32: =SUMIFS(COLLECTION!$E:$E, COLLECTION!$D:$D,DEPARTMENTS!$B:$B, COLLECTION!$B:$B, AL$12, COLLECTION!$C:$C, AL$13) + SUMIFS(BANK!$E:$E, BANK!$D:$D,DEPARTMENTS!$B:$B, BANK!$B:$B, AL$12, BANK!$C:$C, AL$13) + SUMIFS(TRUST!$E:$E, TRUST!$D:$D,DEPARTMENTS!$B:$B, TRUST!$B:$B, AL$12, TRUST!$C:$C, AL$13) -> 0 | AM32: =SUMIFS(COLLECTION!$E:$E, COLLECTION!$D:$D,DEPARTMENTS!$B:$B, COLLECTION!$B:$B, AM$12, COLLECTION!$C:$C, AM$13) + SUMIFS(BANK!$E:$E, BANK!$D:$D,DEPARTMENTS!$B:$B, BANK!$B:$B, AM$12, BANK!$C:$C, AM$13) + SUMIFS(TRUST!$E:$E, TRUST!$D:$D,DEPARTMENTS!$B:$B, TRUST!$B:$B, AM$12, TRUST!$C:$C, AM$13) -> 0 | AN32: =SUMIFS(COLLECTION!$E:$E, COLLECTION!$D:$D,DEPARTMENTS!$B:$B, COLLECTION!$B:$B, AN$12, COLLECTION!$C:$C, AN$13) + SUMIFS(BANK!$E:$E, BANK!$D:$D,DEPARTMENTS!$B:$B, BANK!$B:$B, AN$12, BANK!$C:$C, AN$13) + SUMIFS(TRUST!$E:$E, TRUST!$D:$D,DEPARTMENTS!$B:$B, TRUST!$B:$B, AN$12, TRUST!$C:$C, AN$13) -> 0 | AO32: =SUMIFS(COLLECTION!$E:$E, COLLECTION!$D:$D,DEPARTMENTS!$B:$B, COLLECTION!$B:$B, AO$12, COLLECTION!$C:$C, AO$13) + SUMIFS(BANK!$E:$E, BANK!$D:$D,DEPARTMENTS!$B:$B, BANK!$B:$B, AO$12, BANK!$C:$C, AO$13) + SUMIFS(TRUST!$E:$E, TRUST!$D:$D,DEPARTMENTS!$B:$B, TRUST!$B:$B, AO$12, TRUST!$C:$C, AO$13) -> 0 | AP32: =SUMIFS(COLLECTION!$E:$E, COLLECTION!$D:$D,DEPARTMENTS!$B:$B, COLLECTION!$B:$B, AP$12, COLLECTION!$C:$C, AP$13) + SUMIFS(BANK!$E:$E, BANK!$D:$D,DEPARTMENTS!$B:$B, BANK!$B:$B, AP$12, BANK!$C:$C, AP$13) + SUMIFS(TRUST!$E:$E, TRUST!$D:$D,DEPARTMENTS!$B:$B, TRUST!$B:$B, AP$12, TRUST!$C:$C, AP$13) -> 0 | AQ32: =SUMIFS(COLLECTION!$E:$E, COLLECTION!$D:$D,DEPARTMENTS!$B:$B, COLLECTION!$B:$B, AQ$12, COLLECTION!$C:$C, AQ$13) + SUMIFS(BANK!$E:$E, BANK!$D:$D,DEPARTMENTS!$B:$B, BANK!$B:$B, AQ$12, BANK!$C:$C, AQ$13) + SUMIFS(TRUST!$E:$E, TRUST!$D:$D,DEPARTMENTS!$B:$B, TRUST!$B:$B, AQ$12, TRUST!$C:$C, AQ$13) -> 0 | AR32: =SUMIFS(COLLECTION!$E:$E, COLLECTION!$D:$D,DEPARTMENTS!$B:$B, COLLECTION!$B:$B, AR$12, COLLECTION!$C:$C, AR$13) + SUMIFS(BANK!$E:$E, BANK!$D:$D,DEPARTMENTS!$B:$B, BANK!$B:$B, AR$12, BANK!$C:$C, AR$13) + SUMIFS(TRUST!$E:$E, TRUST!$D:$D,DEPARTMENTS!$B:$B, TRUST!$B:$B, AR$12, TRUST!$C:$C, AR$13) -> 0 | ... CQ32: =SUMIFS(COLLECTION!$E:$E, COLLECTION!$D:$D,DEPARTMENTS!$B:$B, COLLECTION!$B:$B, CQ$12, COLLECTION!$C:$C, CQ$13) + SUMIFS(BANK!$E:$E, BANK!$D:$D,DEPARTMENTS!$B:$B, BANK!$B:$B, CQ$12, BANK!$C:$C, CQ$13) + SUMIFS(TRUST!$E:$E, TRUST!$D:$D,DEPARTMENTS!$B:$B, TRUST!$B:$B, CQ$12, TRUST!$C:$C, CQ$13) -> 0 | CR32: =SUM(AK32:CQ32) -> 300
B33: CHURCH_CHOIR_LAUNCH | C33: 0 | D33: =SUMIF(COLLECTION!D:D,DEPARTMENTS!B:B,COLLECTION!E:E)+SUMIF(BANK!D:D,DEPARTMENTS!B:B,BANK!E:E)+SUMIF(TRUST!D:D,DEPARTMENTS!B:B,TRUST!E:E)+E85 -> 400913 | E33: =SUMIF(EXPENSES!D:D,DEPARTMENTS!B:B,EXPENSES!F:F) -> 63101 | F33: =D33-E33+C33 -> 337812 | H33: =SUMIFS(COLLECTION!$E:$E, COLLECTION!$D:$D,DEPARTMENTS!$B:$B, COLLECTION!$B:$B, H$13, COLLECTION!$B:$B, H$13) + SUMIFS(BANK!$E:$E, BANK!$D:$D,DEPARTMENTS!$B:$B, BANK!$B:$B, H$13, BANK!$B:$B, H$13) + SUMIFS(TRUST!$E:$E, TRUST!$D:$D,DEPARTMENTS!$B:$B, TRUST!$B:$B, H$13, TRUST!$B:$B, H$13)+H85 -> 0 | I33: =SUMIFS(COLLECTION!$E:$E, COLLECTION!$D:$D,DEPARTMENTS!$B:$B, COLLECTION!$B:$B, I$13, COLLECTION!$B:$B, I$13) + SUMIFS(BANK!$E:$E, BANK!$D:$D,DEPARTMENTS!$B:$B, BANK!$B:$B, I$13, BANK!$B:$B, I$13) + SUMIFS(TRUST!$E:$E, TRUST!$D:$D,DEPARTMENTS!$B:$B, TRUST!$B:$B, I$13, TRUST!$B:$B, I$13)+I85 -> 0 | J33: =SUMIFS(COLLECTION!$E:$E, COLLECTION!$D:$D,DEPARTMENTS!$B:$B, COLLECTION!$B:$B, J$13, COLLECTION!$B:$B, J$13) + SUMIFS(BANK!$E:$E, BANK!$D:$D,DEPARTMENTS!$B:$B, BANK!$B:$B, J$13, BANK!$B:$B, J$13) + SUMIFS(TRUST!$E:$E, TRUST!$D:$D,DEPARTMENTS!$B:$B, TRUST!$B:$B, J$13, TRUST!$B:$B, J$13)+J85 -> 96451 | K33: =SUMIFS(COLLECTION!$E:$E, COLLECTION!$D:$D,DEPARTMENTS!$B:$B, COLLECTION!$B:$B, K$13, COLLECTION!$B:$B, K$13) + SUMIFS(BANK!$E:$E, BANK!$D:$D,DEPARTMENTS!$B:$B, BANK!$B:$B, K$13, BANK!$B:$B, K$13) + SUMIFS(TRUST!$E:$E, TRUST!$D:$D,DEPARTMENTS!$B:$B, TRUST!$B:$B, K$13, TRUST!$B:$B, K$13)+K85 -> 304462 | L33: =SUMIFS(COLLECTION!$E:$E, COLLECTION!$D:$D,DEPARTMENTS!$B:$B, COLLECTION!$B:$B, L$13, COLLECTION!$B:$B, L$13) + SUMIFS(BANK!$E:$E, BANK!$D:$D,DEPARTMENTS!$B:$B, BANK!$B:$B, L$13, BANK!$B:$B, L$13) + SUMIFS(TRUST!$E:$E, TRUST!$D:$D,DEPARTMENTS!$B:$B, TRUST!$B:$B, L$13, TRUST!$B:$B, L$13)+L85 -> 0 | M33: =SUMIFS(COLLECTION!$E:$E, COLLECTION!$D:$D,DEPARTMENTS!$B:$B, COLLECTION!$B:$B, M$13, COLLECTION!$B:$B, M$13) + SUMIFS(BANK!$E:$E, BANK!$D:$D,DEPARTMENTS!$B:$B, BANK!$B:$B, M$13, BANK!$B:$B, M$13) + SUMIFS(TRUST!$E:$E, TRUST!$D:$D,DEPARTMENTS!$B:$B, TRUST!$B:$B, M$13, TRUST!$B:$B, M$13)+M85 -> 0 | N33: =SUMIFS(COLLECTION!$E:$E, COLLECTION!$D:$D,DEPARTMENTS!$B:$B, COLLECTION!$B:$B, N$13, COLLECTION!$B:$B, N$13) + SUMIFS(BANK!$E:$E, BANK!$D:$D,DEPARTMENTS!$B:$B, BANK!$B:$B, N$13, BANK!$B:$B, N$13) + SUMIFS(TRUST!$E:$E, TRUST!$D:$D,DEPARTMENTS!$B:$B, TRUST!$B:$B, N$13, TRUST!$B:$B, N$13)+N85 -> 0 | O33: =SUMIFS(COLLECTION!$E:$E, COLLECTION!$D:$D,DEPARTMENTS!$B:$B, COLLECTION!$B:$B, O$13, COLLECTION!$B:$B, O$13) + SUMIFS(BANK!$E:$E, BANK!$D:$D,DEPARTMENTS!$B:$B, BANK!$B:$B, O$13, BANK!$B:$B, O$13) + SUMIFS(TRUST!$E:$E, TRUST!$D:$D,DEPARTMENTS!$B:$B, TRUST!$B:$B, O$13, TRUST!$B:$B, O$13)+O85 -> 0 | ... S33: =SUMIFS(COLLECTION!$E:$E, COLLECTION!$D:$D,DEPARTMENTS!$B:$B, COLLECTION!$B:$B, S$13, COLLECTION!$B:$B, S$13) + SUMIFS(BANK!$E:$E, BANK!$D:$D,DEPARTMENTS!$B:$B, BANK!$B:$B, S$13, BANK!$B:$B, S$13) + SUMIFS(TRUST!$E:$E, TRUST!$D:$D,DEPARTMENTS!$B:$B, TRUST!$B:$B, S$13, TRUST!$B:$B, S$13)+S85 -> 0 | T33: =SUM(H33:S33) -> 400913 | V33: =SUMIFS(EXPENSES!$F:$F, EXPENSES!$D:$D,DEPARTMENTS!$B:$B, EXPENSES!$B:$B, V$13) -> 0 | W33: =SUMIFS(EXPENSES!$F:$F, EXPENSES!$D:$D,DEPARTMENTS!$B:$B, EXPENSES!$B:$B, W$13) -> 0 | X33: =SUMIFS(EXPENSES!$F:$F, EXPENSES!$D:$D,DEPARTMENTS!$B:$B, EXPENSES!$B:$B, X$13) -> 0 | Y33: =SUMIFS(EXPENSES!$F:$F, EXPENSES!$D:$D,DEPARTMENTS!$B:$B, EXPENSES!$B:$B, Y$13) -> 63101 | Z33: =SUMIFS(EXPENSES!$F:$F, EXPENSES!$D:$D,DEPARTMENTS!$B:$B, EXPENSES!$B:$B, Z$13) -> 0 | AA33: =SUMIFS(EXPENSES!$F:$F, EXPENSES!$D:$D,DEPARTMENTS!$B:$B, EXPENSES!$B:$B, AA$13) -> 0 | AB33: =SUMIFS(EXPENSES!$F:$F, EXPENSES!$D:$D,DEPARTMENTS!$B:$B, EXPENSES!$B:$B, AB$13) -> 0 | AC33: =SUMIFS(EXPENSES!$F:$F, EXPENSES!$D:$D,DEPARTMENTS!$B:$B, EXPENSES!$B:$B, AC$13) -> 0 | ... AG33: =SUMIFS(EXPENSES!$F:$F, EXPENSES!$D:$D,DEPARTMENTS!$B:$B, EXPENSES!$B:$B, AG$13) -> 0 | AH33: =SUM(V33:AG33) -> 63101 | AK33: =SUMIFS(COLLECTION!$E:$E, COLLECTION!$D:$D,DEPARTMENTS!$B:$B, COLLECTION!$B:$B, AK$12, COLLECTION!$C:$C, AK$13) + SUMIFS(BANK!$E:$E, BANK!$D:$D,DEPARTMENTS!$B:$B, BANK!$B:$B, AK$12, BANK!$C:$C, AK$13) + SUMIFS(TRUST!$E:$E, TRUST!$D:$D,DEPARTMENTS!$B:$B, TRUST!$B:$B, AK$12, TRUST!$C:$C, AK$13)+AK85 -> 0 | AL33: =SUMIFS(COLLECTION!$E:$E, COLLECTION!$D:$D,DEPARTMENTS!$B:$B, COLLECTION!$B:$B, AL$12, COLLECTION!$C:$C, AL$13) + SUMIFS(BANK!$E:$E, BANK!$D:$D,DEPARTMENTS!$B:$B, BANK!$B:$B, AL$12, BANK!$C:$C, AL$13) + SUMIFS(TRUST!$E:$E, TRUST!$D:$D,DEPARTMENTS!$B:$B, TRUST!$B:$B, AL$12, TRUST!$C:$C, AL$13)+AL85 -> 0 | AM33: =SUMIFS(COLLECTION!$E:$E, COLLECTION!$D:$D,DEPARTMENTS!$B:$B, COLLECTION!$B:$B, AM$12, COLLECTION!$C:$C, AM$13) + SUMIFS(BANK!$E:$E, BANK!$D:$D,DEPARTMENTS!$B:$B, BANK!$B:$B, AM$12, BANK!$C:$C, AM$13) + SUMIFS(TRUST!$E:$E, TRUST!$D:$D,DEPARTMENTS!$B:$B, TRUST!$B:$B, AM$12, TRUST!$C:$C, AM$13)+AM85 -> 0 | AN33: =SUMIFS(COLLECTION!$E:$E, COLLECTION!$D:$D,DEPARTMENTS!$B:$B, COLLECTION!$B:$B, AN$12, COLLECTION!$C:$C, AN$13) + SUMIFS(BANK!$E:$E, BANK!$D:$D,DEPARTMENTS!$B:$B, BANK!$B:$B, AN$12, BANK!$C:$C, AN$13) + SUMIFS(TRUST!$E:$E, TRUST!$D:$D,DEPARTMENTS!$B:$B, TRUST!$B:$B, AN$12, TRUST!$C:$C, AN$13)+AN85 -> 0 | AO33: =SUMIFS(COLLECTION!$E:$E, COLLECTION!$D:$D,DEPARTMENTS!$B:$B, COLLECTION!$B:$B, AO$12, COLLECTION!$C:$C, AO$13) + SUMIFS(BANK!$E:$E, BANK!$D:$D,DEPARTMENTS!$B:$B, BANK!$B:$B, AO$12, BANK!$C:$C, AO$13) + SUMIFS(TRUST!$E:$E, TRUST!$D:$D,DEPARTMENTS!$B:$B, TRUST!$B:$B, AO$12, TRUST!$C:$C, AO$13)+AO85 -> 0 | AP33: =SUMIFS(COLLECTION!$E:$E, COLLECTION!$D:$D,DEPARTMENTS!$B:$B, COLLECTION!$B:$B, AP$12, COLLECTION!$C:$C, AP$13) + SUMIFS(BANK!$E:$E, BANK!$D:$D,DEPARTMENTS!$B:$B, BANK!$B:$B, AP$12, BANK!$C:$C, AP$13) + SUMIFS(TRUST!$E:$E, TRUST!$D:$D,DEPARTMENTS!$B:$B, TRUST!$B:$B, AP$12, TRUST!$C:$C, AP$13)+AP85 -> 0 | AQ33: =SUMIFS(COLLECTION!$E:$E, COLLECTION!$D:$D,DEPARTMENTS!$B:$B, COLLECTION!$B:$B, AQ$12, COLLECTION!$C:$C, AQ$13) + SUMIFS(BANK!$E:$E, BANK!$D:$D,DEPARTMENTS!$B:$B, BANK!$B:$B, AQ$12, BANK!$C:$C, AQ$13) + SUMIFS(TRUST!$E:$E, TRUST!$D:$D,DEPARTMENTS!$B:$B, TRUST!$B:$B, AQ$12, TRUST!$C:$C, AQ$13)+AQ85 -> 0 | AR33: =SUMIFS(COLLECTION!$E:$E, COLLECTION!$D:$D,DEPARTMENTS!$B:$B, COLLECTION!$B:$B, AR$12, COLLECTION!$C:$C, AR$13) + SUMIFS(BANK!$E:$E, BANK!$D:$D,DEPARTMENTS!$B:$B, BANK!$B:$B, AR$12, BANK!$C:$C, AR$13) + SUMIFS(TRUST!$E:$E, TRUST!$D:$D,DEPARTMENTS!$B:$B, TRUST!$B:$B, AR$12, TRUST!$C:$C, AR$13)+AR85 -> 0 | ... CQ33: =SUMIFS(COLLECTION!$E:$E, COLLECTION!$D:$D,DEPARTMENTS!$B:$B, COLLECTION!$B:$B, CQ$12, COLLECTION!$C:$C, CQ$13) + SUMIFS(BANK!$E:$E, BANK!$D:$D,DEPARTMENTS!$B:$B, BANK!$B:$B, CQ$12, BANK!$C:$C, CQ$13) + SUMIFS(TRUST!$E:$E, TRUST!$D:$D,DEPARTMENTS!$B:$B, TRUST!$B:$B, CQ$12, TRUST!$C:$C, CQ$13)+CQ85 -> 0 | CR33: =SUM(AK33:CQ33) -> 400913
B34: MATOPENI | C34: 1700 | D34: =SUMIF(COLLECTION!D:D,DEPARTMENTS!B:B,COLLECTION!E:E)+SUMIF(BANK!D:D,DEPARTMENTS!B:B,BANK!E:E)+SUMIF(TRUST!D:D,DEPARTMENTS!B:B,TRUST!E:E) -> 0 | E34: =SUMIF(EXPENSES!D:D,DEPARTMENTS!B:B,EXPENSES!F:F) -> 0 | F34: =D34-E34+C34 -> 1700 | H34: =SUMIFS(COLLECTION!$E:$E, COLLECTION!$D:$D,DEPARTMENTS!$B:$B, COLLECTION!$B:$B, H$13, COLLECTION!$B:$B, H$13) + SUMIFS(BANK!$E:$E, BANK!$D:$D,DEPARTMENTS!$B:$B, BANK!$B:$B, H$13, BANK!$B:$B, H$13) + SUMIFS(TRUST!$E:$E, TRUST!$D:$D,DEPARTMENTS!$B:$B, TRUST!$B:$B, H$13, TRUST!$B:$B, H$13) -> 0 | I34: =SUMIFS(COLLECTION!$E:$E, COLLECTION!$D:$D,DEPARTMENTS!$B:$B, COLLECTION!$B:$B, I$13, COLLECTION!$B:$B, I$13) + SUMIFS(BANK!$E:$E, BANK!$D:$D,DEPARTMENTS!$B:$B, BANK!$B:$B, I$13, BANK!$B:$B, I$13) + SUMIFS(TRUST!$E:$E, TRUST!$D:$D,DEPARTMENTS!$B:$B, TRUST!$B:$B, I$13, TRUST!$B:$B, I$13) -> 0 | J34: =SUMIFS(COLLECTION!$E:$E, COLLECTION!$D:$D,DEPARTMENTS!$B:$B, COLLECTION!$B:$B, J$13, COLLECTION!$B:$B, J$13) + SUMIFS(BANK!$E:$E, BANK!$D:$D,DEPARTMENTS!$B:$B, BANK!$B:$B, J$13, BANK!$B:$B, J$13) + SUMIFS(TRUST!$E:$E, TRUST!$D:$D,DEPARTMENTS!$B:$B, TRUST!$B:$B, J$13, TRUST!$B:$B, J$13) -> 0 | K34: =SUMIFS(COLLECTION!$E:$E, COLLECTION!$D:$D,DEPARTMENTS!$B:$B, COLLECTION!$B:$B, K$13, COLLECTION!$B:$B, K$13) + SUMIFS(BANK!$E:$E, BANK!$D:$D,DEPARTMENTS!$B:$B, BANK!$B:$B, K$13, BANK!$B:$B, K$13) + SUMIFS(TRUST!$E:$E, TRUST!$D:$D,DEPARTMENTS!$B:$B, TRUST!$B:$B, K$13, TRUST!$B:$B, K$13) -> 0 | L34: =SUMIFS(COLLECTION!$E:$E, COLLECTION!$D:$D,DEPARTMENTS!$B:$B, COLLECTION!$B:$B, L$13, COLLECTION!$B:$B, L$13) + SUMIFS(BANK!$E:$E, BANK!$D:$D,DEPARTMENTS!$B:$B, BANK!$B:$B, L$13, BANK!$B:$B, L$13) + SUMIFS(TRUST!$E:$E, TRUST!$D:$D,DEPARTMENTS!$B:$B, TRUST!$B:$B, L$13, TRUST!$B:$B, L$13) -> 0 | M34: =SUMIFS(COLLECTION!$E:$E, COLLECTION!$D:$D,DEPARTMENTS!$B:$B, COLLECTION!$B:$B, M$13, COLLECTION!$B:$B, M$13) + SUMIFS(BANK!$E:$E, BANK!$D:$D,DEPARTMENTS!$B:$B, BANK!$B:$B, M$13, BANK!$B:$B, M$13) + SUMIFS(TRUST!$E:$E, TRUST!$D:$D,DEPARTMENTS!$B:$B, TRUST!$B:$B, M$13, TRUST!$B:$B, M$13) -> 0 | N34: =SUMIFS(COLLECTION!$E:$E, COLLECTION!$D:$D,DEPARTMENTS!$B:$B, COLLECTION!$B:$B, N$13, COLLECTION!$B:$B, N$13) + SUMIFS(BANK!$E:$E, BANK!$D:$D,DEPARTMENTS!$B:$B, BANK!$B:$B, N$13, BANK!$B:$B, N$13) + SUMIFS(TRUST!$E:$E, TRUST!$D:$D,DEPARTMENTS!$B:$B, TRUST!$B:$B, N$13, TRUST!$B:$B, N$13) -> 0 | O34: =SUMIFS(COLLECTION!$E:$E, COLLECTION!$D:$D,DEPARTMENTS!$B:$B, COLLECTION!$B:$B, O$13, COLLECTION!$B:$B, O$13) + SUMIFS(BANK!$E:$E, BANK!$D:$D,DEPARTMENTS!$B:$B, BANK!$B:$B, O$13, BANK!$B:$B, O$13) + SUMIFS(TRUST!$E:$E, TRUST!$D:$D,DEPARTMENTS!$B:$B, TRUST!$B:$B, O$13, TRUST!$B:$B, O$13) -> 0 | ... S34: =SUMIFS(COLLECTION!$E:$E, COLLECTION!$D:$D,DEPARTMENTS!$B:$B, COLLECTION!$B:$B, S$13, COLLECTION!$B:$B, S$13) + SUMIFS(BANK!$E:$E, BANK!$D:$D,DEPARTMENTS!$B:$B, BANK!$B:$B, S$13, BANK!$B:$B, S$13) + SUMIFS(TRUST!$E:$E, TRUST!$D:$D,DEPARTMENTS!$B:$B, TRUST!$B:$B, S$13, TRUST!$B:$B, S$13) -> 0 | T34: =SUM(H34:S34) -> 0 | V34: =SUMIFS(EXPENSES!$F:$F, EXPENSES!$D:$D,DEPARTMENTS!$B:$B, EXPENSES!$B:$B, V$13) -> 0 | W34: =SUMIFS(EXPENSES!$F:$F, EXPENSES!$D:$D,DEPARTMENTS!$B:$B, EXPENSES!$B:$B, W$13) -> 0 | X34: =SUMIFS(EXPENSES!$F:$F, EXPENSES!$D:$D,DEPARTMENTS!$B:$B, EXPENSES!$B:$B, X$13) -> 0 | Y34: =SUMIFS(EXPENSES!$F:$F, EXPENSES!$D:$D,DEPARTMENTS!$B:$B, EXPENSES!$B:$B, Y$13) -> 0 | Z34: =SUMIFS(EXPENSES!$F:$F, EXPENSES!$D:$D,DEPARTMENTS!$B:$B, EXPENSES!$B:$B, Z$13) -> 0 | AA34: =SUMIFS(EXPENSES!$F:$F, EXPENSES!$D:$D,DEPARTMENTS!$B:$B, EXPENSES!$B:$B, AA$13) -> 0 | AB34: =SUMIFS(EXPENSES!$F:$F, EXPENSES!$D:$D,DEPARTMENTS!$B:$B, EXPENSES!$B:$B, AB$13) -> 0 | AC34: =SUMIFS(EXPENSES!$F:$F, EXPENSES!$D:$D,DEPARTMENTS!$B:$B, EXPENSES!$B:$B, AC$13) -> 0 | ... AG34: =SUMIFS(EXPENSES!$F:$F, EXPENSES!$D:$D,DEPARTMENTS!$B:$B, EXPENSES!$B:$B, AG$13) -> 0 | AH34: =SUM(V34:AG34) -> 0 | AK34: =SUMIFS(COLLECTION!$E:$E, COLLECTION!$D:$D,DEPARTMENTS!$B:$B, COLLECTION!$B:$B, AK$12, COLLECTION!$C:$C, AK$13) + SUMIFS(BANK!$E:$E, BANK!$D:$D,DEPARTMENTS!$B:$B, BANK!$B:$B, AK$12, BANK!$C:$C, AK$13) + SUMIFS(TRUST!$E:$E, TRUST!$D:$D,DEPARTMENTS!$B:$B, TRUST!$B:$B, AK$12, TRUST!$C:$C, AK$13) -> 0 | AL34: =SUMIFS(COLLECTION!$E:$E, COLLECTION!$D:$D,DEPARTMENTS!$B:$B, COLLECTION!$B:$B, AL$12, COLLECTION!$C:$C, AL$13) + SUMIFS(BANK!$E:$E, BANK!$D:$D,DEPARTMENTS!$B:$B, BANK!$B:$B, AL$12, BANK!$C:$C, AL$13) + SUMIFS(TRUST!$E:$E, TRUST!$D:$D,DEPARTMENTS!$B:$B, TRUST!$B:$B, AL$12, TRUST!$C:$C, AL$13) -> 0 | AM34: =SUMIFS(COLLECTION!$E:$E, COLLECTION!$D:$D,DEPARTMENTS!$B:$B, COLLECTION!$B:$B, AM$12, COLLECTION!$C:$C, AM$13) + SUMIFS(BANK!$E:$E, BANK!$D:$D,DEPARTMENTS!$B:$B, BANK!$B:$B, AM$12, BANK!$C:$C, AM$13) + SUMIFS(TRUST!$E:$E, TRUST!$D:$D,DEPARTMENTS!$B:$B, TRUST!$B:$B, AM$12, TRUST!$C:$C, AM$13) -> 0 | AN34: =SUMIFS(COLLECTION!$E:$E, COLLECTION!$D:$D,DEPARTMENTS!$B:$B, COLLECTION!$B:$B, AN$12, COLLECTION!$C:$C, AN$13) + SUMIFS(BANK!$E:$E, BANK!$D:$D,DEPARTMENTS!$B:$B, BANK!$B:$B, AN$12, BANK!$C:$C, AN$13) + SUMIFS(TRUST!$E:$E, TRUST!$D:$D,DEPARTMENTS!$B:$B, TRUST!$B:$B, AN$12, TRUST!$C:$C, AN$13) -> 0 | AO34: =SUMIFS(COLLECTION!$E:$E, COLLECTION!$D:$D,DEPARTMENTS!$B:$B, COLLECTION!$B:$B, AO$12, COLLECTION!$C:$C, AO$13) + SUMIFS(BANK!$E:$E, BANK!$D:$D,DEPARTMENTS!$B:$B, BANK!$B:$B, AO$12, BANK!$C:$C, AO$13) + SUMIFS(TRUST!$E:$E, TRUST!$D:$D,DEPARTMENTS!$B:$B, TRUST!$B:$B, AO$12, TRUST!$C:$C, AO$13) -> 0 | AP34: =SUMIFS(COLLECTION!$E:$E, COLLECTION!$D:$D,DEPARTMENTS!$B:$B, COLLECTION!$B:$B, AP$12, COLLECTION!$C:$C, AP$13) + SUMIFS(BANK!$E:$E, BANK!$D:$D,DEPARTMENTS!$B:$B, BANK!$B:$B, AP$12, BANK!$C:$C, AP$13) + SUMIFS(TRUST!$E:$E, TRUST!$D:$D,DEPARTMENTS!$B:$B, TRUST!$B:$B, AP$12, TRUST!$C:$C, AP$13) -> 0 | AQ34: =SUMIFS(COLLECTION!$E:$E, COLLECTION!$D:$D,DEPARTMENTS!$B:$B, COLLECTION!$B:$B, AQ$12, COLLECTION!$C:$C, AQ$13) + SUMIFS(BANK!$E:$E, BANK!$D:$D,DEPARTMENTS!$B:$B, BANK!$B:$B, AQ$12, BANK!$C:$C, AQ$13) + SUMIFS(TRUST!$E:$E, TRUST!$D:$D,DEPARTMENTS!$B:$B, TRUST!$B:$B, AQ$12, TRUST!$C:$C, AQ$13) -> 0 | AR34: =SUMIFS(COLLECTION!$E:$E, COLLECTION!$D:$D,DEPARTMENTS!$B:$B, COLLECTION!$B:$B, AR$12, COLLECTION!$C:$C, AR$13) + SUMIFS(BANK!$E:$E, BANK!$D:$D,DEPARTMENTS!$B:$B, BANK!$B:$B, AR$12, BANK!$C:$C, AR$13) + SUMIFS(TRUST!$E:$E, TRUST!$D:$D,DEPARTMENTS!$B:$B, TRUST!$B:$B, AR$12, TRUST!$C:$C, AR$13) -> 0 | ... CQ34: =SUMIFS(COLLECTION!$E:$E, COLLECTION!$D:$D,DEPARTMENTS!$B:$B, COLLECTION!$B:$B, CQ$12, COLLECTION!$C:$C, CQ$13) + SUMIFS(BANK!$E:$E, BANK!$D:$D,DEPARTMENTS!$B:$B, BANK!$B:$B, CQ$12, BANK!$C:$C, CQ$13) + SUMIFS(TRUST!$E:$E, TRUST!$D:$D,DEPARTMENTS!$B:$B, TRUST!$B:$B, CQ$12, TRUST!$C:$C, CQ$13) -> 0 | CR34: =SUM(AK34:CQ34) -> 0
B35: EMERGENCY_FUND | C35: 5992 | D35: =SUMIF(COLLECTION!D:D,DEPARTMENTS!B:B,COLLECTION!E:E)+SUMIF(BANK!D:D,DEPARTMENTS!B:B,BANK!E:E)+SUMIF(TRUST!D:D,DEPARTMENTS!B:B,TRUST!E:E) -> 0 | E35: =SUMIF(EXPENSES!D:D,DEPARTMENTS!B:B,EXPENSES!F:F) -> 0 | F35: =D35-E35+C35 -> 5992 | H35: =SUMIFS(COLLECTION!$E:$E, COLLECTION!$D:$D,DEPARTMENTS!$B:$B, COLLECTION!$B:$B, H$13, COLLECTION!$B:$B, H$13) + SUMIFS(BANK!$E:$E, BANK!$D:$D,DEPARTMENTS!$B:$B, BANK!$B:$B, H$13, BANK!$B:$B, H$13) + SUMIFS(TRUST!$E:$E, TRUST!$D:$D,DEPARTMENTS!$B:$B, TRUST!$B:$B, H$13, TRUST!$B:$B, H$13) -> 0 | I35: =SUMIFS(COLLECTION!$E:$E, COLLECTION!$D:$D,DEPARTMENTS!$B:$B, COLLECTION!$B:$B, I$13, COLLECTION!$B:$B, I$13) + SUMIFS(BANK!$E:$E, BANK!$D:$D,DEPARTMENTS!$B:$B, BANK!$B:$B, I$13, BANK!$B:$B, I$13) + SUMIFS(TRUST!$E:$E, TRUST!$D:$D,DEPARTMENTS!$B:$B, TRUST!$B:$B, I$13, TRUST!$B:$B, I$13) -> 0 | J35: =SUMIFS(COLLECTION!$E:$E, COLLECTION!$D:$D,DEPARTMENTS!$B:$B, COLLECTION!$B:$B, J$13, COLLECTION!$B:$B, J$13) + SUMIFS(BANK!$E:$E, BANK!$D:$D,DEPARTMENTS!$B:$B, BANK!$B:$B, J$13, BANK!$B:$B, J$13) + SUMIFS(TRUST!$E:$E, TRUST!$D:$D,DEPARTMENTS!$B:$B, TRUST!$B:$B, J$13, TRUST!$B:$B, J$13) -> 0 | K35: =SUMIFS(COLLECTION!$E:$E, COLLECTION!$D:$D,DEPARTMENTS!$B:$B, COLLECTION!$B:$B, K$13, COLLECTION!$B:$B, K$13) + SUMIFS(BANK!$E:$E, BANK!$D:$D,DEPARTMENTS!$B:$B, BANK!$B:$B, K$13, BANK!$B:$B, K$13) + SUMIFS(TRUST!$E:$E, TRUST!$D:$D,DEPARTMENTS!$B:$B, TRUST!$B:$B, K$13, TRUST!$B:$B, K$13) -> 0 | L35: =SUMIFS(COLLECTION!$E:$E, COLLECTION!$D:$D,DEPARTMENTS!$B:$B, COLLECTION!$B:$B, L$13, COLLECTION!$B:$B, L$13) + SUMIFS(BANK!$E:$E, BANK!$D:$D,DEPARTMENTS!$B:$B, BANK!$B:$B, L$13, BANK!$B:$B, L$13) + SUMIFS(TRUST!$E:$E, TRUST!$D:$D,DEPARTMENTS!$B:$B, TRUST!$B:$B, L$13, TRUST!$B:$B, L$13) -> 0 | M35: =SUMIFS(COLLECTION!$E:$E, COLLECTION!$D:$D,DEPARTMENTS!$B:$B, COLLECTION!$B:$B, M$13, COLLECTION!$B:$B, M$13) + SUMIFS(BANK!$E:$E, BANK!$D:$D,DEPARTMENTS!$B:$B, BANK!$B:$B, M$13, BANK!$B:$B, M$13) + SUMIFS(TRUST!$E:$E, TRUST!$D:$D,DEPARTMENTS!$B:$B, TRUST!$B:$B, M$13, TRUST!$B:$B, M$13) -> 0 | N35: =SUMIFS(COLLECTION!$E:$E, COLLECTION!$D:$D,DEPARTMENTS!$B:$B, COLLECTION!$B:$B, N$13, COLLECTION!$B:$B, N$13) + SUMIFS(BANK!$E:$E, BANK!$D:$D,DEPARTMENTS!$B:$B, BANK!$B:$B, N$13, BANK!$B:$B, N$13) + SUMIFS(TRUST!$E:$E, TRUST!$D:$D,DEPARTMENTS!$B:$B, TRUST!$B:$B, N$13, TRUST!$B:$B, N$13) -> 0 | O35: =SUMIFS(COLLECTION!$E:$E, COLLECTION!$D:$D,DEPARTMENTS!$B:$B, COLLECTION!$B:$B, O$13, COLLECTION!$B:$B, O$13) + SUMIFS(BANK!$E:$E, BANK!$D:$D,DEPARTMENTS!$B:$B, BANK!$B:$B, O$13, BANK!$B:$B, O$13) + SUMIFS(TRUST!$E:$E, TRUST!$D:$D,DEPARTMENTS!$B:$B, TRUST!$B:$B, O$13, TRUST!$B:$B, O$13) -> 0 | ... S35: =SUMIFS(COLLECTION!$E:$E, COLLECTION!$D:$D,DEPARTMENTS!$B:$B, COLLECTION!$B:$B, S$13, COLLECTION!$B:$B, S$13) + SUMIFS(BANK!$E:$E, BANK!$D:$D,DEPARTMENTS!$B:$B, BANK!$B:$B, S$13, BANK!$B:$B, S$13) + SUMIFS(TRUST!$E:$E, TRUST!$D:$D,DEPARTMENTS!$B:$B, TRUST!$B:$B, S$13, TRUST!$B:$B, S$13) -> 0 | T35: =SUM(H35:S35) -> 0 | V35: =SUMIFS(EXPENSES!$F:$F, EXPENSES!$D:$D,DEPARTMENTS!$B:$B, EXPENSES!$B:$B, V$13) -> 0 | W35: =SUMIFS(EXPENSES!$F:$F, EXPENSES!$D:$D,DEPARTMENTS!$B:$B, EXPENSES!$B:$B, W$13) -> 0 | X35: =SUMIFS(EXPENSES!$F:$F, EXPENSES!$D:$D,DEPARTMENTS!$B:$B, EXPENSES!$B:$B, X$13) -> 0 | Y35: =SUMIFS(EXPENSES!$F:$F, EXPENSES!$D:$D,DEPARTMENTS!$B:$B, EXPENSES!$B:$B, Y$13) -> 0 | Z35: =SUMIFS(EXPENSES!$F:$F, EXPENSES!$D:$D,DEPARTMENTS!$B:$B, EXPENSES!$B:$B, Z$13) -> 0 | AA35: =SUMIFS(EXPENSES!$F:$F, EXPENSES!$D:$D,DEPARTMENTS!$B:$B, EXPENSES!$B:$B, AA$13) -> 0 | AB35: =SUMIFS(EXPENSES!$F:$F, EXPENSES!$D:$D,DEPARTMENTS!$B:$B, EXPENSES!$B:$B, AB$13) -> 0 | AC35: =SUMIFS(EXPENSES!$F:$F, EXPENSES!$D:$D,DEPARTMENTS!$B:$B, EXPENSES!$B:$B, AC$13) -> 0 | ... AG35: =SUMIFS(EXPENSES!$F:$F, EXPENSES!$D:$D,DEPARTMENTS!$B:$B, EXPENSES!$B:$B, AG$13) -> 0 | AH35: =SUM(V35:AG35) -> 0 | AK35: =SUMIFS(COLLECTION!$E:$E, COLLECTION!$D:$D,DEPARTMENTS!$B:$B, COLLECTION!$B:$B, AK$12, COLLECTION!$C:$C, AK$13) + SUMIFS(BANK!$E:$E, BANK!$D:$D,DEPARTMENTS!$B:$B, BANK!$B:$B, AK$12, BANK!$C:$C, AK$13) + SUMIFS(TRUST!$E:$E, TRUST!$D:$D,DEPARTMENTS!$B:$B, TRUST!$B:$B, AK$12, TRUST!$C:$C, AK$13) -> 0 | AL35: =SUMIFS(COLLECTION!$E:$E, COLLECTION!$D:$D,DEPARTMENTS!$B:$B, COLLECTION!$B:$B, AL$12, COLLECTION!$C:$C, AL$13) + SUMIFS(BANK!$E:$E, BANK!$D:$D,DEPARTMENTS!$B:$B, BANK!$B:$B, AL$12, BANK!$C:$C, AL$13) + SUMIFS(TRUST!$E:$E, TRUST!$D:$D,DEPARTMENTS!$B:$B, TRUST!$B:$B, AL$12, TRUST!$C:$C, AL$13) -> 0 | AM35: =SUMIFS(COLLECTION!$E:$E, COLLECTION!$D:$D,DEPARTMENTS!$B:$B, COLLECTION!$B:$B, AM$12, COLLECTION!$C:$C, AM$13) + SUMIFS(BANK!$E:$E, BANK!$D:$D,DEPARTMENTS!$B:$B, BANK!$B:$B, AM$12, BANK!$C:$C, AM$13) + SUMIFS(TRUST!$E:$E, TRUST!$D:$D,DEPARTMENTS!$B:$B, TRUST!$B:$B, AM$12, TRUST!$C:$C, AM$13) -> 0 | AN35: =SUMIFS(COLLECTION!$E:$E, COLLECTION!$D:$D,DEPARTMENTS!$B:$B, COLLECTION!$B:$B, AN$12, COLLECTION!$C:$C, AN$13) + SUMIFS(BANK!$E:$E, BANK!$D:$D,DEPARTMENTS!$B:$B, BANK!$B:$B, AN$12, BANK!$C:$C, AN$13) + SUMIFS(TRUST!$E:$E, TRUST!$D:$D,DEPARTMENTS!$B:$B, TRUST!$B:$B, AN$12, TRUST!$C:$C, AN$13) -> 0 | AO35: =SUMIFS(COLLECTION!$E:$E, COLLECTION!$D:$D,DEPARTMENTS!$B:$B, COLLECTION!$B:$B, AO$12, COLLECTION!$C:$C, AO$13) + SUMIFS(BANK!$E:$E, BANK!$D:$D,DEPARTMENTS!$B:$B, BANK!$B:$B, AO$12, BANK!$C:$C, AO$13) + SUMIFS(TRUST!$E:$E, TRUST!$D:$D,DEPARTMENTS!$B:$B, TRUST!$B:$B, AO$12, TRUST!$C:$C, AO$13) -> 0 | AP35: =SUMIFS(COLLECTION!$E:$E, COLLECTION!$D:$D,DEPARTMENTS!$B:$B, COLLECTION!$B:$B, AP$12, COLLECTION!$C:$C, AP$13) + SUMIFS(BANK!$E:$E, BANK!$D:$D,DEPARTMENTS!$B:$B, BANK!$B:$B, AP$12, BANK!$C:$C, AP$13) + SUMIFS(TRUST!$E:$E, TRUST!$D:$D,DEPARTMENTS!$B:$B, TRUST!$B:$B, AP$12, TRUST!$C:$C, AP$13) -> 0 | AQ35: =SUMIFS(COLLECTION!$E:$E, COLLECTION!$D:$D,DEPARTMENTS!$B:$B, COLLECTION!$B:$B, AQ$12, COLLECTION!$C:$C, AQ$13) + SUMIFS(BANK!$E:$E, BANK!$D:$D,DEPARTMENTS!$B:$B, BANK!$B:$B, AQ$12, BANK!$C:$C, AQ$13) + SUMIFS(TRUST!$E:$E, TRUST!$D:$D,DEPARTMENTS!$B:$B, TRUST!$B:$B, AQ$12, TRUST!$C:$C, AQ$13) -> 0 | AR35: =SUMIFS(COLLECTION!$E:$E, COLLECTION!$D:$D,DEPARTMENTS!$B:$B, COLLECTION!$B:$B, AR$12, COLLECTION!$C:$C, AR$13) + SUMIFS(BANK!$E:$E, BANK!$D:$D,DEPARTMENTS!$B:$B, BANK!$B:$B, AR$12, BANK!$C:$C, AR$13) + SUMIFS(TRUST!$E:$E, TRUST!$D:$D,DEPARTMENTS!$B:$B, TRUST!$B:$B, AR$12, TRUST!$C:$C, AR$13) -> 0 | ... CQ35: =SUMIFS(COLLECTION!$E:$E, COLLECTION!$D:$D,DEPARTMENTS!$B:$B, COLLECTION!$B:$B, CQ$12, COLLECTION!$C:$C, CQ$13) + SUMIFS(BANK!$E:$E, BANK!$D:$D,DEPARTMENTS!$B:$B, BANK!$B:$B, CQ$12, BANK!$C:$C, CQ$13) + SUMIFS(TRUST!$E:$E, TRUST!$D:$D,DEPARTMENTS!$B:$B, TRUST!$B:$B, CQ$12, TRUST!$C:$C, CQ$13) -> 0 | CR35: =SUM(AK35:CQ35) -> 0
B36: LOCAL_EVANGELISM | C36: 0 | D36: =SUMIF(COLLECTION!D:D,DEPARTMENTS!B:B,COLLECTION!E:E)+SUMIF(BANK!D:D,DEPARTMENTS!B:B,BANK!E:E)+SUMIF(TRUST!D:D,DEPARTMENTS!B:B,TRUST!E:E) -> 4305 | E36: =SUMIF(EXPENSES!D:D,DEPARTMENTS!B:B,EXPENSES!F:F) -> 0 | F36: =D36-E36+C36 -> 4305 | H36: =SUMIFS(COLLECTION!$E:$E, COLLECTION!$D:$D,DEPARTMENTS!$B:$B, COLLECTION!$B:$B, H$13, COLLECTION!$B:$B, H$13) + SUMIFS(BANK!$E:$E, BANK!$D:$D,DEPARTMENTS!$B:$B, BANK!$B:$B, H$13, BANK!$B:$B, H$13) + SUMIFS(TRUST!$E:$E, TRUST!$D:$D,DEPARTMENTS!$B:$B, TRUST!$B:$B, H$13, TRUST!$B:$B, H$13) -> 105 | I36: =SUMIFS(COLLECTION!$E:$E, COLLECTION!$D:$D,DEPARTMENTS!$B:$B, COLLECTION!$B:$B, I$13, COLLECTION!$B:$B, I$13) + SUMIFS(BANK!$E:$E, BANK!$D:$D,DEPARTMENTS!$B:$B, BANK!$B:$B, I$13, BANK!$B:$B, I$13) + SUMIFS(TRUST!$E:$E, TRUST!$D:$D,DEPARTMENTS!$B:$B, TRUST!$B:$B, I$13, TRUST!$B:$B, I$13) -> 0 | J36: =SUMIFS(COLLECTION!$E:$E, COLLECTION!$D:$D,DEPARTMENTS!$B:$B, COLLECTION!$B:$B, J$13, COLLECTION!$B:$B, J$13) + SUMIFS(BANK!$E:$E, BANK!$D:$D,DEPARTMENTS!$B:$B, BANK!$B:$B, J$13, BANK!$B:$B, J$13) + SUMIFS(TRUST!$E:$E, TRUST!$D:$D,DEPARTMENTS!$B:$B, TRUST!$B:$B, J$13, TRUST!$B:$B, J$13) -> 730 | K36: =SUMIFS(COLLECTION!$E:$E, COLLECTION!$D:$D,DEPARTMENTS!$B:$B, COLLECTION!$B:$B, K$13, COLLECTION!$B:$B, K$13) + SUMIFS(BANK!$E:$E, BANK!$D:$D,DEPARTMENTS!$B:$B, BANK!$B:$B, K$13, BANK!$B:$B, K$13) + SUMIFS(TRUST!$E:$E, TRUST!$D:$D,DEPARTMENTS!$B:$B, TRUST!$B:$B, K$13, TRUST!$B:$B, K$13) -> 100 | L36: =SUMIFS(COLLECTION!$E:$E, COLLECTION!$D:$D,DEPARTMENTS!$B:$B, COLLECTION!$B:$B, L$13, COLLECTION!$B:$B, L$13) + SUMIFS(BANK!$E:$E, BANK!$D:$D,DEPARTMENTS!$B:$B, BANK!$B:$B, L$13, BANK!$B:$B, L$13) + SUMIFS(TRUST!$E:$E, TRUST!$D:$D,DEPARTMENTS!$B:$B, TRUST!$B:$B, L$13, TRUST!$B:$B, L$13) -> 1720 | M36: =SUMIFS(COLLECTION!$E:$E, COLLECTION!$D:$D,DEPARTMENTS!$B:$B, COLLECTION!$B:$B, M$13, COLLECTION!$B:$B, M$13) + SUMIFS(BANK!$E:$E, BANK!$D:$D,DEPARTMENTS!$B:$B, BANK!$B:$B, M$13, BANK!$B:$B, M$13) + SUMIFS(TRUST!$E:$E, TRUST!$D:$D,DEPARTMENTS!$B:$B, TRUST!$B:$B, M$13, TRUST!$B:$B, M$13) -> 1650 | N36: =SUMIFS(COLLECTION!$E:$E, COLLECTION!$D:$D,DEPARTMENTS!$B:$B, COLLECTION!$B:$B, N$13, COLLECTION!$B:$B, N$13) + SUMIFS(BANK!$E:$E, BANK!$D:$D,DEPARTMENTS!$B:$B, BANK!$B:$B, N$13, BANK!$B:$B, N$13) + SUMIFS(TRUST!$E:$E, TRUST!$D:$D,DEPARTMENTS!$B:$B, TRUST!$B:$B, N$13, TRUST!$B:$B, N$13) -> 0 | O36: =SUMIFS(COLLECTION!$E:$E, COLLECTION!$D:$D,DEPARTMENTS!$B:$B, COLLECTION!$B:$B, O$13, COLLECTION!$B:$B, O$13) + SUMIFS(BANK!$E:$E, BANK!$D:$D,DEPARTMENTS!$B:$B, BANK!$B:$B, O$13, BANK!$B:$B, O$13) + SUMIFS(TRUST!$E:$E, TRUST!$D:$D,DEPARTMENTS!$B:$B, TRUST!$B:$B, O$13, TRUST!$B:$B, O$13) -> 0 | ... S36: =SUMIFS(COLLECTION!$E:$E, COLLECTION!$D:$D,DEPARTMENTS!$B:$B, COLLECTION!$B:$B, S$13, COLLECTION!$B:$B, S$13) + SUMIFS(BANK!$E:$E, BANK!$D:$D,DEPARTMENTS!$B:$B, BANK!$B:$B, S$13, BANK!$B:$B, S$13) + SUMIFS(TRUST!$E:$E, TRUST!$D:$D,DEPARTMENTS!$B:$B, TRUST!$B:$B, S$13, TRUST!$B:$B, S$13) -> 0 | T36: =SUM(H36:S36) -> 4305 | V36: =SUMIFS(EXPENSES!$F:$F, EXPENSES!$D:$D,DEPARTMENTS!$B:$B, EXPENSES!$B:$B, V$13) -> 0 | W36: =SUMIFS(EXPENSES!$F:$F, EXPENSES!$D:$D,DEPARTMENTS!$B:$B, EXPENSES!$B:$B, W$13) -> 0 | X36: =SUMIFS(EXPENSES!$F:$F, EXPENSES!$D:$D,DEPARTMENTS!$B:$B, EXPENSES!$B:$B, X$13) -> 0 | Y36: =SUMIFS(EXPENSES!$F:$F, EXPENSES!$D:$D,DEPARTMENTS!$B:$B, EXPENSES!$B:$B, Y$13) -> 0 | Z36: =SUMIFS(EXPENSES!$F:$F, EXPENSES!$D:$D,DEPARTMENTS!$B:$B, EXPENSES!$B:$B, Z$13) -> 0 | AA36: =SUMIFS(EXPENSES!$F:$F, EXPENSES!$D:$D,DEPARTMENTS!$B:$B, EXPENSES!$B:$B, AA$13) -> 0 | AB36: =SUMIFS(EXPENSES!$F:$F, EXPENSES!$D:$D,DEPARTMENTS!$B:$B, EXPENSES!$B:$B, AB$13) -> 0 | AC36: =SUMIFS(EXPENSES!$F:$F, EXPENSES!$D:$D,DEPARTMENTS!$B:$B, EXPENSES!$B:$B, AC$13) -> 0 | ... AG36: =SUMIFS(EXPENSES!$F:$F, EXPENSES!$D:$D,DEPARTMENTS!$B:$B, EXPENSES!$B:$B, AG$13) -> 0 | AH36: =SUM(V36:AG36) -> 0 | AK36: =SUMIFS(COLLECTION!$E:$E, COLLECTION!$D:$D,DEPARTMENTS!$B:$B, COLLECTION!$B:$B, AK$12, COLLECTION!$C:$C, AK$13) + SUMIFS(BANK!$E:$E, BANK!$D:$D,DEPARTMENTS!$B:$B, BANK!$B:$B, AK$12, BANK!$C:$C, AK$13) + SUMIFS(TRUST!$E:$E, TRUST!$D:$D,DEPARTMENTS!$B:$B, TRUST!$B:$B, AK$12, TRUST!$C:$C, AK$13) -> 0 | AL36: =SUMIFS(COLLECTION!$E:$E, COLLECTION!$D:$D,DEPARTMENTS!$B:$B, COLLECTION!$B:$B, AL$12, COLLECTION!$C:$C, AL$13) + SUMIFS(BANK!$E:$E, BANK!$D:$D,DEPARTMENTS!$B:$B, BANK!$B:$B, AL$12, BANK!$C:$C, AL$13) + SUMIFS(TRUST!$E:$E, TRUST!$D:$D,DEPARTMENTS!$B:$B, TRUST!$B:$B, AL$12, TRUST!$C:$C, AL$13) -> 0 | AM36: =SUMIFS(COLLECTION!$E:$E, COLLECTION!$D:$D,DEPARTMENTS!$B:$B, COLLECTION!$B:$B, AM$12, COLLECTION!$C:$C, AM$13) + SUMIFS(BANK!$E:$E, BANK!$D:$D,DEPARTMENTS!$B:$B, BANK!$B:$B, AM$12, BANK!$C:$C, AM$13) + SUMIFS(TRUST!$E:$E, TRUST!$D:$D,DEPARTMENTS!$B:$B, TRUST!$B:$B, AM$12, TRUST!$C:$C, AM$13) -> 80 | AN36: =SUMIFS(COLLECTION!$E:$E, COLLECTION!$D:$D,DEPARTMENTS!$B:$B, COLLECTION!$B:$B, AN$12, COLLECTION!$C:$C, AN$13) + SUMIFS(BANK!$E:$E, BANK!$D:$D,DEPARTMENTS!$B:$B, BANK!$B:$B, AN$12, BANK!$C:$C, AN$13) + SUMIFS(TRUST!$E:$E, TRUST!$D:$D,DEPARTMENTS!$B:$B, TRUST!$B:$B, AN$12, TRUST!$C:$C, AN$13) -> 25 | AO36: =SUMIFS(COLLECTION!$E:$E, COLLECTION!$D:$D,DEPARTMENTS!$B:$B, COLLECTION!$B:$B, AO$12, COLLECTION!$C:$C, AO$13) + SUMIFS(BANK!$E:$E, BANK!$D:$D,DEPARTMENTS!$B:$B, BANK!$B:$B, AO$12, BANK!$C:$C, AO$13) + SUMIFS(TRUST!$E:$E, TRUST!$D:$D,DEPARTMENTS!$B:$B, TRUST!$B:$B, AO$12, TRUST!$C:$C, AO$13) -> 0 | AP36: =SUMIFS(COLLECTION!$E:$E, COLLECTION!$D:$D,DEPARTMENTS!$B:$B, COLLECTION!$B:$B, AP$12, COLLECTION!$C:$C, AP$13) + SUMIFS(BANK!$E:$E, BANK!$D:$D,DEPARTMENTS!$B:$B, BANK!$B:$B, AP$12, BANK!$C:$C, AP$13) + SUMIFS(TRUST!$E:$E, TRUST!$D:$D,DEPARTMENTS!$B:$B, TRUST!$B:$B, AP$12, TRUST!$C:$C, AP$13) -> 0 | AQ36: =SUMIFS(COLLECTION!$E:$E, COLLECTION!$D:$D,DEPARTMENTS!$B:$B, COLLECTION!$B:$B, AQ$12, COLLECTION!$C:$C, AQ$13) + SUMIFS(BANK!$E:$E, BANK!$D:$D,DEPARTMENTS!$B:$B, BANK!$B:$B, AQ$12, BANK!$C:$C, AQ$13) + SUMIFS(TRUST!$E:$E, TRUST!$D:$D,DEPARTMENTS!$B:$B, TRUST!$B:$B, AQ$12, TRUST!$C:$C, AQ$13) -> 0 | AR36: =SUMIFS(COLLECTION!$E:$E, COLLECTION!$D:$D,DEPARTMENTS!$B:$B, COLLECTION!$B:$B, AR$12, COLLECTION!$C:$C, AR$13) + SUMIFS(BANK!$E:$E, BANK!$D:$D,DEPARTMENTS!$B:$B, BANK!$B:$B, AR$12, BANK!$C:$C, AR$13) + SUMIFS(TRUST!$E:$E, TRUST!$D:$D,DEPARTMENTS!$B:$B, TRUST!$B:$B, AR$12, TRUST!$C:$C, AR$13) -> 0 | ... CQ36: =SUMIFS(COLLECTION!$E:$E, COLLECTION!$D:$D,DEPARTMENTS!$B:$B, COLLECTION!$B:$B, CQ$12, COLLECTION!$C:$C, CQ$13) + SUMIFS(BANK!$E:$E, BANK!$D:$D,DEPARTMENTS!$B:$B, BANK!$B:$B, CQ$12, BANK!$C:$C, CQ$13) + SUMIFS(TRUST!$E:$E, TRUST!$D:$D,DEPARTMENTS!$B:$B, TRUST!$B:$B, CQ$12, TRUST!$C:$C, CQ$13) -> 0 | CR36: =SUM(AK36:CQ36) -> 4305
B37: CAMP EXPENSE | C37: 0 | D37: =SUMIF(COLLECTION!D:D,DEPARTMENTS!B:B,COLLECTION!E:E)+SUMIF(BANK!D:D,DEPARTMENTS!B:B,BANK!E:E)+SUMIF(TRUST!D:D,DEPARTMENTS!B:B,TRUST!E:E)+E188 -> 1500 | E37: =SUMIF(EXPENSES!D:D,DEPARTMENTS!B:B,EXPENSES!F:F) -> 0 | F37: =D37-E37+C37 -> 1500 | H37: =SUMIFS(COLLECTION!$E:$E, COLLECTION!$D:$D,DEPARTMENTS!$B:$B, COLLECTION!$B:$B, H$13, COLLECTION!$B:$B, H$13) + SUMIFS(BANK!$E:$E, BANK!$D:$D,DEPARTMENTS!$B:$B, BANK!$B:$B, H$13, BANK!$B:$B, H$13) + SUMIFS(TRUST!$E:$E, TRUST!$D:$D,DEPARTMENTS!$B:$B, TRUST!$B:$B, H$13, TRUST!$B:$B, H$13)+H188 -> 0 | I37: =SUMIFS(COLLECTION!$E:$E, COLLECTION!$D:$D,DEPARTMENTS!$B:$B, COLLECTION!$B:$B, I$13, COLLECTION!$B:$B, I$13) + SUMIFS(BANK!$E:$E, BANK!$D:$D,DEPARTMENTS!$B:$B, BANK!$B:$B, I$13, BANK!$B:$B, I$13) + SUMIFS(TRUST!$E:$E, TRUST!$D:$D,DEPARTMENTS!$B:$B, TRUST!$B:$B, I$13, TRUST!$B:$B, I$13)+I188 -> 0 | J37: =SUMIFS(COLLECTION!$E:$E, COLLECTION!$D:$D,DEPARTMENTS!$B:$B, COLLECTION!$B:$B, J$13, COLLECTION!$B:$B, J$13) + SUMIFS(BANK!$E:$E, BANK!$D:$D,DEPARTMENTS!$B:$B, BANK!$B:$B, J$13, BANK!$B:$B, J$13) + SUMIFS(TRUST!$E:$E, TRUST!$D:$D,DEPARTMENTS!$B:$B, TRUST!$B:$B, J$13, TRUST!$B:$B, J$13)+J188 -> 0 | K37: =SUMIFS(COLLECTION!$E:$E, COLLECTION!$D:$D,DEPARTMENTS!$B:$B, COLLECTION!$B:$B, K$13, COLLECTION!$B:$B, K$13) + SUMIFS(BANK!$E:$E, BANK!$D:$D,DEPARTMENTS!$B:$B, BANK!$B:$B, K$13, BANK!$B:$B, K$13) + SUMIFS(TRUST!$E:$E, TRUST!$D:$D,DEPARTMENTS!$B:$B, TRUST!$B:$B, K$13, TRUST!$B:$B, K$13)+K188 -> 1500 | L37: =SUMIFS(COLLECTION!$E:$E, COLLECTION!$D:$D,DEPARTMENTS!$B:$B, COLLECTION!$B:$B, L$13, COLLECTION!$B:$B, L$13) + SUMIFS(BANK!$E:$E, BANK!$D:$D,DEPARTMENTS!$B:$B, BANK!$B:$B, L$13, BANK!$B:$B, L$13) + SUMIFS(TRUST!$E:$E, TRUST!$D:$D,DEPARTMENTS!$B:$B, TRUST!$B:$B, L$13, TRUST!$B:$B, L$13)+L188 -> 0 | M37: =SUMIFS(COLLECTION!$E:$E, COLLECTION!$D:$D,DEPARTMENTS!$B:$B, COLLECTION!$B:$B, M$13, COLLECTION!$B:$B, M$13) + SUMIFS(BANK!$E:$E, BANK!$D:$D,DEPARTMENTS!$B:$B, BANK!$B:$B, M$13, BANK!$B:$B, M$13) + SUMIFS(TRUST!$E:$E, TRUST!$D:$D,DEPARTMENTS!$B:$B, TRUST!$B:$B, M$13, TRUST!$B:$B, M$13)+M188 -> 0 | N37: =SUMIFS(COLLECTION!$E:$E, COLLECTION!$D:$D,DEPARTMENTS!$B:$B, COLLECTION!$B:$B, N$13, COLLECTION!$B:$B, N$13) + SUMIFS(BANK!$E:$E, BANK!$D:$D,DEPARTMENTS!$B:$B, BANK!$B:$B, N$13, BANK!$B:$B, N$13) + SUMIFS(TRUST!$E:$E, TRUST!$D:$D,DEPARTMENTS!$B:$B, TRUST!$B:$B, N$13, TRUST!$B:$B, N$13)+N188 -> 0 | O37: =SUMIFS(COLLECTION!$E:$E, COLLECTION!$D:$D,DEPARTMENTS!$B:$B, COLLECTION!$B:$B, O$13, COLLECTION!$B:$B, O$13) + SUMIFS(BANK!$E:$E, BANK!$D:$D,DEPARTMENTS!$B:$B, BANK!$B:$B, O$13, BANK!$B:$B, O$13) + SUMIFS(TRUST!$E:$E, TRUST!$D:$D,DEPARTMENTS!$B:$B, TRUST!$B:$B, O$13, TRUST!$B:$B, O$13)+O188 -> 0 | ... S37: =SUMIFS(COLLECTION!$E:$E, COLLECTION!$D:$D,DEPARTMENTS!$B:$B, COLLECTION!$B:$B, S$13, COLLECTION!$B:$B, S$13) + SUMIFS(BANK!$E:$E, BANK!$D:$D,DEPARTMENTS!$B:$B, BANK!$B:$B, S$13, BANK!$B:$B, S$13) + SUMIFS(TRUST!$E:$E, TRUST!$D:$D,DEPARTMENTS!$B:$B, TRUST!$B:$B, S$13, TRUST!$B:$B, S$13)+S188 -> 0 | T37: =SUM(H37:S37) -> 1500 | V37: =SUMIFS(EXPENSES!$F:$F, EXPENSES!$D:$D,DEPARTMENTS!$B:$B, EXPENSES!$B:$B, V$13) -> 0 | W37: =SUMIFS(EXPENSES!$F:$F, EXPENSES!$D:$D,DEPARTMENTS!$B:$B, EXPENSES!$B:$B, W$13) -> 0 | X37: =SUMIFS(EXPENSES!$F:$F, EXPENSES!$D:$D,DEPARTMENTS!$B:$B, EXPENSES!$B:$B, X$13) -> 0 | Y37: =SUMIFS(EXPENSES!$F:$F, EXPENSES!$D:$D,DEPARTMENTS!$B:$B, EXPENSES!$B:$B, Y$13) -> 0 | Z37: =SUMIFS(EXPENSES!$F:$F, EXPENSES!$D:$D,DEPARTMENTS!$B:$B, EXPENSES!$B:$B, Z$13) -> 0 | AA37: =SUMIFS(EXPENSES!$F:$F, EXPENSES!$D:$D,DEPARTMENTS!$B:$B, EXPENSES!$B:$B, AA$13) -> 0 | AB37: =SUMIFS(EXPENSES!$F:$F, EXPENSES!$D:$D,DEPARTMENTS!$B:$B, EXPENSES!$B:$B, AB$13) -> 0 | AC37: =SUMIFS(EXPENSES!$F:$F, EXPENSES!$D:$D,DEPARTMENTS!$B:$B, EXPENSES!$B:$B, AC$13) -> 0 | ... AG37: =SUMIFS(EXPENSES!$F:$F, EXPENSES!$D:$D,DEPARTMENTS!$B:$B, EXPENSES!$B:$B, AG$13) -> 0 | AH37: =SUM(V37:AG37) -> 0 | AK37: =SUMIFS(COLLECTION!$E:$E, COLLECTION!$D:$D,DEPARTMENTS!$B:$B, COLLECTION!$B:$B, AK$12, COLLECTION!$C:$C, AK$13) + SUMIFS(BANK!$E:$E, BANK!$D:$D,DEPARTMENTS!$B:$B, BANK!$B:$B, AK$12, BANK!$C:$C, AK$13) + SUMIFS(TRUST!$E:$E, TRUST!$D:$D,DEPARTMENTS!$B:$B, TRUST!$B:$B, AK$12, TRUST!$C:$C, AK$13) -> 0 | AL37: =SUMIFS(COLLECTION!$E:$E, COLLECTION!$D:$D,DEPARTMENTS!$B:$B, COLLECTION!$B:$B, AL$12, COLLECTION!$C:$C, AL$13) + SUMIFS(BANK!$E:$E, BANK!$D:$D,DEPARTMENTS!$B:$B, BANK!$B:$B, AL$12, BANK!$C:$C, AL$13) + SUMIFS(TRUST!$E:$E, TRUST!$D:$D,DEPARTMENTS!$B:$B, TRUST!$B:$B, AL$12, TRUST!$C:$C, AL$13) -> 0 | AM37: =SUMIFS(COLLECTION!$E:$E, COLLECTION!$D:$D,DEPARTMENTS!$B:$B, COLLECTION!$B:$B, AM$12, COLLECTION!$C:$C, AM$13) + SUMIFS(BANK!$E:$E, BANK!$D:$D,DEPARTMENTS!$B:$B, BANK!$B:$B, AM$12, BANK!$C:$C, AM$13) + SUMIFS(TRUST!$E:$E, TRUST!$D:$D,DEPARTMENTS!$B:$B, TRUST!$B:$B, AM$12, TRUST!$C:$C, AM$13) -> 0 | AN37: =SUMIFS(COLLECTION!$E:$E, COLLECTION!$D:$D,DEPARTMENTS!$B:$B, COLLECTION!$B:$B, AN$12, COLLECTION!$C:$C, AN$13) + SUMIFS(BANK!$E:$E, BANK!$D:$D,DEPARTMENTS!$B:$B, BANK!$B:$B, AN$12, BANK!$C:$C, AN$13) + SUMIFS(TRUST!$E:$E, TRUST!$D:$D,DEPARTMENTS!$B:$B, TRUST!$B:$B, AN$12, TRUST!$C:$C, AN$13) -> 0 | AO37: =SUMIFS(COLLECTION!$E:$E, COLLECTION!$D:$D,DEPARTMENTS!$B:$B, COLLECTION!$B:$B, AO$12, COLLECTION!$C:$C, AO$13) + SUMIFS(BANK!$E:$E, BANK!$D:$D,DEPARTMENTS!$B:$B, BANK!$B:$B, AO$12, BANK!$C:$C, AO$13) + SUMIFS(TRUST!$E:$E, TRUST!$D:$D,DEPARTMENTS!$B:$B, TRUST!$B:$B, AO$12, TRUST!$C:$C, AO$13) -> 0 | AP37: =SUMIFS(COLLECTION!$E:$E, COLLECTION!$D:$D,DEPARTMENTS!$B:$B, COLLECTION!$B:$B, AP$12, COLLECTION!$C:$C, AP$13) + SUMIFS(BANK!$E:$E, BANK!$D:$D,DEPARTMENTS!$B:$B, BANK!$B:$B, AP$12, BANK!$C:$C, AP$13) + SUMIFS(TRUST!$E:$E, TRUST!$D:$D,DEPARTMENTS!$B:$B, TRUST!$B:$B, AP$12, TRUST!$C:$C, AP$13) -> 0 | AQ37: =SUMIFS(COLLECTION!$E:$E, COLLECTION!$D:$D,DEPARTMENTS!$B:$B, COLLECTION!$B:$B, AQ$12, COLLECTION!$C:$C, AQ$13) + SUMIFS(BANK!$E:$E, BANK!$D:$D,DEPARTMENTS!$B:$B, BANK!$B:$B, AQ$12, BANK!$C:$C, AQ$13) + SUMIFS(TRUST!$E:$E, TRUST!$D:$D,DEPARTMENTS!$B:$B, TRUST!$B:$B, AQ$12, TRUST!$C:$C, AQ$13) -> 0 | AR37: =SUMIFS(COLLECTION!$E:$E, COLLECTION!$D:$D,DEPARTMENTS!$B:$B, COLLECTION!$B:$B, AR$12, COLLECTION!$C:$C, AR$13) + SUMIFS(BANK!$E:$E, BANK!$D:$D,DEPARTMENTS!$B:$B, BANK!$B:$B, AR$12, BANK!$C:$C, AR$13) + SUMIFS(TRUST!$E:$E, TRUST!$D:$D,DEPARTMENTS!$B:$B, TRUST!$B:$B, AR$12, TRUST!$C:$C, AR$13) -> 0 | ... CQ37: =SUMIFS(COLLECTION!$E:$E, COLLECTION!$D:$D,DEPARTMENTS!$B:$B, COLLECTION!$B:$B, CQ$12, COLLECTION!$C:$C, CQ$13) + SUMIFS(BANK!$E:$E, BANK!$D:$D,DEPARTMENTS!$B:$B, BANK!$B:$B, CQ$12, BANK!$C:$C, CQ$13) + SUMIFS(TRUST!$E:$E, TRUST!$D:$D,DEPARTMENTS!$B:$B, TRUST!$B:$B, CQ$12, TRUST!$C:$C, CQ$13) -> 0 | CR37: =SUM(AK37:CQ37) -> 0
