Workbook

Sheet OFFERING SUMMARY
C2: SDA CHURCH KAHAWA WENDANI
C3: COLLECTION SUMMARY FROM 7 FEB 2026 TO 28TH FEB 2026
D4: 46060 | E4: =D4+7 -> 46067 | F4: =E4+7 -> 46074 | G4: =F4+7 -> 46081 | I4: TOTAL
C5: TITHE | D5: ='SABBATH 1'!C160 -> 70623 | E5: ='SABBATH 2'!C157 -> 103901 | F5: ='SABBAATH 3'!C120 -> 56147 | G5: ='SABBATH 4'!C106 -> 172641 | I5: =SUM(D5:H5) -> 403312
C6: COMBINED OFFERING 50% | D6: ='SABBATH 1'!C161 -> 2834.5 | E6: ='SABBATH 2'!C158 -> 8829.5 | F6: ='SABBAATH 3'!C121 -> 3627.5 | G6: ='SABBATH 4'!C107 -> 3455 | I6: =SUM(D6:H6) -> 18746.5
C7: THANKS GIVING 50% | D7: ='SABBATH 1'!C163 -> 2925 | E7: ='SABBATH 2'!C160 -> 350 | F7: ='SABBAATH 3'!C123 -> 2700 | G7: ='SABBATH 4'!C109 -> 650 | I7: =SUM(D7:H7) -> 6625
C8: 13TH SABBATH OFFERING | D8: 0 | E8: 0 | F8: 0 | G8: 0 | I8: =SUM(D8:H8) -> 0
C9: CAMP OFFERING | D9: ='SABBATH 1'!C162 -> 385 | E9: ='SABBATH 2'!C159 -> 740 | F9: ='SABBAATH 3'!C122 -> 200 | G9: ='SABBATH 4'!C108 -> 760 | I9: =SUM(D9:H9) -> 2085
C10: STATION DEVELOPMENT | D10: ='SABBATH 1'!C165 -> 0 | E10: ='SABBATH 2'!C162 -> 0 | F10: ='SABBAATH 3'!C125 -> 0 | G10: ='SABBATH 4'!C111 -> 0 | I10: =SUM(D10:H10) -> 0
C11: FIELD EVANGELISM | D11: ='SABBATH 1'!C164 -> 0 | E11: ='SABBATH 2'!C161 -> 0 | F11: ='SABBAATH 3'!C124 -> 0 | G11: ='SABBATH 4'!C110 -> 0 | I11: =SUM(D11:H11) -> 0
C12: TOTAL TRUST FUNDS | D12: =SUM(D5:D11) -> 76767.5 | E12: =SUM(E5:E11) -> 113820.5 | F12: =SUM(F5:F11) -> 62674.5 | G12: =SUM(G5:G11) -> 177506 | I12: =SUM(I5:I11) -> 430768.5
C14: COMBINED OFFERING 50% | D14: ='SABBATH 1'!C169 -> 2834.5 | E14: =E6 -> 8829.5 | F14: ='SABBAATH 3'!C129 -> 3627.5 | G14: ='SABBATH 4'!C115 -> 3455 | I14: =SUM(D14:H14) -> 18746.5
C15: THANKS GIVING 50% | D15: ='SABBATH 1'!C170 -> 2925 | E15: ='SABBATH 2'!C167 -> 350 | F15: ='SABBAATH 3'!C130 -> 2700 | G15: ='SABBATH 4'!C116 -> 650 | I15: =SUM(D15:H15) -> 6625
C16: CHURCH BUDGET | D16: ='SABBATH 1'!C173 -> 4570 | E16: ='SABBATH 2'!C170 -> 6650 | F16: ='SABBAATH 3'!C134 -> 13870 | G16: ='SABBATH 4'!C119 -> 5800 | I16: =SUM(D16:H16) -> 30890
C17: EVANGELISM LOCAL | D17: ='SABBATH 1'!C171 -> 0 | E17: ='SABBATH 2'!C168 -> 0 | G17: ='SABBATH 4'!C117 -> 0 | I17: =SUM(D17:H17) -> 0
C18: DEVELOPMENT | D18: ='SABBATH 1'!C172 -> 23835 | E18: ='SABBATH 2'!C169 -> 3010 | F18: ='SABBAATH 3'!C132 -> 880 | G18: ='SABBATH 4'!C118 -> 20125 | I18: =SUM(D18:H18) -> 47850
C19: SABBATH SCHOOL | D19: 0 | E19: ='SABBATH 2'!C172 -> 160 | F19: ='SABBAATH 3'!C131 -> 30 | G19: ='SABBATH 4'!C120 -> 100 | I19: =SUM(D19:H19) -> 290
C20: PATHFINDER REG | D20: ='SABBATH 1'!C174 -> 200 | E20: ='SABBATH 2'!C173 -> 0 | I20: =SUM(D20:H20) -> 200
C21: MSAMARIA | D21: 0 | E21: ='SABBATH 2'!C174 -> 1550 | F21: ='SABBAATH 3'!C133 -> 0 | I21: =SUM(D21:H21) -> 1550
C22: TOTAL CHURCH FUNDS | D22: =SUM(D14:D21) -> 34364.5 | E22: =SUM(E14:E21) -> 20549.5 | F22: =SUM(F14:F21) -> 21107.5 | G22: =SUM(G14:G21) -> 30130 | H22: =SUM(H14:H21) -> 0 | I22: =SUM(I14:I21) -> 106151.5
C24: TOTAL COLLECTION | D24: =D22+D12 -> 111132 | E24: =E22+E12 -> 134370 | F24: =F22+F12 -> 83782 | G24: =G22+G12 -> 207636 | H24: =H22+H12 -> 0 | I24: =SUM(D24:H24) -> 536920
C28: TREASURER: | D28: EDWIN K. ORIOKI | E28: ELDER: | F28: CALVINCE OUMA | G28: PASTOR: | H28: MACJOE MASESI
C29: SIGNATURE: | E29: SIGNATURE: | G29: SIGNATURE:
C30: DATE: | E30: DATE: | G30: DATE:

Sheet 4TH MARCH 2023
C2: TREASURERS CASH STATEMENT, 4TH MARCH 2023
A3: Date | B3: Contributor Name | C3: Receipt Number | D3: Total Amount | E3: Tithe | F3: Combined Offerings | G3: Camp Meeting | H3: Church Building Fund | I3: Local Church Budget | J3: Thanks Giving | K3: Evangelism-Field | L3: Evangelism-local | M3: Chairs | N3: GYD | O3: Sabbath School | P3: Master Guide | Q3: Station Dev. Fund | R3: Adventist Possibility Ministry (APM)
A4: 44989 | B4: KAHAWA SUKARI SDA | C4: 506436 | D4: 8151 | I4: 8151
A5: 44989 | B5: ZIPPORAH MAIRURA | C5: 506437 | D5: 300 | R5: 300
A6: 44989 | B6: DAMARIS WAMBUI KAMAU | C6: 506438 | D6: 200 | F6: 200
A7: 44989 | B7: ABEDNEGO GWAYA | C7: 506439 | D7: 220000 | H7: 220000
A8: 44989 | B8: CECILIA ATUTI | C8: 506440 | D8: 1000 | I8: 1000
A9: 44989 | B9: DR.(MRS.) TERESA NYAMBEGERA | C9: 506441 | D9: 12000 | E9: 11000 | F9: 200 | I9: 800
A10: 44989 | B10: CHELSEY KIOKO | C10: 506442 | D10: 60 | E10: 50 | F10: 10
A11: 44989 | B11: DENISH OTIENO | C11: 506443 | D11: 200 | E11: 200
A12: 44989 | B12: JACINTA MARUTI | C12: 506444 | D12: 100 | E12: 50 | F12: 50
A13: 44989 | B13: JOSEPHINE MORANGA | C13: 506445 | D13: 200 | E13: 100 | H13: 100
A14: 44989 | B14: ZAINABU ISRAEL | C14: 506446 | D14: 700 | E14: 700
A15: 44989 | B15: FAITH KORIR | C15: 506447 | D15: 700 | E15: 700
A16: 44989 | B16: MARY MIRINGA | C16: 506448 | D16: 200 | I16: 200
A17: 44989 | B17: BRENDA JUMBE | C17: 506449 | D17: 200 | E17: 100 | I17: 100
A18: 44989 | B18: EMILY OYUGI | C18: 506450 | D18: 600 | F18: 300 | I18: 300
A19: 44989 | B19: ABEDNEGO GWAYA | C19: 506451 | D19: 1000 | F19: 1000
A20: 44989 | B20: NATHANIEL NYAGOL | C20: 506452 | D20: 300 | E20: 300
A21: 44989 | B21: BETTY MWANGI | C21: 506453 | D21: 6000 | E21: 5700 | F21: 300
A22: 44989 | B22: RAHAB NYAKUNDI | C22: 506454 | D22: 100 | F22: 100
A23: 44989 | B23: BENFILAS JUMA | C23: 506455 | D23: 200 | F23: 50 | H23: 150
A24: 44989 | B24: SILAS MBECHE | C24: 506456 | D24: 200 | E24: 100 | I24: 100
A25: 44989 | B25: JUSTUS OKENYE | C25: 506457 | D25: 200 | G25: 100 | I25: 100
A26: 44989 | B26: MARTHA MAKORI | C26: 506458 | D26: 100 | F26: 50 | K26: 50
A27: 44989 | B27: NGIGI KARANJA | C27: 506459 | D27: 200 | F27: 200
A28: 44989 | B28: DOMINIC GICHANA | C28: 506460 | D28: 240 | E28: 240
A29: 44989 | B29: FRIDAH NKUNDA | C29: 506461 | D29: 50 | F29: 50
A30: 44989 | B30: ANNAH OSEBE | C30: 506462 | D30: 100 | K30: 100
A31: 44989 | B31: LILIAN OMBAYE | C31: 506463 | D31: 500 | F31: 500
A32: 44989 | B32: TITUS NDIWA’S FAMILY | C32: 506464 | D32: 1000 | F32: 500 | I32: 500
A33: 44989 | B33: ADRIELLE CORRIDLO | C33: 506465 | D33: 100 | E33: 100
A34: 44989 | B34: LUCY OMWENO | C34: 506466 | D34: 2000 | I34: 2000
A35: 44989 | B35: LYDIA MORAA | C35: 506467 | D35: 2200 | F35: 2200
A36: 44989 | B36: MARTINAH NYAKUNDI | C36: 506468 | D36: 5000 | E36: 4689 | I36: 311
A37: 44989 | B37: NIRAH | C37: 506469 | D37: 500 | E37: 500
A38: 44989 | B38: SARAH OTHOO | C38: 506470 | D38: 300 | E38: 250 | F38: 50
A39: 44989 | B39: RAQUEL MODI | C39: 506471 | D39: 3500 | E39: 3500
A40: 44989 | B40: NO NAME | C40: 506472 | D40: 1000 | I40: 1000
A41: 44989 | B41: OMBATI WILSON | C41: 506473 | D41: 29000 | E41: 20800 | H41: 5200 | M41: 2000 | N41: 1000
A42: 44989 | B42: EDWINA NYABUTI | C42: 506474 | D42: 100 | I42: 100
A43: 44989 | B43: LEON MBUGUA | C43: 506475 | D43: 2000 | E43: 1600 | F43: 400
A44: 44989 | B44: MRS. OSORO | C44: 506476 | D44: 100 | J44: 100
A45: 44989 | B45: Isaac Nyantika | C45: 506477 | D45: 110000 | E45: 40000 | I45: 70000
A46: 44989 | B46: MAKWORO’S FAMILY | C46: 506478 | D46: 200 | I46: 200
A47: 44989 | B47: JAMES MUGUNDA | C47: 506479 | D47: 1000 | E47: 800 | F47: 200
A48: 44989 | B48: ERICK NYAMBEGERA | C48: 506480 | D48: 100 | E48: 100
A49: 44989 | B49: ZACHARIAH BOSIRE | C49: 506481 | D49: 600 | E49: 600
A50: 44989 | B50: FAITH OSORO | C50: 506482 | D50: 13000 | E50: 13000
A51: 44989 | B51: ALLAN KEITH ABONYO | C51: 506483 | D51: 2300 | E51: 2300
A52: 44989 | B52: WINNIE AKINYI ODUOR | C52: 506484 | D52: 5972 | E52: 5072 | I52: 100 | M52: 800
A53: 44989 | B53: ASHLYN BHOKE | C53: 506485 | D53: 500 | E53: 500
A54: 44989 | B54: PERIS ISABOKE | C54: 506486 | D54: 15000 | H54: 15000
A55: 44989 | B55: DORAH HELLEN ALOO | C55: 506487 | D55: 300 | E55: 300
A56: 44989 | B56: BERNARD OGERO | C56: 506488 | D56: 8100 | E56: 8000 | I56: 100
A57: 44989 | B57: STANLEY MACHARIA | C57: 506489 | D57: 210 | E57: 210
A58: 44989 | B58: LORINE OCHIENG | C58: 506490 | D58: 2100 | E58: 2100
A59: 44989 | B59: ESTHER MOMANYI | C59: 506491 | D59: 12700 | E59: 12700
A60: 44989 | B60: GRACE MBANE | C60: 506492 | D60: 500 | H60: 500
A61: 44989 | B61: MICAH MAKWORO | C61: 506493 | D61: 7500 | E61: 6000 | I61: 1500
A62: 44989 | B62: ANNAH ANYANGO | C62: 506494 | D62: 9918 | E62: 4959 | I62: 4959
A63: 44989 | B63: STANLEY MACHARIA | C63: 506495 | D63: 1000 | N63: 1000
A64: 44989 | B64: LUCAS N. NYANGWESO | C64: 506496 | D64: 5000 | H64: 5000
A65: 44989 | B65: MMICA OTIENO | C65: 506497 | D65: 200 | F65: 200
A66: 44989 | B66: EVANS OGATO | C66: 506498 | D66: 400 | E66: 400
A67: 44989 | B67: SILAS MBECHE | C67: 506499 | D67: 1600 | M67: 1600
A68: 44989 | B68: KAREN KAUNDA | C68: 506500 | D68: 10000 | E68: 10000
A69: 44989 | B69: ESTHER N. MIZE | C69: 506501 | D69: 415 | E69: 415
A70: 44989 | B70: MARGARET MOGUSU | C70: 506502 | D70: 6000 | E70: 3000 | H70: 3000
A71: 44989 | B71: GEORGE NYAKOE | C71: 506503 | D71: 1000 | I71: 500 | L71: 200
A72: 44989 | B72: ENOCK KOMBO | C72: 506504 | D72: 4000 | M72: 4000
A73: 44989 | B73: BETTY BARONGO RATEMO | C73: 506505 | D73: 6400 | E73: 6400
A74: 44989 | B74: EPHY AWUOR | C74: 506506 | D74: 100 | E74: 100
A75: 44989 | B75: NYAMARI GEKONDE | C75: 506507 | D75: 500 | I75: 500
A76: 44989 | B76: DOROTHY OTHOO | C76: 506508 | D76: 500 | F76: 500
A77: 44989 | B77: SUSAN OTIENDE | C77: 506509 | D77: 200 | F77: 200
A78: 44989 | B78: TONY OCHIENG | C78: 506510 | D78: 100 | E78: 100
A79: 44989 | B79: STEPHEN MOKAYA | C79: 506511 | D79: 100 | F79: 100
A80: 44989 | B80: JOAN MAGETO | C80: 506512 | D80: 100 | F80: 100
A81: 44989 | B81: ALPHONCE MANYONI | C81: 506513 | D81: 500 | I81: 300 | N81: 200 | O81: 300
A82: 44989 | B82: PAUL KOSKEI | C82: 506514 | D82: 1200 | E82: 1200
A83: 44989 | B83: NELSON NYAUNDI | C83: 506515 | D83: 200 | O83: 200
A84: 44989 | B84: NYAMARI GEKONDE | C84: 506516 | D84: 4000 | M84: 4000
A85: 44989 | B85: LINNER LIMO | C85: 506517 | D85: 5700 | E85: 5500 | F85: 200
A86: 44989 | B86: ZACHARIAH BOSIRE | C86: 506518 | D86: 106000 | E86: 106000
A87: 44989 | B87: ROSE GEKE | C87: 506519 | D87: 300 | F87: 300
A88: 44989 | B88: KENNEDY KOMBO | C88: 506520 | D88: 360 | E88: 360
A89: 44989 | B89: BENARD KARANJA & FAMILY | C89: 506521 | D89: 2800 | E89: 1000 | F89: 200 | M89: 1600
A90: TOTAL | D90: =SUM(D4:D89) -> 649276 | E90: =SUM(E4:E89) -> 281795 | F90: =SUM(F4:F89) -> 8160 | G90: =SUM(G4:G89) -> 100 | H90: =SUM(H4:H89) -> 248950 | I90: =SUM(I4:I89) -> 92821 | J90: =SUM(J4:J89) -> 100 | K90: =SUM(K4:K89) -> 150 | ... R90: =SUM(R4:R89) -> 300 | S90: =SUM(E90:R90) -> 649276
E92: =D90-S90 -> 0
B93: SUMMARY
B94: TRUST FUNDS
B95: TITHE | C95: =E90 -> 281795
B96: COMBINED OFFFERING 50% | C96: =F90/2 -> 4080
B97: CAMP MEETING OFFERING | C97: =G90 -> 100
B98: THANKS GIVING 50% | C98: =J90/2 -> 50
B99: EVANGELISM FIELD | C99: =K90 -> 150
B100: STATION DEV FUND | C100: =Q90 -> 0
B101: TOTAL | C101: =SUM(C95:C100) -> 286175
B103: LOCAL CHURCH FUNDS
...

Sheet 4TH-EXPENSES
C2: LOCAL CHURCH -EXPENSES
C3: DESCRIPTION | D3: DATE | E3: AMOUNT
C4: Deaconary Funds for March 2023 | D4: 44989 | E4: 28820
C5: Pr. Facilitation within the week | D5: 44989 | E5: 4000
C6: Speaker facilitation-Stewarship week of prayer | D6: 44989 | E6: 10000
C7: Additional Lunch for the Funds Drive-Visitors | D7: 44989 | E7: 4000
C8: Bulletin Printing (2 sabbaths) | D8: 44989 | E8: 1200
C21: TOTALS | E21: =SUM(E4:E20) -> 48020

Sheet 11TH MARCH 2023
C2: TREASURERS CASH STATEMENT, 11TH MARCH 2023
A3: Date | B3: Contributor Name | C3: Receipt Number | D3: Total Amount | E3: Tithe | F3: Combined Offerings | G3: Camp Meeting | H3: Church Building Fund | I3: Local Church Budget | J3: Thanks Giving | K3: Evangelism-Field | L3: Evangelism-local | M3: Chairs | N3: GYD | O3: Sabbath School | P3: Master Guide | Q3: Station Dev. Fund | R3: Adventist Possibility Ministry (APM)
A4: 44996 | B4: CHARLES GICHUKI | C4: 506522 | D4: 100 | H4: 100
A5: 44996 | B5: MARTHA BOCHERE | C5: 506523 | D5: 100 | E5: 50 | F5: 50
A6: 44996 | B6: LUCAS N. NYAMBEGERA | C6: 506524 | D6: 10000 | E6: 8000 | I6: 2000
A7: 44996 | B7: JOSPHAT MAIKARA | C7: 506525 | D7: 1000 | F7: 1000
A8: 44996 | B8: DAMARIS WWMBUI KAMAU | C8: 506526 | D8: 100 | F8: 100
A9: 44996 | B9: NGIGI KARANJA | C9: 506527 | D9: 200 | F9: 200
A10: 44996 | B10: LINET KEMUNTO | C10: 506528 | D10: 1000 | E10: 1000
A11: 44996 | B11: ACHIENG LENCER | C11: 506529 | D11: 20 | E11: 20
A12: 44996 | B12: ELIZABETH N. KIMONGE | C12: 506530 | D12: 500 | F12: 300 | I12: 200
A13: 44996 | B13: SPINGS OGUGU | C13: 506531 | D13: 500 | H13: 500
A14: 44996 | B14: ROSE NYAMAO MAGOMA | C14: 506532 | D14: 3000 | F14: 1000 | H14: 2000
A15: 44996 | B15: JUSTUS OKENYE | C15: 506533 | D15: 200 | G15: 100 | I15: 50 | K15: 50
A16: 44996 | B16: SHELINE OYOO | C16: 506534 | D16: 4000 | E16: 3900 | F16: 100
A17: 44996 | B17: JOSEPHINE MORANGA | C17: 506535 | D17: 100 | E17: 100
A18: 44996 | B18: TAMARA ADHIAMBO | C18: 506536 | D18: 20 | E18: 20
A19: 44996 | B19: MERCYLINE NYANKIRA | C19: 506537 | D19: 200 | E19: 200
A20: 44996 | B20: EMILY OYUGI | C20: 506538 | D20: 500 | F20: 200 | I20: 300
A21: 44996 | B21: ANNAH OSEBE | C21: 506539 | D21: 500 | I21: 100 | J21: 400
A22: 44996 | B22: NO NAME | C22: 506540 | D22: 20 | H22: 20
A23: 44996 | B23: RAHAB NYAKUNDI | C23: 506541 | D23: 750 | E23: 750
A24: 44996 | B24: JEMMY JAMES | C24: 506542 | D24: 100 | E24: 100
A25: 44996 | B25: EVANS TSOMBE | C25: 506543 | D25: 200 | E25: 200
A26: 44996 | B26: IBRAHIM NYABUTI | C26: 506544 | D26: 500 | E26: 500
A27: 44996 | B27: DORIS NYAMARI | C27: 506545 | D27: 100 | P27: 100
A28: 44996 | B28: DR.(MRS.) TERESA NYAMBEGERA | C28: 506546 | D28: 1000 | F28: 200 | I28: 800
A29: 44996 | B29: JACINTA KIPROP | C29: 506547 | D29: 100 | H29: 100
A30: 44996 | B30: MONYENYE OMBATI | C30: 506548 | D30: 500 | H30: 500
A31: 44996 | B31: LILIAN OMBAYE | C31: 506549 | D31: 500 | H31: 500
A32: 44996 | B32: EDNAH OBAIGWA | C32: 506550 | D32: 100 | H32: 100
A33: 44996 | B33: DRUSILLA MAKWORO | C33: 506551 | D33: 5000 | H33: 5000
A34: 44996 | B34: EMILY OYUGI | C34: 506552 | D34: 2000 | H34: 2000
A35: 44996 | B35: STELLAH MASESE | C35: 506553 | D35: 1000 | H35: 1000
A36: 44996 | B36: LINET KEMUNTO | C36: 506554 | D36: 1000 | H36: 1000
A37: 44996 | B37: DAMARIS WWMBUI KAMAU | C37: 506555 | D37: 500 | H37: 500
A38: 44996 | B38: KEFA GEKONDE | C38: 506556 | D38: 1000 | H38: 1000
A39: 44996 | B39: YABESH KIBAI | C39: 506557 | D39: 3000 | H39: 3000
A40: 44996 | B40: BENFILAS JUMA | C40: 506558 | D40: 1150 | F40: 50 | H40: 1100
A41: 44996 | B41: MICAH MAKWORO | C41: 506559 | D41: 35000 | H41: 35000
A42: 44996 | B42: ENOCK KOMBO | C42: 506560 | D42: 1000 | H42: 1000
A43: 44996 | B43: RHODA NYANDUKO | C43: 506561 | D43: 10000 | H43: 10000
A44: 44996 | B44: OMBATI WILSON | C44: 506562 | D44: 1000 | H44: 1000
A45: 44996 | B45: JERIAH OMAO | C45: 506563 | D45: 200 | H45: 200
A46: 44996 | B46: JARED NYAUMA | C46: 506564 | D46: 14000 | H46: 14000
A47: 44996 | B47: KEFA GEKONDE | C47: 506565 | D47: 1000 | H47: 1000
A48: 44996 | B48: RUTH KWAMBOKA | C48: 506566 | D48: 200 | H48: 200
A49: 44996 | B49: STEPHEN KAMAU | C49: 506567 | D49: 3100 | H49: 3100
A50: 44996 | B50: CATHERINE KEMUNTO | C50: 506568 | D50: 50 | H50: 50
A51: 44996 | B51: CAROLYN BOSIBORI | C51: 506569 | D51: 500 | H51: 500
A52: 44996 | B52: BERNARD OGERO | C52: 506570 | D52: 1000 | H52: 1000
... A57: 44996 | B57: YVONNE KERUBO | C57: 506575 | D57: 200 | H57: 200
A58: 44996 | B58: EILEEN MORAA | C58: 506576 | D58: 1000 | H58: 900 | I58: 100
A59: 44996 | B59: DAMARIS NYABOKE | C59: 506577 | D59: 100 | H59: 100
A60: 44996 | B60: DOREEN OBENGO | C60: 506578 | D60: 50 | H60: 50
A61: 44996 | B61: FELIX BIRGEN | C61: 506579 | D61: 200 | H61: 200
A62: 44996 | B62: LUCAS K. OMBASA | C62: 506580 | D62: 4750 | E62: 2750 | H62: 2000
A63: 44996 | B63: DEBORA | C63: 506581 | D63: 500 | E63: 500
A64: 44996 | B64: DEBORA | C64: 506582 | D64: 200 | H64: 200
A65: 44996 | B65: MRS. A. OSORO | C65: 506583 | D65: 500 | H65: 500
A66: 44996 | B66: ROSEMARY MANYWANDA | C66: 506584 | D66: 6500 | H66: 6500
A67: 44996 | B67: BRENDA JUMBE | C67: 506585 | D67: 2000 | H67: 2000
A68: 44996 | B68: CECILIA ATUTI | C68: 506586 | D68: 3000 | H68: 3000
A69: 44996 | B69: JULIE OBARE | C69: 506587 | D69: 50 | H69: 50
A70: 44996 | B70: JENIFFER CHEPCHUMBA | C70: 506588 | D70: 100 | H70: 100
A71: 44996 | B71: DR.(MRS.) TERESA NYAMBEGERA | C71: 506589 | D71: 4000 | N71: 4000
A72: 44996 | B72: ANNAH OSEBE | C72: 506590 | D72: 1000 | N72: 1000
A73: 44996 | B73: BRENDA JUMBE | C73: 506591 | D73: 300 | N73: 300
A74: 44996 | B74: LINNER LIMO | C74: 506592 | D74: 500 | N74: 500
A75: 44996 | B75: CATHERINE KARIUKI | C75: 506593 | D75: 100 | N75: 100
A76: 44996 | B76: MARY MIRINGA | C76: 506594 | D76: 10000 | H76: 10000
A77: 44996 | B77: NGIGI KARANJA | C77: 506595 | D77: 10000 | H77: 10000
A78: 44996 | B78: ENG. OKOTH | C78: 506596 | D78: 70000 | H78: 70000
A79: 44996 | B79: JARED NYAUMA | C79: 506597 | D79: 12000 | H79: 12000
A80: 44996 | B80: GEORGE NYAKOE | C80: 506598 | D80: 5000 | M80: 5000
A81: 44996 | B81: TITUS NDIWA | C81: 506599 | D81: 2000 | M81: 2000
A82: 44996 | B82: NYAMARI GEKONDE | C82: 506600 | D82: 10000 | H82: 10000
A83: 44996 | B83: LEAH KARIUKI | C83: 528401 | D83: 2758 | E83: 2758
A84: 44996 | B84: DOMINIC GICHANA | C84: 528402 | D84: 360 | E84: 360
A85: 44996 | B85: HELLEN OGENCHE | C85: 528403 | D85: 20000 | H85: 20000
A86: 44996 | B86: ERICK NYAKORA | C86: 528404 | D86: 10000 | H86: 10000
A87: 44996 | B87: JANE MWANGI | C87: 528405 | D87: 30000 | H87: 30000
A88: 44996 | B88: KEFA GEKONDE | C88: 528406 | D88: 54000 | H88: 54000
A89: 44996 | B89: MARY GEKONDE | C89: 528407 | D89: 225 | E89: 225
A90: 44996 | B90: DORAH HELLEN AKINYI | C90: 528408 | D90: 300 | E90: 300
A91: 44996 | B91: ROGGERS ABONG’O | C91: 528409 | D91: 1000 | N91: 1000
A92: 44996 | B92: DRUSILLA MAKWORO | C92: 528410 | D92: 200 | N92: 200
A93: 44996 | B93: SHELINE OYOO | C93: 528411 | D93: 1000 | N93: 1000
A94: 44996 | B94: MERALDA INDA | C94: 528412 | D94: 1300 | E94: 1300
A95: 44996 | B95: JARED NYAUMA | C95: 528413 | D95: 5500 | H95: 5500
A96: 44996 | B96: VINCENT ONCHWERI | C96: 528414 | D96: 1000 | N96: 1000
A97: 44996 | B97: ERICK NYAKORA | C97: 528415 | D97: 10000 | H97: 10000
A98: 44996 | B98: SILAS MBECHE | C98: 528416 | D98: 10000 | H98: 10000
A99: 44996 | B99: TITUS NDIWA | C99: 528417 | D99: 20000 | H99: 20000
A100: 44996 | B100: STEPHEN KAMAU | C100: 528418 | D100: 3100 | H100: 3100
A101: 44996 | B101: ERICK NYAMBEGERA | C101: 528419 | D101: 1600 | E101: 1600
A102: 44996 | B102: BERNARD OGERO | C102: 528420 | D102: 1000 | H102: 1000
A103: 44996 | B103: ANN WACHIRA( NYABERI ) | C103: 528421 | D103: 30000 | H103: 30000
A104: 44996 | B104: MARGARET MOGUSU | C104: 528422 | D104: 4000 | E104: 3000 | F104: 250 | G104: 250 | I104: 500
A105: 44996 | B105: MARY MIRINGA | C105: 528423 | D105: 17000 | H105: 17000
...

Sheet 11TH-EXPENSES
C2: LOCAL CHURCH -EXPENSES
C3: DESCRIPTION | D3: DATE | E3: AMOUNT
C4: Internet Payment | D4: 44996 | E4: 5800
C5: Garbage collection fee (Nov 2022 to Feb 2023) | D5: 44996 | E5: 1200
C6: GYD collection Payout | D6: 44996 | E6: 13300
C7: GYD Youth Lunch | D7: 44996 | E7: 3000
C8: GYD Adventurers Lunch | D8: 44996 | E8: 3000
C9: GYD Ambasdors Lunch | D9: 44996 | E9: 900
C21: TOTALS | E21: =SUM(E4:E20) -> 27200

Sheet 18TH MARCH 2023
C2: TREASURERS CASH STATEMENT, 18TH MARCH 2023
A3: Date | B3: Contributor Name | C3: Receipt Number | D3: Total Amount | E3: Tithe | F3: Combined Offerings | G3: Camp Meeting | H3: Church Building Fund | I3: Local Church Budget | J3: Thanks Giving | K3: Evangelism-Field | L3: Evangelism-local | M3: Chairs | N3: GYD | O3: Sabbath School | P3: Master Guide | Q3: Station Dev. Fund | R3: Adventist Possibility Ministry (APM)
A4: 45003 | B4: NATHANIEL NYAGOL | C4: 528521 | D4: 1000 | E4: 1000
A5: 45003 | B5: OBUYA'S FAMILY | C5: =C4+1 -> 528522 | D5: 6000 | E5: 2000 | F5: 2000 | H5: 2000
A6: 45003 | B6: HELLEN OGENCHE | C6: =C5+1 -> 528523 | D6: 200 | E6: 200
A7: 45003 | B7: DOROTHY NGALA | C7: =C6+1 -> 528524 | D7: 1000 | F7: 1000
A8: 45003 | B8: KEFA GEKONDE | C8: =C7+1 -> 528525 | D8: 1000 | E8: 1000
A9: 45003 | B9: MR. & MRS. ERICK GWARO | C9: =C8+1 -> 528526 | D9: 6000 | E9: 5500 | F9: 500
A10: 45003 | B10: NYAMARI GEKONDE | C10: =C9+1 -> 528527 | D10: 107000 | E10: 106000 | I10: 1000
A11: 45003 | B11: YABESH KIBAI | C11: =C10+1 -> 528528 | D11: 100 | I11: 100
A12: 45003 | B12: ANNAH OSEBE | C12: =C11+1 -> 528529 | D12: 300 | J12: 200 | K12: 100
A13: 45003 | B13: OMBATI WILSON | C13: =C12+1 -> 528530 | D13: 3000 | H13: 3000
A14: 45003 | B14: NGIGI KARANJA | C14: =C13+1 -> 528531 | D14: 200 | F14: 200
A15: 45003 | B15: EMILY OYUGI | C15: =C14+1 -> 528532 | D15: 500 | F15: 200 | I15: 300
A16: 45003 | B16: LINET KEMUNTO | C16: =C15+1 -> 528533 | D16: 200 | I16: 200
A17: 45003 | B17: CORNELIUS KIPTOO | C17: =C16+1 -> 528534 | D17: 1000 | E17: 1000
A18: 45003 | B18: NDIWA'S FAMILY | C18: =C17+1 -> 528535 | D18: 1000 | E18: 1000
A19: 45003 | B19: MIRRIAM WEISIKO | C19: =C18+1 -> 528536 | D19: 200 | I19: 200
A20: 45003 | B20: RHODA NYANDUKO | C20: =C19+1 -> 528537 | D20: 100 | F20: 100
A21: 45003 | B21: JUSTUS OKENYE | C21: =C20+1 -> 528538 | D21: 200 | F21: 100 | I21: 50 | K21: 50
A22: 45003 | B22: ZADIAN ANGWENYI | C22: =C21+1 -> 528539 | D22: 500 | J22: 500
A23: 45003 | B23: JOSEPH MORANGÁ | C23: =C22+1 -> 528540 | D23: 100 | E23: 100
A24: 45003 | B24: JOSEPHAT NYAGERO | C24: =C23+1 -> 528541 | D24: 200 | F24: 200
A25: 45003 | B25: BENFILAS JUMA | C25: =C24+1 -> 528542 | D25: 200 | F25: 50 | H25: 150
A26: 45003 | B26: LUCY OMWENO | C26: =C25+1 -> 528543 | D26: 2000 | I26: 2000
A27: 45003 | B27: ESTHER KWAMBOKA | C27: =C26+1 -> 528544 | D27: 200 | E27: 200
A28: 45003 | B28: DAMARIS WAMBUI | C28: =C27+1 -> 528545 | D28: 100 | F28: 100
A29: 45003 | B29: PRINCESS ERICK LUCAS | C29: =C28+1 -> 528546 | D29: 200 | E29: 200
A30: 45003 | B30: ELIZABETH KIMONGE | C30: =C29+1 -> 528547 | D30: 500 | F30: 300 | I30: 200
A31: 45003 | B31: KAHAWA SUKARI | C31: =C30+1 -> 528548 | D31: 5124 | I31: 5124
A32: 45003 | B32: ESTHER MOMANYI | C32: =C31+1 -> 528549 | D32: 1000 | N32: 1000
A33: 45003 | B33: CELESTINE NYANCHAMA | C33: =C32+1 -> 528550 | D33: 100 | N33: 100
A34: 45003 | B34: SILAS MBECHE | C34: =C33+1 -> 528551 | D34: 500 | N34: 500
A35: 45003 | B35: DOMINIC GICHANA | C35: =C34+1 -> 528552 | D35: 120 | E35: 120
A36: 45003 | B36: BONFACE OSINDI | C36: =C35+1 -> 528553 | D36: 150 | E36: 150
A37: 45003 | B37: JILLANI YAWA | C37: =C36+1 -> 528554 | D37: 40000 | H37: 40000
A38: 45003 | B38: MARY GEKONDE | C38: =C37+1 -> 528555 | D38: 60 | E38: 60
A39: 45003 | B39: STANLEY MACHARIA | C39: =C38+1 -> 528556 | D39: 50 | E39: 50
A40: 45003 | B40: VINCENT NGÉNO | C40: =C39+1 -> 528557 | D40: 30000 | H40: 30000
A41: 45003 | B41: ERICK GWARO | C41: =C40+1 -> 528558 | D41: 900 | E41: 900
A42: 45003 | B42: MWITA BHOKE | C42: =C41+1 -> 528559 | D42: 500 | E42: 500
A43: 45003 | B43: JANE MWANGI | C43: =C42+1 -> 528560 | D43: 27263 | E43: 27263
A44: 45003 | B44: DOROTHY NGALA | C44: =C43+1 -> 528561 | D44: 57855 | E44: 57855
A45: 45003 | B45: TIMOTHY NYAKUNDI | C45: =C44+1 -> 528562 | D45: 2000 | H45: 2000
A46: 45003 | B46: CORNELIUS KIPTOO | C46: =C45+1 -> 528563 | D46: 300 | N46: 300
A47: 45003 | B47: NELLY ORINA | C47: =C46+1 -> 528564 | D47: 50 | E47: 25 | F47: 25
A48: 45003 | B48: NYAMARI GEKONDE | C48: =C47+1 -> 528565 | D48: 100 | O48: 100
A49: 45003 | B49: SOPHIE BIRONGA | C49: =C48+1 -> 528566 | D49: 7000 | E49: 6550 | F49: 150 | I49: 200 | K49: 100
A50: 45003 | B50: STEPHEN MOKAYA | C50: =C49+1 -> 528567 | D50: 200 | F50: 200
A51: 45003 | B51: CONCHELLA OCHIENG | C51: =C50+1 -> 528568 | D51: 50 | E51: 50
A52: 45003 | B52: KEVIN MORANG''A | C52: =C51+1 -> 528569 | D52: 100 | F52: 100
A53: 45003 | B53: CECILIA KEMUNTO | C53: =C52+1 -> 528570 | D53: 200 | F53: 200
A54: 45003 | B54: LEAH KARIUKI | C54: =C53+1 -> 528571 | D54: 3960 | E54: 3960
A55: 45003 | B55: APOLLO KARIUKI | C55: =C54+1 -> 528572 | D55: 100 | F55: 100
A56: 45003 | B56: SUSAN OTIENDE | C56: =C55+1 -> 528573 | D56: 100 | F56: 100
A57: 45003 | B57: GLADYS KEBASO | C57: =C56+1 -> 528574 | D57: 200 | F57: 200
A58: 45003 | B58: FAITH KURIA | C58: =C57+1 -> 528575 | D58: 200 | F58: 200
A59: 45003 | B59: VINCENT MOGIRE | C59: =C58+1 -> 528576 | D59: 200 | E59: 200
A60: 45003 | B60: BRIAN OBARE | C60: =C59+1 -> 528577 | D60: 2000 | H60: 2000
A61: 45003 | B61: LABAN KIPTOO | C61: =C60+1 -> 528578 | D61: 80 | F61: 80
A62: 45003 | B62: VIENNA MOENGA | C62: =C61+1 -> 528579 | D62: 400 | F62: 400
A63: 45003 | B63: PATRICK MARIONYA | C63: =C62+1 -> 528580 | D63: 500 | F63: 500
A64: 45003 | B64: WENDY MBATA | C64: =C63+1 -> 528581 | D64: 100 | F64: 100
A65: 45003 | B65: ERICK NYAKORA | C65: =C64+1 -> 528582 | D65: 2000 | J65: 2000
A66: 45003 | B66: PAUL KOSKEI | C66: =C65+1 -> 528583 | D66: 6500 | E66: 6500
A67: 45003 | B67: MASESE MONGÍNA | C67: =C66+1 -> 528584 | D67: 200 | F67: 200
A68: 45003 | B68: CECILIA NYAUMA | C68: =C67+1 -> 528585 | D68: 13000 | E68: 13000
A69: 45003 | B69: JOSEPHAT NYAGERO | C69: =C68+1 -> 528586 | D69: 10000 | H69: 10000
A70: 45003 | B70: ABEDNEGO GWAYA | C70: =C69+1 -> 528587 | D70: 2000 | F70: 2000
A71: TOTAL | D71: =SUM(D4:D70) -> 348162 | E71: =SUM(E4:E70) -> 235383 | F71: =SUM(F4:F70) -> 9305 | G71: =SUM(G4:G70) -> 0 | H71: =SUM(H4:H70) -> 89150 | I71: =SUM(I4:I70) -> 9374 | J71: =SUM(J4:J70) -> 2700 | K71: =SUM(K4:K70) -> 250 | ... R71: =SUM(R4:R70) -> 0 | S71: =SUM(E71:R71) -> 348162
D73: =D71-S71 -> 0
B74: SUMMARY
B75: TRUST FUNDS
B76: TITHE | C76: =E71 -> 235383
B77: COMBINED OFFFERING 50% | C77: =F71/2 -> 4652.5
B78: CAMP MEETING OFFERING | C78: =G71 -> 0
B79: THANKS GIVING 50% | C79: =J71/2 -> 1350
B80: EVANGELISM FIELD | C80: =K71 -> 250
B81: STATION DEV FUND | C81: =Q71 -> 0
B82: TOTAL | C82: =SUM(C76:C81) -> 241635.5
B84: LOCAL CHURCH FUNDS
B85: COMBINED OFFFERING 50% | C85: =F71/2 -> 4652.5
B86: CAMP MEETING EXPENSE | C86: 0
B87: THANKS GIVING 50% | C87: =J71/2 -> 1350
B88: EVANGELISM -LOCAL | C88: =L71 -> 0
B89: Building/Plot | C89: =H71 -> 89150
B90: LCB | C90: =I71 -> 9374
B91: Chairs | C91: =M71 -> 0
B92: GYD | C92: =N71 -> 1900
B93: AMO, ETC | C93: 0
B94: TOTAL | C94: =SUM(C85:C93) -> 106426.5

Sheet 18TH-EXPENSES
C2: LOCAL CHURCH -EXPENSES
C3: DESCRIPTION | D3: DATE | E3: AMOUNT
C4: Fuel and transport | D4: 45003 | E4: 2000
C5: Water Tank Refill (5000L) | D5: 45003 | E5: 2500
C6: KPLC Power bill | D6: 45003 | E6: 19500
C7: Internet payment | D7: 45003 | E7: 800
C21: TOTALS | E21: =SUM(E4:E20) -> 24800

Sheet 25TH MARCH 2023
C2: TREASURERS CASH STATEMENT, 25TH MARCH 2023
A3: Date | B3: Contributor Name | C3: Receipt Number | D3: Total Amount | E3: Tithe | F3: Combined Offerings | G3: Camp Meeting | H3: Church Building Fund | I3: Local Church Budget | J3: Thanks Giving | K3: Evangelism-Field | L3: Evangelism-local | M3: Chairs | N3: GYD | O3: Sabbath School | P3: Master Guide | Q3: Station Dev. Fund | R3: Lunch
A4: 45010 | B4: Kahawa Sukari | C4: 528588 | D4: 6282 | I4: 6282
A5: 45010 | B5: Wilson Ombati | C5: 528589 | D5: 13000 | E5: 12000 | M5: 1000
A6: 45010 | B6: Jacinta Maruti | C6: 528590 | D6: 50 | F6: 50
A7: 45010 | B7: Mary Gekonde | C7: 528591 | D7: 2500 | E7: 2500
A8: 45010 | B8: Monyenye Ombati | C8: 528592 | D8: 16000 | E8: 15720 | G8: 280
A9: 45010 | B9: Eucabeth Mosero | C9: 528593 | D9: 200 | E9: 200
A10: 45010 | B10: Bernad Ondara | C10: 528594 | D10: 1000 | I10: 500 | K10: 500
A11: 45010 | B11: Josphat Maikara | C11: 528595 | D11: 1000 | F11: 1000
A12: 45010 | B12: Rahab Nyakundi | C12: 528596 | D12: 220 | E12: 120 | F12: 100
A13: 45010 | B13: Yabesh Kibai | C13: 528597 | D13: 100 | I13: 100
A14: 45010 | B14: Denish Otieno | C14: 528598 | D14: 100 | E14: 100
A15: 45010 | B15: Mr & Mrs Eric Gwaro | C15: 528599 | D15: 100 | I15: 100
A16: 45010 | B16: Gakubu Ruth | C16: 528600 | D16: 90 | E16: 90
A17: 45010 | B17: Mr & Mrs Vincent Onchweri | C17: 499801 | D17: 1000 | E17: 500 | F17: 500
A18: 45010 | B18: Eng Okoth | C18: 499802 | D18: 4000 | I18: 3500 | R18: 500
A19: 45010 | B19: Karen Kaunda | C19: 499803 | D19: 2000 | E19: 2000
A20: 45010 | B20: No Name | C20: 499804 | D20: 200 | E20: 200
A21: 45010 | B21: Ruth Mining | C21: 499805 | D21: 1700 | E21: 1700
A22: 45010 | B22: Alphonce Manyoni | C22: 499806 | D22: 200 | F22: 100 | J22: 100
A23: 45010 | B23: No Name | C23: 499807 | D23: 200 | I23: 200
A24: 45010 | B24: Mary Miringa | C24: 499808 | D24: 200 | I24: 200
A25: 45010 | B25: Ndiwas | C25: 499809 | D25: 200 | E25: 200
A26: 45010 | B26: Rosemary Manywanda | C26: 499810 | D26: 6000 | E26: 5800 | R26: 200
A27: 45010 | B27: Benfilas Juma | C27: 499811 | D27: 200 | F27: 50 | H27: 150
A28: 45010 | B28: Tabitha Akinyi | C28: 499812 | D28: 200 | E28: 150 | I28: 50
A29: 45010 | B29: Emelda Vai | C29: 499813 | D29: 1600 | E29: 1500 | F29: 100
A30: 45010 | B30: Lucas Nyangweso | C30: 499814 | D30: 200 | I30: 200
A31: 45010 | B31: Emily Oyugi | C31: 499815 | D31: 500 | F31: 200 | I31: 300
A32: 45010 | B32: Evans Ogato | C32: 499816 | D32: 430 | E32: 430
A33: 45010 | B33: Mrs Roggers Abongo | C33: 499817 | D33: 500 | E33: 500
A34: 45010 | B34: Tabitha Onserio | C34: 499818 | D34: 200 | I34: 200
A35: 45010 | B35: Cornelius Kiptoo | C35: 499819 | D35: 1000 | E35: 800 | H35: 200
A36: 45010 | B36: Elizabeth Kimonge | C36: 499820 | D36: 1150 | G36: 1000 | I36: 150
A37: 45010 | B37: Brenda Jumbe | C37: 499821 | D37: 400 | E37: 300 | I37: 50 | K37: 50
A38: 45010 | B38: Annah Osebe | C38: 499822 | D38: 10300 | H38: 10000 | I38: 100 | J38: 200
A39: 45010 | B39: Ruth Moindi | C39: 499823 | D39: 800 | H39: 800
A40: 45010 | B40: Winnie Akinyi | C40: 499824 | D40: 200 | E40: 200
A41: 45010 | B41: Zadrian Makori | C41: 499825 | D41: 1000 | H41: 1000
A42: 45010 | B42: Dorothy Ngala | C42: 499826 | D42: 7938 | E42: 7938
A43: 45010 | B43: Erick Gwaro | C43: 499827 | D43: 400 | E43: 200 | J43: 200
A44: 45010 | B44: Stanley Macharia | C44: 499828 | D44: 420 | E44: 120 | H44: 200 | R44: 100
A45: 45010 | B45: Joan Mageto | C45: 499829 | D45: 500 | H45: 500
A46: 45010 | B46: Drusilla Makworo | C46: 499830 | D46: 22370 | E46: 22370
A47: 45010 | B47: Dr Mrs Teresa Nyamberegera | C47: 499831 | D47: 500 | I47: 200 | L47: 300
A48: 45010 | B48: Paul Otema | C48: 499832 | D48: 100 | F48: 100
A49: 45010 | B49: Margaret Mogusu | C49: 499833 | D49: 200 | F49: 200
A50: 45010 | B50: Kefah Gekonde | C50: 499834 | D50: 3000 | M50: 3000
A51: 45010 | B51: Abednego Gwaya | C51: 499835 | D51: 1000 | F51: 1000
A52: 45010 | B52: Linet Kemunto | C52: 499836 | D52: 1000 | I52: 1000
A53: 45010 | B53: Silas Mbeche | C53: 499837 | D53: 2000 | E53: 2000
A54: 45010 | B54: Elijah Ateka | C54: 499838 | D54: 10000 | H54: 10000
A55: 45010 | B55: Christine Achieng | C55: 499839 | D55: 50 | F55: 50
A56: 45010 | B56: Duncan Muthomi | C56: 499840 | D56: 100 | E56: 100
A57: 45010 | B57: Zephania Ochiki | C57: 499841 | D57: 500 | F57: 500
A58: 45010 | B58: Machaka Nyaburi | C58: 499842 | D58: 2000 | H58: 2000
A59: 45010 | B59: Josphine Moraa Mangoa | C59: 499843 | D59: 20 | F59: 20
A60: 45010 | B60: Micah Makworo | C60: 499844 | D60: 200 | I60: 200
A61: 45010 | B61: Denis Otieno Lango | C61: 499845 | D61: 20 | E61: 20
A62: 45010 | B62: Joan Mageto | C62: 499846 | D62: 100 | F62: 100
A63: 45010 | B63: Jane Mwangi | C63: 499847 | D63: 100 | F63: 100
A64: 45010 | B64: Stephene Mokaya | C64: 499848 | D64: 100 | F64: 100
A65: 45010 | B65: Erick Nyakora | C65: 499849 | D65: 5000 | E65: 5000
A66: 45010 | B66: Lilian Omoke | C66: 499850 | D66: 500 | I66: 500
A67: 45010 | B67: George Nyakoe | C67: 499851 | D67: 500 | I67: 300 | L67: 200
A68: 45010 | B68: Varsity Nasungu | C68: 499852 | D68: 1000 | F68: 1000
A69: 45010 | B69: Tom Machana | C69: 499853 | D69: 100 | F69: 100
A70: 45010 | B70: Cynthia Nyanchera | C70: 499854 | D70: 500 | E70: 500
A71: 45010 | B71: Rose Atieno | C71: 499855 | D71: 100 | E71: 100
A72: 45010 | B72: Julius Otumba | C72: 499856 | D72: 100 | F72: 100
A73: 45010 | B73: Samuel Njunji | C73: 499857 | D73: 500 | E73: 500
A74: 45010 | B74: Gladys Masau | C74: 499858 | D74: 300 | J74: 300
A75: 45010 | B75: Veronicah Nyambura | C75: 499859 | D75: 200 | E75: 200
A76: 45010 | B76: Bernad Ogero | C76: 499860 | D76: 100 | J76: 100
A77: 45010 | B77: Nyamari Gekonde | C77: 499861 | D77: 500 | I77: 500
A78: 45010 | B78: Mary Oswald | C78: 499862 | D78: 350 | I78: 350
A79: 45010 | B79: Zainab Israel | C79: 499863 | D79: 500 | E79: 430 | I79: 70
A80: 45010 | B80: Kahawa Sukari | C80: 499864 | D80: 520 | I80: 520
A81: TOTAL | D81: =SUM(D4:D80) -> 138410 | E81: =SUM(E4:E80) -> 84488 | F81: =SUM(F4:F80) -> 5470 | G81: =SUM(G4:G80) -> 1280 | H81: =SUM(H4:H80) -> 24850 | I81: =SUM(I4:I80) -> 15572 | J81: =SUM(J4:J80) -> 900 | K81: =SUM(K4:K80) -> 550 | ... R81: =SUM(R4:R80) -> 800 | S81: =SUM(E81:R81) -> 138410
D83: =D81-S81 -> 0
B84: SUMMARY
B85: TRUST FUNDS
B86: TITHE | C86: =E81 -> 84488
B87: COMBINED OFFFERING 50% | C87: =F81/2 -> 2735
B88: CAMP MEETING OFFERING | C88: =G81 -> 1280
B89: THANKS GIVING 50% | C89: =J81/2 -> 450
B90: EVANGELISM FIELD | C90: =K81 -> 550
B91: STATION DEV FUND | C91: =Q81 -> 0
B92: TOTAL | C92: =SUM(C86:C91) -> 89503
B94: LOCAL CHURCH FUNDS
B95: COMBINED OFFFERING 50% | C95: =F81/2 -> 2735
B96: CAMP MEETING EXPENSE | C96: 0
B97: THANKS GIVING 50% | C97: =J81/2 -> 450
B98: EVANGELISM -LOCAL | C98: =L81 -> 500
B99: Building/Plot | C99: =H81 -> 24850
B100: Chairs | C100: =M81 -> 4000
B101: Lunch | C101: =R81 -> 800
B102: LCB | C102: =I81 -> 15572
B103: AMO, ETC | C103: 0
...

Sheet SABBATH 1
A2: No | B2: CONTRIBUTOR NAME | C2: RECEIPT NUMBER | D2: TOTAL | E2: TITHE | F2: COMBINED OFFERINGS | G2: CAMP MEETING OFFERINGS | H2: CHURCH BUILDING FUND | I2: LOCAL CHURCH BUDGET (LCB) | J2: THANKS GIVING | K2: PATHFINDER REG
A3: 1 | B3: WESLEY MATOKE | C3: 84169 | D3: 200 | H3: 200 | L3: =SUM(E3:K3)-D3 -> 0
A4: 2 | B4: SAMUEL KERAUNI | C4: 84170 | D4: 500 | H4: 500 | L4: =SUM(E4:K4)-D4 -> 0
A5: 3 | B5: ELVINA BOSIBORI | C5: 84171 | D5: 100 | E5: 100 | L5: =SUM(E5:K5)-D5 -> 0
A6: 4 | B6: WYCLIFF ONSANGO | C6: 84172 | D6: 100 | E6: 100 | L6: =SUM(E6:K6)-D6 -> 0
A7: 5 | B7: EMILY MOGAKA | C7: 84173 | D7: 100 | H7: 100 | L7: =SUM(E7:K7)-D7 -> 0
A8: 6 | B8: MARY KEMUNTO | C8: 84174 | D8: 50 | F8: 25 | G8: 25 | L8: =SUM(E8:K8)-D8 -> 0
A9: 7 | B9: ELIAZAR ONGARA | C9: 84175 | D9: 500 | E9: 500 | L9: =SUM(E9:K9)-D9 -> 0
A10: 8 | B10: ESTHER MBONE | C10: 84176 | D10: 200 | H10: 200 | L10: =SUM(E10:K10)-D10 -> 0
A11: 9 | B11: VERONICAH KIMANI | C11: 84177 | D11: 200 | E11: 200 | L11: =SUM(E11:K11)-D11 -> 0
A12: 10 | B12: FAITH KERUBO | C12: 84178 | D12: 200 | H12: 200 | L12: =SUM(E12:K12)-D12 -> 0
A13: 11 | B13: JULIET ORURU | C13: 84179 | D13: 200 | F13: 200 | L13: =SUM(E13:K13)-D13 -> 0
A14: 12 | B14: LAVINA ALELA | C14: 84180 | D14: 200 | E14: 100 | F14: 50 | G14: 50 | L14: =SUM(E14:K14)-D14 -> 0
A15: 13 | B15: MARTHA BITENGO | C15: 84181 | D15: 50 | E15: 50 | L15: =SUM(E15:K15)-D15 -> 0
A16: 14 | B16: ELSA BISIERI OUKO | C16: 84182 | D16: 50 | F16: 50 | L16: =SUM(E16:K16)-D16 -> 0
A17: 15 | B17: REBECCA OGUTU | C17: 84183 | D17: 50 | I17: 50 | L17: =SUM(E17:K17)-D17 -> 0
A18: 16 | B18: ALBERT MAINA | C18: 84184 | D18: 4000 | E18: 4000 | L18: =SUM(E18:K18)-D18 -> 0
A19: 17 | B19: MANYALA JOHN | C19: 84185 | D19: 300 | E19: 100 | H19: 200 | L19: =SUM(E19:K19)-D19 -> 0
A20: 18 | B20: MILKA NYANJAMA | C20: 84186 | D20: 100 | E20: 100 | L20: =SUM(E20:K20)-D20 -> 0
A21: 19 | B21: VALLENCY JUSTICE | C21: 84187 | D21: 100 | E21: 50 | H21: 50 | L21: =SUM(E21:K21)-D21 -> 0
A22: 20 | B22: TIMOTHY OMARE | C22: 84188 | D22: 200 | F22: 100 | I22: 100 | L22: =SUM(E22:K22)-D22 -> 0
A23: 21 | B23: JOHNES JUMA | C23: 84189 | D23: 100 | F23: 100 | L23: =SUM(E23:K23)-D23 -> 0
A24: 22 | B24: JOSEPHINE NYAKOE | C24: 84190 | D24: 1000 | H24: 1000 | L24: =SUM(E24:K24)-D24 -> 0
A25: 23 | B25: DANIEL NJOROGE | C25: 84191 | D25: 50 | H25: 50 | L25: =SUM(E25:K25)-D25 -> 0
A26: 24 | B26: ELIJAH PAPAI | C26: 84192 | D26: 500 | H26: 500 | L26: =SUM(E26:K26)-D26 -> 0
A27: 25 | B27: MAXWEL ODHIAMBO | C27: 84193 | D27: 1000 | H27: 1000 | L27: =SUM(E27:K27)-D27 -> 0
A28: 26 | B28: WILFRED NYAOSI | C28: 84194 | D28: 150 | E28: 150 | L28: =SUM(E28:K28)-D28 -> 0
A29: 27 | B29: BRIAN OMENYI | C29: 84195 | D29: 500 | I29: 500 | L29: =SUM(E29:K29)-D29 -> 0
A30: 28 | B30: ERICK OMOSA | C30: 84196 | D30: 1000 | F30: 1000 | L30: =SUM(E30:K30)-D30 -> 0
A31: 29 | B31: JOHN MOMANYI | C31: 84197 | D31: 2000 | H31: 2000 | L31: =SUM(E31:K31)-D31 -> 0
A32: 30 | B32: ELDER OUMA'S FAMILY | C32: 84198 | D32: 400 | G32: 200 | I32: 200 | L32: =SUM(E32:K32)-D32 -> 0
A33: 31 | B33: OTISO MOSES | C33: 84199 | D33: 50 | E33: 15 | F33: 15 | G33: 10 | H33: 10 | L33: =SUM(E33:K33)-D33 -> 0
A34: 32 | B34: NANCY OBARE | C34: 84200 | D34: 7026 | E34: 7026 | L34: =SUM(E34:K34)-D34 -> 0
A35: 33 | B35: ELEN KIMANI | C35: 262201 | D35: 2265 | E35: 2265 | L35: =SUM(E35:K35)-D35 -> 0
A36: 34 | B36: JESSA ADHIAMBO | C36: 262202 | D36: 100 | E36: 100 | L36: =SUM(E36:K36)-D36 -> 0
A37: 35 | B37: SAMUEL OGEMBO | C37: 262203 | D37: 100 | I37: 100 | L37: =SUM(E37:K37)-D37 -> 0
A38: 36 | B38: CLIFFORD SIOCHA | C38: 262204 | D38: 1000 | I38: 1000 | L38: =SUM(E38:K38)-D38 -> 0
A39: 37 | B39: FELIX MUSIU | C39: 262205 | D39: 100 | I39: 100 | L39: =SUM(E39:K39)-D39 -> 0
A40: 38 | B40: CHERYL ORIOKI | C40: 262206 | D40: 5000 | E40: 5000 | L40: =SUM(E40:K40)-D40 -> 0
A41: 39 | B41: BENEDICT ODHIAMBO | C41: 262207 | D41: 500 | E41: 500 | L41: =SUM(E41:K41)-D41 -> 0
A42: 40 | B42: MIKE MACKEY OUMA | C42: 262208 | D42: 50 | E42: 50 | L42: =SUM(E42:K42)-D42 -> 0
A43: 41 | B43: ELDER MWATHI | C43: 262209 | D43: 300 | H43: 300 | L43: =SUM(E43:K43)-D43 -> 0
A44: 42 | B44: LEVINAH WYCKLIFFE | C44: 262210 | D44: 100 | E44: 100 | L44: =SUM(E44:K44)-D44 -> 0
A45: 43 | B45: CHRISTINE KAWIRA | C45: 262211 | D45: 100 | E45: 100 | L45: =SUM(E45:K45)-D45 -> 0
A46: 44 | B46: LYTE GLARDEN | C46: 262212 | D46: 100 | E46: 100 | L46: =SUM(E46:K46)-D46 -> 0
A47: 45 | B47: WANJARA LYDIA | C47: 262213 | D47: 100 | E47: 100 | L47: =SUM(E47:K47)-D47 -> 0
A48: 46 | B48: DAVID KIPLANGAT | C48: 262214 | D48: 1000 | J48: 1000 | L48: =SUM(E48:K48)-D48 -> 0
A49: 47 | B49: BRAVINN ENOCK | C49: 262215 | D49: 100 | E49: 100 | L49: =SUM(E49:K49)-D49 -> 0
A50: 48 | B50: CALLEN GESARE | C50: 262216 | D50: 200 | F50: 100 | I50: 100 | L50: =SUM(E50:K50)-D50 -> 0
A51: 49 | B51: OLIVENT ANYANGO | C51: 262217 | D51: 100 | E51: 100 | L51: =SUM(E51:K51)-D51 -> 0
A52: 50 | B52: CECENA JAINE | C52: 262218 | D52: 100 | E52: 50 | I52: 50 | L52: =SUM(E52:K52)-D52 -> 0
A53: 51 | B53: OKINYI ODHIAMBO | C53: 262219 | D53: 50 | F53: 50 | L53: =SUM(E53:K53)-D53 -> 0
A54: 52 | B54: OCHIENG VICTOR | C54: 262220 | D54: 1500 | J54: 1500 | L54: =SUM(E54:K54)-D54 -> 0
A55: 53 | B55: WISSON MARANGU | C55: 262221 | D55: 1000 | E55: 1000 | L55: =SUM(E55:K55)-D55 -> 0
A56: 54 | B56: WILLIAM DULO | C56: 262222 | D56: 50 | E56: 50 | L56: =SUM(E56:K56)-D56 -> 0
A57: 55 | B57: VIOLET JUMA | C57: 262223 | D57: 100 | F57: 100 | L57: =SUM(E57:K57)-D57 -> 0
A58: 56 | B58: VIOLENE ANDAI | C58: 262224 | D58: 100 | F58: 100 | L58: =SUM(E58:K58)-D58 -> 0
A59: 57 | B59: SILAS MANYASA | C59: 262225 | D59: 150 | F59: 150 | L59: =SUM(E59:K59)-D59 -> 0
A60: 58 | B60: SHAFNER NYANGWONO | C60: 262226 | D60: 50 | J60: 50 | L60: =SUM(E60:K60)-D60 -> 0
A61: 59 | B61: SAMUEL WAITHAKA | C61: 262227 | D61: 100 | J61: 100 | L61: =SUM(E61:K61)-D61 -> 0
A62: 60 | B62: RUTH MOMANYI | C62: 262228 | D62: 2605 | E62: 2605 | L62: =SUM(E62:K62)-D62 -> 0
A63: 61 | B63: MAUREEN NYAMAMBA | C63: 262229 | D63: 500 | F63: 500 | L63: =SUM(E63:K63)-D63 -> 0
A64: 62 | B64: MARTHA OWANDE | C64: 262230 | D64: 50 | E64: 50 | L64: =SUM(E64:K64)-D64 -> 0
A65: 63 | B65: MARK NDEGWA | C65: 262231 | D65: 50 | F65: 50 | L65: =SUM(E65:K65)-D65 -> 0
A66: 64 | B66: ROBBINSON MOKORA | C66: 262232 | D66: 50 | E66: 50 | L66: =SUM(E66:K66)-D66 -> 0
A67: 65 | B67: PHYLIS KEFA | C67: 262233 | D67: 2692 | E67: 2692 | L67: =SUM(E67:K67)-D67 -> 0
A68: 66 | B68: PETER KAIRU | C68: 262234 | D68: 300 | E68: 300 | L68: =SUM(E68:K68)-D68 -> 0
A69: 67 | B69: OTIENO VIVIAN | C69: 262235 | D69: 4000 | E69: 4000 | L69: =SUM(E69:K69)-D69 -> 0
A70: 68 | B70: NAOMI NJUGUNA | C70: 262236 | D70: 200 | F70: 200 | L70: =SUM(E70:K70)-D70 -> 0
A71: 69 | B71: MIRITA TABITHA | C71: 262237 | D71: 2400 | E71: 2400 | L71: =SUM(E71:K71)-D71 -> 0
A72: 70 | B72: MILDRED SHIKUKU | C72: 262238 | D72: 300 | E72: 300 | L72: =SUM(E72:K72)-D72 -> 0
A73: 71 | B73: MERYL ODERA | C73: 262239 | D73: 200 | E73: 200 | L73: =SUM(E73:K73)-D73 -> 0
A74: 72 | B74: MERCY GUDA | C74: 262240 | D74: 100 | F74: 100 | L74: =SUM(E74:K74)-D74 -> 0
A75: 73 | B75: MAYLENE ATUTI | C75: 262241 | D75: 1200 | E75: 1200 | L75: =SUM(E75:K75)-D75 -> 0
A76: 74 | B76: RODA NGWATO | C76: 262242 | D76: 50 | F76: 50 | L76: =SUM(E76:K76)-D76 -> 0
A77: 75 | B77: MERCY AKUONGO | C77: 262243 | D77: 100 | F77: 100 | L77: =SUM(E77:K77)-D77 -> 0
A78: 76 | B78: LYDIA MOTARI | C78: 262244 | D78: 70 | E78: 70 | L78: =SUM(E78:K78)-D78 -> 0
A79: 77 | B79: LYDIA | C79: 262245 | D79: 180 | E79: 180 | L79: =SUM(E79:K79)-D79 -> 0
A80: 78 | B80: LEON OCHIENG | C80: 262246 | D80: 40 | E80: 40 | L80: =SUM(E80:K80)-D80 -> 0
A81: 79 | B81: LAVENDA OPATO | C81: 262247 | D81: 50 | F81: 50 | L81: =SUM(E81:K81)-D81 -> 0
A82: 80 | B82: JULIET NDUNGU | C82: 262248 | D82: 200 | F82: 200 | L82: =SUM(E82:K82)-D82 -> 0
A83: 81 | B83: GROUP 41 | C83: 83309 | D83: 3825 | H83: 3825 | L83: =SUM(E83:K83)-D83 -> 0
A84: 82 | B84: DISMUSS NDUKO - 32 | C84: 83310 | D84: 2000 | H84: 2000 | L84: =SUM(E84:K84)-D84 -> 0
A85: 83 | B85: BILHA KWAMBOKA - 32 | C85: 83311 | D85: 600 | H85: 600 | L85: =SUM(E85:K85)-D85 -> 0
A86: 84 | B86: GEKOMBE RONALD - 9 | C86: 83312 | D86: 500 | H86: 500 | L86: =SUM(E86:K86)-D86 -> 0
A87: 85 | B87: SUSAN MOMANYI - 22 | C87: 83313 | D87: 500 | H87: 500 | L87: =SUM(E87:K87)-D87 -> 0
A88: 86 | B88: DELLEYS NYABOKE | C88: 83314 | D88: 500 | E88: 200 | F88: 100 | G88: 100 | I88: 100 | L88: =SUM(E88:K88)-D88 -> 0
A89: 87 | B89: ALLAN MOTURO - 40 | C89: 83315 | D89: 500 | H89: 500 | L89: =SUM(E89:K89)-D89 -> 0
A90: 88 | B90: BRAVIN ENOCK | C90: 83316 | D90: 200 | K90: 200 | L90: =SUM(E90:K90)-D90 -> 0
A91: 89 | B91: SARAH ABAYA | C91: 83317 | D91: 10100 | E91: 10000 | H91: 100 | L91: =SUM(E91:K91)-D91 -> 0
A92: 90 | B92: EVERYLINE ARIKA | C92: 83318 | D92: 100 | E92: 100 | L92: =SUM(E92:K92)-D92 -> 0
A93: 91 | B93: ELD REUBEN OGUTU | C93: 83319 | D93: 50 | F93: 30 | I93: 20 | L93: =SUM(E93:K93)-D93 -> 0
A94: 92 | B94: EMMACULATE OCHIENG MIRERI | C94: 83320 | D94: 100 | E94: 50 | H94: 50 | L94: =SUM(E94:K94)-D94 -> 0
A95: 93 | B95: FLORENCE BOCHABERI OMBORI | C95: 83321 | D95: 100 | F95: 100 | L95: =SUM(E95:K95)-D95 -> 0
A96: 94 | B96: AMAYA OROTO | C96: 83322 | D96: 50 | H96: 50 | L96: =SUM(E96:K96)-D96 -> 0
A97: 95 | B97: FRED SIMON MWATHI | C97: 83323 | D97: 200 | E97: 200 | L97: =SUM(E97:K97)-D97 -> 0
A98: 96 | B98: GLADYS MOGOI | C98: 83324 | D98: 200 | H98: 200 | L98: =SUM(E98:K98)-D98 -> 0
A99: 97 | B99: DANIEL NJOROGE | C99: 83325 | D99: 200 | E99: 200 | L99: =SUM(E99:K99)-D99 -> 0
A100: 98 | B100: CAROLINE JEMUTAI - 19 | C100: 83326 | D100: 1000 | H100: 1000 | L100: =SUM(E100:K100)-D100 -> 0
A101: 99 | B101: KENNEDY AKETCH - 10 | C101: 83327 | D101: 1000 | E101: 1000 | L101: =SUM(E101:K101)-D101 -> 0
...

Sheet SABBATH 2
A1: TREASURERS CASH STATEMENT 14 FEB 2026
A2: No | B2: CONTRIBUTOR NAME | C2: RECEIPT NUMBER | D2: TOTAL AMOUNT | E2: TITHE | F2: COMBINED OFFERINGS | G2: CAMP MEETING OFFERINGS | H2: CHURCH BUILDING FUND | I2: LOCAL CHURCH BUDGET (LCB) | J2: THANKS GIVING | K2: SABBATH SCHOOL | L2: EVANGELISM LOCAL
A3: 1 | B3: DAMARIS | C3: 262249 | D3: 100 | F3: 100
A4: 2 | B4: EMMACULATE OCHIENG | C4: 262250 | D4: 100 | E4: 30 | F4: 30 | H4: 40
A5: 3 | B5: EVERLYNE ARIKA | C5: 262251 | D5: 100 | E5: 50 | I5: 50
A6: 4 | B6: WINNNIE REBECCA | C6: 262252 | D6: 200 | E6: 100 | F6: 50 | G6: 50
A7: 5 | B7: ROGERS MACHOKA | C7: 262253 | D7: 1000 | E7: 500 | F7: 500
A8: 6 | B8: ETHAN AND ADRIEL | C8: 262254 | D8: 100 | F8: 100
A9: 7 | B9: GRACE OGOLA | C9: 262255 | D9: 300 | F9: 100 | I9: 200
A10: 8 | B10: SHERYL M | C10: 262256 | D10: 100 | F10: 100
A11: 9 | B11: SHANTELLE MUMBO | C11: 262257 | D11: 100 | F11: 100
A12: 10 | B12: LENCER OKWAH | C12: 262258 | D12: 200 | I12: 200
A13: 11 | B13: ROSELYNE AOKO | C13: 262259 | D13: 50 | F13: 50
A14: 12 | B14: JANICE CHAYA | C14: 262260 | D14: 50 | E14: 20 | F14: 20 | G14: 10
A15: 13 | B15: KENNEDY AKECH | C15: 262261 | D15: 100 | E15: 100
A16: 14 | B16: WANJARA LYDIA | C16: 262262 | D16: 100 | E16: 100
A17: 15 | B17: BEAUTTAH NYAUMA | C17: 262263 | D17: 200 | I17: 200
A18: 16 | B18: MILKA NYANJAMA | C18: 262264 | D18: 50 | E18: 50
A19: 17 | B19: ADHER BITUTU | C19: 262265 | D19: 200 | F19: 100 | G19: 50 | I19: 50
A20: 18 | B20: LAVINA ALELA | C20: 262266 | D20: 150 | E20: 100 | G20: 30 | H20: 20
A21: 19 | B21: ELD. JAMES MIRERI | C21: 262267 | D21: 500 | E21: 100 | F21: 100 | G21: 100 | H21: 200
A22: 20 | B22: NANCY OSORO | C22: 262268 | D22: 200 | E22: 200
A23: 21 | B23: NYABUTO OONGE | C23: 262269 | D23: 1300 | G23: 300 | I23: 1000
A24: 22 | B24: BRIAN OMENYI | C24: 262270 | D24: 38500 | E24: 38500
A25: 23 | B25: JUDITH ODOYO | C25: 262271 | D25: 400 | E25: 300 | H25: 100
A26: 24 | B26: CHERYL ORIOKI | C26: 262272 | D26: 200 | I26: 200
A27: 25 | B27: JEMIMAH NYOLOO | C27: 262273 | D27: 100 | H27: 100
A28: 26 | B28: SAMSON NYARERU | C28: 262274 | D28: 100 | F28: 50 | G28: 50
A29: 27 | B29: JOHN MOMANYI | C29: 262275 | D29: 1000 | H29: 1000
A30: 28 | B30: ERICK OMOSA | C30: 262276 | D30: 1000 | F30: 1000
A31: 29 | B31: JANE NYAMONGO | C31: 262277 | D31: 300 | I31: 300
A32: 30 | B32: GLADYS MOGOI | C32: 262278 | D32: 100 | E32: 100
A33: 31 | B33: NAOMI KWAMBOKA | C33: 262279 | D33: 500 | E33: 500
A34: 32 | B34: LINET MAGETO | C34: 262280 | D34: 1000 | E34: 700 | I34: 300
A35: 33 | B35: LAVINAH WYCLIFFE | C35: 262281 | D35: 200 | E35: 200
A36: 34 | B36: COLLINS MBOYA | C36: 262282 | D36: 50 | E36: 50
A37: 35 | B37: LIAM OROTO | C37: 262283 | D37: 100 | E37: 100
A38: 36 | B38: LEOMA LIVA | C38: 262284 | D38: 50 | I38: 50
A39: 37 | B39: KERINA OKUMU | C39: 262285 | D39: 100 | F39: 100
A40: 38 | B40: MILCAH MOKAMBA | C40: 262286 | D40: 30 | K40: 30
A41: 39 | B41: JANET KARITHI | C41: 262287 | D41: 50 | F41: 50
A42: 40 | B42: ELD JAMES MIRERI | C42: 262288 | D42: 500 | F42: 500
A43: 41 | B43: JANET MORANGA | C43: 262289 | D43: 100 | F43: 100
A44: 42 | B44: LANCER GANDA | C44: 262290 | D44: 50 | E44: 50
A45: 43 | B45: KIPTOO STEPHEN | C45: 262291 | D45: 20 | E45: 20
A46: 44 | B46: LILIAN MOGUTO | C46: 262292 | D46: 1500 | E46: 1500
A47: 45 | B47: JOSEPH WANJOHI | C47: 262293 | D47: 30 | K47: 30
A48: 46 | B48: JOHN ONGWESA | C48: 262294 | D48: 100 | K48: 100
A49: 47 | B49: STANFORD OUMA | C49: 262295 | D49: 100 | E49: 100
A50: 48 | B50: STEPHEN OGANDA | C50: 262296 | D50: 40 | E50: 40
A51: 49 | B51: SYDNEY NDLOVU | C51: 262297 | D51: 2228 | E51: 1528 | I51: 700
A52: 50 | B52: TOM BIRUNDU | C52: 262298 | D52: 200 | I52: 200
A53: 51 | B53: VILET MOGATA | C53: 262299 | D53: 100 | E53: 100
A54: 52 | B54: VIOLA ABUGA | C54: 262300 | D54: 50 | E54: 50
A55: 53 | B55: VIVIAN OKUMU | C55: 262301 | D55: 100 | E55: 100
A56: 54 | B56: WILKISTER MAGARA | C56: 262302 | D56: 1000 | F56: 1000
A57: 55 | B57: WINNIE OWITI | C57: 262303 | D57: 50 | F57: 50
A58: 56 | B58: LYDIA WAMAYI | C58: 262304 | D58: 150 | F58: 150
A59: 57 | B59: MANDELA AREDHA | C59: 262305 | D59: 500 | E59: 500
A60: 58 | B60: MARK NDEGWA | C60: 262306 | D60: 50 | F60: 50
A61: 59 | B61: MARY GITURU | C61: 262307 | D61: 5000 | E61: 5000
A62: 60 | B62: MAUREEN NABISWA | C62: 262308 | D62: 80 | E62: 80
A63: 61 | B63: MELVIN SIBWOGA | C63: 262309 | D63: 50 | E63: 50
A64: 62 | B64: MWITA JARED | C64: 262310 | D64: 100 | E64: 100
A65: 63 | B65: NORAH NYAGWOKA | C65: 262311 | D65: 1000 | E65: 1000
A66: 64 | B66: OCHIENG VICTOR | C66: 262312 | D66: 100 | E66: 100
A67: 65 | B67: PENINAH KERUBO | C67: 262313 | D67: 1000 | E67: 1000
A68: 66 | B68: PURITY JOHN | C68: 262314 | D68: 1530 | E68: 1530
A69: 67 | B69: RISPA OENGA | C69: 262315 | D69: 100 | F69: 100
A70: 68 | B70: SAMUEL WAITHAKA | C70: 262316 | D70: 100 | J70: 100
A71: 69 | B71: SETH MUNENE | C71: 262317 | D71: 100 | E71: 100
A72: 70 | B72: SHELINE OYOO | C72: 262318 | D72: 2400 | E72: 2400
A73: 71 | B73: CAROLINE AUMA | C73: 262319 | D73: 1000 | H73: 1000
A74: 72 | B74: DAMARIS OMBATI | C74: 83377 | D74: 100 | F74: 50 | L74: 50
A75: 73 | B75: HYLINE KERUBO | C75: 83378 | D75: 700 | F75: 700
A76: 74 | B76: WINNIE MCHANA | C76: 83379 | D76: 100 | E76: 100
A77: 75 | B77: SHARON ACHIENG NYAMBURI | C77: 83380 | D77: 500 | F77: 500
A78: 76 | B78: JOHNES JUMA | C78: 83381 | D78: 100 | E78: 100
A79: 77 | B79: JOHNREY OMBATI | C79: 83382 | D79: 25 | F79: 25
A80: 78 | B80: WINNIE KEMUNTO | C80: 83383 | D80: 100 | L80: 100
A81: 79 | B81: FAITH OSORO | C81: 83384 | D81: 720 | E81: 360 | F81: 360
A82: 80 | B82: JOSEPHINE ONTITA | C82: 83385 | D82: 200 | F82: 100 | L82: 100
A83: 81 | B83: ELD DANIEL OMBATI | C83: 83386 | D83: 200 | E83: 100 | L83: 100
A84: 82 | B84: OTISO MOSES | C84: 83387 | D84: 200 | E84: 50 | F84: 50 | G84: 50 | H84: 50
A85: 83 | B85: DOROTHY NYANCHERA | C85: 83388 | D85: 100 | E85: 100
A86: 84 | B86: BILHA KWAMBOKA | C86: 83389 | D86: 50 | L86: 50
A87: 85 | B87: HELLEN KEMUNTO | C87: 83390 | D87: 100 | E87: 100
A88: 86 | B88: SUSAN OMETE | C88: 83391 | D88: 300 | F88: 100 | I88: 200
A89: 87 | B89: FRED CARSON O | C89: 83392 | D89: 50 | E89: 50
A90: 88 | B90: JAMES MICH | C90: 83393 | D90: 30 | E90: 30
A91: 89 | B91: VINCENT NYAGAKA | C91: 83394 | D91: 800 | E91: 750 | L91: 50
A92: 90 | B92: CHRISTINE KAWIRA | C92: 83395 | D92: 100 | E92: 100
A93: 91 | B93: BEATRICE AWUOR | C93: 83396 | D93: 100 | L93: 100
A94: 92 | B94: EDWIN ODHIAMBO | C94: 83397 | D94: 500 | E94: 200 | F94: 200 | L94: 100
A95: 93 | B95: ELD CALVINCE FAMILY | C95: 83398 | D95: 12000 | E95: 10000 | I95: 2000
A96: 94 | B96: FRANCIS DEDE | C96: 83399 | D96: 50 | E96: 50
A97: 95 | B97: LORINE DEDE | C97: 83400 | D97: 50 | E97: 50
A98: 96 | B98: SAMUEL ABAYA | C98: 322001 | D98: 1000 | F98: 300 | H98: 500 | I98: 200
A99: 97 | B99: DISMUS NDUKO | C99: 322002 | D99: 1000 | E99: 500 | F99: 500
A100: 98 | B100: JOSEPHINE AYIENDA | C100: 322003 | D100: 500 | E100: 500
...

Sheet SABBAATH 3
A1: TREASURERS CASH STATEMENT, 21 FEB 2026
B2: CONTRIBUTOR NAME | C2: RECEIPT NUMBER | D2: TOTAL AMOUNT | E2: TITHE | F2: COMBINED OFFERINGS | G2: CAMP MEETING OFFERINGS | H2: CHURCH BUILDING FUND | I2: LOCAL CHURCH BUDGET (LCB) | J2: THANKS | K2: SABBATH SCHOOL
A3: 1 | B3: BILL OROTO | C3: 262320 | D3: 500 | I3: 500
A4: 2 | B4: LYDIAH MOTARI | C4: 262321 | D4: 100 | E4: 100
A5: 3 | B5: CHRSTINE KAWIRA | C5: 262322 | D5: 100 | F5: 100
A6: 4 | B6: HELLEN ABUGA | C6: 262323 | D6: 100 | I6: 100
A7: 5 | B7: JOHNES JUMA | C7: 262324 | D7: 50 | F7: 50
A8: 6 | B8: LAVINA ALELA | C8: 262325 | D8: 100 | E8: 50 | F8: 10 | G8: 20 | H8: 20
A9: 7 | B9: LIAM OROTO | C9: 262326 | D9: 100 | F9: 100
A10: 8 | B10: NAOMI KWAMBOKA | C10: 262327 | D10: 200 | E10: 200
A11: 9 | B11: DAMARIS OMBATI | C11: 262328 | D11: 100 | F11: 50 | I11: 50
A12: 10 | B12: NZIOKA SAMUEL | C12: 262329 | D12: 1000 | E12: 500 | F12: 500
A13: 11 | B13: VIOLET JUMA | C13: 262330 | D13: 8750 | E13: 8750
A14: 12 | B14: MARTHA BITENGO | C14: 262331 | D14: 100 | F14: 80 | I14: 20
A15: 13 | B15: EMMACULATE OCHIENG | C15: 262332 | D15: 50 | E15: 30 | G15: 20
A16: 14 | B16: CHRISTINE MOMANYI | C16: 262333 | D16: 50 | F16: 50
A17: 15 | B17: JOYCE MONGINA | C17: 262334 | D17: 100 | E17: 100
A18: 16 | B18: FLORENCE BOCHABERI | C18: 262335 | D18: 1000 | E18: 1000
A19: 17 | B19: BEAVON OSUMO | C19: 262336 | D19: 100 | E19: 100
A20: 18 | B20: BRIAN OSORO | C20: 262337 | D20: 200 | J20: 200
A21: 19 | B21: DAVIES JAMES | C21: 262338 | D21: 100 | E21: 100
A22: 20 | B22: BEAVON RORI | C22: 262339 | D22: 100 | E22: 100
A23: 21 | B23: CHARLES NDUNGU | C23: 262340 | D23: 85 | E23: 85
A24: 22 | B24: EDWIN EKIRAPA | C24: 262341 | D24: 200 | I24: 200
A25: 23 | B25: EVERLYNE OKEYO | C25: 262342 | D25: 50 | E25: 50
A26: 24 | B26: DIVINAH NYAKEYO | C26: 262343 | D26: 80 | E26: 80
A27: 25 | B27: ELIZAR ATULA | C27: 262344 | D27: 50 | E27: 50
A28: 26 | B28: FUN MISIANI | C28: 262345 | D28: 100 | E28: 100
A29: 27 | B29: HELLEN NAIMADU | C29: 262346 | D29: 5000 | J29: 5000
A30: 28 | B30: FREDRICK NYATEMU | C30: 262347 | D30: 100 | E30: 100
A31: 29 | B31: HILDER OUDU | C31: 262348 | D31: 200 | E31: 200
A32: 30 | B32: LEVINE OTIENO | C32: 262349 | D32: 50 | E32: 50
A33: 31 | B33: FIDEL OLUOCH | C33: 262350 | D33: 20 | E33: 20
A34: 32 | B34: JANET KARITHI | C34: 262351 | D34: 50 | E34: 50
A35: 33 | B35: GOULDAH MBYUTA | C35: 262352 | D35: 2500 | E35: 2300 | J35: 200
A36: 34 | B36: ELEN KIMANI | C36: 262353 | D36: 440 | E36: 440
A37: 35 | B37: CAROLINE K | C37: 262354 | D37: 20 | E37: 20
A38: 36 | B38: EVANS NYAKWARA | C38: 262355 | D38: 100 | I38: 100
A39: 37 | B39: DAVIS MIRONGA | C39: 262356 | D39: 1562 | E39: 1562
A40: 38 | B40: BRENDA AUMA | C40: 262357 | D40: 200 | F40: 200
A41: 39 | B41: VINCENT ONSEMBE | C41: 262358 | D41: 100 | E41: 100
A42: 40 | B42: SILAS MANYASA | C42: 262359 | D42: 700 | E42: 700
A43: 41 | B43: SHADRACK ODHIAMBO | C43: 262360 | D43: 500 | E43: 500
A44: 42 | B44: ANTONINA AWUOR | C44: 262361 | D44: 200 | E44: 200
A45: 43 | B45: ANTONY OBWANGI | C45: 262362 | D45: 50 | E45: 50
A46: 44 | B46: IRENE MIRIOBA | C46: 262363 | D46: 50 | E46: 50
A47: 45 | B47: GEOFFREY OTIENO | C47: 262364 | D47: 50 | E47: 50
A48: 46 | B48: GIFTMACVANE MOMANYI | C48: 262365 | D48: 2515 | E48: 1515 | F48: 500 | H48: 500
A49: 47 | B49: SYLVIAH NYAKUNDI | C49: 262366 | D49: 100 | I49: 100
A50: 48 | B50: SYDNEY NDLOVU | C50: 262367 | D50: 7800 | E50: 3900 | F50: 3900
A51: 49 | B51: SETH MUNENE | C51: 262368 | D51: 200 | E51: 200
A52: 50 | B52: ETHAN & ADRIEL MOMANYI | C52: 322049 | D52: 100 | F52: 100
A53: 51 | B53: JOSEPHINE ONTITA | C53: 322050 | D53: 100 | F53: 100
A54: 52 | B54: LEONARD JOHNSON | C54: 322051 | D54: 100 | F54: 100
A55: 53 | B55: LYDIA MOTARI | C55: 322052 | D55: 200 | E55: 200
A56: 54 | B56: JAMES MICH | C56: 322053 | D56: 80 | E56: 80
A57: 55 | B57: DANIEL SAGWE | C57: 322054 | D57: 200 | I57: 200
A58: 56 | B58: GRACE KANYI | C58: 322055 | D58: 50 | I58: 50
A59: 57 | B59: VINIC ONDIEKI | C59: 322056 | D59: 6000 | E59: 6000
A60: 58 | B60: CANNON ODHIAMBO | C60: 322057 | D60: 100 | F60: 100
A61: 59 | B61: AMAYA OROTO | C61: 322058 | D61: 100 | F61: 100
A62: 60 | B62: DAMACLINE GESARE | C62: 322059 | D62: 50 | F62: 50
A63: 61 | B63: LEVINAH WYCLIFFE | C63: 322060 | D63: 200 | E63: 200
A64: 62 | B64: ADONIJAH OMETE | C64: 322061 | D64: 50 | H64: 50
A65: 63 | B65: WINNIE MCHANA | C65: 322062 | D65: 100 | E65: 100
A66: 64 | B66: ADHER BITUTU | C66: 322063 | D66: 200 | F66: 100 | G66: 50 | I66: 50
A67: 65 | B67: BERYL ADHIAMBO OTIENO | C67: 322064 | D67: 100 | E67: 100
A68: 66 | B68: FRED SIMON MWATHI | C68: 322065 | D68: 200 | E68: 200
A69: 67 | B69: OTISO MOSES | C69: 322066 | D69: 50 | E69: 15 | F69: 15 | G69: 10 | H69: 10
A70: 68 | B70: BILIAH KWAMBOKA | C70: 322067 | D70: 50 | I70: 50
A71: 69 | B71: JESCA ADHIAMBO OCHIENG | C71: 322068 | D71: 50 | E71: 50
A72: 70 | B72: MAUREEN NGOCHI | C72: 322069 | D72: 1000 | E72: 500 | F72: 500
A73: 71 | B73: ATAI FAMILY | C73: 322070 | D73: 300 | I73: 300
A74: 72 | B74: SAMUEL OGEMBO | C74: 322071 | D74: 50 | I74: 50
A75: 73 | B75: BRIAN OMENYI | C75: 322072 | D75: 10000 | I75: 10000
A76: 74 | B76: SAMSON NYARERU | C76: 322073 | D76: 1100 | F76: 50 | G76: 50 | I76: 1000
A77: 75 | B77: JANE NYAMONGO | C77: 322074 | D77: 200 | I77: 200
A78: 76 | B78: STELLAH KERUBO | C78: 322075 | D78: 100 | F78: 100
A79: 77 | B79: GRACE OGOLA | C79: 322076 | D79: 3000 | E79: 3000
A80: 78 | B80: ANNE MOGIRE | C80: 322077 | D80: 4350 | E80: 4350
A81: 79 | B81: NANCY OTIENO | C81: 322078 | D81: 200 | E81: 200
A82: 80 | B82: SUSAN OMETE | C82: 322079 | D82: 500 | E82: 500
A83: 81 | B83: CECILIA WANGUI | C83: 322080 | D83: 240 | E83: 240
A84: 82 | B84: SHELINE OYOO | C84: 322081 | D84: 100 | G84: 50 | I84: 50
A85: 83 | B85: NANCY OBARE | C85: 322082 | D85: 200 | I85: 200
A86: 84 | B86: ELD OUMA AND FAMILY | C86: 322083 | D86: 100 | I86: 100
A87: 85 | B87: LORINE DEDE | C87: 322084 | D87: 100 | H87: 100
A88: 86 | B88: FRANCIS DEDE | C88: 322085 | D88: 100 | H88: 100
A89: 87 | B89: JEMIMA NYOLOO | C89: 322086 | D89: 100 | H89: 100
A90: 88 | B90: EDWIN ODHIAMBO | C90: 322087 | D90: 100 | E90: 100
A91: 89 | B91: FELIX M MUSIU | C91: 322088 | D91: 100 | I91: 100
A92: 90 | B92: MR GILBERT SHIKUKU | C92: 322089 | D92: 150 | I92: 150
A93: 91 | B93: JOHN ONGWESA | C93: 322090 | D93: 100 | I93: 100
A94: 92 | B94: KENNEDY OLENDI | C94: 322091 | D94: 100 | I94: 100
A95: 93 | B95: JOSEPH WANJOHI | C95: 322092 | D95: 30 | K95: 30
A96: 94 | B96: JOSEPH NGWATO | C96: 322093 | D96: 100 | I96: 100
A97: 95 | B97: JOSEPH KIMO | C97: 322094 | D97: 150 | F97: 150
A98: 96 | B98: REBECCA BARASA | C98: 322095 | D98: 50 | E98: 50
A99: 97 | B99: REAL ROBBY | C99: 322096 | D99: 50 | E99: 50
A100: 98 | B100: PENINAH KERUBO | C100: 322097 | D100: 500 | E100: 500
...

Sheet SABBATH 4
A1: TREASURERS CASH STATEMENT, 28 FEB 2026
B2: CONTRIBUTOR NAME | C2: RECEIPT NUMBER | D2: TOTAL AMOUNT | E2: TITHE | F2: COMBINED OFFERINGS | G2: CAMP MEETING OFFERINGS | H2: CHURCH BUILDING FUND | I2: LOCAL CHURCH BUDGET (LCB) | J2: THANKS GIVING | K2: SABBATH SCHOOL
A3: 1 | B3: Dorice Chebet | C3: 262369 | D3: 100 | H3: 100 | L3: =SUM(E3:K3)-D3 -> 0
A4: 2 | B4: Gift Macvanne Momanyi | C4: 262370 | D4: 200 | F4: 200 | L4: =SUM(E4:K4)-D4 -> 0
A5: 3 | B5: Judith Odoyo | C5: 262371 | D5: 200 | E5: 200 | L5: =SUM(E5:K5)-D5 -> 0
A6: 4 | B6: Samwel Abaya | C6: 262372 | D6: 200 | F6: 100 | I6: 100 | L6: =SUM(E6:K6)-D6 -> 0
A7: 5 | B7: Brenda Awino | C7: 262373 | D7: 50 | E7: 50 | L7: =SUM(E7:K7)-D7 -> 0
A8: 6 | B8: Martha Bitengo | C8: 262374 | D8: 50 | F8: 50 | L8: =SUM(E8:K8)-D8 -> 0
A9: 7 | B9: Christine Kawira | C9: 262375 | D9: 100 | F9: 100 | L9: =SUM(E9:K9)-D9 -> 0
A10: 8 | B10: Daniel Njoroge | C10: 262376 | D10: 200 | E10: 200 | L10: =SUM(E10:K10)-D10 -> 0
A11: 9 | B11: Bill Oroto | C11: 262377 | D11: 500 | F11: 500 | L11: =SUM(E11:K11)-D11 -> 0
A12: 10 | B12: Sarah Abaya | C12: 262378 | D12: 10100 | E12: 10000 | I12: 100 | L12: =SUM(E12:K12)-D12 -> 0
A13: 11 | B13: Joy Mellen Faith | C13: 262379 | D13: 50 | F13: 50 | L13: =SUM(E13:K13)-D13 -> 0
A14: 12 | B14: Millicent Atieno | C14: 262380 | D14: 400 | F14: 200 | I14: 200 | L14: =SUM(E14:K14)-D14 -> 0
A15: 13 | B15: SYLIVIA ALWANGA | C15: 262381 | D15: 300 | H15: 300 | L15: =SUM(E15:K15)-D15 -> 0
A16: 14 | B16: CALVINS OUMA -GRP 16 | C16: 262382 | D16: 10000 | H16: 10000 | L16: =SUM(E16:K16)-D16 -> 0
A17: 15 | B17: GRACE WANGARE | C17: 262383 | D17: 50 | I17: 50 | L17: =SUM(E17:K17)-D17 -> 0
A18: 16 | B18: ERIC NYAMAMBA | C18: 262384 | D18: 10500 | E18: 10500 | L18: =SUM(E18:K18)-D18 -> 0
A19: 17 | B19: ELIAZAR ONGARA | C19: 262385 | D19: 500 | E19: 500 | L19: =SUM(E19:K19)-D19 -> 0
A20: 18 | B20: WINNY-GRP 34 | C20: 262386 | D20: 100 | H20: 100 | L20: =SUM(E20:K20)-D20 -> 0
A21: 19 | B21: ADVENTURERS GROUP | C21: 262387 | D21: 2060 | H21: 2060 | L21: =SUM(E21:K21)-D21 -> 0
A22: 20 | B22: SUSAN OMETE | C22: 262388 | D22: 200 | F22: 200 | L22: =SUM(E22:K22)-D22 -> 0
A23: 21 | B23: EDWIN BOGE -GRP 24 | C23: 262389 | D23: 3250 | H23: 3250 | L23: =SUM(E23:K23)-D23 -> 0
A24: 22 | B24: CECILIA WANGUI | C24: 262390 | D24: 200 | E24: 200 | L24: =SUM(E24:K24)-D24 -> 0
A25: 23 | B25: ROBINSON NYARIBO'S FAMILY | C25: 262391 | D25: 23000 | E25: 22000 | I25: 1000 | L25: =SUM(E25:K25)-D25 -> 0
A26: 24 | B26: OMOSA'S FAMILY | C26: 262392 | D26: 3000 | F26: 2000 | J26: 1000 | L26: =SUM(E26:K26)-D26 -> 0
A27: 25 | B27: MOSETI'S FAMILY | C27: 262393 | D27: 34100 | E27: 34100 | L27: =SUM(E27:K27)-D27 -> 0
A28: 26 | B28: HILDERGAUD KAMANDA | C28: 262394 | D28: 700 | I28: 500 | J28: 200 | L28: =SUM(E28:K28)-D28 -> 0
A29: 27 | B29: ELIAZAR ATULA | C29: 262395 | D29: 150 | E29: 150 | L29: =SUM(E29:K29)-D29 -> 0
A30: 28 | B30: CLEOPAS OMETE | C30: 262396 | D30: 1000 | E30: 1000 | L30: =SUM(E30:K30)-D30 -> 0
A31: 29 | B31: CLIFFORD SIOCHA | C31: 262397 | D31: 500 | I31: 500 | L31: =SUM(E31:K31)-D31 -> 0
A32: 30 | B32: CYNTHIA HUDZON | C32: 262398 | D32: 50 | E32: 50 | L32: =SUM(E32:K32)-D32 -> 0
A33: 31 | B33: DAVIS MIRONGA | C33: 262399 | D33: 1350 | E33: 1350 | L33: =SUM(E33:K33)-D33 -> 0
A34: 32 | B34: DETE OCHIENG | C34: 262400 | D34: 150 | E34: 150 | L34: =SUM(E34:K34)-D34 -> 0
A35: 33 | B35: BOCHABERI OMBORI | C35: 322108 | D35: 200 | H35: 200 | L35: =SUM(E35:K35)-D35 -> 0
A36: 34 | B36: IRENE VARSITY -GRP 11 | C36: 322109 | D36: 200 | H36: 200 | L36: =SUM(E36:K36)-D36 -> 0
A37: 35 | B37: EDWARD ONYANGO-GRP 2 | C37: 322110 | D37: 200 | H37: 200 | L37: =SUM(E37:K37)-D37 -> 0
A38: 36 | B38: PURITY MBATHA -GRP 26 | C38: 322111 | D38: 500 | H38: 500 | L38: =SUM(E38:K38)-D38 -> 0
A39: 37 | B39: GRP 40 | C39: 322112 | D39: 845 | H39: 845 | L39: =SUM(E39:K39)-D39 -> 0
A40: 38 | B40: ESTHER SIOCHA'S FAMILY | C40: 322113 | D40: 6000 | E40: 5000 | H40: 1000 | L40: =SUM(E40:K40)-D40 -> 0
A41: 39 | B41: HELLEN NAIMADU | C41: 322114 | D41: 6500 | E41: 5890 | G41: 210 | I41: 400 | L41: =SUM(E41:K41)-D41 -> 0
A42: 40 | B42: ISAAC MOMANYI | C42: 322115 | D42: 1000 | E42: 1000 | L42: =SUM(E42:K42)-D42 -> 0
A43: 41 | B43: BRIAN PASSY | C43: 322116 | D43: 300 | E43: 300 | L43: =SUM(E43:K43)-D43 -> 0
A44: 42 | B44: JANE NYAMONGO | C44: 322117 | D44: 200 | I44: 200 | L44: =SUM(E44:K44)-D44 -> 0
A45: 43 | B45: JOB MITITI'S FAMILY | C45: 322118 | D45: 500 | E45: 300 | I45: 200 | L45: =SUM(E45:K45)-D45 -> 0
A46: 44 | B46: HYLINE KERUBO | C46: 322119 | D46: 200 | E46: 200 | L46: =SUM(E46:K46)-D46 -> 0
A47: 45 | B47: LEVINAH WYCLIFE | C47: 322120 | D47: 200 | E47: 200 | L47: =SUM(E47:K47)-D47 -> 0
A48: 46 | B48: ALBERT MAINA | C48: 322121 | D48: 5000 | E48: 5000 | L48: =SUM(E48:K48)-D48 -> 0
A49: 47 | B49: BRAVIAN ENOCK | C49: 322122 | D49: 50 | I49: 50 | L49: =SUM(E49:K49)-D49 -> 0
A50: 48 | B50: BILHA KWAMBOKA | C50: 322123 | D50: 50 | I50: 50 | L50: =SUM(E50:K50)-D50 -> 0
A51: 49 | B51: DORCAH GESARE OSANO | C51: 322124 | D51: 50 | F51: 50 | L51: =SUM(E51:K51)-D51 -> 0
A52: 50 | B52: JOHNES JUMA | C52: 322125 | D52: 100 | F52: 100 | L52: =SUM(E52:K52)-D52 -> 0
A53: 51 | B53: JACKSON OUMA | C53: 322126 | D53: 50 | H53: 50 | L53: =SUM(E53:K53)-D53 -> 0
A54: 52 | B54: AZIEL OUMA | C54: 322127 | D54: 10 | H54: 10 | L54: =SUM(E54:K54)-D54 -> 0
A55: 53 | B55: MAURICE MUNGA | C55: 322128 | D55: 300 | H55: 300 | L55: =SUM(E55:K55)-D55 -> 0
A56: 54 | B56: NANCY OTIENO | C56: 322129 | D56: 3000 | E56: 3000 | L56: =SUM(E56:K56)-D56 -> 0
A57: 55 | B57: PEREZ OLOGI | C57: 322130 | D57: 100 | I57: 100 | L57: =SUM(E57:K57)-D57 -> 0
A58: 56 | B58: CALLEN AKAMA | C58: 322131 | D58: 300 | F58: 100 | G58: 100 | I58: 100 | L58: =SUM(E58:K58)-D58 -> 0
A59: 57 | B59: IVAN HORACE | C59: 322132 | D59: 10 | H59: 10 | L59: =SUM(E59:K59)-D59 -> 0
A60: 58 | B60: NYABUTO OONGE | C60: 322133 | D60: 1000 | G60: 400 | I60: 600 | L60: =SUM(E60:K60)-D60 -> 0
A61: 59 | B61: PURITY JOHN | C61: 322134 | D61: 5680 | E61: 5180 | F61: 500 | L61: =SUM(E61:K61)-D61 -> 0
A62: 60 | B62: LEVI KABATI | C62: 322135 | D62: 200 | F62: 200 | L62: =SUM(E62:K62)-D62 -> 0
A63: 61 | B63: SAMSON NYARERU | C63: 322136 | D63: 5100 | E63: 4000 | F63: 50 | G63: 50 | H63: 1000 | L63: =SUM(E63:K63)-D63 -> 0
A64: 62 | B64: CHARLES NJOROGE | C64: 322137 | D64: 100 | F64: 100 | L64: =SUM(E64:K64)-D64 -> 0
A65: 63 | B65: ANGELA KYENDE | C65: 322138 | D65: 100 | F65: 100 | L65: =SUM(E65:K65)-D65 -> 0
A66: 64 | B66: ASNATH MATARA | C66: 322139 | D66: 13200 | E66: 13200 | L66: =SUM(E66:K66)-D66 -> 0
A67: 65 | B67: AWINO ASENATH | C67: 322140 | D67: 1000 | E67: 1000 | L67: =SUM(E67:K67)-D67 -> 0
A68: 66 | B68: BEAVON OSUMO | C68: 322141 | D68: 100 | F68: 100 | L68: =SUM(E68:K68)-D68 -> 0
A69: 67 | B69: BRENDA MATOKE | C69: 322142 | D69: 300 | I69: 300 | L69: =SUM(E69:K69)-D69 -> 0
A70: 68 | B70: BRIAN OINDI | C70: 322143 | D70: 100 | F70: 100 | L70: =SUM(E70:K70)-D70 -> 0
A71: 69 | B71: BRIAN OMENYI | C71: 322144 | D71: 1000 | I71: 1000 | L71: =SUM(E71:K71)-D71 -> 0
A72: 70 | B72: DIVINAH NYAKEYO | C72: 322145 | D72: 100 | F72: 100 | L72: =SUM(E72:K72)-D72 -> 0
A73: 71 | B73: DONA ODERO | C73: 322146 | D73: 100 | E73: 100 | L73: =SUM(E73:K73)-D73 -> 0
A74: 72 | B74: ELEN KIMANI | C74: 322147 | D74: 1006 | E74: 1006 | L74: =SUM(E74:K74)-D74 -> 0
A75: 73 | B75: EUNICE KERAGE | C75: 322148 | D75: 100 | K75: 100 | L75: =SUM(E75:K75)-D75 -> 0
A76: 74 | B76: EVANCE OJWANG | C76: 322149 | D76: 1000 | E76: 1000 | L76: =SUM(E76:K76)-D76 -> 0
A77: 75 | B77: FELIX ONYANGO | C77: 322150 | D77: 1250 | E77: 1250 | L77: =SUM(E77:K77)-D77 -> 0
A78: 76 | B78: FIDEL OLUOCH | C78: 322151 | D78: 30 | E78: 30 | L78: =SUM(E78:K78)-D78 -> 0
A79: 77 | B79: FLORENCE ACHOKI | C79: 322152 | D79: 100 | F79: 100 | L79: =SUM(E79:K79)-D79 -> 0
A80: 78 | B80: FRIDAH ISOE | C80: 322153 | D80: 100 | E80: 100 | L80: =SUM(E80:K80)-D80 -> 0
A81: 79 | B81: GOULDAH MBYUTA | C81: 322154 | D81: 200 | F81: 200 | L81: =SUM(E81:K81)-D81 -> 0
A82: 80 | B82: GRACE OGOLA | C82: 322155 | D82: 300 | I82: 300 | L82: =SUM(E82:K82)-D82 -> 0
A83: 81 | B83: JOSEPH KIMO | C83: 322156 | D83: 100 | F83: 100 | L83: =SUM(E83:K83)-D83 -> 0
A84: 82 | B84: JOSEPH NGWATO | C84: 322157 | D84: 50 | I84: 50 | L84: =SUM(E84:K84)-D84 -> 0
A85: 83 | B85: JULIET BANGE | C85: 322158 | D85: 23000 | E85: 23000 | L85: =SUM(E85:K85)-D85 -> 0
A86: 84 | B86: LINET KEBASO | C86: 322159 | D86: 100 | E86: 100 | L86: =SUM(E86:K86)-D86 -> 0
A87: 85 | B87: LYDIA MOTARI | C87: 322160 | D87: 400 | E87: 400 | L87: =SUM(E87:K87)-D87 -> 0
A88: 86 | B88: MARK NDEGWA | C88: 322161 | D88: 50 | F88: 50 | L88: =SUM(E88:K88)-D88 -> 0
A89: 87 | B89: MARWA KERARIO | C89: 322162 | D89: 100 | F89: 100 | L89: =SUM(E89:K89)-D89 -> 0
A90: 88 | B90: MERAB WANDOLLAH | C90: 322163 | D90: 100 | E90: 100 | L90: =SUM(E90:K90)-D90 -> 0
A91: 89 | B91: MOSES SINGH | C91: 322164 | D91: 20 | E91: 20 | L91: =SUM(E91:K91)-D91 -> 0
A92: 90 | B92: NAOMI NGITHI | C92: 322165 | D92: 14798 | E92: 14798 | L92: =SUM(E92:K92)-D92 -> 0
A93: 91 | B93: PURITY JOHN | C93: 322166 | D93: 617 | E93: 617 | L93: =SUM(E93:K93)-D93 -> 0
A94: 92 | B94: SAMWEL WAITHAKA | C94: 322167 | D94: 100 | J94: 100 | L94: =SUM(E94:K94)-D94 -> 0
A95: 93 | B95: SARAH AWITI | C95: 322168 | D95: 4000 | E95: 4000 | L95: =SUM(E95:K95)-D95 -> 0
A96: 94 | B96: SYDNEY NDLOVU | C96: 322169 | D96: 2800 | E96: 1400 | F96: 1400 | L96: =SUM(E96:K96)-D96 -> 0
A97: 95 | B97: VERAH NYAGAKA | C97: 322170 | D97: 60 | F97: 60 | L97: =SUM(E97:K97)-D97 -> 0
L98: =SUM(E98:K98)-D98 -> 0
L99: =SUM(E99:K99)-D99 -> 0
K100: =SUM(E100:J100)-D100 -> 0 | L100: =SUM(E100:K100)-D100 -> 0
...

Sheet Sheet2
G8: KAMAKIS CRUSADE
G9: DATE | H9: AMOUNT
G10: 45402 | H10: 61750
G11: 45395 | H11: 44350
G12: 45388 | H12: 34600
G13: TOTAL COLLECTION | H13: =SUM(H10:H12) -> 140700
G14: EXPENSES (20/04/2024) | H14: 73000
G16: BALANCE | H16: =H13-H14 -> 67700

Sheet 25TH-EXPENSES
C2: LOCAL CHURCH -EXPENSES
C3: DESCRIPTION | D3: DATE | E3: AMOUNT
C4: 6KG Gas Refill | D4: 45010 | E4: 1500
C5: Holy Communion consumables | D5: 45010 | E5: 4500
C21: TOTALS | E21: =SUM(E4:E20) -> 6000
